Workbook

Sheet 06-30-23
C1: 45107
C3: MANAGED ACCT | X3: Current | AC3: IBD
H4: Cost | J4: P/L | N4: Group | P4: EPS | R4: pivot | S4: last | W4: cost | X4: Stop | Y4: Stop | Z4: % | AB4: EPS | AC4: Comp
A5: Symbol | B5: Position | C5: Name | D5: Qty | E5: Current | F5: Value | G5: Cost | H5: per share | I5: P/L $ | J5: per sh | K5: Date purch | L5: days held | M5: % incr | N5: Rank | O5: RS | P5: RS | Q5: pivot | R5: -0.07 | S5: low | T5: 0.25 | U5: 0.5 | V5: 1 | W5: -0.07 | X5: Loss | Y5: Loss% | Z5: of port | AB5: Due | AC5: Rank
F6: =E6*D6 -> 0 | H6: =G6/D6 -> #DIV/0! | I6: =F6-G6 -> 0 | J6: =E6-H6 -> #DIV/0! | L6: =DAYS360(K6,$C$1) -> 44460 | M6: =(I6/G6) -> #DIV/0! | R6: =Q6*0.93 -> 0 | T6: =Q6*1.25 -> 0 | U6: =Q6*1.5 -> 0 | V6: =Q6*2 -> 0 | W6: =H6-(H6*0.07) -> #DIV/0! | Y6: =(X6-H6)/H6 -> #DIV/0! | Z6: =F6/F$22 -> 0
A7: MCK | B7: Long | C7: McKesson | D7: 123.3931 | E7: 428.17 | F7: =E7*D7 -> 52833.224 | G7: 50990.97 | H7: =G7/D7 -> 413.24004 | I7: =F7-G7 -> 1842.2536 | J7: =E7-H7 -> 14.929957 | K7: 45104 | L7: =DAYS360(K7,$C$1) -> 3 | M7: =(I7/G7) -> 0.036129017 | N7: 56 | O7: 85 | P7: 95 | Q7: 401.53 | R7: =Q7*0.93 -> 373.4229 | S7: 373.28 | T7: =Q7*1.25 -> 501.9125 | U7: =Q7*1.5 -> 602.295 | V7: =Q7*2 -> 803.06 | W7: =H7-(H7*0.07) -> 384.31324 | X7: 399 | Y7: =(X7-H7)/H7 -> -0.034459495 | Z7: =F7/F$22 -> 0.10329671 | AC7: 88 | AD7: Bought after pullback to 10dma
A8: DXCM | B8: Long | C8: DexCom | D8: 278.2008 | E8: 128.8 | F8: =E8*D8 -> 35832.263 | G8: 35723.77 | H8: =G8/D8 -> 128.41002 | I8: =F8-G8 -> 108.49304 | J8: =E8-H8 -> 0.38998105 | K8: 45106 | L8: =DAYS360(K8,$C$1) -> 1 | M8: =(I8/G8) -> 0.0030369986 | N8: 47 | O8: 90 | P8: 98 | Q8: 126.44 | R8: =Q8*0.93 -> 117.5892 | S8: 121.79 | T8: =Q8*1.25 -> 158.05 | U8: =Q8*1.5 -> 189.66 | V8: =Q8*2 -> 252.88 | W8: =H8-(H8*0.07) -> 119.42132 | X8: 120 | Y8: =(X8-H8)/H8 -> -0.06549348 | Z8: =F8/F$22 -> 0.070057333 | AB8: 44596 | AC8: 97 | AD8: Bought after pullback to 50dma and pivot area.
F9: =E9*D9 -> 0 | H9: =G9/D9 -> #DIV/0! | I9: =F9-G9 -> 0 | J9: =E9-H9 -> #DIV/0! | L9: =DAYS360(K9,$C$1) -> 44460 | M9: =(I9/G9) -> #DIV/0! | R9: =Q9*0.93 -> 0 | T9: =Q9*1.25 -> 0 | U9: =Q9*1.5 -> 0 | V9: =Q9*2 -> 0 | W9: =H9-(H9*0.07) -> #DIV/0! | Y9: =(X9-H9)/H9 -> #DIV/0! | Z9: =F9/F$22 -> 0 | AB9: 44596 | AC9: 75
F10: =E10*D10 -> 0 | H10: =G10/D10 -> #DIV/0! | I10: =F10-G10 -> 0 | J10: =E10-H10 -> #DIV/0! | L10: =DAYS360(K10,$C$1) -> 44460 | M10: =(I10/G10) -> #DIV/0! | R10: =Q10*0.93 -> 0 | T10: =Q10*1.25 -> 0 | U10: =Q10*1.5 -> 0 | V10: =Q10*2 -> 0 | W10: =H10-(H10*0.07) -> #DIV/0! | Y10: =(X10-H10)/H10 -> #DIV/0! | Z10: =F10/F$22 -> 0 | AB10: 44589 | AC10: 87
F11: =E11*D11 -> 0 | H11: =G11/D11 -> #DIV/0! | I11: =F11-G11 -> 0 | J11: =E11-H11 -> #DIV/0! | L11: =DAYS360(K11,$C$1) -> 44460 | M11: =(I11/G11) -> #DIV/0! | R11: =Q11*0.93 -> 0 | T11: =Q11*1.25 -> 0 | U11: =Q11*1.5 -> 0 | V11: =Q11*2 -> 0 | W11: =H11-(H11*0.07) -> #DIV/0! | Y11: =(X11-H11)/H11 -> #DIV/0! | Z11: =F11/F$22 -> 0 | AB11: 44581 | AC11: 99
F12: =E12*D12 -> 0 | H12: =G12/D12 -> #DIV/0! | I12: =F12-G12 -> 0 | J12: =E12-H12 -> #DIV/0! | L12: =DAYS360(K12,$C$1) -> 44460 | M12: =(I12/G12) -> #DIV/0! | R12: =Q12*0.93 -> 0 | T12: =Q12*1.25 -> 0 | U12: =Q12*1.5 -> 0 | V12: =Q12*2 -> 0 | W12: =H12-(H12*0.07) -> #DIV/0! | Y12: =(X12-H12)/H12 -> #DIV/0! | Z12: =F12/F$22 -> 0 | AB12: 44568 | AC12: 90
F13: =E13*D13 -> 0 | H13: =G13/D13 -> #DIV/0! | I13: =F13-G13 -> 0 | J13: =E13-H13 -> #DIV/0! | L13: =DAYS360(K13,$C$1) -> 44460 | M13: =(I13/G13) -> #DIV/0! | R13: =Q13*0.93 -> 0 | T13: =Q13*1.25 -> 0 | U13: =Q13*1.5 -> 0 | V13: =Q13*2 -> 0 | W13: =H13-(H13*0.07) -> #DIV/0! | Y13: =(X13-H13)/H13 -> #DIV/0! | Z13: =F13/F$22 -> 0 | AB13: 44601 | AC13: 99
F14: =E14*D14 -> 0 | H14: =G14/D14 -> #DIV/0! | I14: =F14-G14 -> 0 | J14: =E14-H14 -> #DIV/0! | L14: =DAYS360(K14,$C$1) -> 44460 | M14: =(I14/G14) -> #DIV/0! | R14: =Q14*0.93 -> 0 | T14: =Q14*1.25 -> 0 | U14: =Q14*1.5 -> 0 | V14: =Q14*2 -> 0 | W14: =H14-(H14*0.07) -> #DIV/0! | Y14: =(X14-H14)/H14 -> #DIV/0! | Z14: =F14/F$22 -> 0 | AB14: 44610 | AC14: 92
F15: =E15*D15 -> 0 | H15: =G15/D15 -> #DIV/0! | I15: =F15-G15 -> 0 | J15: =E15-H15 -> #DIV/0! | L15: =DAYS360(K15,$C$1) -> 44460 | M15: =(I15/G15) -> #DIV/0! | R15: =Q15*0.93 -> 0 | T15: =Q15*1.25 -> 0 | U15: =Q15*1.5 -> 0 | V15: =Q15*2 -> 0 | W15: =H15-(H15*0.07) -> #DIV/0! | Y15: =(X15-H15)/H15 -> #DIV/0! | Z15: =F15/F$22 -> 0
F16: =E16*D16 -> 0 | H16: =G16/D16 -> #DIV/0! | I16: =F16-G16 -> 0 | J16: =E16-H16 -> #DIV/0! | L16: =DAYS360(K16,$C$1) -> 44460 | M16: =(I16/G16) -> #DIV/0! | R16: =Q16*0.93 -> 0 | T16: =Q16*1.25 -> 0 | U16: =Q16*1.5 -> 0 | V16: =Q16*2 -> 0 | W16: =H16-(H16*0.07) -> #DIV/0! | Y16: =(X16-H16)/H16 -> #DIV/0! | Z16: =F16/F$22 -> 0
A17: BIL | B17: Long | C17: Tbill ETF | D17: 2778.4118 | E17: 91.83 | F17: =E17*D17 -> 255141.56 | G17: 254613.66 | H17: =G17/D17 -> 91.640001 | I17: =F17-G17 -> 527.89559 | J17: =E17-H17 -> 0.18999905 | L17: =DAYS360(K17,$C$1) -> 44460 | M17: =(I17/G17) -> 0.00207332 | R17: =Q17*0.93 -> 0 | T17: =Q17*1.25 -> 0 | U17: =Q17*1.5 -> 0 | V17: =Q17*2 -> 0 | W17: =H17-(H17*0.07) -> 85.225201 | Y17: =(X17-H17)/H17 -> -1 | Z17: =F17/F$22 -> 0.49883919
A18: SQQQ | B18: Long | C18: QQQ Triple short | D18: 511.2918 | E18: 18.82 | F18: =E18*D18 -> 9622.5117 | G18: 24797.66 | H18: =G18/D18 -> 48.500015 | I18: =F18-G18 -> -15175.148 | J18: =E18-H18 -> -29.680015 | L18: =DAYS360(K18,$C$1) -> 44460 | M18: =(I18/G18) -> -0.61195888 | R18: =Q18*0.93 -> 0 | T18: =Q18*1.25 -> 0 | U18: =Q18*1.5 -> 0 | V18: =Q18*2 -> 0 | W18: =H18-(H18*0.07) -> 45.105014 | Y18: =(X18-H18)/H18 -> -1 | Z18: =F18/F$22 -> 0.018813423
F19: =E19*D19 -> 0 | H19: =G19/D19 -> #DIV/0! | I19: =F19-G19 -> 0 | J19: =E19-H19 -> #DIV/0! | L19: =DAYS360(K19,$C$1) -> 44460 | M19: =(I19/G19) -> #DIV/0! | R19: =Q19*0.93 -> 0 | T19: =Q19*1.25 -> 0 | U19: =Q19*1.5 -> 0 | V19: =Q19*2 -> 0 | W19: =H19-(H19*0.07) -> #DIV/0! | Y19: =(X19-H19)/H19 -> #DIV/0! | Z19: =F19/F$22 -> 0
A20: Sub-Total | F20: =SUM(F6:F19) -> 353429.55 | G20: =SUM(G6:G19) -> 366126.06 | I20: =SUM(I6:I19) -> -12696.506
D21: Cash, other | F21: 158041 | G21: =F21/F22 -> 0.30899335
D22: Total | F22: =SUM(F20:F21) -> 511470.55
F23: Yesterday's close >>>> | H23: Last week's close | I23: 509801
F24: Day's change >>> | G24: =(F22-G23)/G23 -> #DIV/0! | H24: Week's change | I24: =(F22-I23-F25)/I23 -> 0.003274913
M26: days
A27: 2023 Closed Trades - Managed Acct | D27: Qty | E27: Cost/sh | F27: $ cost | G27: Proc/sh | H27: $Proc | I27: Profit/loss | J27: % | K27: Date purch | L27: Date sold | M27: held | P27: Comments

Sheet 07-07-23
C1: 45114
C3: MANAGED ACCT | X3: Current | AC3: IBD
H4: Cost | J4: P/L | N4: Group | P4: EPS | R4: pivot | S4: last | W4: cost | X4: Stop | Y4: Stop | Z4: % | AB4: EPS | AC4: Comp
A5: Symbol | B5: Position | C5: Name | D5: Qty | E5: Current | F5: Value | G5: Cost | H5: per share | I5: P/L $ | J5: per sh | K5: Date purch | L5: days held | M5: % incr | N5: Rank | O5: RS | P5: RS | Q5: pivot | R5: -0.07 | S5: low | T5: 0.25 | U5: 0.5 | V5: 1 | W5: -0.07 | X5: Loss | Y5: Loss% | Z5: of port | AB5: Due | AC5: Rank
F6: =E6*D6 -> 0 | H6: =G6/D6 -> #DIV/0! | I6: =F6-G6 -> 0 | J6: =E6-H6 -> #DIV/0! | L6: =DAYS360(K6,$C$1) -> 44467 | M6: =(I6/G6) -> #DIV/0! | R6: =Q6*0.93 -> 0 | T6: =Q6*1.25 -> 0 | U6: =Q6*1.5 -> 0 | V6: =Q6*2 -> 0 | W6: =H6-(H6*0.07) -> #DIV/0! | Y6: =(X6-H6)/H6 -> #DIV/0! | Z6: =F6/F$22 -> 0
A7: MCK | B7: Long | C7: McKesson | D7: 123.3931 | E7: 414.8 | F7: =E7*D7 -> 51183.458 | G7: 50990.97 | H7: =G7/D7 -> 413.24004 | I7: =F7-G7 -> 192.48788 | J7: =E7-H7 -> 1.5599566 | K7: 45104 | L7: =DAYS360(K7,$C$1) -> 10 | M7: =(I7/G7) -> 0.0037749405 | N7: 39 | O7: 83 | P7: 95 | Q7: 401.53 | R7: =Q7*0.93 -> 373.4229 | S7: 373.28 | T7: =Q7*1.25 -> 501.9125 | U7: =Q7*1.5 -> 602.295 | V7: =Q7*2 -> 803.06 | W7: =H7-(H7*0.07) -> 384.31324 | X7: 399 | Y7: =(X7-H7)/H7 -> -0.034459495 | Z7: =F7/F$22 -> 0.10043628 | AB7: 45140 | AC7: 88 | AD7: Bought after pullback to 10dma
A8: DXCM | B8: Long | C8: DexCom | D8: 278.2008 | E8: 126.71 | F8: =E8*D8 -> 35250.823 | G8: 35723.77 | H8: =G8/D8 -> 128.41002 | I8: =F8-G8 -> -472.94663 | J8: =E8-H8 -> -1.700019 | K8: 45106 | L8: =DAYS360(K8,$C$1) -> 8 | M8: =(I8/G8) -> -0.01323899 | N8: 47 | O8: 89 | P8: 98 | Q8: 126.44 | R8: =Q8*0.93 -> 117.5892 | S8: 121.79 | T8: =Q8*1.25 -> 158.05 | U8: =Q8*1.5 -> 189.66 | V8: =Q8*2 -> 252.88 | W8: =H8-(H8*0.07) -> 119.42132 | X8: 122.45 | Y8: =(X8-H8)/H8 -> -0.046413971 | Z8: =F8/F$22 -> 0.069171986 | AB8: 45140 | AC8: 97 | AD8: Bought after pullback to 50dma and pivot area.
A9: HXL | B9: Long | C9: Hexcel | D9: 665.9739 | E9: 76.82 | F9: =E9*D9 -> 51160.115 | G9: 51028 | H9: =G9/D9 -> 76.621621 | I9: =F9-G9 -> 132.115 | J9: =E9-H9 -> 0.19837864 | K9: 45112 | L9: =DAYS360(K9,$C$1) -> 2 | M9: =(I9/G9) -> 0.0025890687 | N9: 44 | O9: 90 | P9: 82 | Q9: 74.44 | R9: =Q9*0.93 -> 69.2292 | S9: 70.88 | T9: =Q9*1.25 -> 93.05 | U9: =Q9*1.5 -> 111.66 | V9: =Q9*2 -> 148.88 | W9: =H9-(H9*0.07) -> 71.258108 | X9: 73.25 | Y9: =(X9-H9)/H9 -> -0.044003524 | Z9: =F9/F$22 -> 0.10039047 | AB9: 45131 | AC9: 97 | AD9: Bought after pivot test. Katie recommends also.
F10: =E10*D10 -> 0 | H10: =G10/D10 -> #DIV/0! | I10: =F10-G10 -> 0 | J10: =E10-H10 -> #DIV/0! | L10: =DAYS360(K10,$C$1) -> 44467 | M10: =(I10/G10) -> #DIV/0! | R10: =Q10*0.93 -> 0 | T10: =Q10*1.25 -> 0 | U10: =Q10*1.5 -> 0 | V10: =Q10*2 -> 0 | W10: =H10-(H10*0.07) -> #DIV/0! | Y10: =(X10-H10)/H10 -> #DIV/0! | Z10: =F10/F$22 -> 0 | AB10: 44589 | AC10: 87
F11: =E11*D11 -> 0 | H11: =G11/D11 -> #DIV/0! | I11: =F11-G11 -> 0 | J11: =E11-H11 -> #DIV/0! | L11: =DAYS360(K11,$C$1) -> 44467 | M11: =(I11/G11) -> #DIV/0! | R11: =Q11*0.93 -> 0 | T11: =Q11*1.25 -> 0 | U11: =Q11*1.5 -> 0 | V11: =Q11*2 -> 0 | W11: =H11-(H11*0.07) -> #DIV/0! | Y11: =(X11-H11)/H11 -> #DIV/0! | Z11: =F11/F$22 -> 0 | AB11: 44581 | AC11: 99
F12: =E12*D12 -> 0 | H12: =G12/D12 -> #DIV/0! | I12: =F12-G12 -> 0 | J12: =E12-H12 -> #DIV/0! | L12: =DAYS360(K12,$C$1) -> 44467 | M12: =(I12/G12) -> #DIV/0! | R12: =Q12*0.93 -> 0 | T12: =Q12*1.25 -> 0 | U12: =Q12*1.5 -> 0 | V12: =Q12*2 -> 0 | W12: =H12-(H12*0.07) -> #DIV/0! | Y12: =(X12-H12)/H12 -> #DIV/0! | Z12: =F12/F$22 -> 0 | AB12: 44568 | AC12: 90
F13: =E13*D13 -> 0 | H13: =G13/D13 -> #DIV/0! | I13: =F13-G13 -> 0 | J13: =E13-H13 -> #DIV/0! | L13: =DAYS360(K13,$C$1) -> 44467 | M13: =(I13/G13) -> #DIV/0! | R13: =Q13*0.93 -> 0 | T13: =Q13*1.25 -> 0 | U13: =Q13*1.5 -> 0 | V13: =Q13*2 -> 0 | W13: =H13-(H13*0.07) -> #DIV/0! | Y13: =(X13-H13)/H13 -> #DIV/0! | Z13: =F13/F$22 -> 0 | AB13: 44601 | AC13: 99
F14: =E14*D14 -> 0 | H14: =G14/D14 -> #DIV/0! | I14: =F14-G14 -> 0 | J14: =E14-H14 -> #DIV/0! | L14: =DAYS360(K14,$C$1) -> 44467 | M14: =(I14/G14) -> #DIV/0! | R14: =Q14*0.93 -> 0 | T14: =Q14*1.25 -> 0 | U14: =Q14*1.5 -> 0 | V14: =Q14*2 -> 0 | W14: =H14-(H14*0.07) -> #DIV/0! | Y14: =(X14-H14)/H14 -> #DIV/0! | Z14: =F14/F$22 -> 0 | AB14: 44610 | AC14: 92
F15: =E15*D15 -> 0 | H15: =G15/D15 -> #DIV/0! | I15: =F15-G15 -> 0 | J15: =E15-H15 -> #DIV/0! | L15: =DAYS360(K15,$C$1) -> 44467 | M15: =(I15/G15) -> #DIV/0! | R15: =Q15*0.93 -> 0 | T15: =Q15*1.25 -> 0 | U15: =Q15*1.5 -> 0 | V15: =Q15*2 -> 0 | W15: =H15-(H15*0.07) -> #DIV/0! | Y15: =(X15-H15)/H15 -> #DIV/0! | Z15: =F15/F$22 -> 0
F16: =E16*D16 -> 0 | H16: =G16/D16 -> #DIV/0! | I16: =F16-G16 -> 0 | J16: =E16-H16 -> #DIV/0! | L16: =DAYS360(K16,$C$1) -> 44467 | M16: =(I16/G16) -> #DIV/0! | R16: =Q16*0.93 -> 0 | T16: =Q16*1.25 -> 0 | U16: =Q16*1.5 -> 0 | V16: =Q16*2 -> 0 | W16: =H16-(H16*0.07) -> #DIV/0! | Y16: =(X16-H16)/H16 -> #DIV/0! | Z16: =F16/F$22 -> 0
A17: BIL | B17: Long | C17: Tbill ETF | D17: 2778.4118 | E17: 91.52 | F17: =E17*D17 -> 254280.25 | G17: 254613.66 | H17: =G17/D17 -> 91.640001 | I17: =F17-G17 -> -333.41206 | J17: =E17-H17 -> -0.12000095 | L17: =DAYS360(K17,$C$1) -> 44467 | M17: =(I17/G17) -> -0.0013094822 | R17: =Q17*0.93 -> 0 | T17: =Q17*1.25 -> 0 | U17: =Q17*1.5 -> 0 | V17: =Q17*2 -> 0 | W17: =H17-(H17*0.07) -> 85.225201 | Y17: =(X17-H17)/H17 -> -1 | Z17: =F17/F$22 -> 0.49896904
A18: SQQQ | B18: Long | C18: QQQ Triple short | D18: 511.2918 | E18: 19.45 | F18: =E18*D18 -> 9944.6255 | G18: 24797.66 | H18: =G18/D18 -> 48.500015 | I18: =F18-G18 -> -14853.034 | J18: =E18-H18 -> -29.050015 | L18: =DAYS360(K18,$C$1) -> 44467 | M18: =(I18/G18) -> -0.5989692 | R18: =Q18*0.93 -> 0 | T18: =Q18*1.25 -> 0 | U18: =Q18*1.5 -> 0 | V18: =Q18*2 -> 0 | W18: =H18-(H18*0.07) -> 45.105014 | Y18: =(X18-H18)/H18 -> -1 | Z18: =F18/F$22 -> 0.01951414
F19: =E19*D19 -> 0 | H19: =G19/D19 -> #DIV/0! | I19: =F19-G19 -> 0 | J19: =E19-H19 -> #DIV/0! | L19: =DAYS360(K19,$C$1) -> 44467 | M19: =(I19/G19) -> #DIV/0! | R19: =Q19*0.93 -> 0 | T19: =Q19*1.25 -> 0 | U19: =Q19*1.5 -> 0 | V19: =Q19*2 -> 0 | W19: =H19-(H19*0.07) -> #DIV/0! | Y19: =(X19-H19)/H19 -> #DIV/0! | Z19: =F19/F$22 -> 0
A20: Sub-Total | F20: =SUM(F6:F19) -> 401819.27 | G20: =SUM(G6:G19) -> 417154.06 | I20: =SUM(I6:I19) -> -15334.79
D21: Cash, other | F21: 107792 | G21: =F21/F22 -> 0.21151809
D22: Total | F22: =SUM(F20:F21) -> 509611.27
F23: Yesterday's close >>>> | H23: Last week's close | I23: 511470.55
F24: Day's change >>> | G24: =(F22-G23)/G23 -> #DIV/0! | H24: Week's change | I24: =(F22-I23-F25)/I23 -> -0.0036351659
M26: days
A27: 2023 Closed Trades - Managed Acct | D27: Qty | E27: Cost/sh | F27: $ cost | G27: Proc/sh | H27: $Proc | I27: Profit/loss | J27: % | K27: Date purch | L27: Date sold | M27: held | P27: Comments

Sheet 07-14-23
C1: 45121
C3: MANAGED ACCT | X3: Current | AC3: IBD
H4: Cost | J4: P/L | N4: Group | P4: EPS | R4: pivot | S4: last | W4: cost | X4: Stop | Y4: Stop | Z4: % | AB4: EPS | AC4: Comp
A5: Symbol | B5: Position | C5: Name | D5: Qty | E5: Current | F5: Value | G5: Cost | H5: per share | I5: P/L $ | J5: per sh | K5: Date purch | L5: days held | M5: % incr | N5: Rank | O5: RS | P5: RS | Q5: pivot | R5: -0.07 | S5: low | T5: 0.25 | U5: 0.5 | V5: 1 | W5: -0.07 | X5: Loss | Y5: Loss% | Z5: of port | AB5: Due | AC5: Rank
F6: =E6*D6 -> 0 | H6: =G6/D6 -> #DIV/0! | I6: =F6-G6 -> 0 | J6: =E6-H6 -> #DIV/0! | L6: =DAYS360(K6,$C$1) -> 44474 | M6: =(I6/G6) -> #DIV/0! | R6: =Q6*0.93 -> 0 | T6: =Q6*1.25 -> 0 | U6: =Q6*1.5 -> 0 | V6: =Q6*2 -> 0 | W6: =H6-(H6*0.07) -> #DIV/0! | Y6: =(X6-H6)/H6 -> #DIV/0! | Z6: =F6/F$22 -> 0
A7: MCK | B7: Long | C7: McKesson | D7: 123.3931 | E7: 409.5 | F7: =E7*D7 -> 50529.474 | G7: 50990.97 | H7: =G7/D7 -> 413.24004 | I7: =F7-G7 -> -461.49555 | J7: =E7-H7 -> -3.7400434 | K7: 45104 | L7: =DAYS360(K7,$C$1) -> 17 | M7: =(I7/G7) -> -0.0090505348 | N7: 39 | O7: 83 | P7: 95 | Q7: 401.53 | R7: =Q7*0.93 -> 373.4229 | S7: 373.28 | T7: =Q7*1.25 -> 501.9125 | U7: =Q7*1.5 -> 602.295 | V7: =Q7*2 -> 803.06 | W7: =H7-(H7*0.07) -> 384.31324 | X7: 399 | Y7: =(X7-H7)/H7 -> -0.034459495 | Z7: =F7/F$22 -> 0.098459082 | AB7: 45140 | AC7: 88 | AD7: Bought after pullback to 10dma
A8: DXCM | B8: Long | C8: DexCom | D8: 278.2008 | E8: 137.32 | F8: =E8*D8 -> 38202.534 | G8: 35723.77 | H8: =G8/D8 -> 128.41002 | I8: =F8-G8 -> 2478.7639 | J8: =E8-H8 -> 8.909981 | K8: 45106 | L8: =DAYS360(K8,$C$1) -> 15 | M8: =(I8/G8) -> 0.069386962 | N8: 47 | O8: 89 | P8: 98 | Q8: 126.44 | R8: =Q8*0.93 -> 117.5892 | S8: 121.79 | T8: =Q8*1.25 -> 158.05 | U8: =Q8*1.5 -> 189.66 | V8: =Q8*2 -> 252.88 | W8: =H8-(H8*0.07) -> 119.42132 | X8: 122.45 | Y8: =(X8-H8)/H8 -> -0.046413971 | Z8: =F8/F$22 -> 0.074439452 | AB8: 45140 | AC8: 97 | AD8: Bought after pullback to 50dma and pivot area.
A9: HXL | B9: Long | C9: Hexcel | D9: 665.9739 | E9: 76.17 | F9: =E9*D9 -> 50727.232 | G9: 51028 | H9: =G9/D9 -> 76.621621 | I9: =F9-G9 -> -300.76804 | J9: =E9-H9 -> -0.45162136 | K9: 45112 | L9: =DAYS360(K9,$C$1) -> 9 | M9: =(I9/G9) -> -0.0058941765 | N9: 44 | O9: 90 | P9: 82 | Q9: 74.44 | R9: =Q9*0.93 -> 69.2292 | S9: 70.88 | T9: =Q9*1.25 -> 93.05 | U9: =Q9*1.5 -> 111.66 | V9: =Q9*2 -> 148.88 | W9: =H9-(H9*0.07) -> 71.258108 | X9: 73.25 | Y9: =(X9-H9)/H9 -> -0.044003524 | Z9: =F9/F$22 -> 0.098844422 | AB9: 45131 | AC9: 97 | AD9: Bought after pivot test. Katie recommends also.
A10: SNPS | B10: Long | C10: Synopsys | D10: 115.8536 | E10: 454.11 | F10: =E10*D10 -> 52610.278 | G10: 51225.83 | H10: =G10/D10 -> 442.16002 | I10: =F10-G10 -> 1384.4483 | J10: =E10-H10 -> 11.949981 | K10: 45117 | L10: =DAYS360(K10,$C$1) -> 4 | M10: =(I10/G10) -> 0.027026371 | N10: 22 | O10: 89 | P10: 90 | Q10: 392.79 | R10: =Q10*0.93 -> 365.2947 | S10: 416.87 | T10: =Q10*1.25 -> 490.9875 | U10: =Q10*1.5 -> 589.185 | V10: =Q10*2 -> 785.58 | W10: =H10-(H10*0.07) -> 411.20882 | X10: 415 | Y10: =(X10-H10)/H10 -> -0.061425769 | Z10: =F10/F$22 -> 0.10251363 | AB10: 45154 | AC10: 96 | AD10: Bought when breaking out of bull flag in volume.
F11: =E11*D11 -> 0 | H11: =G11/D11 -> #DIV/0! | I11: =F11-G11 -> 0 | J11: =E11-H11 -> #DIV/0! | L11: =DAYS360(K11,$C$1) -> 44474 | M11: =(I11/G11) -> #DIV/0! | R11: =Q11*0.93 -> 0 | T11: =Q11*1.25 -> 0 | U11: =Q11*1.5 -> 0 | V11: =Q11*2 -> 0 | W11: =H11-(H11*0.07) -> #DIV/0! | Y11: =(X11-H11)/H11 -> #DIV/0! | Z11: =F11/F$22 -> 0 | AB11: 44581 | AC11: 99
F12: =E12*D12 -> 0 | H12: =G12/D12 -> #DIV/0! | I12: =F12-G12 -> 0 | J12: =E12-H12 -> #DIV/0! | L12: =DAYS360(K12,$C$1) -> 44474 | M12: =(I12/G12) -> #DIV/0! | R12: =Q12*0.93 -> 0 | T12: =Q12*1.25 -> 0 | U12: =Q12*1.5 -> 0 | V12: =Q12*2 -> 0 | W12: =H12-(H12*0.07) -> #DIV/0! | Y12: =(X12-H12)/H12 -> #DIV/0! | Z12: =F12/F$22 -> 0 | AB12: 44568 | AC12: 90
F13: =E13*D13 -> 0 | H13: =G13/D13 -> #DIV/0! | I13: =F13-G13 -> 0 | J13: =E13-H13 -> #DIV/0! | L13: =DAYS360(K13,$C$1) -> 44474 | M13: =(I13/G13) -> #DIV/0! | R13: =Q13*0.93 -> 0 | T13: =Q13*1.25 -> 0 | U13: =Q13*1.5 -> 0 | V13: =Q13*2 -> 0 | W13: =H13-(H13*0.07) -> #DIV/0! | Y13: =(X13-H13)/H13 -> #DIV/0! | Z13: =F13/F$22 -> 0 | AB13: 44601 | AC13: 99
F14: =E14*D14 -> 0 | H14: =G14/D14 -> #DIV/0! | I14: =F14-G14 -> 0 | J14: =E14-H14 -> #DIV/0! | L14: =DAYS360(K14,$C$1) -> 44474 | M14: =(I14/G14) -> #DIV/0! | R14: =Q14*0.93 -> 0 | T14: =Q14*1.25 -> 0 | U14: =Q14*1.5 -> 0 | V14: =Q14*2 -> 0 | W14: =H14-(H14*0.07) -> #DIV/0! | Y14: =(X14-H14)/H14 -> #DIV/0! | Z14: =F14/F$22 -> 0 | AB14: 44610 | AC14: 92
F15: =E15*D15 -> 0 | H15: =G15/D15 -> #DIV/0! | I15: =F15-G15 -> 0 | J15: =E15-H15 -> #DIV/0! | L15: =DAYS360(K15,$C$1) -> 44474 | M15: =(I15/G15) -> #DIV/0! | R15: =Q15*0.93 -> 0 | T15: =Q15*1.25 -> 0 | U15: =Q15*1.5 -> 0 | V15: =Q15*2 -> 0 | W15: =H15-(H15*0.07) -> #DIV/0! | Y15: =(X15-H15)/H15 -> #DIV/0! | Z15: =F15/F$22 -> 0
F16: =E16*D16 -> 0 | H16: =G16/D16 -> #DIV/0! | I16: =F16-G16 -> 0 | J16: =E16-H16 -> #DIV/0! | L16: =DAYS360(K16,$C$1) -> 44474 | M16: =(I16/G16) -> #DIV/0! | R16: =Q16*0.93 -> 0 | T16: =Q16*1.25 -> 0 | U16: =Q16*1.5 -> 0 | V16: =Q16*2 -> 0 | W16: =H16-(H16*0.07) -> #DIV/0! | Y16: =(X16-H16)/H16 -> #DIV/0! | Z16: =F16/F$22 -> 0
A17: BIL | B17: Long | C17: Tbill ETF | D17: 2778.4118 | E17: 91.62 | F17: =E17*D17 -> 254558.09 | G17: 254613.66 | H17: =G17/D17 -> 91.640001 | I17: =F17-G17 -> -55.570884 | J17: =E17-H17 -> -0.020000953 | L17: =DAYS360(K17,$C$1) -> 44474 | M17: =(I17/G17) -> -0.00021825571 | R17: =Q17*0.93 -> 0 | T17: =Q17*1.25 -> 0 | U17: =Q17*1.5 -> 0 | V17: =Q17*2 -> 0 | W17: =H17-(H17*0.07) -> 85.225201 | Y17: =(X17-H17)/H17 -> -1 | Z17: =F17/F$22 -> 0.49601853
A18: SQQQ | B18: Long | C18: QQQ Triple short | D18: 511.2918 | E18: 17.55 | F18: =E18*D18 -> 8973.1711 | G18: 24797.66 | H18: =G18/D18 -> 48.500015 | I18: =F18-G18 -> -15824.489 | J18: =E18-H18 -> -30.950015 | L18: =DAYS360(K18,$C$1) -> 44474 | M18: =(I18/G18) -> -0.63814444 | R18: =Q18*0.93 -> 0 | T18: =Q18*1.25 -> 0 | U18: =Q18*1.5 -> 0 | V18: =Q18*2 -> 0 | W18: =H18-(H18*0.07) -> 45.105014 | Y18: =(X18-H18)/H18 -> -1 | Z18: =F18/F$22 -> 0.01748465
F19: =E19*D19 -> 0 | H19: =G19/D19 -> #DIV/0! | I19: =F19-G19 -> 0 | J19: =E19-H19 -> #DIV/0! | L19: =DAYS360(K19,$C$1) -> 44474 | M19: =(I19/G19) -> #DIV/0! | R19: =Q19*0.93 -> 0 | T19: =Q19*1.25 -> 0 | U19: =Q19*1.5 -> 0 | V19: =Q19*2 -> 0 | W19: =H19-(H19*0.07) -> #DIV/0! | Y19: =(X19-H19)/H19 -> #DIV/0! | Z19: =F19/F$22 -> 0
A20: Sub-Total | F20: =SUM(F6:F19) -> 455600.78 | G20: =SUM(G6:G19) -> 468379.89 | I20: =SUM(I6:I19) -> -12779.111
D21: Cash, other | F21: 57602 | G21: =F21/F22 -> 0.11224023
D22: Total | F22: =SUM(F20:F21) -> 513202.78
F23: Yesterday's close >>>> | H23: Last week's close | I23: 509611.27
F24: Day's change >>> | G24: =(F22-G23)/G23 -> #DIV/0! | H24: Week's change | I24: =(F22-I23-F25)/I23 -> 0.0070475458
M26: days
A27: 2023 Closed Trades - Managed Acct | D27: Qty | E27: Cost/sh | F27: $ cost | G27: Proc/sh | H27: $Proc | I27: Profit/loss | J27: % | K27: Date purch | L27: Date sold | M27: held | P27: Comments

Sheet 07-21-23
C1: 45128
C3: MANAGED ACCT | X3: Current | AC3: IBD
H4: Cost | J4: P/L | N4: Group | P4: EPS | R4: pivot | S4: last | W4: cost | X4: Stop | Y4: Stop | Z4: % | AB4: EPS | AC4: Comp
A5: Symbol | B5: Position | C5: Name | D5: Qty | E5: Current | F5: Value | G5: Cost | H5: per share | I5: P/L $ | J5: per sh | K5: Date purch | L5: days held | M5: % incr | N5: Rank | O5: RS | P5: RS | Q5: pivot | R5: -0.07 | S5: low | T5: 0.25 | U5: 0.5 | V5: 1 | W5: -0.07 | X5: Loss | Y5: Loss% | Z5: of port | AB5: Due | AC5: Rank
F6: =E6*D6 -> 0 | H6: =G6/D6 -> #DIV/0! | I6: =F6-G6 -> 0 | J6: =E6-H6 -> #DIV/0! | L6: =DAYS360(K6,$C$1) -> 44481 | M6: =(I6/G6) -> #DIV/0! | R6: =Q6*0.93 -> 0 | T6: =Q6*1.25 -> 0 | U6: =Q6*1.5 -> 0 | V6: =Q6*2 -> 0 | W6: =H6-(H6*0.07) -> #DIV/0! | Y6: =(X6-H6)/H6 -> #DIV/0! | Z6: =F6/F$22 -> 0
A7: MCK | B7: Long | C7: McKesson | D7: 123.3931 | E7: 414.25 | F7: =E7*D7 -> 51115.592 | G7: 50990.97 | H7: =G7/D7 -> 413.24004 | I7: =F7-G7 -> 124.62168 | J7: =E7-H7 -> 1.0099566 | K7: 45104 | L7: =DAYS360(K7,$C$1) -> 24 | M7: =(I7/G7) -> 0.002443995 | N7: 67 | O7: 79 | P7: 95 | Q7: 401.53 | R7: =Q7*0.93 -> 373.4229 | S7: 373.28 | T7: =Q7*1.25 -> 501.9125 | U7: =Q7*1.5 -> 602.295 | V7: =Q7*2 -> 803.06 | W7: =H7-(H7*0.07) -> 384.31324 | X7: 399 | Y7: =(X7-H7)/H7 -> -0.034459495 | Z7: =F7/F$22 -> 0.099867344 | AB7: 45140 | AC7: 84 | AD7: Bought after pullback to 10dma
A8: DXCM | B8: Long | C8: DexCom | D8: 278.2008 | E8: 130.6 | F8: =E8*D8 -> 36333.024 | G8: 35723.77 | H8: =G8/D8 -> 128.41002 | I8: =F8-G8 -> 609.25448 | J8: =E8-H8 -> 2.189981 | K8: 45106 | L8: =DAYS360(K8,$C$1) -> 22 | M8: =(I8/G8) -> 0.017054596 | N8: 56 | O8: 87 | P8: 98 | Q8: 126.44 | R8: =Q8*0.93 -> 117.5892 | S8: 121.79 | T8: =Q8*1.25 -> 158.05 | U8: =Q8*1.5 -> 189.66 | V8: =Q8*2 -> 252.88 | W8: =H8-(H8*0.07) -> 119.42132 | X8: 122.45 | Y8: =(X8-H8)/H8 -> -0.046413971 | Z8: =F8/F$22 -> 0.070985829 | AB8: 45140 | AC8: 96 | AD8: Bought after pullback to 50dma and pivot area.
A9: HXL | B9: Long | C9: Hexcel | D9: 665.9739 | E9: 75.36 | F9: =E9*D9 -> 50187.793 | G9: 51028 | H9: =G9/D9 -> 76.621621 | I9: =F9-G9 -> -840.2069 | J9: =E9-H9 -> -1.2616214 | K9: 45112 | L9: =DAYS360(K9,$C$1) -> 16 | M9: =(I9/G9) -> -0.016465605 | N9: 47 | O9: 85 | P9: 82 | Q9: 74.44 | R9: =Q9*0.93 -> 69.2292 | S9: 70.88 | T9: =Q9*1.25 -> 93.05 | U9: =Q9*1.5 -> 111.66 | V9: =Q9*2 -> 148.88 | W9: =H9-(H9*0.07) -> 71.258108 | X9: 73.25 | Y9: =(X9-H9)/H9 -> -0.044003524 | Z9: =F9/F$22 -> 0.098054653 | AB9: 45131 | AC9: 93 | AD9: Bought after pivot test. Katie recommends also.
A10: SNPS | B10: Long | C10: Synopsys | D10: 115.8536 | E10: 454 | F10: =E10*D10 -> 52597.534 | G10: 51225.83 | H10: =G10/D10 -> 442.16002 | I10: =F10-G10 -> 1371.7044 | J10: =E10-H10 -> 11.839981 | K10: 45117 | L10: =DAYS360(K10,$C$1) -> 11 | M10: =(I10/G10) -> 0.026777592 | N10: 19 | O10: 90 | P10: 90 | Q10: 392.79 | R10: =Q10*0.93 -> 365.2947 | S10: 416.87 | T10: =Q10*1.25 -> 490.9875 | U10: =Q10*1.5 -> 589.185 | V10: =Q10*2 -> 785.58 | W10: =H10-(H10*0.07) -> 411.20882 | X10: 415 | Y10: =(X10-H10)/H10 -> -0.061425769 | Z10: =F10/F$22 -> 0.1027627 | AB10: 45154 | AC10: 96 | AD10: Bought when breaking out of bull flag in volume.
F11: =E11*D11 -> 0 | H11: =G11/D11 -> #DIV/0! | I11: =F11-G11 -> 0 | J11: =E11-H11 -> #DIV/0! | L11: =DAYS360(K11,$C$1) -> 44481 | M11: =(I11/G11) -> #DIV/0! | R11: =Q11*0.93 -> 0 | T11: =Q11*1.25 -> 0 | U11: =Q11*1.5 -> 0 | V11: =Q11*2 -> 0 | W11: =H11-(H11*0.07) -> #DIV/0! | Y11: =(X11-H11)/H11 -> #DIV/0! | Z11: =F11/F$22 -> 0 | AB11: 44581 | AC11: 99
F12: =E12*D12 -> 0 | H12: =G12/D12 -> #DIV/0! | I12: =F12-G12 -> 0 | J12: =E12-H12 -> #DIV/0! | L12: =DAYS360(K12,$C$1) -> 44481 | M12: =(I12/G12) -> #DIV/0! | R12: =Q12*0.93 -> 0 | T12: =Q12*1.25 -> 0 | U12: =Q12*1.5 -> 0 | V12: =Q12*2 -> 0 | W12: =H12-(H12*0.07) -> #DIV/0! | Y12: =(X12-H12)/H12 -> #DIV/0! | Z12: =F12/F$22 -> 0 | AB12: 44568 | AC12: 90
F13: =E13*D13 -> 0 | H13: =G13/D13 -> #DIV/0! | I13: =F13-G13 -> 0 | J13: =E13-H13 -> #DIV/0! | L13: =DAYS360(K13,$C$1) -> 44481 | M13: =(I13/G13) -> #DIV/0! | R13: =Q13*0.93 -> 0 | T13: =Q13*1.25 -> 0 | U13: =Q13*1.5 -> 0 | V13: =Q13*2 -> 0 | W13: =H13-(H13*0.07) -> #DIV/0! | Y13: =(X13-H13)/H13 -> #DIV/0! | Z13: =F13/F$22 -> 0 | AB13: 44601 | AC13: 99
F14: =E14*D14 -> 0 | H14: =G14/D14 -> #DIV/0! | I14: =F14-G14 -> 0 | J14: =E14-H14 -> #DIV/0! | L14: =DAYS360(K14,$C$1) -> 44481 | M14: =(I14/G14) -> #DIV/0! | R14: =Q14*0.93 -> 0 | T14: =Q14*1.25 -> 0 | U14: =Q14*1.5 -> 0 | V14: =Q14*2 -> 0 | W14: =H14-(H14*0.07) -> #DIV/0! | Y14: =(X14-H14)/H14 -> #DIV/0! | Z14: =F14/F$22 -> 0 | AB14: 44610 | AC14: 92
F15: =E15*D15 -> 0 | H15: =G15/D15 -> #DIV/0! | I15: =F15-G15 -> 0 | J15: =E15-H15 -> #DIV/0! | L15: =DAYS360(K15,$C$1) -> 44481 | M15: =(I15/G15) -> #DIV/0! | R15: =Q15*0.93 -> 0 | T15: =Q15*1.25 -> 0 | U15: =Q15*1.5 -> 0 | V15: =Q15*2 -> 0 | W15: =H15-(H15*0.07) -> #DIV/0! | Y15: =(X15-H15)/H15 -> #DIV/0! | Z15: =F15/F$22 -> 0
F16: =E16*D16 -> 0 | H16: =G16/D16 -> #DIV/0! | I16: =F16-G16 -> 0 | J16: =E16-H16 -> #DIV/0! | L16: =DAYS360(K16,$C$1) -> 44481 | M16: =(I16/G16) -> #DIV/0! | R16: =Q16*0.93 -> 0 | T16: =Q16*1.25 -> 0 | U16: =Q16*1.5 -> 0 | V16: =Q16*2 -> 0 | W16: =H16-(H16*0.07) -> #DIV/0! | Y16: =(X16-H16)/H16 -> #DIV/0! | Z16: =F16/F$22 -> 0
A17: BIL | B17: Long | C17: Tbill ETF | D17: 2778.4118 | E17: 91.7 | F17: =E17*D17 -> 254780.36 | G17: 254613.66 | H17: =G17/D17 -> 91.640001 | I17: =F17-G17 -> 166.70206 | J17: =E17-H17 -> 0.059999047 | L17: =DAYS360(K17,$C$1) -> 44481 | M17: =(I17/G17) -> 0.00065472552 | R17: =Q17*0.93 -> 0 | T17: =Q17*1.25 -> 0 | U17: =Q17*1.5 -> 0 | V17: =Q17*2 -> 0 | W17: =H17-(H17*0.07) -> 85.225201 | Y17: =(X17-H17)/H17 -> -1 | Z17: =F17/F$22 -> 0.49777841
A18: SQQQ | B18: Long | C18: QQQ Triple short | D18: 511.2918 | E18: 18.03 | F18: =E18*D18 -> 9218.5912 | G18: 24797.66 | H18: =G18/D18 -> 48.500015 | I18: =F18-G18 -> -15579.069 | J18: =E18-H18 -> -30.470015 | L18: =DAYS360(K18,$C$1) -> 44481 | M18: =(I18/G18) -> -0.62824754 | R18: =Q18*0.93 -> 0 | T18: =Q18*1.25 -> 0 | U18: =Q18*1.5 -> 0 | V18: =Q18*2 -> 0 | W18: =H18-(H18*0.07) -> 45.105014 | Y18: =(X18-H18)/H18 -> -1 | Z18: =F18/F$22 -> 0.018010869
F19: =E19*D19 -> 0 | H19: =G19/D19 -> #DIV/0! | I19: =F19-G19 -> 0 | J19: =E19-H19 -> #DIV/0! | L19: =DAYS360(K19,$C$1) -> 44481 | M19: =(I19/G19) -> #DIV/0! | R19: =Q19*0.93 -> 0 | T19: =Q19*1.25 -> 0 | U19: =Q19*1.5 -> 0 | V19: =Q19*2 -> 0 | W19: =H19-(H19*0.07) -> #DIV/0! | Y19: =(X19-H19)/H19 -> #DIV/0! | Z19: =F19/F$22 -> 0
A20: Sub-Total | F20: =SUM(F6:F19) -> 454232.9 | G20: =SUM(G6:G19) -> 468379.89 | I20: =SUM(I6:I19) -> -14146.993
D21: Cash, other | F21: 57602 | G21: =F21/F22 -> 0.1125402
D22: Total | F22: =SUM(F20:F21) -> 511834.9
H23: Last week's close | I23: 513598.81
H24: Week's change | I24: =(F22-I23-F25)/I23 -> -0.0034344183
M26: days
A27: 2023 Closed Trades - Managed Acct | D27: Qty | E27: Cost/sh | F27: $ cost | G27: Proc/sh | H27: $Proc | I27: Profit/loss | J27: % | K27: Date purch | L27: Date sold | M27: held | P27: Comments

Sheet 07-28-23
C1: 45135
C3: MANAGED ACCT | X3: Current | AC3: IBD
H4: Cost | J4: P/L | N4: Group | P4: EPS | R4: pivot | S4: last | W4: cost | X4: Stop | Y4: Stop | Z4: % | AB4: EPS | AC4: Comp
A5: Symbol | B5: Position | C5: Name | D5: Qty | E5: Current | F5: Value | G5: Cost | H5: per share | I5: P/L $ | J5: per sh | K5: Date purch | L5: days held | M5: % incr | N5: Rank | O5: RS | P5: RS | Q5: pivot | R5: -0.07 | S5: low | T5: 0.25 | U5: 0.5 | V5: 1 | W5: -0.07 | X5: Loss | Y5: Loss% | Z5: of port | AB5: Due | AC5: Rank
F6: =E6*D6 -> 0 | H6: =G6/D6 -> #DIV/0! | I6: =F6-G6 -> 0 | J6: =E6-H6 -> #DIV/0! | L6: =DAYS360(K6,$C$1) -> 44488 | M6: =(I6/G6) -> #DIV/0! | R6: =Q6*0.93 -> 0 | T6: =Q6*1.25 -> 0 | U6: =Q6*1.5 -> 0 | V6: =Q6*2 -> 0 | W6: =H6-(H6*0.07) -> #DIV/0! | Y6: =(X6-H6)/H6 -> #DIV/0! | Z6: =F6/F$16 -> 0
A7: MCK | B7: Long | C7: McKesson | D7: 123.3931 | E7: 402.97 | F7: =E7*D7 -> 49723.718 | G7: 50990.97 | H7: =G7/D7 -> 413.24004 | I7: =F7-G7 -> -1267.2525 | J7: =E7-H7 -> -10.270043 | K7: 45104 | L7: =DAYS360(K7,$C$1) -> 31 | M7: =(I7/G7) -> -0.024852488 | N7: 74 | O7: 72 | P7: 95 | Q7: 401.53 | R7: =Q7*0.93 -> 373.4229 | S7: 373.28 | T7: =Q7*1.25 -> 501.9125 | U7: =Q7*1.5 -> 602.295 | V7: =Q7*2 -> 803.06 | W7: =H7-(H7*0.07) -> 384.31324 | X7: 399 | Y7: =(X7-H7)/H7 -> -0.034459495 | Z7: =F7/F$16 -> 0.098356884 | AB7: 45140 | AC7: 78 | AD7: Bought after pullback to 10dma
A8: DXCM | B8: Long | C8: DexCom | D8: 278.2008 | E8: 132.38 | F8: =E8*D8 -> 36828.222 | G8: 35723.77 | H8: =G8/D8 -> 128.41002 | I8: =F8-G8 -> 1104.4519 | J8: =E8-H8 -> 3.969981 | K8: 45106 | L8: =DAYS360(K8,$C$1) -> 29 | M8: =(I8/G8) -> 0.030916443 | N8: 60 | O8: 86 | P8: 98 | Q8: 126.44 | R8: =Q8*0.93 -> 117.5892 | S8: 126.81 | T8: =Q8*1.25 -> 158.05 | U8: =Q8*1.5 -> 189.66 | V8: =Q8*2 -> 252.88 | W8: =H8-(H8*0.07) -> 119.42132 | X8: 124 | Y8: =(X8-H8)/H8 -> -0.034343262 | Z8: =F8/F$16 -> 0.072848719 | AB8: 45140 | AC8: 94 | AD8: Bought after pullback to 50dma and pivot area.
A9: SNPS | B9: Long | C9: Synopsys | D9: 115.8536 | E9: 450.94 | F9: =E9*D9 -> 52243.022 | G9: 51225.83 | H9: =G9/D9 -> 442.16002 | I9: =F9-G9 -> 1017.1924 | J9: =E9-H9 -> 8.7799808 | K9: 45117 | L9: =DAYS360(K9,$C$1) -> 18 | M9: =(I9/G9) -> 0.019857021 | N9: 31 | O9: 91 | P9: 91 | Q9: 392.79 | R9: =Q9*0.93 -> 365.2947 | S9: 416.87 | T9: =Q9*1.25 -> 490.9875 | U9: =Q9*1.5 -> 589.185 | V9: =Q9*2 -> 785.58 | W9: =H9-(H9*0.07) -> 411.20882 | X9: 415 | Y9: =(X9-H9)/H9 -> -0.061425769 | Z9: =F9/F$16 -> 0.10334024 | AB9: 45154 | AC9: 97 | AD9: Bought when breaking out of bull flag in volume.
B10: Long | C10: MNSO | D10: 1211.7123 | E10: 21 | F10: =E10*D10 -> 25445.958 | G10: 25318.9 | H10: =G10/D10 -> 20.895142 | I10: =F10-G10 -> 127.0583 | J10: =E10-H10 -> 0.10485847 | K10: 45135 | L10: =DAYS360(K10,$C$1) -> 0 | M10: =(I10/G10) -> 0.0050183183 | N10: 148 | O10: 99 | P10: 98 | Q10: 19.48 | R10: =Q10*0.93 -> 18.1164 | S10: 17.57 | T10: =Q10*1.25 -> 24.35 | U10: =Q10*1.5 -> 29.22 | V10: =Q10*2 -> 38.96 | W10: =H10-(H10*0.07) -> 19.432482 | X10: 18.12 | Y10: =(X10-H10)/H10 -> -0.13281277 | Z10: =F10/F$16 -> 0.05033383 | AB10: 45162 | AC10: 99 | AD10: Bought after 07/24 b/o.
A11: BIL | B11: Long | C11: Tbill ETF | D11: 2778.4118 | E11: 91.79 | F11: =E11*D11 -> 255030.42 | G11: 254613.66 | H11: =G11/D11 -> 91.640001 | I11: =F11-G11 -> 416.75912 | J11: =E11-H11 -> 0.14999905 | L11: =DAYS360(K11,$C$1) -> 44488 | M11: =(I11/G11) -> 0.0016368294 | R11: =Q11*0.93 -> 0 | T11: =Q11*1.25 -> 0 | U11: =Q11*1.5 -> 0 | V11: =Q11*2 -> 0 | W11: =H11-(H11*0.07) -> 85.225201 | Y11: =(X11-H11)/H11 -> -1 | Z11: =F11/F$16 -> 0.50446746
A12: SQQQ | B12: Long | C12: QQQ Triple short | D12: 511.2918 | E12: 16.96 | F12: =E12*D12 -> 8671.5089 | G12: 24797.66 | H12: =G12/D12 -> 48.500015 | I12: =F12-G12 -> -16126.151 | J12: =E12-H12 -> -31.540015 | L12: =DAYS360(K12,$C$1) -> 44488 | M12: =(I12/G12) -> -0.65030939 | R12: =Q12*0.93 -> 0 | T12: =Q12*1.25 -> 0 | U12: =Q12*1.5 -> 0 | V12: =Q12*2 -> 0 | W12: =H12-(H12*0.07) -> 45.105014 | Y12: =(X12-H12)/H12 -> -1 | Z12: =F12/F$16 -> 0.017152832
F13: =E13*D13 -> 0 | H13: =G13/D13 -> #DIV/0! | I13: =F13-G13 -> 0 | J13: =E13-H13 -> #DIV/0! | L13: =DAYS360(K13,$C$1) -> 44488 | M13: =(I13/G13) -> #DIV/0! | R13: =Q13*0.93 -> 0 | T13: =Q13*1.25 -> 0 | U13: =Q13*1.5 -> 0 | V13: =Q13*2 -> 0 | W13: =H13-(H13*0.07) -> #DIV/0! | Y13: =(X13-H13)/H13 -> #DIV/0! | Z13: =F13/F$16 -> 0
A14: Sub-Total | F14: =SUM(F6:F13) -> 427942.85 | G14: =SUM(G6:G13) -> 442670.79 | I14: =SUM(I6:I13) -> -14727.942
D15: Cash, other | F15: 77601 | G15: =F15/F16 -> 0.15350004
D16: Total | F16: =SUM(F14:F15) -> 505543.85
H17: Last week's close | I17: 511834.9
H18: Week's change | I18: =(F16-I17-F19)/I17 -> -0.012291174
M20: days
A21: 2023 Closed Trades - Managed Acct | D21: Qty | E21: Cost/sh | F21: $ cost | G21: Proc/sh | H21: $Proc | I21: Profit/loss | J21: % | K21: Date purch | L21: Date sold | M21: held | P21: Comments
A23: HXL | B23: Long | C23: Hexcel | D23: 665.9739 | E23: =F23/D23 -> 76.621621 | F23: 51028 | G23: 45324.79 | H23: =G23/D23 -> 68.057907 | I23: =G23-F23 -> -5703.21 | J23: =I23/F23 -> -0.11176629 | K23: 45106 | L23: 45132 | O23: Bad reaction to EPS report. Stopped out.

Sheet 08-04-23
C1: 45142
C3: MANAGED ACCT | X3: Current | AC3: IBD
H4: Cost | J4: P/L | N4: Group | P4: EPS | R4: pivot | S4: last | W4: cost | X4: Stop | Y4: Stop | Z4: % | AB4: EPS | AC4: Comp
A5: Symbol | B5: Position | C5: Name | D5: Qty | E5: Current | F5: Value | G5: Cost | H5: per share | I5: P/L $ | J5: per sh | K5: Date purch | L5: days held | M5: % incr | N5: Rank | O5: RS | P5: RS | Q5: pivot | R5: -0.07 | S5: low | T5: 0.25 | U5: 0.5 | V5: 1 | W5: -0.07 | X5: Loss | Y5: Loss% | Z5: of port | AB5: Due | AC5: Rank
F6: =E6*D6 -> 0 | H6: =G6/D6 -> #DIV/0! | I6: =F6-G6 -> 0 | J6: =E6-H6 -> #DIV/0! | L6: =DAYS360(K6,$C$1) -> 44494 | M6: =(I6/G6) -> #DIV/0! | R6: =Q6*0.93 -> 0 | T6: =Q6*1.25 -> 0 | U6: =Q6*1.5 -> 0 | V6: =Q6*2 -> 0 | W6: =H6-(H6*0.07) -> #DIV/0! | Y6: =(X6-H6)/H6 -> #DIV/0! | Z6: =F6/F$16 -> 0
F7: =E7*D7 -> 0 | H7: =G7/D7 -> #DIV/0! | I7: =F7-G7 -> 0 | J7: =E7-H7 -> #DIV/0! | L7: =DAYS360(K7,$C$1) -> 44494 | M7: =(I7/G7) -> #DIV/0! | R7: =Q7*0.93 -> 0 | T7: =Q7*1.25 -> 0 | U7: =Q7*1.5 -> 0 | V7: =Q7*2 -> 0 | W7: =H7-(H7*0.07) -> #DIV/0! | Y7: =(X7-H7)/H7 -> #DIV/0! | Z7: =F7/F$16 -> 0
F8: =E8*D8 -> 0 | H8: =G8/D8 -> #DIV/0! | I8: =F8-G8 -> 0 | J8: =E8-H8 -> #DIV/0! | L8: =DAYS360(K8,$C$1) -> 44494 | M8: =(I8/G8) -> #DIV/0! | R8: =Q8*0.93 -> 0 | T8: =Q8*1.25 -> 0 | U8: =Q8*1.5 -> 0 | V8: =Q8*2 -> 0 | W8: =H8-(H8*0.07) -> #DIV/0! | Y8: =(X8-H8)/H8 -> #DIV/0! | Z8: =F8/F$16 -> 0
A9: SNPS | B9: Long | C9: Synopsys | D9: 115.8536 | E9: 441.42 | F9: =E9*D9 -> 51140.096 | G9: 51225.83 | H9: =G9/D9 -> 442.16002 | I9: =F9-G9 -> -85.733888 | J9: =E9-H9 -> -0.7400192 | K9: 45117 | L9: =DAYS360(K9,$C$1) -> 24 | M9: =(I9/G9) -> -0.0016736457 | N9: 39 | O9: 90 | P9: 90 | Q9: 392.79 | R9: =Q9*0.93 -> 365.2947 | S9: 416.87 | T9: =Q9*1.25 -> 490.9875 | U9: =Q9*1.5 -> 589.185 | V9: =Q9*2 -> 785.58 | W9: =H9-(H9*0.07) -> 411.20882 | X9: 415 | Y9: =(X9-H9)/H9 -> -0.061425769 | Z9: =F9/F$16 -> 0.10178489 | AB9: 45154 | AC9: 96 | AD9: Bought when breaking out of bull flag in volume.
A10: MNSO | B10: Long | C10: Minoso | D10: 1211.7123 | E10: 20.97 | F10: =E10*D10 -> 25409.607 | G10: 25318.9 | H10: =G10/D10 -> 20.895142 | I10: =F10-G10 -> 90.706931 | J10: =E10-H10 -> 0.074858472 | K10: 45135 | L10: =DAYS360(K10,$C$1) -> 6 | M10: =(I10/G10) -> 0.0035825779 | N10: 150 | O10: 99 | P10: 98 | Q10: 19.48 | R10: =Q10*0.93 -> 18.1164 | S10: 17.57 | T10: =Q10*1.25 -> 24.35 | U10: =Q10*1.5 -> 29.22 | V10: =Q10*2 -> 38.96 | W10: =H10-(H10*0.07) -> 19.432482 | X10: 18.12 | Y10: =(X10-H10)/H10 -> -0.13281277 | Z10: =F10/F$16 -> 0.050573118 | AB10: 45162 | AC10: 95 | AD10: Bought after 07/24 b/o.
A11: BIL | B11: Long | C11: Tbill ETF | D11: 2778.4118 | E11: 91.5 | F11: =E11*D11 -> 254224.68 | G11: 254613.66 | H11: =G11/D11 -> 91.640001 | I11: =F11-G11 -> -388.9803 | J11: =E11-H11 -> -0.14000095 | L11: =DAYS360(K11,$C$1) -> 44494 | M11: =(I11/G11) -> -0.0015277275 | R11: =Q11*0.93 -> 0 | T11: =Q11*1.25 -> 0 | U11: =Q11*1.5 -> 0 | V11: =Q11*2 -> 0 | W11: =H11-(H11*0.07) -> 85.225201 | Y11: =(X11-H11)/H11 -> -1 | Z11: =F11/F$16 -> 0.50598715
A12: SQQQ | B12: Long | C12: QQQ Triple short | D12: 511.2918 | E12: 18.57 | F12: =E12*D12 -> 9494.6887 | G12: 24797.66 | H12: =G12/D12 -> 48.500015 | I12: =F12-G12 -> -15302.971 | J12: =E12-H12 -> -29.930015 | L12: =DAYS360(K12,$C$1) -> 44494 | M12: =(I12/G12) -> -0.61711352 | R12: =Q12*0.93 -> 0 | T12: =Q12*1.25 -> 0 | U12: =Q12*1.5 -> 0 | V12: =Q12*2 -> 0 | W12: =H12-(H12*0.07) -> 45.105014 | Y12: =(X12-H12)/H12 -> -1 | Z12: =F12/F$16 -> 0.01889742
F13: =E13*D13 -> 0 | H13: =G13/D13 -> #DIV/0! | I13: =F13-G13 -> 0 | J13: =E13-H13 -> #DIV/0! | L13: =DAYS360(K13,$C$1) -> 44494 | M13: =(I13/G13) -> #DIV/0! | R13: =Q13*0.93 -> 0 | T13: =Q13*1.25 -> 0 | U13: =Q13*1.5 -> 0 | V13: =Q13*2 -> 0 | W13: =H13-(H13*0.07) -> #DIV/0! | Y13: =(X13-H13)/H13 -> #DIV/0! | Z13: =F13/F$16 -> 0
A14: Sub-Total | F14: =SUM(F6:F13) -> 340269.07 | G14: =SUM(G6:G13) -> 355956.05 | I14: =SUM(I6:I13) -> -15686.979
D15: Cash, other | F15: 162164 | G15: =F15/F16 -> 0.32275742
D16: Total | F16: =SUM(F14:F15) -> 502433.07
H17: Last week's close | I17: 505543.83
H18: Week's change | I18: =(F16-I17-F19)/I17 -> -0.0061532915
M20: days
A21: 2023 Closed Trades - Managed Acct | D21: Qty | E21: Cost/sh | F21: $ cost | G21: $Proc | H21: Proc/sh | I21: Profit/loss | J21: % | K21: Date purch | L21: Date sold | M21: held | P21: Comments
A23: HXL | B23: Long | C23: Hexcel | D23: 665.9739 | E23: =F23/D23 -> 76.621621 | F23: 51028 | G23: 45324.79 | H23: =G23/D23 -> 68.057907 | I23: =G23-F23 -> -5703.21 | J23: =I23/F23 -> -0.11176629 | K23: 45106 | L23: 45132 | O23: Bad reaction to EPS report. Stopped out.
A24: MCK | B24: Long | C24: McKesson | D24: 123.3931 | E24: =F24/D24 -> 413.24004 | F24: 50990.97 | G24: 48894.94 | H24: =G24/D24 -> 396.25344 | I24: =G24-F24 -> -2096.03 | J24: =I24/F24 -> -0.041105906 | K24: 45104 | L24: 45138 | O24: Broke original stop and 50dma. EPS coming in a few days.
A25: DXCM | B25: Long | C25: DexCom | D25: 278.2008 | E25: =F25/D25 -> 128.41002 | F25: 35723.77 | G25: 34855.72 | H25: =G25/D25 -> 125.28979 | I25: =G25-F25 -> -868.05 | J25: =I25/F25 -> -0.024298947 | K25: 45106 | L25: 45138 | O25: The positive reaction to EPS report was rejected at the old high and reversed. Didn't like the action.

Sheet 08-11-23
C1: 45149
C3: MANAGED ACCT | X3: Current | AC3: IBD
H4: Cost | J4: P/L | N4: Group | P4: EPS | R4: pivot | S4: last | W4: cost | X4: Stop | Y4: Stop | Z4: % | AB4: EPS | AC4: Comp
A5: Symbol | B5: Position | C5: Name | D5: Qty | E5: Current | F5: Value | G5: Cost | H5: per share | I5: P/L $ | J5: per sh | K5: Date purch | L5: days held | M5: % incr | N5: Rank | O5: RS | P5: RS | Q5: pivot | R5: -0.07 | S5: low | T5: 0.25 | U5: 0.5 | V5: 1 | W5: -0.07 | X5: Loss | Y5: Loss% | Z5: of port | AB5: Due | AC5: Rank
F6: =E6*D6 -> 0 | H6: =G6/D6 -> #DIV/0! | I6: =F6-G6 -> 0 | J6: =E6-H6 -> #DIV/0! | L6: =DAYS360(K6,$C$1) -> 44501 | M6: =(I6/G6) -> #DIV/0! | R6: =Q6*0.93 -> 0 | T6: =Q6*1.25 -> 0 | U6: =Q6*1.5 -> 0 | V6: =Q6*2 -> 0 | W6: =H6-(H6*0.07) -> #DIV/0! | Y6: =(X6-H6)/H6 -> #DIV/0! | Z6: =F6/F$16 -> 0
F7: =E7*D7 -> 0 | H7: =G7/D7 -> #DIV/0! | I7: =F7-G7 -> 0 | J7: =E7-H7 -> #DIV/0! | L7: =DAYS360(K7,$C$1) -> 44501 | M7: =(I7/G7) -> #DIV/0! | R7: =Q7*0.93 -> 0 | T7: =Q7*1.25 -> 0 | U7: =Q7*1.5 -> 0 | V7: =Q7*2 -> 0 | W7: =H7-(H7*0.07) -> #DIV/0! | Y7: =(X7-H7)/H7 -> #DIV/0! | Z7: =F7/F$16 -> 0
F8: =E8*D8 -> 0 | H8: =G8/D8 -> #DIV/0! | I8: =F8-G8 -> 0 | J8: =E8-H8 -> #DIV/0! | L8: =DAYS360(K8,$C$1) -> 44501 | M8: =(I8/G8) -> #DIV/0! | R8: =Q8*0.93 -> 0 | T8: =Q8*1.25 -> 0 | U8: =Q8*1.5 -> 0 | V8: =Q8*2 -> 0 | W8: =H8-(H8*0.07) -> #DIV/0! | Y8: =(X8-H8)/H8 -> #DIV/0! | Z8: =F8/F$16 -> 0
A9: SNPS | B9: Long | C9: Synopsys | D9: 115.8536 | E9: 428.46 | F9: =E9*D9 -> 49638.633 | G9: 51225.83 | H9: =G9/D9 -> 442.16002 | I9: =F9-G9 -> -1587.1965 | J9: =E9-H9 -> -13.700019 | K9: 45117 | L9: =DAYS360(K9,$C$1) -> 31 | M9: =(I9/G9) -> -0.030984301 | N9: 64 | O9: 87 | P9: 90 | Q9: 392.79 | R9: =Q9*0.93 -> 365.2947 | S9: 416.87 | T9: =Q9*1.25 -> 490.9875 | U9: =Q9*1.5 -> 589.185 | V9: =Q9*2 -> 785.58 | W9: =H9-(H9*0.07) -> 411.20882 | X9: 415 | Y9: =(X9-H9)/H9 -> -0.061425769 | Z9: =F9/F$16 -> 0.099218525 | AB9: 45154 | AC9: 93 | AD9: Bought when breaking out of bull flag in volume.
A10: MNSO | B10: Long | C10: Minoso | D10: =1211.7123+804.6763 -> 2016.3886 | E10: 19.12 | F10: =E10*D10 -> 38553.35 | G10: =25318.9+15999 -> 41317.9 | H10: =G10/D10 -> 20.49104 | I10: =F10-G10 -> -2764.55 | J10: =E10-H10 -> -1.3710403 | K10: 45135 | L10: =DAYS360(K10,$C$1) -> 13 | M10: =(I10/G10) -> -0.066909256 | N10: 161 | O10: 98 | P10: 98 | Q10: 19.48 | R10: =Q10*0.93 -> 18.1164 | S10: 17.57 | T10: =Q10*1.25 -> 24.35 | U10: =Q10*1.5 -> 29.22 | V10: =Q10*2 -> 38.96 | W10: =H10-(H10*0.07) -> 19.056667 | X10: 18.12 | Y10: =(X10-H10)/H10 -> -0.11571107 | Z10: =F10/F$16 -> 0.077061076 | AB10: 45162 | AC10: 92 | AD10: Bought after 07/24 b/o. Added at the 21dema.
A11: BIL | B11: Long | C11: Tbill ETF | D11: 2778.4118 | E11: 91.59 | F11: =E11*D11 -> 254474.74 | G11: 254613.66 | H11: =G11/D11 -> 91.640001 | I11: =F11-G11 -> -138.92324 | J11: =E11-H11 -> -0.050000953 | L11: =DAYS360(K11,$C$1) -> 44501 | M11: =(I11/G11) -> -0.00054562366 | R11: =Q11*0.93 -> 0 | T11: =Q11*1.25 -> 0 | U11: =Q11*1.5 -> 0 | V11: =Q11*2 -> 0 | W11: =H11-(H11*0.07) -> 85.225201 | Y11: =(X11-H11)/H11 -> -1 | Z11: =F11/F$16 -> 0.50864833
A12: SQQQ | B12: Long | C12: QQQ Triple short | D12: 511.2918 | E12: 19.51 | F12: =E12*D12 -> 9975.303 | G12: 24797.66 | H12: =G12/D12 -> 48.500015 | I12: =F12-G12 -> -14822.357 | J12: =E12-H12 -> -28.990015 | L12: =DAYS360(K12,$C$1) -> 44501 | M12: =(I12/G12) -> -0.59773208 | R12: =Q12*0.93 -> 0 | T12: =Q12*1.25 -> 0 | U12: =Q12*1.5 -> 0 | V12: =Q12*2 -> 0 | W12: =H12-(H12*0.07) -> 45.105014 | Y12: =(X12-H12)/H12 -> -1 | Z12: =F12/F$16 -> 0.019938801
F13: =E13*D13 -> 0 | H13: =G13/D13 -> #DIV/0! | I13: =F13-G13 -> 0 | J13: =E13-H13 -> #DIV/0! | L13: =DAYS360(K13,$C$1) -> 44501 | M13: =(I13/G13) -> #DIV/0! | R13: =Q13*0.93 -> 0 | T13: =Q13*1.25 -> 0 | U13: =Q13*1.5 -> 0 | V13: =Q13*2 -> 0 | W13: =H13-(H13*0.07) -> #DIV/0! | Y13: =(X13-H13)/H13 -> #DIV/0! | Z13: =F13/F$16 -> 0
A14: Sub-Total | F14: =SUM(F6:F13) -> 352642.02 | G14: =SUM(G6:G13) -> 371955.05 | I14: =SUM(I6:I13) -> -19313.027
D15: Cash, other | F15: 147654 | G15: =F15/F16 -> 0.29513327
D16: Total | F16: =SUM(F14:F15) -> 500296.02
H17: Last week's close | I17: 502433.07 | K17: 45107 | L17: 509801
H18: Week's change | I18: =(F16-I17-F19)/I17 -> -0.0042533958 | K18: chg % | L18: =(F16-L17)/L17 -> -0.018644484
M20: days
A21: 2023 Closed Trades - Managed Acct | D21: Qty | E21: Cost/sh | F21: $ cost | G21: $Proc | H21: Proc/sh | I21: Profit/loss | J21: % | K21: Date purch | L21: Date sold | M21: held | P21: Comments
A23: HXL | B23: Long | C23: Hexcel | D23: 665.9739 | E23: =F23/D23 -> 76.621621 | F23: 51028 | G23: 45324.79 | H23: =G23/D23 -> 68.057907 | I23: =G23-F23 -> -5703.21 | J23: =I23/F23 -> -0.11176629 | K23: 45106 | L23: 45132 | O23: Bad reaction to EPS report. Stopped out.
A24: MCK | B24: Long | C24: McKesson | D24: 123.3931 | E24: =F24/D24 -> 413.24004 | F24: 50990.97 | G24: 48894.94 | H24: =G24/D24 -> 396.25344 | I24: =G24-F24 -> -2096.03 | J24: =I24/F24 -> -0.041105906 | K24: 45104 | L24: 45138 | O24: Broke original stop and 50dma. EPS coming in a few days.
A25: DXCM | B25: Long | C25: DexCom | D25: 278.2008 | E25: =F25/D25 -> 128.41002 | F25: 35723.77 | G25: 34855.72 | H25: =G25/D25 -> 125.28979 | I25: =G25-F25 -> -868.05 | J25: =I25/F25 -> -0.024298947 | K25: 45106 | L25: 45138 | O25: The positive reaction to EPS report was rejected at the old high and reversed. Didn't like the action.

Sheet 08-18-23
C1: 45156
C3: MANAGED ACCT | X3: Current | AC3: IBD
H4: Cost | J4: P/L | N4: Group | P4: EPS | R4: pivot | S4: last | W4: cost | X4: Stop | Y4: Stop | Z4: % | AB4: EPS | AC4: Comp
A5: Symbol | B5: Position | C5: Name | D5: Qty | E5: Current | F5: Value | G5: Cost | H5: per share | I5: P/L $ | J5: per sh | K5: Date purch | L5: days held | M5: % incr | N5: Rank | O5: RS | P5: RS | Q5: pivot | R5: -0.07 | S5: low | T5: 0.25 | U5: 0.5 | V5: 1 | W5: -0.07 | X5: Loss | Y5: Loss% | Z5: of port | AB5: Due | AC5: Rank
F6: =E6*D6 -> 0 | H6: =G6/D6 -> #DIV/0! | I6: =F6-G6 -> 0 | J6: =E6-H6 -> #DIV/0! | L6: =DAYS360(K6,$C$1) -> 44508 | M6: =(I6/G6) -> #DIV/0! | R6: =Q6*0.93 -> 0 | T6: =Q6*1.25 -> 0 | U6: =Q6*1.5 -> 0 | V6: =Q6*2 -> 0 | W6: =H6-(H6*0.07) -> #DIV/0! | Y6: =(X6-H6)/H6 -> #DIV/0! | Z6: =F6/F$16 -> 0
F7: =E7*D7 -> 0 | H7: =G7/D7 -> #DIV/0! | I7: =F7-G7 -> 0 | J7: =E7-H7 -> #DIV/0! | L7: =DAYS360(K7,$C$1) -> 44508 | M7: =(I7/G7) -> #DIV/0! | R7: =Q7*0.93 -> 0 | T7: =Q7*1.25 -> 0 | U7: =Q7*1.5 -> 0 | V7: =Q7*2 -> 0 | W7: =H7-(H7*0.07) -> #DIV/0! | Y7: =(X7-H7)/H7 -> #DIV/0! | Z7: =F7/F$16 -> 0
A8: AIT | B8: Long | C8: Applied Ind Tec | D8: 266.8733 | E8: 147.4 | F8: =E8*D8 -> 39337.124 | G8: 40425.83 | H8: =G8/D8 -> 151.47948 | I8: =F8-G8 -> -1088.7056 | J8: =E8-H8 -> -4.0794848 | K8: 45153 | L8: =DAYS360(K8,$C$1) -> 3 | M8: =(I8/G8) -> -0.026930939 | N8: 110 | O8: 88 | P8: 94 | Q8: 150.07 | R8: =Q8*0.93 -> 139.5651 | S8: 138.38 | T8: =Q8*1.25 -> 187.5875 | U8: =Q8*1.5 -> 225.105 | V8: =Q8*2 -> 300.14 | W8: =H8-(H8*0.07) -> 140.87592 | X8: 145.2 | Y8: =(X8-H8)/H8 -> -0.041454358 | Z8: =F8/F$16 -> 0.078368319 | AB8: 45225 | AC8: 91 | AD8: Bought at pivot test area.
A9: SNPS | B9: Long | C9: Synopsys | D9: 115.8536 | E9: 426.02 | F9: =E9*D9 -> 49355.951 | G9: 51225.83 | H9: =G9/D9 -> 442.16002 | I9: =F9-G9 -> -1869.8793 | J9: =E9-H9 -> -16.140019 | K9: 45117 | L9: =DAYS360(K9,$C$1) -> 38 | M9: =(I9/G9) -> -0.036502665 | N9: 77 | O9: 88 | P9: 95 | Q9: 392.79 | R9: =Q9*0.93 -> 365.2947 | S9: 416.87 | T9: =Q9*1.25 -> 490.9875 | U9: =Q9*1.5 -> 589.185 | V9: =Q9*2 -> 785.58 | W9: =H9-(H9*0.07) -> 411.20882 | X9: 415 | Y9: =(X9-H9)/H9 -> -0.061425769 | Z9: =F9/F$16 -> 0.098328054 | AB9: 45259 | AC9: 97 | AD9: Bought when breaking out of bull flag in volume.
A10: MNSO | B10: Long | C10: Minoso | D10: =1211.7123+804.6763 -> 2016.3886 | E10: 20.15 | F10: =E10*D10 -> 40630.23 | G10: =25318.9+15999 -> 41317.9 | H10: =G10/D10 -> 20.49104 | I10: =F10-G10 -> -687.66971 | J10: =E10-H10 -> -0.34104027 | K10: 45135 | L10: =DAYS360(K10,$C$1) -> 20 | M10: =(I10/G10) -> -0.016643385 | N10: 144 | O10: 99 | P10: 98 | Q10: 19.48 | R10: =Q10*0.93 -> 18.1164 | S10: 17.57 | T10: =Q10*1.25 -> 24.35 | U10: =Q10*1.5 -> 29.22 | V10: =Q10*2 -> 38.96 | W10: =H10-(H10*0.07) -> 19.056667 | X10: 18.12 | Y10: =(X10-H10)/H10 -> -0.11571107 | Z10: =F10/F$16 -> 0.080944474 | AB10: 45160 | AC10: 96 | AD10: Bought after 07/24 b/o. Added at the 21dema.
A11: BIL | B11: Long | C11: Tbill ETF | D11: 2778.4118 | E11: 91.68 | F11: =E11*D11 -> 254724.79 | G11: 254613.66 | H11: =G11/D11 -> 91.640001 | I11: =F11-G11 -> 111.13382 | J11: =E11-H11 -> 0.039999047 | L11: =DAYS360(K11,$C$1) -> 44508 | M11: =(I11/G11) -> 0.00043648021 | R11: =Q11*0.93 -> 0 | T11: =Q11*1.25 -> 0 | U11: =Q11*1.5 -> 0 | V11: =Q11*2 -> 0 | W11: =H11-(H11*0.07) -> 85.225201 | Y11: =(X11-H11)/H11 -> -1 | Z11: =F11/F$16 -> 0.50746856
A12: SQQQ | B12: Long | C12: QQQ Triple short | D12: 511.2918 | E12: 20.88 | F12: =E12*D12 -> 10675.773 | G12: 24797.66 | H12: =G12/D12 -> 48.500015 | I12: =F12-G12 -> -14121.887 | J12: =E12-H12 -> -27.620015 | L12: =DAYS360(K12,$C$1) -> 44508 | M12: =(I12/G12) -> -0.56948467 | R12: =Q12*0.93 -> 0 | T12: =Q12*1.25 -> 0 | U12: =Q12*1.5 -> 0 | V12: =Q12*2 -> 0 | W12: =H12-(H12*0.07) -> 45.105014 | Y12: =(X12-H12)/H12 -> -1 | Z12: =F12/F$16 -> 0.021268519
F13: =E13*D13 -> 0 | H13: =G13/D13 -> #DIV/0! | I13: =F13-G13 -> 0 | J13: =E13-H13 -> #DIV/0! | L13: =DAYS360(K13,$C$1) -> 44508 | M13: =(I13/G13) -> #DIV/0! | R13: =Q13*0.93 -> 0 | T13: =Q13*1.25 -> 0 | U13: =Q13*1.5 -> 0 | V13: =Q13*2 -> 0 | W13: =H13-(H13*0.07) -> #DIV/0! | Y13: =(X13-H13)/H13 -> #DIV/0! | Z13: =F13/F$16 -> 0
A14: Sub-Total | F14: =SUM(F6:F13) -> 394723.87 | G14: =SUM(G6:G13) -> 412380.88 | I14: =SUM(I6:I13) -> -17657.008
D15: Cash, other | F15: 107228 | G15: =F15/F16 -> 0.21362207
D16: Total | F16: =SUM(F14:F15) -> 501951.87
H17: Last week's close | I17: 500296.07 | K17: 45107 | L17: 509801
H18: Week's change | I18: =(F16-I17-F19)/I17 -> 0.0033096442 | K18: chg % | L18: =(F16-L17)/L17 -> -0.015396455
M20: days
A21: 2023 Closed Trades - Managed Acct | D21: Qty | E21: Cost/sh | F21: $ cost | G21: $Proc | H21: Proc/sh | I21: Profit/loss | J21: % | K21: Date purch | L21: Date sold | M21: held | P21: Comments
A23: HXL | B23: Long | C23: Hexcel | D23: 665.9739 | E23: =F23/D23 -> 76.621621 | F23: 51028 | G23: 45324.79 | H23: =G23/D23 -> 68.057907 | I23: =G23-F23 -> -5703.21 | J23: =I23/F23 -> -0.11176629 | K23: 45106 | L23: 45132 | O23: Bad reaction to EPS report. Stopped out.
A24: MCK | B24: Long | C24: McKesson | D24: 123.3931 | E24: =F24/D24 -> 413.24004 | F24: 50990.97 | G24: 48894.94 | H24: =G24/D24 -> 396.25344 | I24: =G24-F24 -> -2096.03 | J24: =I24/F24 -> -0.041105906 | K24: 45104 | L24: 45138 | O24: Broke original stop and 50dma. EPS coming in a few days.
A25: DXCM | B25: Long | C25: DexCom | D25: 278.2008 | E25: =F25/D25 -> 128.41002 | F25: 35723.77 | G25: 34855.72 | H25: =G25/D25 -> 125.28979 | I25: =G25-F25 -> -868.05 | J25: =I25/F25 -> -0.024298947 | K25: 45106 | L25: 45138 | O25: The positive reaction to EPS report was rejected at the old high and reversed. Didn't like the action.
J31: Avg
H32: # of losses | I32: 3 | J32: =(J23+J24+J25)/3 -> -0.059057046

Sheet 08-25-23
C1: 45163
C3: MANAGED ACCT | X3: Current | AC3: IBD
H4: Cost | J4: P/L | N4: Group | P4: EPS | R4: pivot | S4: last | W4: cost | X4: Stop | Y4: Stop | Z4: % | AB4: EPS | AC4: Comp
A5: Symbol | B5: Position | C5: Name | D5: Qty | E5: Current | F5: Value | G5: Cost | H5: per share | I5: P/L $ | J5: per sh | K5: Date purch | L5: days held | M5: % incr | N5: Rank | O5: RS | P5: RS | Q5: pivot | R5: -0.07 | S5: low | T5: 0.25 | U5: 0.5 | V5: 1 | W5: -0.07 | X5: Loss | Y5: Loss% | Z5: of port | AB5: Due | AC5: Rank
F6: =E6*D6 -> 0 | H6: =G6/D6 -> #DIV/0! | I6: =F6-G6 -> 0 | J6: =E6-H6 -> #DIV/0! | L6: =DAYS360(K6,$C$1) -> 44515 | M6: =(I6/G6) -> #DIV/0! | R6: =Q6*0.93 -> 0 | T6: =Q6*1.25 -> 0 | U6: =Q6*1.5 -> 0 | V6: =Q6*2 -> 0 | W6: =H6-(H6*0.07) -> #DIV/0! | Y6: =(X6-H6)/H6 -> #DIV/0! | Z6: =F6/F$16 -> 0
F7: =E7*D7 -> 0 | H7: =G7/D7 -> #DIV/0! | I7: =F7-G7 -> 0 | J7: =E7-H7 -> #DIV/0! | L7: =DAYS360(K7,$C$1) -> 44515 | M7: =(I7/G7) -> #DIV/0! | R7: =Q7*0.93 -> 0 | T7: =Q7*1.25 -> 0 | U7: =Q7*1.5 -> 0 | V7: =Q7*2 -> 0 | W7: =H7-(H7*0.07) -> #DIV/0! | Y7: =(X7-H7)/H7 -> #DIV/0! | Z7: =F7/F$16 -> 0
A8: AIT | B8: Long | C8: Applied Ind Tec | D8: 266.8733 | E8: 153.98 | F8: =E8*D8 -> 41093.151 | G8: 40425.83 | H8: =G8/D8 -> 151.47948 | I8: =F8-G8 -> 667.32073 | J8: =E8-H8 -> 2.5005152 | K8: 45153 | L8: =DAYS360(K8,$C$1) -> 10 | M8: =(I8/G8) -> 0.016507286 | N8: 91 | O8: 91 | P8: 94 | Q8: 150.07 | R8: =Q8*0.93 -> 139.5651 | S8: 138.38 | T8: =Q8*1.25 -> 187.5875 | U8: =Q8*1.5 -> 225.105 | V8: =Q8*2 -> 300.14 | W8: =H8-(H8*0.07) -> 140.87592 | X8: 145.2 | Y8: =(X8-H8)/H8 -> -0.041454358 | Z8: =F8/F$16 -> 0.080531285 | AB8: 45225 | AC8: 93 | AD8: Bought at pivot test area.
A9: SNPS | B9: Long | C9: Synopsys | D9: 115.8536 | E9: 442.24 | F9: =E9*D9 -> 51235.096 | G9: 51225.83 | H9: =G9/D9 -> 442.16002 | I9: =F9-G9 -> 9.266064 | J9: =E9-H9 -> 0.079980803 | K9: 45117 | L9: =DAYS360(K9,$C$1) -> 45 | M9: =(I9/G9) -> 0.00018088656 | N9: 89 | O9: 87 | P9: 95 | Q9: 392.79 | R9: =Q9*0.93 -> 365.2947 | S9: 416.87 | T9: =Q9*1.25 -> 490.9875 | U9: =Q9*1.5 -> 589.185 | V9: =Q9*2 -> 785.58 | W9: =H9-(H9*0.07) -> 411.20882 | X9: 415 | Y9: =(X9-H9)/H9 -> -0.061425769 | Z9: =F9/F$16 -> 0.10040671 | AB9: 45259 | AC9: 97 | AD9: Bought when breaking out of bull flag in volume.
A10: MNSO | B10: Long | C10: Minoso | D10: =1211.7123+804.6763 -> 2016.3886 | E10: 22.62 | F10: =E10*D10 -> 45610.71 | G10: =25318.9+15999 -> 41317.9 | H10: =G10/D10 -> 20.49104 | I10: =F10-G10 -> 4292.8101 | J10: =E10-H10 -> 2.1289597 | K10: 45135 | L10: =DAYS360(K10,$C$1) -> 27 | M10: =(I10/G10) -> 0.1038971 | N10: 181 | O10: 99 | P10: 99 | Q10: 19.48 | R10: =Q10*0.93 -> 18.1164 | S10: 17.57 | T10: =Q10*1.25 -> 24.35 | U10: =Q10*1.5 -> 29.22 | V10: =Q10*2 -> 38.96 | W10: =H10-(H10*0.07) -> 19.056667 | X10: 20.5 | Y10: =(X10-H10)/H10 -> 0.00043725117 | Z10: =F10/F$16 -> 0.08938446 | AB10: 45245 | AC10: 97 | AD10: Bought after 07/24 b/o. Added at the 21dema.
A11: BIL | B11: Long | C11: Tbill ETF | D11: 2778.4118 | E11: 91.77 | F11: =E11*D11 -> 254974.85 | G11: 254613.66 | H11: =G11/D11 -> 91.640001 | I11: =F11-G11 -> 361.19089 | J11: =E11-H11 -> 0.12999905 | L11: =DAYS360(K11,$C$1) -> 44515 | M11: =(I11/G11) -> 0.0014185841 | R11: =Q11*0.93 -> 0 | T11: =Q11*1.25 -> 0 | U11: =Q11*1.5 -> 0 | V11: =Q11*2 -> 0 | W11: =H11-(H11*0.07) -> 85.225201 | Y11: =(X11-H11)/H11 -> -1 | Z11: =F11/F$16 -> 0.49968065
A12: SQQQ | B12: Long | C12: QQQ Triple short | D12: 511.2918 | E12: 19.82 | F12: =E12*D12 -> 10133.803 | G12: 24797.66 | H12: =G12/D12 -> 48.500015 | I12: =F12-G12 -> -14663.857 | J12: =E12-H12 -> -28.680015 | L12: =DAYS360(K12,$C$1) -> 44515 | M12: =(I12/G12) -> -0.59134033 | R12: =Q12*0.93 -> 0 | T12: =Q12*1.25 -> 0 | U12: =Q12*1.5 -> 0 | V12: =Q12*2 -> 0 | W12: =H12-(H12*0.07) -> 45.105014 | Y12: =(X12-H12)/H12 -> -1 | Z12: =F12/F$16 -> 0.019859471
F13: =E13*D13 -> 0 | H13: =G13/D13 -> #DIV/0! | I13: =F13-G13 -> 0 | J13: =E13-H13 -> #DIV/0! | L13: =DAYS360(K13,$C$1) -> 44515 | M13: =(I13/G13) -> #DIV/0! | R13: =Q13*0.93 -> 0 | T13: =Q13*1.25 -> 0 | U13: =Q13*1.5 -> 0 | V13: =Q13*2 -> 0 | W13: =H13-(H13*0.07) -> #DIV/0! | Y13: =(X13-H13)/H13 -> #DIV/0! | Z13: =F13/F$16 -> 0
A14: Sub-Total | F14: =SUM(F6:F13) -> 403047.61 | G14: =SUM(G6:G13) -> 412380.88 | I14: =SUM(I6:I13) -> -9333.2687
D15: Cash, other | F15: 107228 | G15: =F15/F16 -> 0.21013742
D16: Total | F16: =SUM(F14:F15) -> 510275.61
H17: Last week's close | I17: 501951.87 | K17: 45107 | L17: 509801
H18: Week's change | I18: =(F16-I17-F19)/I17 -> 0.016582748 | K18: chg % | L18: =(F16-L17)/L17 -> 0.00093097364
M20: days
A21: 2023 Closed Trades - Managed Acct | D21: Qty | E21: Cost/sh | F21: $ cost | G21: $Proc | H21: Proc/sh | I21: Profit/loss | J21: % | K21: Date purch | L21: Date sold | M21: held | P21: Comments
A23: HXL | B23: Long | C23: Hexcel | D23: 665.9739 | E23: =F23/D23 -> 76.621621 | F23: 51028 | G23: 45324.79 | H23: =G23/D23 -> 68.057907 | I23: =G23-F23 -> -5703.21 | J23: =I23/F23 -> -0.11176629 | K23: 45106 | L23: 45132 | O23: Bad reaction to EPS report. Stopped out.
A24: MCK | B24: Long | C24: McKesson | D24: 123.3931 | E24: =F24/D24 -> 413.24004 | F24: 50990.97 | G24: 48894.94 | H24: =G24/D24 -> 396.25344 | I24: =G24-F24 -> -2096.03 | J24: =I24/F24 -> -0.041105906 | K24: 45104 | L24: 45138 | O24: Broke original stop and 50dma. EPS coming in a few days.
A25: DXCM | B25: Long | C25: DexCom | D25: 278.2008 | E25: =F25/D25 -> 128.41002 | F25: 35723.77 | G25: 34855.72 | H25: =G25/D25 -> 125.28979 | I25: =G25-F25 -> -868.05 | J25: =I25/F25 -> -0.024298947 | K25: 45106 | L25: 45138 | O25: The positive reaction to EPS report was rejected at the old high and reversed. Didn't like the action.
I31: =SUM(I23:I30) -> -8667.29 | J31: Avg
H32: # of losses | I32: 3 | J32: =(J23+J24+J25)/3 -> -0.059057046

Sheet 09-01-23
C1: 45170
C3: MANAGED ACCT | X3: Current | AC3: IBD
H4: Cost | J4: P/L | N4: Group | P4: EPS | R4: pivot | S4: last | W4: cost | X4: Stop | Y4: Stop | Z4: % | AB4: EPS | AC4: Comp
A5: Symbol | B5: Position | C5: Name | D5: Qty | E5: Current | F5: Value | G5: Cost | H5: per share | I5: P/L $ | J5: per sh | K5: Date purch | L5: days held | M5: % incr | N5: Rank | O5: RS | P5: RS | Q5: pivot | R5: -0.07 | S5: low | T5: 0.25 | U5: 0.5 | V5: 1 | W5: -0.07 | X5: Loss | Y5: Loss% | Z5: of port | AB5: Due | AC5: Rank
F6: =E6*D6 -> 0 | H6: =G6/D6 -> #DIV/0! | I6: =F6-G6 -> 0 | J6: =E6-H6 -> #DIV/0! | L6: =DAYS360(K6,$C$1) -> 44521 | M6: =(I6/G6) -> #DIV/0! | R6: =Q6*0.93 -> 0 | T6: =Q6*1.25 -> 0 | U6: =Q6*1.5 -> 0 | V6: =Q6*2 -> 0 | W6: =H6-(H6*0.07) -> #DIV/0! | Y6: =(X6-H6)/H6 -> #DIV/0! | Z6: =F6/F$16 -> 0
A7: MTSI | B7: Long | C7: MACOM Tech Sol | D7: 507.0754 | E7: 83.12 | F7: 41156.14 | G7: 41151 | H7: =G7/D7 -> 81.153611 | I7: =F7-G7 -> 5.14 | J7: =E7-H7 -> 1.9663885 | K7: 45167 | L7: =DAYS360(K7,$C$1) -> 2 | M7: =(I7/G7) -> 0.00012490583 | N7: 130 | O7: 93 | P7: 90 | Q7: 77.47 | R7: =Q7*0.93 -> 72.0471 | S7: 70.6 | T7: =Q7*1.25 -> 96.8375 | U7: =Q7*1.5 -> 116.205 | V7: =Q7*2 -> 154.94 | W7: =H7-(H7*0.07) -> 75.472859 | X7: 75.75 | Y7: =(X7-H7)/H7 -> -0.066584978 | Z7: =F7/F$16 -> 0.079378129 | AB7: 45244 | AC7: 89 | AD7: B/o on 08/23. Bought after pivot test.
A8: AIT | B8: Long | C8: Applied Ind Tec | D8: 266.8733 | E8: 157.08 | F8: =E8*D8 -> 41920.458 | G8: 40425.83 | H8: =G8/D8 -> 151.47948 | I8: =F8-G8 -> 1494.628 | J8: =E8-H8 -> 5.6005152 | K8: 45153 | L8: =DAYS360(K8,$C$1) -> 16 | M8: =(I8/G8) -> 0.036972103 | N8: 91 | O8: 91 | P8: 94 | Q8: 150.07 | R8: =Q8*0.93 -> 139.5651 | S8: 138.38 | T8: =Q8*1.25 -> 187.5875 | U8: =Q8*1.5 -> 225.105 | V8: =Q8*2 -> 300.14 | W8: =H8-(H8*0.07) -> 140.87592 | X8: 145.2 | Y8: =(X8-H8)/H8 -> -0.041454358 | Z8: =F8/F$16 -> 0.080852275 | AB8: 45225 | AC8: 93 | AD8: Bought at pivot test area.
A9: SNPS | B9: Long | C9: Synopsys | D9: 115.8536 | E9: 460.45 | F9: =E9*D9 -> 53344.79 | G9: 51225.83 | H9: =G9/D9 -> 442.16002 | I9: =F9-G9 -> 2118.9601 | J9: =E9-H9 -> 18.289981 | K9: 45117 | L9: =DAYS360(K9,$C$1) -> 51 | M9: =(I9/G9) -> 0.041365071 | N9: 89 | O9: 87 | P9: 95 | Q9: 392.79 | R9: =Q9*0.93 -> 365.2947 | S9: 416.87 | T9: =Q9*1.25 -> 490.9875 | U9: =Q9*1.5 -> 589.185 | V9: =Q9*2 -> 785.58 | W9: =H9-(H9*0.07) -> 411.20882 | X9: 415 | Y9: =(X9-H9)/H9 -> -0.061425769 | Z9: =F9/F$16 -> 0.10288646 | AB9: 45259 | AC9: 97 | AD9: Bought when breaking out of bull flag in volume.
A10: MNSO | B10: Long | C10: Minoso | D10: =1211.7123+804.6763 -> 2016.3886 | E10: 26.07 | F10: =E10*D10 -> 52567.251 | G10: =25318.9+15999 -> 41317.9 | H10: =G10/D10 -> 20.49104 | I10: =F10-G10 -> 11249.351 | J10: =E10-H10 -> 5.5789597 | K10: 45135 | L10: =DAYS360(K10,$C$1) -> 33 | M10: =(I10/G10) -> 0.27226337 | N10: 181 | O10: 99 | P10: 99 | Q10: 19.48 | R10: =Q10*0.93 -> 18.1164 | S10: 17.57 | T10: =Q10*1.25 -> 24.35 | U10: =Q10*1.5 -> 29.22 | V10: =Q10*2 -> 38.96 | W10: =H10-(H10*0.07) -> 19.056667 | X10: 20.5 | Y10: =(X10-H10)/H10 -> 0.00043725117 | Z10: =F10/F$16 -> 0.10138682 | AB10: 45245 | AC10: 97 | AD10: Bought after 07/24 b/o. Added at the 21dema.
A11: BIL | B11: Long | C11: Tbill ETF | D11: 2778.4118 | E11: 91.54 | F11: =E11*D11 -> 254335.82 | G11: 254613.66 | H11: =G11/D11 -> 91.640001 | I11: =F11-G11 -> -277.84383 | J11: =E11-H11 -> -0.10000095 | L11: =DAYS360(K11,$C$1) -> 44521 | M11: =(I11/G11) -> -0.0010912369 | R11: =Q11*0.93 -> 0 | T11: =Q11*1.25 -> 0 | U11: =Q11*1.5 -> 0 | V11: =Q11*2 -> 0 | W11: =H11-(H11*0.07) -> 85.225201 | Y11: =(X11-H11)/H11 -> -1 | Z11: =F11/F$16 -> 0.49053923
A12: SQQQ | B12: Long | C12: QQQ Triple short | D12: 511.2918 | E12: 17.77 | F12: =E12*D12 -> 9085.6553 | G12: 24797.66 | H12: =G12/D12 -> 48.500015 | I12: =F12-G12 -> -15712.005 | J12: =E12-H12 -> -30.730015 | L12: =DAYS360(K12,$C$1) -> 44521 | M12: =(I12/G12) -> -0.63360836 | R12: =Q12*0.93 -> 0 | T12: =Q12*1.25 -> 0 | U12: =Q12*1.5 -> 0 | V12: =Q12*2 -> 0 | W12: =H12-(H12*0.07) -> 45.105014 | Y12: =(X12-H12)/H12 -> -1 | Z12: =F12/F$16 -> 0.017523566
F13: =E13*D13 -> 0 | H13: =G13/D13 -> #DIV/0! | I13: =F13-G13 -> 0 | J13: =E13-H13 -> #DIV/0! | L13: =DAYS360(K13,$C$1) -> 44521 | M13: =(I13/G13) -> #DIV/0! | R13: =Q13*0.93 -> 0 | T13: =Q13*1.25 -> 0 | U13: =Q13*1.5 -> 0 | V13: =Q13*2 -> 0 | W13: =H13-(H13*0.07) -> #DIV/0! | Y13: =(X13-H13)/H13 -> #DIV/0! | Z13: =F13/F$16 -> 0
A14: Sub-Total | F14: =SUM(F6:F13) -> 452410.11 | G14: =SUM(G6:G13) -> 453531.88 | I14: =SUM(I6:I13) -> -1121.7697
D15: Cash, other | F15: 66072 | G15: =F15/F16 -> 0.12743352
D16: Total | F16: =SUM(F14:F15) -> 518482.11
H17: Last week's close | I17: 510275.61 | K17: 45107 | L17: 509801
H18: Week's change | I18: =(F16-I17-F19)/I17 -> 0.016082486 | K18: chg % | L18: =(F16-L17)/L17 -> 0.017028429
M20: days
A21: 2023 Closed Trades - Managed Acct | D21: Qty | E21: Cost/sh | F21: $ cost | G21: $Proc | H21: Proc/sh | I21: Profit/loss | J21: % | K21: Date purch | L21: Date sold | M21: held | P21: Comments
A23: HXL | B23: Long | C23: Hexcel | D23: 665.9739 | E23: =F23/D23 -> 76.621621 | F23: 51028 | G23: 45324.79 | H23: =G23/D23 -> 68.057907 | I23: =G23-F23 -> -5703.21 | J23: =I23/F23 -> -0.11176629 | K23: 45106 | L23: 45132 | O23: Bad reaction to EPS report. Stopped out.
A24: MCK | B24: Long | C24: McKesson | D24: 123.3931 | E24: =F24/D24 -> 413.24004 | F24: 50990.97 | G24: 48894.94 | H24: =G24/D24 -> 396.25344 | I24: =G24-F24 -> -2096.03 | J24: =I24/F24 -> -0.041105906 | K24: 45104 | L24: 45138 | O24: Broke original stop and 50dma. EPS coming in a few days.
A25: DXCM | B25: Long | C25: DexCom | D25: 278.2008 | E25: =F25/D25 -> 128.41002 | F25: 35723.77 | G25: 34855.72 | H25: =G25/D25 -> 125.28979 | I25: =G25-F25 -> -868.05 | J25: =I25/F25 -> -0.024298947 | K25: 45106 | L25: 45138 | O25: The positive reaction to EPS report was rejected at the old high and reversed. Didn't like the action.
I31: =SUM(I23:I30) -> -8667.29 | J31: Avg
H32: # of losses | I32: 3 | J32: =(J23+J24+J25)/3 -> -0.059057046

Sheet 09-08-23
C1: 45177
C3: MANAGED ACCT | X3: Current | AC3: IBD
H4: Cost | J4: P/L | N4: Group | P4: EPS | R4: pivot | S4: last | W4: cost | X4: Stop | Y4: Stop | Z4: % | AB4: EPS | AC4: Comp
A5: Symbol | B5: Position | C5: Name | D5: Qty | E5: Current | F5: Value | G5: Cost | H5: per share | I5: P/L $ | J5: per sh | K5: Date purch | L5: days held | M5: % incr | N5: Rank | O5: RS | P5: RS | Q5: pivot | R5: -0.07 | S5: low | T5: 0.25 | U5: 0.5 | V5: 1 | W5: -0.07 | X5: Loss | Y5: Loss% | Z5: of port | AB5: Due | AC5: Rank
F6: =E6*D6 -> 0 | H6: =G6/D6 -> #DIV/0! | I6: =F6-G6 -> 0 | J6: =E6-H6 -> #DIV/0! | L6: =DAYS360(K6,$C$1) -> 44528 | M6: =(I6/G6) -> #DIV/0! | R6: =Q6*0.93 -> 0 | T6: =Q6*1.25 -> 0 | U6: =Q6*1.5 -> 0 | V6: =Q6*2 -> 0 | W6: =H6-(H6*0.07) -> #DIV/0! | Y6: =(X6-H6)/H6 -> #DIV/0! | Z6: =F6/F$16 -> 0
A7: MTSI | B7: Long | C7: MACOM Tech Sol | D7: 507.0754 | E7: 79.39 | F7: =E7*D7 -> 40256.716 | G7: 41151 | H7: =G7/D7 -> 81.153611 | I7: =F7-G7 -> -894.28399 | J7: =E7-H7 -> -1.7636115 | K7: 45167 | L7: =DAYS360(K7,$C$1) -> 9 | M7: =(I7/G7) -> -0.021731768 | N7: 153 | O7: 93 | P7: 89 | Q7: 77.47 | R7: =Q7*0.93 -> 72.0471 | S7: 70.6 | T7: =Q7*1.25 -> 96.8375 | U7: =Q7*1.5 -> 116.205 | V7: =Q7*2 -> 154.94 | W7: =H7-(H7*0.07) -> 75.472859 | X7: 75.75 | Y7: =(X7-H7)/H7 -> -0.066584978 | Z7: =F7/F$16 -> 0.077169922 | AB7: 45244 | AC7: 86 | AD7: B/o on 08/23. Bought after pivot test.
A8: AIT | B8: Long | C8: Applied Ind Tec | D8: 266.8733 | E8: 157.42 | F8: =E8*D8 -> 42011.195 | G8: 40425.83 | H8: =G8/D8 -> 151.47948 | I8: =F8-G8 -> 1585.3649 | J8: =E8-H8 -> 5.9405152 | K8: 45153 | L8: =DAYS360(K8,$C$1) -> 23 | M8: =(I8/G8) -> 0.039216632 | N8: 149 | O8: 91 | P8: 94 | Q8: 150.07 | R8: =Q8*0.93 -> 139.5651 | S8: 138.38 | T8: =Q8*1.25 -> 187.5875 | U8: =Q8*1.5 -> 225.105 | V8: =Q8*2 -> 300.14 | W8: =H8-(H8*0.07) -> 140.87592 | X8: 148.75 | Y8: =(X8-H8)/H8 -> -0.018018842 | Z8: =F8/F$16 -> 0.080533162 | AB8: 45225 | AC8: 90 | AD8: Bought at pivot test area.
A9: SNPS | B9: Long | C9: Synopsys | D9: 115.8536 | E9: 459.14 | F9: =E9*D9 -> 53193.022 | G9: 51225.83 | H9: =G9/D9 -> 442.16002 | I9: =F9-G9 -> 1967.1919 | J9: =E9-H9 -> 16.979981 | K9: 45117 | L9: =DAYS360(K9,$C$1) -> 58 | M9: =(I9/G9) -> 0.038402343 | N9: 69 | O9: 91 | P9: 95 | Q9: 392.79 | R9: =Q9*0.93 -> 365.2947 | S9: 416.87 | T9: =Q9*1.25 -> 490.9875 | U9: =Q9*1.5 -> 589.185 | V9: =Q9*2 -> 785.58 | W9: =H9-(H9*0.07) -> 411.20882 | X9: 441 | Y9: =(X9-H9)/H9 -> -0.002623528 | Z9: =F9/F$16 -> 0.10196811 | AB9: 45259 | AC9: 97 | AD9: Bought when breaking out of bull flag in volume.
A10: MNSO | B10: Long | C10: Minoso | D10: =1211.7123+804.6763 -> 2016.3886 | E10: 26.69 | F10: =E10*D10 -> 53817.412 | G10: =25318.9+15999 -> 41317.9 | H10: =G10/D10 -> 20.49104 | I10: =F10-G10 -> 12499.512 | J10: =E10-H10 -> 6.1989597 | K10: 45135 | L10: =DAYS360(K10,$C$1) -> 40 | M10: =(I10/G10) -> 0.3025205 | N10: 186 | O10: 99 | P10: 99 | Q10: 19.48 | R10: =Q10*0.93 -> 18.1164 | S10: 17.57 | T10: =Q10*1.25 -> 24.35 | U10: =Q10*1.5 -> 29.22 | V10: =Q10*2 -> 38.96 | W10: =H10-(H10*0.07) -> 19.056667 | X10: 23 | Y10: =(X10-H10)/H10 -> 0.12244179 | Z10: =F10/F$16 -> 0.10316503 | AB10: 45245 | AC10: 97 | AD10: Bought after 07/24 b/o. Added at the 21dema.
A11: BIL | B11: Long | C11: Tbill ETF | D11: 2778.4118 | E11: 91.55 | F11: =E11*D11 -> 254363.6 | G11: 254613.66 | H11: =G11/D11 -> 91.640001 | I11: =F11-G11 -> -250.05971 | J11: =E11-H11 -> -0.090000953 | L11: =DAYS360(K11,$C$1) -> 44528 | M11: =(I11/G11) -> -0.00098211427 | R11: =Q11*0.93 -> 0 | T11: =Q11*1.25 -> 0 | U11: =Q11*1.5 -> 0 | V11: =Q11*2 -> 0 | W11: =H11-(H11*0.07) -> 85.225201 | Y11: =(X11-H11)/H11 -> -1 | Z11: =F11/F$16 -> 0.48760111
A12: SQQQ | B12: Long | C12: QQQ Triple short | D12: 511.2918 | E12: 18.54 | F12: =E12*D12 -> 9479.35 | G12: 24797.66 | H12: =G12/D12 -> 48.500015 | I12: =F12-G12 -> -15318.31 | J12: =E12-H12 -> -29.960015 | L12: =DAYS360(K12,$C$1) -> 44528 | M12: =(I12/G12) -> -0.61773208 | R12: =Q12*0.93 -> 0 | T12: =Q12*1.25 -> 0 | U12: =Q12*1.5 -> 0 | V12: =Q12*2 -> 0 | W12: =H12-(H12*0.07) -> 45.105014 | Y12: =(X12-H12)/H12 -> -1 | Z12: =F12/F$16 -> 0.018171395
F13: =E13*D13 -> 0 | H13: =G13/D13 -> #DIV/0! | I13: =F13-G13 -> 0 | J13: =E13-H13 -> #DIV/0! | L13: =DAYS360(K13,$C$1) -> 44528 | M13: =(I13/G13) -> #DIV/0! | R13: =Q13*0.93 -> 0 | T13: =Q13*1.25 -> 0 | U13: =Q13*1.5 -> 0 | V13: =Q13*2 -> 0 | W13: =H13-(H13*0.07) -> #DIV/0! | Y13: =(X13-H13)/H13 -> #DIV/0! | Z13: =F13/F$16 -> 0
A14: Sub-Total | F14: =SUM(F6:F13) -> 453121.29 | G14: =SUM(G6:G13) -> 453531.88 | I14: =SUM(I6:I13) -> -410.58521
D15: Cash, other | F15: 68542 | G15: =F15/F16 -> 0.13139126
D16: Total | F16: =SUM(F14:F15) -> 521663.29
H17: Last week's close | I17: 518482.11 | K17: 45107 | L17: 509801
H18: Week's change | I18: =(F16-I17)/I17 -> 0.0061355729 | K18: chg % | L18: =(F16-L17)/L17 -> 0.023268481
M20: days
A21: 2023 Closed Trades - Managed Acct | D21: Qty | E21: Cost/sh | F21: $ cost | G21: $Proc | H21: Proc/sh | I21: Profit/loss | J21: % | K21: Date purch | L21: Date sold | M21: held | P21: Comments
A23: HXL | B23: Long | C23: Hexcel | D23: 665.9739 | E23: =F23/D23 -> 76.621621 | F23: 51028 | G23: 45324.79 | H23: =G23/D23 -> 68.057907 | I23: =G23-F23 -> -5703.21 | J23: =I23/F23 -> -0.11176629 | K23: 45106 | L23: 45132 | M23: =DAYS360(K23,L23) -> 26 | O23: Bad reaction to EPS report. Stopped out.
A24: MCK | B24: Long | C24: McKesson | D24: 123.3931 | E24: =F24/D24 -> 413.24004 | F24: 50990.97 | G24: 48894.94 | H24: =G24/D24 -> 396.25344 | I24: =G24-F24 -> -2096.03 | J24: =I24/F24 -> -0.041105906 | K24: 45104 | L24: 45138 | M24: =DAYS360(K24,L24) -> 34 | O24: Broke original stop and 50dma. EPS coming in a few days.
A25: DXCM | B25: Long | C25: DexCom | D25: 278.2008 | E25: =F25/D25 -> 128.41002 | F25: 35723.77 | G25: 34855.72 | H25: =G25/D25 -> 125.28979 | I25: =G25-F25 -> -868.05 | J25: =I25/F25 -> -0.024298947 | K25: 45106 | L25: 45138 | M25: =DAYS360(K25,L25) -> 32 | O25: The positive reaction to EPS report was rejected at the old high and reversed. Didn't like the action.
I31: =SUM(I23:I30) -> -8667.29 | J31: Avg
H32: # of losses | I32: 3 | J32: =(J23+J24+J25)/3 -> -0.059057046

Sheet 09-15-23
C1: 45184
C3: MANAGED ACCT | X3: Current | AC3: IBD
H4: Cost | J4: P/L | N4: Group | P4: EPS | R4: pivot | S4: last | W4: cost | X4: Stop | Y4: Stop | Z4: % | AB4: EPS | AC4: Comp
A5: Symbol | B5: Position | C5: Name | D5: Qty | E5: Current | F5: Value | G5: Cost | H5: per share | I5: P/L $ | J5: per sh | K5: Date purch | L5: days held | M5: % incr | N5: Rank | O5: RS | P5: RS | Q5: pivot | R5: -0.07 | S5: low | T5: 0.25 | U5: 0.5 | V5: 1 | W5: -0.07 | X5: Loss | Y5: Loss% | Z5: of port | AB5: Due | AC5: Rank
A7: MTSI | B7: Long | C7: MACOM Tech Sol | D7: 507.0754 | E7: 77.96 | F7: =E7*D7 -> 39531.598 | G7: 41151 | H7: =G7/D7 -> 81.153611 | I7: =F7-G7 -> -1619.4018 | J7: =E7-H7 -> -3.1936115 | K7: 45167 | L7: =DAYS360(K7,$C$1) -> 16 | M7: =(I7/G7) -> -0.039352672 | N7: 153 | O7: 93 | P7: 89 | Q7: 77.47 | R7: =Q7*0.93 -> 72.0471 | S7: 70.6 | T7: =Q7*1.25 -> 96.8375 | U7: =Q7*1.5 -> 116.205 | V7: =Q7*2 -> 154.94 | W7: =H7-(H7*0.07) -> 75.472859 | X7: 75.75 | Y7: =(X7-H7)/H7 -> -0.066584978 | Z7: =F7/F$16 -> 0.076022128 | AB7: 45244 | AC7: 86 | AD7: B/o on 08/23. Bought after pivot test.
A8: AIT | B8: Long | C8: Applied Ind Tec | D8: 266.8733 | E8: 156.97 | F8: =E8*D8 -> 41891.102 | G8: 40425.83 | H8: =G8/D8 -> 151.47948 | I8: =F8-G8 -> 1465.2719 | J8: =E8-H8 -> 5.4905152 | K8: 45153 | L8: =DAYS360(K8,$C$1) -> 30 | M8: =(I8/G8) -> 0.036245932 | N8: 149 | O8: 91 | P8: 94 | Q8: 150.07 | R8: =Q8*0.93 -> 139.5651 | S8: 138.38 | T8: =Q8*1.25 -> 187.5875 | U8: =Q8*1.5 -> 225.105 | V8: =Q8*2 -> 300.14 | W8: =H8-(H8*0.07) -> 140.87592 | X8: 148.75 | Y8: =(X8-H8)/H8 -> -0.018018842 | Z8: =F8/F$16 -> 0.080559624 | AB8: 45225 | AC8: 90 | AD8: Bought at pivot test area.
A10: MNSO | B10: Long | C10: Minoso | D10: =1211.7123+804.6763 -> 2016.3886 | E10: 28.15 | F10: =E10*D10 -> 56761.339 | G10: =25318.9+15999 -> 41317.9 | H10: =G10/D10 -> 20.49104 | I10: =F10-G10 -> 15443.439 | J10: =E10-H10 -> 7.6589597 | K10: 45135 | L10: =DAYS360(K10,$C$1) -> 47 | M10: =(I10/G10) -> 0.37377115 | N10: 186 | O10: 99 | P10: 99 | Q10: 19.48 | R10: =Q10*0.93 -> 18.1164 | S10: 17.57 | T10: =Q10*1.25 -> 24.35 | U10: =Q10*1.5 -> 29.22 | V10: =Q10*2 -> 38.96 | W10: =H10-(H10*0.07) -> 19.056667 | X10: 26 | Y10: =(X10-H10)/H10 -> 0.26884725 | Z10: =F10/F$16 -> 0.10915617 | AB10: 45245 | AC10: 97 | AD10: Bought after 07/24 b/o. Added at the 21dema.
A11: BIL | B11: Long | C11: Tbill ETF | D11: 2778.4118 | E11: 91.64 | F11: =E11*D11 -> 254613.66 | G11: 254613.66 | H11: =G11/D11 -> 91.640001 | I11: =F11-G11 -> -0.002648 | J11: =E11-H11 -> -9.5306247e-07 | L11: =DAYS360(K11,$C$1) -> 44535 | M11: =(I11/G11) -> -1.0400071e-08 | R11: =Q11*0.93 -> 0 | T11: =Q11*1.25 -> 0 | U11: =Q11*1.5 -> 0 | V11: =Q11*2 -> 0 | W11: =H11-(H11*0.07) -> 85.225201 | Y11: =(X11-H11)/H11 -> -1 | Z11: =F11/F$16 -> 0.48964051
A12: SQQQ | B12: Long | C12: QQQ Triple short | D12: 511.2918 | E12: 18.82 | F12: =E12*D12 -> 9622.5117 | G12: 24797.66 | H12: =G12/D12 -> 48.500015 | I12: =F12-G12 -> -15175.148 | J12: =E12-H12 -> -29.680015 | L12: =DAYS360(K12,$C$1) -> 44535 | M12: =(I12/G12) -> -0.61195888 | R12: =Q12*0.93 -> 0 | T12: =Q12*1.25 -> 0 | U12: =Q12*1.5 -> 0 | V12: =Q12*2 -> 0 | W12: =H12-(H12*0.07) -> 45.105014 | Y12: =(X12-H12)/H12 -> -1 | Z12: =F12/F$16 -> 0.018504787
F13: =E13*D13 -> 0 | H13: =G13/D13 -> #DIV/0! | I13: =F13-G13 -> 0 | J13: =E13-H13 -> #DIV/0! | L13: =DAYS360(K13,$C$1) -> 44535 | M13: =(I13/G13) -> #DIV/0! | R13: =Q13*0.93 -> 0 | T13: =Q13*1.25 -> 0 | U13: =Q13*1.5 -> 0 | V13: =Q13*2 -> 0 | W13: =H13-(H13*0.07) -> #DIV/0! | Y13: =(X13-H13)/H13 -> #DIV/0! | Z13: =F13/F$16 -> 0
A14: Sub-Total | F14: =SUM(F6:F13) -> 402420.21 | G14: =SUM(G6:G13) -> 402306.05 | I14: =SUM(I6:I13) -> 114.1582
D15: Cash, other | F15: 117581 | G15: =F15/F16 -> 0.22611678
D16: Total | F16: =SUM(F14:F15) -> 520001.21
H17: Last week's close | I17: 521663.29 | K17: 45107 | L17: 509801
H18: Week's change | I18: =(F16-I17)/I17 -> -0.0031861199 | K18: chg % | L18: =(F16-L17)/L17 -> 0.020008215
M20: days
A21: 2023 Closed Trades - Managed Acct | D21: Qty | E21: Cost/sh | F21: $ cost | G21: $Proc | H21: Proc/sh | I21: Profit/loss | J21: % | K21: Date purch | L21: Date sold | M21: held | P21: Comments
A23: HXL | B23: Long | C23: Hexcel | D23: 665.9739 | E23: =F23/D23 -> 76.621621 | F23: 51028 | G23: 45324.79 | H23: =G23/D23 -> 68.057907 | I23: =G23-F23 -> -5703.21 | J23: =I23/F23 -> -0.11176629 | K23: 45106 | L23: 45132 | M23: =DAYS360(K23,L23) -> 26 | O23: Bad reaction to EPS report. Stopped out.
A24: MCK | B24: Long | C24: McKesson | D24: 123.3931 | E24: =F24/D24 -> 413.24004 | F24: 50990.97 | G24: 48894.94 | H24: =G24/D24 -> 396.25344 | I24: =G24-F24 -> -2096.03 | J24: =I24/F24 -> -0.041105906 | K24: 45104 | L24: 45138 | M24: =DAYS360(K24,L24) -> 34 | O24: Broke original stop and 50dma. EPS coming in a few days.
A25: DXCM | B25: Long | C25: DexCom | D25: 278.2008 | E25: =F25/D25 -> 128.41002 | F25: 35723.77 | G25: 34855.72 | H25: =G25/D25 -> 125.28979 | I25: =G25-F25 -> -868.05 | J25: =I25/F25 -> -0.024298947 | K25: 45106 | L25: 45138 | M25: =DAYS360(K25,L25) -> 32 | O25: The positive reaction to EPS report was rejected at the old high and reversed. Didn't like the action.
A26: IONQ | B26: Long | C26: IonQ | D26: 1007.1459 | E26: =F26/D26 -> 20.954908 | F26: 21104.65 | G26: 18099.32 | H26: =G26/D26 -> 17.970902 | I26: =G26-F26 -> -3005.33 | J26: =I26/F26 -> -0.14240132 | K26: 45181 | L26: 45183 | M26: =DAYS360(K26,L26) -> 2 | O26: Breakout failure. Only 4% position. Only .6% hit to total.
A27: SNPS | B27: Long | C27: Synopsys | D27: 115.8536 | E27: =F27/D27 -> 442.16002 | F27: 51225.83 | G27: 52055.28 | H27: =G27/D27 -> 449.31949 | I27: =G27-F27 -> 829.45 | J27: =I27/F27 -> 0.016192027 | K27: 45117 | L27: 45184 | M27: =DAYS360(K27,L27) -> 65 | O27: Sold to protect capital on an ugly day.
I31: =SUM(I23:I30) -> -10843.17 | J31: Avg
H32: # of losses | I32: 4 | J32: =SUM(J23:J30)/I32 -> -0.075845108
H33: # of wins | I33: 1 | J33: 0.0162

Sheet 09-22-23
C1: 45191
C3: MANAGED ACCT | X3: Current | AC3: IBD
H4: Cost | J4: P/L | N4: Group | P4: EPS | R4: pivot | S4: last | W4: cost | X4: Stop | Y4: Stop | Z4: % | AB4: EPS | AC4: Comp
A5: Symbol | B5: Position | C5: Name | D5: Qty | E5: Current | F5: Value | G5: Cost | H5: per share | I5: P/L $ | J5: per sh | K5: Date purch | L5: days held | M5: % incr | N5: Rank | O5: RS | P5: RS | Q5: pivot | R5: -0.07 | S5: low | T5: 0.25 | U5: 0.5 | V5: 1 | W5: -0.07 | X5: Loss | Y5: Loss% | Z5: of port | AB5: Due | AC5: Rank
A7: MTSI | B7: Long | C7: MACOM Tech Sol | D7: 507.0754 | E7: 77.89 | F7: =E7*D7 -> 39496.103 | G7: 41151 | H7: =G7/D7 -> 81.153611 | I7: =F7-G7 -> -1654.8971 | J7: =E7-H7 -> -3.2636115 | K7: 45167 | L7: =DAYS360(K7,$C$1) -> 23 | M7: =(I7/G7) -> -0.040215234 | N7: 169 | O7: 93 | P7: 89 | Q7: 77.47 | R7: =Q7*0.93 -> 72.0471 | S7: 70.6 | T7: =Q7*1.25 -> 96.8375 | U7: =Q7*1.5 -> 116.205 | V7: =Q7*2 -> 154.94 | W7: =H7-(H7*0.07) -> 75.472859 | X7: 75.75 | Y7: =(X7-H7)/H7 -> -0.066584978 | Z7: =F7/F$16 -> 0.076583581 | AB7: 45244 | AC7: 83 | AD7: B/o on 08/23. Bought after pivot test.
A8: AIT | B8: Long | C8: Applied Ind Tec | D8: 266.8733 | E8: 154.89 | F8: =E8*D8 -> 41336.005 | G8: 40425.83 | H8: =G8/D8 -> 151.47948 | I8: =F8-G8 -> 910.17544 | J8: =E8-H8 -> 3.4105152 | K8: 45153 | L8: =DAYS360(K8,$C$1) -> 37 | M8: =(I8/G8) -> 0.0225147 | N8: 136 | O8: 91 | P8: 94 | Q8: 150.07 | R8: =Q8*0.93 -> 139.5651 | S8: 138.38 | T8: =Q8*1.25 -> 187.5875 | U8: =Q8*1.5 -> 225.105 | V8: =Q8*2 -> 300.14 | W8: =H8-(H8*0.07) -> 140.87592 | X8: 148.75 | Y8: =(X8-H8)/H8 -> -0.018018842 | Z8: =F8/F$16 -> 0.080151182 | AB8: 45225 | AC8: 93 | AD8: Bought at pivot test area.
A10: MNSO | B10: Long | C10: Minoso | D10: =1211.7123+804.6763 -> 2016.3886 | E10: 25.78 | F10: =E10*D10 -> 51982.498 | G10: =25318.9+15999 -> 41317.9 | H10: =G10/D10 -> 20.49104 | I10: =F10-G10 -> 10664.598 | J10: =E10-H10 -> 5.2889597 | K10: 45135 | L10: =DAYS360(K10,$C$1) -> 54 | M10: =(I10/G10) -> 0.25811085 | N10: 194 | O10: 99 | P10: 99 | Q10: 19.48 | R10: =Q10*0.93 -> 18.1164 | S10: 17.57 | T10: =Q10*1.25 -> 24.35 | U10: =Q10*1.5 -> 29.22 | V10: =Q10*2 -> 38.96 | W10: =H10-(H10*0.07) -> 19.056667 | X10: 26 | Y10: =(X10-H10)/H10 -> 0.26884725 | Z10: =F10/F$16 -> 0.1007949 | AB10: 45245 | AC10: 96 | AD10: Bought after 07/24 b/o. Added at the 21dema.
A11: BIL | B11: Long | C11: Tbill ETF | D11: 2778.4118 | E11: 91.73 | F11: =E11*D11 -> 254863.71 | G11: 254613.66 | H11: =G11/D11 -> 91.640001 | I11: =F11-G11 -> 250.05441 | J11: =E11-H11 -> 0.089999047 | L11: =DAYS360(K11,$C$1) -> 44542 | M11: =(I11/G11) -> 0.00098209347 | R11: =Q11*0.93 -> 0 | T11: =Q11*1.25 -> 0 | U11: =Q11*1.5 -> 0 | V11: =Q11*2 -> 0 | W11: =H11-(H11*0.07) -> 85.225201 | Y11: =(X11-H11)/H11 -> -1 | Z11: =F11/F$16 -> 0.49418486
A12: SQQQ | B12: Long | C12: QQQ Triple short | D12: 511.2918 | E12: 20.47 | F12: =E12*D12 -> 10466.143 | G12: 24797.66 | H12: =G12/D12 -> 48.500015 | I12: =F12-G12 -> -14331.517 | J12: =E12-H12 -> -28.030015 | L12: =DAYS360(K12,$C$1) -> 44542 | M12: =(I12/G12) -> -0.57793828 | R12: =Q12*0.93 -> 0 | T12: =Q12*1.25 -> 0 | U12: =Q12*1.5 -> 0 | V12: =Q12*2 -> 0 | W12: =H12-(H12*0.07) -> 45.105014 | Y12: =(X12-H12)/H12 -> -1 | Z12: =F12/F$16 -> 0.020294021
F13: =E13*D13 -> 0 | H13: =G13/D13 -> #DIV/0! | I13: =F13-G13 -> 0 | J13: =E13-H13 -> #DIV/0! | L13: =DAYS360(K13,$C$1) -> 44542 | M13: =(I13/G13) -> #DIV/0! | R13: =Q13*0.93 -> 0 | T13: =Q13*1.25 -> 0 | U13: =Q13*1.5 -> 0 | V13: =Q13*2 -> 0 | W13: =H13-(H13*0.07) -> #DIV/0! | Y13: =(X13-H13)/H13 -> #DIV/0! | Z13: =F13/F$16 -> 0
A14: Sub-Total | F14: =SUM(F6:F13) -> 398144.46 | G14: =SUM(G6:G13) -> 402306.05 | I14: =SUM(I6:I13) -> -4161.586
D15: Cash, other | F15: 117581 | G15: =F15/F16 -> 0.22799146
D16: Total | F16: =SUM(F14:F15) -> 515725.46
H17: Last week's close | I17: 520001.21 | K17: 45107 | L17: 509801
H18: Week's change | I18: =(F16-I17)/I17 -> -0.0082225693 | K18: chg % | L18: =(F16-L17)/L17 -> 0.011621131
M20: days
A21: 2023 Closed Trades - Managed Acct | D21: Qty | E21: Cost/sh | F21: $ cost | G21: $Proc | H21: Proc/sh | I21: Profit/loss | J21: % | K21: Date purch | L21: Date sold | M21: held | P21: Comments
A23: HXL | B23: Long | C23: Hexcel | D23: 665.9739 | E23: =F23/D23 -> 76.621621 | F23: 51028 | G23: 45324.79 | H23: =G23/D23 -> 68.057907 | I23: =G23-F23 -> -5703.21 | J23: =I23/F23 -> -0.11176629 | K23: 45106 | L23: 45132 | M23: =DAYS360(K23,L23) -> 26 | O23: Bad reaction to EPS report. Stopped out.
A24: MCK | B24: Long | C24: McKesson | D24: 123.3931 | E24: =F24/D24 -> 413.24004 | F24: 50990.97 | G24: 48894.94 | H24: =G24/D24 -> 396.25344 | I24: =G24-F24 -> -2096.03 | J24: =I24/F24 -> -0.041105906 | K24: 45104 | L24: 45138 | M24: =DAYS360(K24,L24) -> 34 | O24: Broke original stop and 50dma. EPS coming in a few days.
A25: DXCM | B25: Long | C25: DexCom | D25: 278.2008 | E25: =F25/D25 -> 128.41002 | F25: 35723.77 | G25: 34855.72 | H25: =G25/D25 -> 125.28979 | I25: =G25-F25 -> -868.05 | J25: =I25/F25 -> -0.024298947 | K25: 45106 | L25: 45138 | M25: =DAYS360(K25,L25) -> 32 | O25: The positive reaction to EPS report was rejected at the old high and reversed. Didn't like the action.
A26: IONQ | B26: Long | C26: IonQ | D26: 1007.1459 | E26: =F26/D26 -> 20.954908 | F26: 21104.65 | G26: 18099.32 | H26: =G26/D26 -> 17.970902 | I26: =G26-F26 -> -3005.33 | J26: =I26/F26 -> -0.14240132 | K26: 45181 | L26: 45183 | M26: =DAYS360(K26,L26) -> 2 | O26: Breakout failure. Only 4% position. Only .6% hit to total.
A27: SNPS | B27: Long | C27: Synopsys | D27: 115.8536 | E27: =F27/D27 -> 442.16002 | F27: 51225.83 | G27: 52055.28 | H27: =G27/D27 -> 449.31949 | I27: =G27-F27 -> 829.45 | J27: =I27/F27 -> 0.016192027 | K27: 45117 | L27: 45184 | M27: =DAYS360(K27,L27) -> 65 | O27: Sold to protect capital on an ugly day.
I31: =SUM(I23:I30) -> -10843.17 | J31: Avg
H32: # of losses | I32: 4 | J32: =SUM(J23:J30)/I32 -> -0.075845108
H33: # of wins | I33: 1 | J33: 0.0162

Sheet 09-29-23
C1: 45198
C3: MANAGED ACCT | X3: Current | AC3: IBD
H4: Cost | J4: P/L | N4: Group | P4: EPS | R4: pivot | S4: last | W4: cost | X4: Stop | Y4: Stop | Z4: % | AB4: EPS | AC4: Comp
A5: Symbol | B5: Position | C5: Name | D5: Qty | E5: Current | F5: Value | G5: Cost | H5: per share | I5: P/L $ | J5: per sh | K5: Date purch | L5: days held | M5: % incr | N5: Rank | O5: RS | P5: RS | Q5: pivot | R5: -0.07 | S5: low | T5: 0.25 | U5: 0.5 | V5: 1 | W5: -0.07 | X5: Loss | Y5: Loss% | Z5: of port | AB5: Due | AC5: Rank
A7: MTSI | B7: Long | C7: MACOM Tech Sol | D7: 507.0754 | E7: 81.58 | F7: =E7*D7 -> 41367.211 | G7: 41151 | H7: =G7/D7 -> 81.153611 | I7: =F7-G7 -> 216.21113 | J7: =E7-H7 -> 0.42638853 | K7: 45167 | L7: =DAYS360(K7,$C$1) -> 30 | M7: =(I7/G7) -> 0.0052540918 | N7: 162 | O7: 94 | P7: 89 | Q7: 77.47 | R7: =Q7*0.93 -> 72.0471 | S7: 70.6 | T7: =Q7*1.25 -> 96.8375 | U7: =Q7*1.5 -> 116.205 | V7: =Q7*2 -> 154.94 | W7: =H7-(H7*0.07) -> 75.472859 | X7: 75.75 | Y7: =(X7-H7)/H7 -> -0.066584978 | Z7: =F7/F$16 -> 0.079666538 | AB7: 45244 | AC7: 85 | AD7: B/o on 08/23. Bought after pivot test.
A8: AIT | B8: Long | C8: Applied Ind Tec | D8: 266.8733 | E8: 154.61 | F8: =E8*D8 -> 41261.281 | G8: 40425.83 | H8: =G8/D8 -> 151.47948 | I8: =F8-G8 -> 835.45091 | J8: =E8-H8 -> 3.1305152 | K8: 45153 | L8: =DAYS360(K8,$C$1) -> 44 | M8: =(I8/G8) -> 0.020666265 | N8: 129 | O8: 90 | P8: 94 | Q8: 150.07 | R8: =Q8*0.93 -> 139.5651 | S8: 138.38 | T8: =Q8*1.25 -> 187.5875 | U8: =Q8*1.5 -> 225.105 | V8: =Q8*2 -> 300.14 | W8: =H8-(H8*0.07) -> 140.87592 | X8: 148.75 | Y8: =(X8-H8)/H8 -> -0.018018842 | Z8: =F8/F$16 -> 0.079462534 | AB8: 45225 | AC8: 93 | AD8: Bought at pivot test area.
A10: MNSO | B10: Long | C10: Minoso | D10: =1211.7123+804.6763 -> 2016.3886 | E10: 25.9 | F10: =E10*D10 -> 52224.465 | G10: =25318.9+15999 -> 41317.9 | H10: =G10/D10 -> 20.49104 | I10: =F10-G10 -> 10906.565 | J10: =E10-H10 -> 5.4089597 | K10: 45135 | L10: =DAYS360(K10,$C$1) -> 61 | M10: =(I10/G10) -> 0.26396706 | N10: 184 | O10: 99 | P10: 99 | Q10: 19.48 | R10: =Q10*0.93 -> 18.1164 | S10: 17.57 | T10: =Q10*1.25 -> 24.35 | U10: =Q10*1.5 -> 29.22 | V10: =Q10*2 -> 38.96 | W10: =H10-(H10*0.07) -> 19.056667 | X10: 26 | Y10: =(X10-H10)/H10 -> 0.26884725 | Z10: =F10/F$16 -> 0.10057585 | AB10: 45245 | AC10: 97 | AD10: Bought after 07/24 b/o. Added at the 21dema.
A11: BIL | B11: Long | C11: Tbill ETF | D11: 2778.4118 | E11: 91.82 | F11: =E11*D11 -> 255113.77 | G11: 254613.66 | H11: =G11/D11 -> 91.640001 | I11: =F11-G11 -> 500.11148 | J11: =E11-H11 -> 0.17999905 | L11: =DAYS360(K11,$C$1) -> 44549 | M11: =(I11/G11) -> 0.0019641973 | R11: =Q11*0.93 -> 0 | T11: =Q11*1.25 -> 0 | U11: =Q11*1.5 -> 0 | V11: =Q11*2 -> 0 | W11: =H11-(H11*0.07) -> 85.225201 | Y11: =(X11-H11)/H11 -> -1 | Z11: =F11/F$16 -> 0.49130774
A12: SQQQ | B12: Long | C12: QQQ Triple short | D12: 511.2918 | E12: 20.44 | F12: =E12*D12 -> 10450.804 | G12: 24797.66 | H12: =G12/D12 -> 48.500015 | I12: =F12-G12 -> -14346.856 | J12: =E12-H12 -> -28.060015 | L12: =DAYS360(K12,$C$1) -> 44549 | M12: =(I12/G12) -> -0.57855683 | R12: =Q12*0.93 -> 0 | T12: =Q12*1.25 -> 0 | U12: =Q12*1.5 -> 0 | V12: =Q12*2 -> 0 | W12: =H12-(H12*0.07) -> 45.105014 | Y12: =(X12-H12)/H12 -> -1 | Z12: =F12/F$16 -> 0.020126554
F13: =E13*D13 -> 0 | H13: =G13/D13 -> #DIV/0! | I13: =F13-G13 -> 0 | J13: =E13-H13 -> #DIV/0! | L13: =DAYS360(K13,$C$1) -> 44549 | M13: =(I13/G13) -> #DIV/0! | R13: =Q13*0.93 -> 0 | T13: =Q13*1.25 -> 0 | U13: =Q13*1.5 -> 0 | V13: =Q13*2 -> 0 | W13: =H13-(H13*0.07) -> #DIV/0! | Y13: =(X13-H13)/H13 -> #DIV/0! | Z13: =F13/F$16 -> 0
A14: Sub-Total | F14: =SUM(F6:F13) -> 400417.53 | G14: =SUM(G6:G13) -> 402306.05 | I14: =SUM(I6:I13) -> -1888.5173
D15: Cash, other | F15: 118837 | G15: =F15/F16 -> 0.22886079
D16: Total | F16: =SUM(F14:F15) -> 519254.53
H17: Last week's close | I17: ='09-22-23'!F16 -> 515725.46 | K17: 45107 | L17: 509801
H18: Week's change | I18: =(F16-I17)/I17 -> 0.0068429211 | K18: chg % | L18: =(F16-L17)/L17 -> 0.018543574
M20: days
A21: 2023 Closed Trades - Managed Acct | D21: Qty | E21: Cost/sh | F21: $ cost | G21: $Proc | H21: Proc/sh | I21: Profit/loss | J21: % | K21: Date purch | L21: Date sold | M21: held | P21: Comments
A23: HXL | B23: Long | C23: Hexcel | D23: 665.9739 | E23: =F23/D23 -> 76.621621 | F23: 51028 | G23: 45324.79 | H23: =G23/D23 -> 68.057907 | I23: =G23-F23 -> -5703.21 | J23: =I23/F23 -> -0.11176629 | K23: 45106 | L23: 45132 | M23: =DAYS360(K23,L23) -> 26 | O23: Bad reaction to EPS report. Stopped out.
A24: MCK | B24: Long | C24: McKesson | D24: 123.3931 | E24: =F24/D24 -> 413.24004 | F24: 50990.97 | G24: 48894.94 | H24: =G24/D24 -> 396.25344 | I24: =G24-F24 -> -2096.03 | J24: =I24/F24 -> -0.041105906 | K24: 45104 | L24: 45138 | M24: =DAYS360(K24,L24) -> 34 | O24: Broke original stop and 50dma. EPS coming in a few days.
A25: DXCM | B25: Long | C25: DexCom | D25: 278.2008 | E25: =F25/D25 -> 128.41002 | F25: 35723.77 | G25: 34855.72 | H25: =G25/D25 -> 125.28979 | I25: =G25-F25 -> -868.05 | J25: =I25/F25 -> -0.024298947 | K25: 45106 | L25: 45138 | M25: =DAYS360(K25,L25) -> 32 | O25: The positive reaction to EPS report was rejected at the old high and reversed. Didn't like the action.
A26: IONQ | B26: Long | C26: IonQ | D26: 1007.1459 | E26: =F26/D26 -> 20.954908 | F26: 21104.65 | G26: 18099.32 | H26: =G26/D26 -> 17.970902 | I26: =G26-F26 -> -3005.33 | J26: =I26/F26 -> -0.14240132 | K26: 45181 | L26: 45183 | M26: =DAYS360(K26,L26) -> 2 | O26: Breakout failure. Only 4% position. Only .6% hit to total.
A27: SNPS | B27: Long | C27: Synopsys | D27: 115.8536 | E27: =F27/D27 -> 442.16002 | F27: 51225.83 | G27: 52055.28 | H27: =G27/D27 -> 449.31949 | I27: =G27-F27 -> 829.45 | J27: =I27/F27 -> 0.016192027 | K27: 45117 | L27: 45184 | M27: =DAYS360(K27,L27) -> 65 | O27: Sold to protect capital on an ugly day.
I31: =SUM(I23:I30) -> -10843.17 | J31: Avg
H32: # of losses | I32: 4 | J32: =SUM(J23:J30)/I32 -> -0.075845108
H33: # of wins | I33: 1 | J33: 0.0162

Sheet 10-06-23
C1: 45205
C3: MANAGED ACCT | X3: Current | AC3: IBD
H4: Cost | J4: P/L | N4: Group | P4: EPS | R4: pivot | S4: last | W4: cost | X4: Stop | Y4: Stop | Z4: % | AB4: EPS | AC4: Comp
A5: Symbol | B5: Position | C5: Name | D5: Qty | E5: Current | F5: Value | G5: Cost | H5: per share | I5: P/L $ | J5: per sh | K5: Date purch | L5: days held | M5: % incr | N5: Rank | O5: RS | P5: RS | Q5: pivot | R5: -0.07 | S5: low | T5: 0.25 | U5: 0.5 | V5: 1 | W5: -0.07 | X5: Loss | Y5: Loss% | Z5: of port | AB5: Due | AC5: Rank
A7: MTSI | B7: Long | C7: MACOM Tech Sol | D7: 507.0754 | E7: 81.7 | F7: =E7*D7 -> 41428.06 | G7: 41151 | H7: =G7/D7 -> 81.153611 | I7: =F7-G7 -> 277.06018 | J7: =E7-H7 -> 0.54638853 | K7: 45167 | L7: =DAYS360(K7,$C$1) -> 37 | M7: =(I7/G7) -> 0.0067327691 | N7: 136 | O7: 95 | P7: 89 | Q7: 77.47 | R7: =Q7*0.93 -> 72.0471 | S7: 70.6 | T7: =Q7*1.25 -> 96.8375 | U7: =Q7*1.5 -> 116.205 | V7: =Q7*2 -> 154.94 | W7: =H7-(H7*0.07) -> 75.472859 | X7: 75.75 | Y7: =(X7-H7)/H7 -> -0.066584978 | Z7: =F7/F$16 -> 0.079983491 | AB7: 45244 | AC7: 87 | AD7: B/o on 08/23. Bought after pivot test.
A8: AIT | B8: Long | C8: Applied Ind Tec | D8: 266.8733 | E8: 156.33 | F8: =E8*D8 -> 41720.303 | G8: 40425.83 | H8: =G8/D8 -> 151.47948 | I8: =F8-G8 -> 1294.473 | J8: =E8-H8 -> 4.8505152 | K8: 45153 | L8: =DAYS360(K8,$C$1) -> 51 | M8: =(I8/G8) -> 0.032020938 | N8: 68 | O8: 93 | P8: 94 | Q8: 150.07 | R8: =Q8*0.93 -> 139.5651 | S8: 138.38 | T8: =Q8*1.25 -> 187.5875 | U8: =Q8*1.5 -> 225.105 | V8: =Q8*2 -> 300.14 | W8: =H8-(H8*0.07) -> 140.87592 | X8: 148.75 | Y8: =(X8-H8)/H8 -> -0.018018842 | Z8: =F8/F$16 -> 0.080547712 | AB8: 45225 | AC8: 94 | AD8: Bought at pivot test area.
A10: MNSO | B10: Long | C10: Minoso | D10: =1211.7123+804.6763 -> 2016.3886 | E10: 24.69 | F10: =E10*D10 -> 49784.635 | G10: =25318.9+15999 -> 41317.9 | H10: =G10/D10 -> 20.49104 | I10: =F10-G10 -> 8466.7345 | J10: =E10-H10 -> 4.1989597 | K10: 45135 | L10: =DAYS360(K10,$C$1) -> 68 | M10: =(I10/G10) -> 0.20491686 | N10: 186 | O10: 99 | P10: 99 | Q10: 19.48 | R10: =Q10*0.93 -> 18.1164 | S10: 17.57 | T10: =Q10*1.25 -> 24.35 | U10: =Q10*1.5 -> 29.22 | V10: =Q10*2 -> 38.96 | W10: =H10-(H10*0.07) -> 19.056667 | X10: 26 | Y10: =(X10-H10)/H10 -> 0.26884725 | Z10: =F10/F$16 -> 0.096117193 | AB10: 45245 | AC10: 96 | AD10: Bought after 07/24 b/o. Added at the 21dema.
A11: BIL | B11: Long | C11: Tbill ETF | D11: 2778.4118 | E11: 91.53 | F11: =E11*D11 -> 254308.03 | G11: 254613.66 | H11: =G11/D11 -> 91.640001 | I11: =F11-G11 -> -305.62795 | J11: =E11-H11 -> -0.11000095 | L11: =DAYS360(K11,$C$1) -> 44556 | M11: =(I11/G11) -> -0.0012003596 | R11: =Q11*0.93 -> 0 | T11: =Q11*1.25 -> 0 | U11: =Q11*1.5 -> 0 | V11: =Q11*2 -> 0 | W11: =H11-(H11*0.07) -> 85.225201 | Y11: =(X11-H11)/H11 -> -1 | Z11: =F11/F$16 -> 0.4909823
A12: SQQQ | B12: Long | C12: QQQ Triple short | D12: 511.2918 | E12: 19.36 | F12: =E12*D12 -> 9898.6092 | G12: 24797.66 | H12: =G12/D12 -> 48.500015 | I12: =F12-G12 -> -14899.051 | J12: =E12-H12 -> -29.140015 | L12: =DAYS360(K12,$C$1) -> 44556 | M12: =(I12/G12) -> -0.60082487 | R12: =Q12*0.93 -> 0 | T12: =Q12*1.25 -> 0 | U12: =Q12*1.5 -> 0 | V12: =Q12*2 -> 0 | W12: =H12-(H12*0.07) -> 45.105014 | Y12: =(X12-H12)/H12 -> -1 | Z12: =F12/F$16 -> 0.019110847
F13: =E13*D13 -> 0 | H13: =G13/D13 -> #DIV/0! | I13: =F13-G13 -> 0 | J13: =E13-H13 -> #DIV/0! | L13: =DAYS360(K13,$C$1) -> 44556 | M13: =(I13/G13) -> #DIV/0! | R13: =Q13*0.93 -> 0 | T13: =Q13*1.25 -> 0 | U13: =Q13*1.5 -> 0 | V13: =Q13*2 -> 0 | W13: =H13-(H13*0.07) -> #DIV/0! | Y13: =(X13-H13)/H13 -> #DIV/0! | Z13: =F13/F$16 -> 0
A14: Sub-Total | F14: =SUM(F6:F13) -> 397139.64 | G14: =SUM(G6:G13) -> 402306.05 | I14: =SUM(I6:I13) -> -5166.411
D15: Cash, other | F15: 120818 | G15: =F15/F16 -> 0.23325846
D16: Total | F16: =SUM(F14:F15) -> 517957.64
H17: Last week's close | I17: 519254.53 | K17: 45107 | L17: 509801
H18: Week's change | I18: =(F16-I17)/I17 -> -0.0024976017 | K18: chg % | L18: =(F16-L17)/L17 -> 0.015999653
M20: days
A21: 2023 Closed Trades - Managed Acct | D21: Qty | E21: Cost/sh | F21: $ cost | G21: $Proc | H21: Proc/sh | I21: Profit/loss | J21: % | K21: Date purch | L21: Date sold | M21: held | P21: Comments
A23: HXL | B23: Long | C23: Hexcel | D23: 665.9739 | E23: =F23/D23 -> 76.621621 | F23: 51028 | G23: 45324.79 | H23: =G23/D23 -> 68.057907 | I23: =G23-F23 -> -5703.21 | J23: =I23/F23 -> -0.11176629 | K23: 45106 | L23: 45132 | M23: =DAYS360(K23,L23) -> 26 | O23: Bad reaction to EPS report. Stopped out.
A24: MCK | B24: Long | C24: McKesson | D24: 123.3931 | E24: =F24/D24 -> 413.24004 | F24: 50990.97 | G24: 48894.94 | H24: =G24/D24 -> 396.25344 | I24: =G24-F24 -> -2096.03 | J24: =I24/F24 -> -0.041105906 | K24: 45104 | L24: 45138 | M24: =DAYS360(K24,L24) -> 34 | O24: Broke original stop and 50dma. EPS coming in a few days.
A25: DXCM | B25: Long | C25: DexCom | D25: 278.2008 | E25: =F25/D25 -> 128.41002 | F25: 35723.77 | G25: 34855.72 | H25: =G25/D25 -> 125.28979 | I25: =G25-F25 -> -868.05 | J25: =I25/F25 -> -0.024298947 | K25: 45106 | L25: 45138 | M25: =DAYS360(K25,L25) -> 32 | O25: The positive reaction to EPS report was rejected at the old high and reversed. Didn't like the action.
A26: IONQ | B26: Long | C26: IonQ | D26: 1007.1459 | E26: =F26/D26 -> 20.954908 | F26: 21104.65 | G26: 18099.32 | H26: =G26/D26 -> 17.970902 | I26: =G26-F26 -> -3005.33 | J26: =I26/F26 -> -0.14240132 | K26: 45181 | L26: 45183 | M26: =DAYS360(K26,L26) -> 2 | O26: Breakout failure. Only 4% position. Only .6% hit to total.
A27: SNPS | B27: Long | C27: Synopsys | D27: 115.8536 | E27: =F27/D27 -> 442.16002 | F27: 51225.83 | G27: 52055.28 | H27: =G27/D27 -> 449.31949 | I27: =G27-F27 -> 829.45 | J27: =I27/F27 -> 0.016192027 | K27: 45117 | L27: 45184 | M27: =DAYS360(K27,L27) -> 65 | O27: Sold to protect capital on an ugly day.
I31: =SUM(I23:I30) -> -10843.17 | J31: Avg
H32: # of losses | I32: 4 | J32: =SUM(J23:J30)/I32 -> -0.075845108
H33: # of wins | I33: 1 | J33: 0.0162

Sheet 10-13-23
C1: 45212
C3: MANAGED ACCT | X3: Current | AC3: IBD
H4: Cost | J4: P/L | N4: Group | P4: EPS | R4: pivot | S4: last | W4: cost | X4: Stop | Y4: Stop | Z4: % | AB4: EPS | AC4: Comp
A5: Symbol | B5: Position | C5: Name | D5: Qty | E5: Current | F5: Value | G5: Cost | H5: per share | I5: P/L $ | J5: per sh | K5: Date purch | L5: days held | M5: % incr | N5: Rank | O5: RS | P5: RS | Q5: pivot | R5: -0.07 | S5: low | T5: 0.25 | U5: 0.5 | V5: 1 | W5: -0.07 | X5: Loss | Y5: Loss% | Z5: of port | AB5: Due | AC5: Rank
A7: MNSO | B7: Long | C7: Minoso | D7: =1211.7123+804.6763 -> 2016.3886 | E7: 25.8 | F7: =E7*D7 -> 52022.826 | G7: =25318.9+15999 -> 41317.9 | H7: =G7/D7 -> 20.49104 | I7: =F7-G7 -> 10704.926 | J7: =E7-H7 -> 5.3089597 | K7: 45135 | L7: =DAYS360(K7,$C$1) -> 75 | M7: =(I7/G7) -> 0.25908688 | N7: 171 | O7: 99 | P7: 99 | Q7: 19.48 | R7: =Q7*0.93 -> 18.1164 | S7: 17.57 | T7: =Q7*1.25 -> 24.35 | U7: =Q7*1.5 -> 29.22 | V7: =Q7*2 -> 38.96 | W7: =H7-(H7*0.07) -> 19.056667 | X7: 26 | Y7: =(X7-H7)/H7 -> 0.26884725 | Z7: =F7/F$17 -> 0.10075957 | AB7: 45245 | AC7: 97 | AD7: Bought after 07/24 b/o. Added at the 21dema.
A8: AIT | B8: Long | C8: Applied Ind Tec | D8: 266.8733 | E8: 159.43 | F8: =E8*D8 -> 42547.61 | G8: 40425.83 | H8: =G8/D8 -> 151.47948 | I8: =F8-G8 -> 2121.7802 | J8: =E8-H8 -> 7.9505152 | K8: 45153 | L8: =DAYS360(K8,$C$1) -> 58 | M8: =(I8/G8) -> 0.052485755 | N8: 51 | O8: 94 | P8: 94 | Q8: 150.07 | R8: =Q8*0.93 -> 139.5651 | S8: 138.38 | T8: =Q8*1.25 -> 187.5875 | U8: =Q8*1.5 -> 225.105 | V8: =Q8*2 -> 300.14 | W8: =H8-(H8*0.07) -> 140.87592 | X8: 150 | Y8: =(X8-H8)/H8 -> -0.009766899 | Z8: =F8/F$17 -> 0.082407649 | AB8: 45225 | AC8: 95 | AD8: Bought at pivot test area.
A9: MTSI | B9: Long | C9: MACOM Tech Sol | D9: 507.0754 | E9: 79.68 | F9: =E9*D9 -> 40403.768 | G9: 41151 | H9: =G9/D9 -> 81.153611 | I9: =F9-G9 -> -747.23213 | J9: =E9-H9 -> -1.4736115 | K9: 45167 | L9: =DAYS360(K9,$C$1) -> 44 | M9: =(I9/G9) -> -0.018158298 | N9: 136 | O9: 95 | P9: 89 | Q9: 77.47 | R9: =Q9*0.93 -> 72.0471 | S9: 70.6 | T9: =Q9*1.25 -> 96.8375 | U9: =Q9*1.5 -> 116.205 | V9: =Q9*2 -> 154.94 | W9: =H9-(H9*0.07) -> 75.472859 | X9: 75.75 | Y9: =(X9-H9)/H9 -> -0.066584978 | Z9: =F9/F$17 -> 0.078255383 | AB9: 45244 | AC9: 87 | AD9: B/o on 08/23. Bought after pivot test.
A10: DUOL | B10: Long | C10: Duolingo | D10: 239.9158 | E10: 160.1 | F10: =E10*D10 -> 38410.52 | G10: 41719.17 | H10: =G10/D10 -> 173.89088 | I10: =F10-G10 -> -3308.6504 | J10: =E10-H10 -> -13.790882 | K10: 45208 | L10: =DAYS360(K10,$C$1) -> 4 | M10: =(I10/G10) -> -0.079307676 | N10: 29 | O10: 97 | P10: 74 | Q10: 167.35 | R10: =Q10*0.93 -> 155.6355 | S10: 147 | T10: =Q10*1.25 -> 209.1875 | U10: =Q10*1.5 -> 251.025 | V10: =Q10*2 -> 334.7 | W10: =H10-(H10*0.07) -> 161.71852 | X10: 161.7 | Y10: =(X10-H10)/H10 -> -0.070106504 | Z10: =F10/F$17 -> 0.074394792 | AB10: 45239 | AC10: 95 | AD10: Bought the b/o on +60% vol.
A11: ZS | B11: Long | C11: Zscaler | D11: 306.1703 | E11: 168.52 | F11: =E11*D11 -> 51595.819 | G11: 52148.98 | H11: =G11/D11 -> 170.32671 | I11: =F11-G11 -> -553.16104 | J11: =E11-H11 -> -1.8067103 | K11: 45208 | L11: =DAYS360(K11,$C$1) -> 4 | M11: =(I11/G11) -> -0.010607322 | N11: 20 | O11: 96 | P11: 99 | Q11: 167.5 | R11: =Q11*0.93 -> 155.775 | S11: 149.63 | T11: =Q11*1.25 -> 209.375 | U11: =Q11*1.5 -> 251.25 | V11: =Q11*2 -> 335 | W11: =H11-(H11*0.07) -> 158.40384 | X11: 158.4 | Y11: =(X11-H11)/H11 -> -0.070022548 | Z11: =F11/F$17 -> 0.099932526 | AB11: 45265 | AC11: 99 | AD11: Bought the b/o on +65% vol.
A12: BIL | B12: Long | C12: Tbill ETF | D12: 2778.4118 | E12: 91.62 | F12: =E12*D12 -> 254558.09 | G12: 254613.66 | H12: =G12/D12 -> 91.640001 | I12: =F12-G12 -> -55.570884 | J12: =E12-H12 -> -0.020000953 | L12: =DAYS360(K12,$C$1) -> 44563 | M12: =(I12/G12) -> -0.00021825571 | R12: =Q12*0.93 -> 0 | T12: =Q12*1.25 -> 0 | U12: =Q12*1.5 -> 0 | V12: =Q12*2 -> 0 | W12: =H12-(H12*0.07) -> 85.225201 | Y12: =(X12-H12)/H12 -> -1 | Z12: =F12/F$17 -> 0.49303671
A13: SQQQ | B13: Long | C13: QQQ Triple short | D13: 511.2918 | E13: 19.3 | F13: =E13*D13 -> 9867.9317 | G13: 24797.66 | H13: =G13/D13 -> 48.500015 | I13: =F13-G13 -> -14929.728 | J13: =E13-H13 -> -29.200015 | L13: =DAYS360(K13,$C$1) -> 44563 | M13: =(I13/G13) -> -0.60206198 | R13: =Q13*0.93 -> 0 | T13: =Q13*1.25 -> 0 | U13: =Q13*1.5 -> 0 | V13: =Q13*2 -> 0 | W13: =H13-(H13*0.07) -> 45.105014 | Y13: =(X13-H13)/H13 -> -1 | Z13: =F13/F$17 -> 0.019112544
F14: =E14*D14 -> 0 | H14: =G14/D14 -> #DIV/0! | I14: =F14-G14 -> 0 | J14: =E14-H14 -> #DIV/0! | L14: =DAYS360(K14,$C$1) -> 44563 | M14: =(I14/G14) -> #DIV/0! | R14: =Q14*0.93 -> 0 | T14: =Q14*1.25 -> 0 | U14: =Q14*1.5 -> 0 | V14: =Q14*2 -> 0 | W14: =H14-(H14*0.07) -> #DIV/0! | Y14: =(X14-H14)/H14 -> #DIV/0! | Z14: =F14/F$17 -> 0
A15: Sub-Total | F15: =SUM(F6:F14) -> 489406.56 | G15: =SUM(G6:G14) -> 496174.2 | I15: =SUM(I6:I14) -> -6767.6366
D16: Cash, other | F16: 26900 | G16: =F16/F17 -> 0.052100829
D17: Total | F17: =SUM(F15:F16) -> 516306.56
H18: Last week's close | I18: ='10-06-23'!F16 -> 517957.64 | K18: 45107 | L18: 509801
H19: Week's change | I19: =(F17-I18)/I18 -> -0.0031876654 | K19: chg % | L19: =(F17-L18)/L18 -> 0.012760986
M21: days
A22: 2023 Closed Trades - Managed Acct | D22: Qty | E22: Cost/sh | F22: $ cost | G22: $Proc | H22: Proc/sh | I22: Profit/loss | J22: % | K22: Date purch | L22: Date sold | M22: held | P22: Comments
A24: HXL | B24: Long | C24: Hexcel | D24: 665.9739 | E24: =F24/D24 -> 76.621621 | F24: 51028 | G24: 45324.79 | H24: =G24/D24 -> 68.057907 | I24: =G24-F24 -> -5703.21 | J24: =I24/F24 -> -0.11176629 | K24: 45106 | L24: 45132 | M24: =DAYS360(K24,L24) -> 26 | O24: Bad reaction to EPS report. Stopped out.
A25: MCK | B25: Long | C25: McKesson | D25: 123.3931 | E25: =F25/D25 -> 413.24004 | F25: 50990.97 | G25: 48894.94 | H25: =G25/D25 -> 396.25344 | I25: =G25-F25 -> -2096.03 | J25: =I25/F25 -> -0.041105906 | K25: 45104 | L25: 45138 | M25: =DAYS360(K25,L25) -> 34 | O25: Broke original stop and 50dma. EPS coming in a few days.
A26: DXCM | B26: Long | C26: DexCom | D26: 278.2008 | E26: =F26/D26 -> 128.41002 | F26: 35723.77 | G26: 34855.72 | H26: =G26/D26 -> 125.28979 | I26: =G26-F26 -> -868.05 | J26: =I26/F26 -> -0.024298947 | K26: 45106 | L26: 45138 | M26: =DAYS360(K26,L26) -> 32 | O26: The positive reaction to EPS report was rejected at the old high and reversed. Didn't like the action.
A27: IONQ | B27: Long | C27: IonQ | D27: 1007.1459 | E27: =F27/D27 -> 20.954908 | F27: 21104.65 | G27: 18099.32 | H27: =G27/D27 -> 17.970902 | I27: =G27-F27 -> -3005.33 | J27: =I27/F27 -> -0.14240132 | K27: 45181 | L27: 45183 | M27: =DAYS360(K27,L27) -> 2 | O27: Breakout failure. Only 4% position. Only .6% hit to total.
A28: SNPS | B28: Long | C28: Synopsys | D28: 115.8536 | E28: =F28/D28 -> 442.16002 | F28: 51225.83 | G28: 52055.28 | H28: =G28/D28 -> 449.31949 | I28: =G28-F28 -> 829.45 | J28: =I28/F28 -> 0.016192027 | K28: 45117 | L28: 45184 | M28: =DAYS360(K28,L28) -> 65 | O28: Sold to protect capital on an ugly day.
I32: =SUM(I24:I31) -> -10843.17 | J32: Avg
H33: # of losses | I33: 4 | J33: =SUM(J24:J31)/I33 -> -0.075845108
H34: # of wins | I34: 1 | J34: 0.0162

Sheet 10-20-23
C1: 45216
C3: MANAGED ACCT | X3: Current | AC3: IBD
H4: Cost | J4: P/L | N4: Group | P4: EPS | R4: pivot | S4: last | W4: cost | X4: Stop | Y4: Stop | Z4: % | AB4: EPS | AC4: Comp
A5: Symbol | B5: Position | C5: Name | D5: Qty | E5: Current | F5: Value | G5: Cost | H5: per share | I5: P/L $ | J5: per sh | K5: Date purch | L5: days held | M5: % incr | N5: Rank | O5: RS | P5: RS | Q5: pivot | R5: -0.07 | S5: low | T5: 0.25 | U5: 0.5 | V5: 1 | W5: -0.07 | X5: Loss | Y5: Loss% | Z5: of port | AB5: Due | AC5: Rank
A7: MNSO | B7: Long | C7: Minoso | D7: =1211.7123+804.6763 -> 2016.3886 | E7: 25.07 | F7: =E7*D7 -> 50550.862 | G7: =25318.9+15999 -> 41317.9 | H7: =G7/D7 -> 20.49104 | I7: =F7-G7 -> 9232.9622 | J7: =E7-H7 -> 4.5789597 | K7: 45135 | L7: =DAYS360(K7,$C$1) -> 79 | M7: =(I7/G7) -> 0.22346156 | N7: 154 | O7: 99 | P7: 99 | Q7: 19.48 | R7: =Q7*0.93 -> 18.1164 | S7: 23.61 | T7: =Q7*1.25 -> 24.35 | U7: =Q7*1.5 -> 29.22 | V7: =Q7*2 -> 38.96 | W7: =H7-(H7*0.07) -> 19.056667 | X7: 26 | Y7: =(X7-H7)/H7 -> 0.26884725 | Z7: =F7/F$17 -> 0.099444743 | AB7: 45245 | AC7: 97 | AD7: Bought after 07/24 b/o. Added at the 21dema.
A8: AIT | B8: Long | C8: Applied Ind Tec | D8: 266.8733 | E8: 153.86 | F8: =E8*D8 -> 41061.126 | G8: 40425.83 | H8: =G8/D8 -> 151.47948 | I8: =F8-G8 -> 635.29594 | J8: =E8-H8 -> 2.3805152 | K8: 45153 | L8: =DAYS360(K8,$C$1) -> 62 | M8: =(I8/G8) -> 0.015715099 | N8: 80 | O8: 93 | P8: 94 | Q8: 150.07 | R8: =Q8*0.93 -> 139.5651 | S8: 152.49 | T8: =Q8*1.25 -> 187.5875 | U8: =Q8*1.5 -> 225.105 | V8: =Q8*2 -> 300.14 | W8: =H8-(H8*0.07) -> 140.87592 | X8: 150 | Y8: =(X8-H8)/H8 -> -0.009766899 | Z8: =F8/F$17 -> 0.08077633 | AB8: 45225 | AC8: 94 | AD8: Bought at pivot test area.
F9: =E9*D9 -> 0 | H9: =G9/D9 -> #DIV/0! | I9: =F9-G9 -> 0 | J9: =E9-H9 -> #DIV/0! | M9: =(I9/G9) -> #DIV/0! | R9: =Q9*0.93 -> 0 | T9: =Q9*1.25 -> 0 | U9: =Q9*1.5 -> 0 | V9: =Q9*2 -> 0 | W9: =H9-(H9*0.07) -> #DIV/0! | Y9: =(X9-H9)/H9 -> #DIV/0! | Z9: =F9/F$17 -> 0
F10: =E10*D10 -> 0 | H10: =G10/D10 -> #DIV/0! | I10: =F10-G10 -> 0 | J10: =E10-H10 -> #DIV/0! | M10: =(I10/G10) -> #DIV/0! | R10: =Q10*0.93 -> 0 | T10: =Q10*1.25 -> 0 | U10: =Q10*1.5 -> 0 | V10: =Q10*2 -> 0 | W10: =H10-(H10*0.07) -> #DIV/0! | Y10: =(X10-H10)/H10 -> #DIV/0! | Z10: =F10/F$17 -> 0
F11: =E11*D11 -> 0 | H11: =G11/D11 -> #DIV/0! | I11: =F11-G11 -> 0 | J11: =E11-H11 -> #DIV/0! | M11: =(I11/G11) -> #DIV/0! | R11: =Q11*0.93 -> 0 | T11: =Q11*1.25 -> 0 | U11: =Q11*1.5 -> 0 | V11: =Q11*2 -> 0 | W11: =H11-(H11*0.07) -> #DIV/0! | Y11: =(X11-H11)/H11 -> #DIV/0! | Z11: =F11/F$17 -> 0
A12: BIL | B12: Long | C12: Tbill ETF | D12: 2778.4118 | E12: 91.71 | F12: =E12*D12 -> 254808.15 | G12: 254613.66 | H12: =G12/D12 -> 91.640001 | I12: =F12-G12 -> 194.48618 | J12: =E12-H12 -> 0.069999047 | M12: =(I12/G12) -> 0.00076384817 | R12: =Q12*0.93 -> 0 | T12: =Q12*1.25 -> 0 | U12: =Q12*1.5 -> 0 | V12: =Q12*2 -> 0 | W12: =H12-(H12*0.07) -> 85.225201 | Y12: =(X12-H12)/H12 -> -1 | Z12: =F12/F$17 -> 0.50126406
A13: SQQQ | B13: Long | C13: QQQ Triple short | D13: 511.2918 | E13: 21.08 | F13: =E13*D13 -> 10778.031 | G13: 24797.66 | H13: =G13/D13 -> 48.500015 | I13: =F13-G13 -> -14019.629 | J13: =E13-H13 -> -27.420015 | M13: =(I13/G13) -> -0.56536096 | R13: =Q13*0.93 -> 0 | T13: =Q13*1.25 -> 0 | U13: =Q13*1.5 -> 0 | V13: =Q13*2 -> 0 | W13: =H13-(H13*0.07) -> 45.105014 | Y13: =(X13-H13)/H13 -> -1 | Z13: =F13/F$17 -> 0.021202775
F14: =E14*D14 -> 0 | H14: =G14/D14 -> #DIV/0! | I14: =F14-G14 -> 0 | J14: =E14-H14 -> #DIV/0! | L14: =DAYS360(K14,$C$1) -> 44567 | M14: =(I14/G14) -> #DIV/0! | R14: =Q14*0.93 -> 0 | T14: =Q14*1.25 -> 0 | U14: =Q14*1.5 -> 0 | V14: =Q14*2 -> 0 | W14: =H14-(H14*0.07) -> #DIV/0! | Y14: =(X14-H14)/H14 -> #DIV/0! | Z14: =F14/F$17 -> 0
A15: Sub-Total | F15: =SUM(F6:F14) -> 357198.17 | G15: =SUM(G6:G14) -> 361155.05 | I15: =SUM(I6:I14) -> -3956.8845
D16: Cash, other | F16: 151133 | G16: =F16/F17 -> 0.29731209
D17: Total | F17: =SUM(F15:F16) -> 508331.17
H18: Last week's close | I18: ='10-13-23'!F17 -> 516306.56 | K18: 45107 | L18: 509801
H19: Week's change | I19: =(F17-I18)/I18 -> -0.01544702 | K19: chg % | L19: =(F17-L18)/L18 -> -0.0028831535
M21: days
A22: 2023 Closed Trades - Managed Acct | D22: Qty | E22: Cost/sh | F22: $ cost | G22: $Proc | H22: Proc/sh | I22: Profit/loss | J22: % | K22: Date purch | L22: Date sold | M22: held | P22: Comments
A24: HXL | B24: Long | C24: Hexcel | D24: 665.9739 | E24: =F24/D24 -> 76.621621 | F24: 51028 | G24: 45324.79 | H24: =G24/D24 -> 68.057907 | I24: =G24-F24 -> -5703.21 | J24: =I24/F24 -> -0.11176629 | K24: 45106 | L24: 45132 | M24: =DAYS360(K24,L24) -> 26 | O24: Bad reaction to EPS report. Stopped out.
A25: MCK | B25: Long | C25: McKesson | D25: 123.3931 | E25: =F25/D25 -> 413.24004 | F25: 50990.97 | G25: 48894.94 | H25: =G25/D25 -> 396.25344 | I25: =G25-F25 -> -2096.03 | J25: =I25/F25 -> -0.041105906 | K25: 45104 | L25: 45138 | M25: =DAYS360(K25,L25) -> 34 | O25: Broke original stop and 50dma. EPS coming in a few days.
A26: DXCM | B26: Long | C26: DexCom | D26: 278.2008 | E26: =F26/D26 -> 128.41002 | F26: 35723.77 | G26: 34855.72 | H26: =G26/D26 -> 125.28979 | I26: =G26-F26 -> -868.05 | J26: =I26/F26 -> -0.024298947 | K26: 45106 | L26: 45138 | M26: =DAYS360(K26,L26) -> 32 | O26: The positive reaction to EPS report was rejected at the old high and reversed. Didn't like the action.
A27: IONQ | B27: Long | C27: IonQ | D27: 1007.1459 | E27: =F27/D27 -> 20.954908 | F27: 21104.65 | G27: 18099.32 | H27: =G27/D27 -> 17.970902 | I27: =G27-F27 -> -3005.33 | J27: =I27/F27 -> -0.14240132 | K27: 45181 | L27: 45183 | M27: =DAYS360(K27,L27) -> 2 | O27: Breakout failure. Only 4% position. Only .6% hit to total.
A28: SNPS | B28: Long | C28: Synopsys | D28: 115.8536 | E28: =F28/D28 -> 442.16002 | F28: 51225.83 | G28: 52055.28 | H28: =G28/D28 -> 449.31949 | I28: =G28-F28 -> 829.45 | J28: =I28/F28 -> 0.016192027 | K28: 45117 | L28: 45184 | M28: =DAYS360(K28,L28) -> 65 | O28: Sold to protect capital on an ugly day.
A29: MTSI | B29: Long | C29: MACOM Tech Sol | D29: 507.0754 | E29: =F29/D29 -> 81.153611 | F29: 41151 | G29: 38871.01 | H29: =G29/D29 -> 76.657258 | I29: =G29-F29 -> -2279.99 | J29: =I29/F29 -> -0.055405458 | K29: 45167 | L29: 45216 | M29: =DAYS360(K29,L29) -> 48 | O29: Lost the 50dma in above avg vol. Sold prior to stop.
A30: ZS | B30: Long | C30: Zscaler | D30: 306.1703 | E30: =F30/D30 -> 170.32671 | F30: 52148.98 | G30: 49351.52 | H30: =G30/D30 -> 161.18977 | I30: =G30-F30 -> -2797.46 | J30: =I30/F30 -> -0.053643619 | K30: 45208 | L30: 45219 | M30: =DAYS360(K30,L30) -> 11 | O30: Lost the pivot in heavy vol. Sold prior to stop.
A31: DUOL | B31: Long | C31: Duolingo | D31: 239.9158 | E31: =F31/D31 -> 173.89088 | F31: 41719.17 | G31: 36026.28 | H31: =G31/D31 -> 150.16218 | I31: =G31-F31 -> -5692.89 | J31: =I31/F31 -> -0.13645741 | K31: 45208 | L31: 45219 | M31: =DAYS360(K31,L31) -> 11 | O31: Blew through my stop in a matter of an hour on Thurs. Sold Friday when it didn't recover early.
I32: =SUM(I24:I31) -> -21613.51 | J32: Avg
H33: # of losses | I33: 7 | J33: -0.0808
H34: # of wins | I34: 1 | J34: 0.0162

Sheet 10-27-23
C1: 45222
C3: MANAGED ACCT | X3: Current | AC3: IBD
H4: Cost | J4: P/L | N4: Group | P4: EPS | R4: pivot | S4: last | W4: cost | X4: Stop | Y4: Stop | Z4: % | AB4: EPS | AC4: Comp
A5: Symbol | B5: Position | C5: Name | D5: Qty | E5: Current | F5: Value | G5: Cost | H5: per share | I5: P/L $ | J5: per sh | K5: Date purch | L5: days held | M5: % incr | N5: Rank | O5: RS | P5: RS | Q5: pivot | R5: -0.07 | S5: low | T5: 0.25 | U5: 0.5 | V5: 1 | W5: -0.07 | X5: Loss | Y5: Loss% | Z5: of port | AB5: Due | AC5: Rank
A7: MNSO | B7: Long | C7: Minoso | D7: =1211.7123+804.6763 -> 2016.3886 | E7: 26.01 | F7: =E7*D7 -> 52446.267 | G7: =25318.9+15999 -> 41317.9 | H7: =G7/D7 -> 20.49104 | I7: =F7-G7 -> 11128.367 | J7: =E7-H7 -> 5.5189597 | K7: 45135 | L7: =DAYS360(K7,$C$1) -> 85 | M7: =(I7/G7) -> 0.26933526 | N7: 153 | O7: 99 | P7: 99 | Q7: 19.48 | R7: =Q7*0.93 -> 18.1164 | S7: 23.61 | T7: =Q7*1.25 -> 24.35 | U7: =Q7*1.5 -> 29.22 | V7: =Q7*2 -> 38.96 | W7: =H7-(H7*0.07) -> 19.056667 | X7: 26 | Y7: =(X7-H7)/H7 -> 0.26884725 | Z7: =F7/F$17 -> 0.10265303 | AB7: 45245 | AC7: 98 | AD7: Bought after 07/24 b/o. Added at the 21dema.
F8: =E8*D8 -> 0 | H8: =G8/D8 -> #DIV/0! | I8: =F8-G8 -> 0 | J8: =E8-H8 -> #DIV/0! | L8: =DAYS360(K8,$C$1) -> 44573 | M8: =(I8/G8) -> #DIV/0! | R8: =Q8*0.93 -> 0 | T8: =Q8*1.25 -> 0 | U8: =Q8*1.5 -> 0 | V8: =Q8*2 -> 0 | W8: =H8-(H8*0.07) -> #DIV/0! | Y8: =(X8-H8)/H8 -> #DIV/0! | Z8: =F8/F$17 -> 0
F9: =E9*D9 -> 0 | H9: =G9/D9 -> #DIV/0! | I9: =F9-G9 -> 0 | J9: =E9-H9 -> #DIV/0! | M9: =(I9/G9) -> #DIV/0! | R9: =Q9*0.93 -> 0 | T9: =Q9*1.25 -> 0 | U9: =Q9*1.5 -> 0 | V9: =Q9*2 -> 0 | W9: =H9-(H9*0.07) -> #DIV/0! | Y9: =(X9-H9)/H9 -> #DIV/0! | Z9: =F9/F$17 -> 0
F10: =E10*D10 -> 0 | H10: =G10/D10 -> #DIV/0! | I10: =F10-G10 -> 0 | J10: =E10-H10 -> #DIV/0! | M10: =(I10/G10) -> #DIV/0! | R10: =Q10*0.93 -> 0 | T10: =Q10*1.25 -> 0 | U10: =Q10*1.5 -> 0 | V10: =Q10*2 -> 0 | W10: =H10-(H10*0.07) -> #DIV/0! | Y10: =(X10-H10)/H10 -> #DIV/0! | Z10: =F10/F$17 -> 0
F11: =E11*D11 -> 0 | H11: =G11/D11 -> #DIV/0! | I11: =F11-G11 -> 0 | J11: =E11-H11 -> #DIV/0! | M11: =(I11/G11) -> #DIV/0! | R11: =Q11*0.93 -> 0 | T11: =Q11*1.25 -> 0 | U11: =Q11*1.5 -> 0 | V11: =Q11*2 -> 0 | W11: =H11-(H11*0.07) -> #DIV/0! | Y11: =(X11-H11)/H11 -> #DIV/0! | Z11: =F11/F$17 -> 0
A12: BIL | B12: Long | C12: Tbill ETF | D12: 2778.4118 | E12: 91.81 | F12: =E12*D12 -> 255085.99 | G12: 254613.66 | H12: =G12/D12 -> 91.640001 | I12: =F12-G12 -> 472.32736 | J12: =E12-H12 -> 0.16999905 | M12: =(I12/G12) -> 0.0018550747 | R12: =Q12*0.93 -> 0 | T12: =Q12*1.25 -> 0 | U12: =Q12*1.5 -> 0 | V12: =Q12*2 -> 0 | W12: =H12-(H12*0.07) -> 85.225201 | Y12: =(X12-H12)/H12 -> -1 | Z12: =F12/F$17 -> 0.49927955
A13: SQQQ | B13: Long | C13: QQQ Triple short | D13: 511.2918 | E13: 22.75 | F13: =E13*D13 -> 11631.888 | G13: 24797.66 | H13: =G13/D13 -> 48.500015 | I13: =F13-G13 -> -13165.772 | J13: =E13-H13 -> -25.750015 | M13: =(I13/G13) -> -0.53092798 | R13: =Q13*0.93 -> 0 | T13: =Q13*1.25 -> 0 | U13: =Q13*1.5 -> 0 | V13: =Q13*2 -> 0 | W13: =H13-(H13*0.07) -> 45.105014 | Y13: =(X13-H13)/H13 -> -1 | Z13: =F13/F$17 -> 0.022767084
F14: =E14*D14 -> 0 | H14: =G14/D14 -> #DIV/0! | I14: =F14-G14 -> 0 | J14: =E14-H14 -> #DIV/0! | L14: =DAYS360(K14,$C$1) -> 44573 | M14: =(I14/G14) -> #DIV/0! | R14: =Q14*0.93 -> 0 | T14: =Q14*1.25 -> 0 | U14: =Q14*1.5 -> 0 | V14: =Q14*2 -> 0 | W14: =H14-(H14*0.07) -> #DIV/0! | Y14: =(X14-H14)/H14 -> #DIV/0! | Z14: =F14/F$17 -> 0
A15: Sub-Total | F15: =SUM(F6:F14) -> 319164.14 | G15: =SUM(G6:G14) -> 320729.22 | I15: =SUM(I6:I14) -> -1565.0767
D16: Cash, other | F16: 191744 | G16: =F16/F17 -> 0.37530034
D17: Total | F17: =SUM(F15:F16) -> 510908.14
H18: Last week's close | I18: ='10-20-23'!F17 -> 508331.17 | K18: 45107 | L18: 509801
H19: Week's change | I19: =(F17-I18)/I18 -> 0.0050694862 | K19: chg % | L19: =(F17-L18)/L18 -> 0.0021717166
M21: days
A22: 2023 Closed Trades - Managed Acct | D22: Qty | E22: Cost/sh | F22: $ cost | G22: $Proc | H22: Proc/sh | I22: Profit/loss | J22: % | K22: Date purch | L22: Date sold | M22: held | P22: Comments
A24: HXL | B24: Long | C24: Hexcel | D24: 665.9739 | E24: =F24/D24 -> 76.621621 | F24: 51028 | G24: 45324.79 | H24: =G24/D24 -> 68.057907 | I24: =G24-F24 -> -5703.21 | J24: =I24/F24 -> -0.11176629 | K24: 45106 | L24: 45132 | M24: =DAYS360(K24,L24) -> 26 | O24: Bad reaction to EPS report. Stopped out.
A25: MCK | B25: Long | C25: McKesson | D25: 123.3931 | E25: =F25/D25 -> 413.24004 | F25: 50990.97 | G25: 48894.94 | H25: =G25/D25 -> 396.25344 | I25: =G25-F25 -> -2096.03 | J25: =I25/F25 -> -0.041105906 | K25: 45104 | L25: 45138 | M25: =DAYS360(K25,L25) -> 34 | O25: Broke original stop and 50dma. EPS coming in a few days.
A26: DXCM | B26: Long | C26: DexCom | D26: 278.2008 | E26: =F26/D26 -> 128.41002 | F26: 35723.77 | G26: 34855.72 | H26: =G26/D26 -> 125.28979 | I26: =G26-F26 -> -868.05 | J26: =I26/F26 -> -0.024298947 | K26: 45106 | L26: 45138 | M26: =DAYS360(K26,L26) -> 32 | O26: The positive reaction to EPS report was rejected at the old high and reversed. Didn't like the action.
A27: IONQ | B27: Long | C27: IonQ | D27: 1007.1459 | E27: =F27/D27 -> 20.954908 | F27: 21104.65 | G27: 18099.32 | H27: =G27/D27 -> 17.970902 | I27: =G27-F27 -> -3005.33 | J27: =I27/F27 -> -0.14240132 | K27: 45181 | L27: 45183 | M27: =DAYS360(K27,L27) -> 2 | O27: Breakout failure. Only 4% position. Only .6% hit to total.
A28: SNPS | B28: Long | C28: Synopsys | D28: 115.8536 | E28: =F28/D28 -> 442.16002 | F28: 51225.83 | G28: 52055.28 | H28: =G28/D28 -> 449.31949 | I28: =G28-F28 -> 829.45 | J28: =I28/F28 -> 0.016192027 | K28: 45117 | L28: 45184 | M28: =DAYS360(K28,L28) -> 65 | O28: Sold to protect capital on an ugly day.
A29: MTSI | B29: Long | C29: MACOM Tech Sol | D29: 507.0754 | E29: =F29/D29 -> 81.153611 | F29: 41151 | G29: 38871.01 | H29: =G29/D29 -> 76.657258 | I29: =G29-F29 -> -2279.99 | J29: =I29/F29 -> -0.055405458 | K29: 45167 | L29: 45216 | M29: =DAYS360(K29,L29) -> 48 | O29: Lost the 50dma in above avg vol. Sold prior to stop.
A30: ZS | B30: Long | C30: Zscaler | D30: 306.1703 | E30: =F30/D30 -> 170.32671 | F30: 52148.98 | G30: 49351.52 | H30: =G30/D30 -> 161.18977 | I30: =G30-F30 -> -2797.46 | J30: =I30/F30 -> -0.053643619 | K30: 45208 | L30: 45219 | M30: =DAYS360(K30,L30) -> 11 | O30: Lost the pivot in heavy vol. Sold prior to stop.
A31: DUOL | B31: Long | C31: Duolingo | D31: 239.9158 | E31: =F31/D31 -> 173.89088 | F31: 41719.17 | G31: 36026.28 | H31: =G31/D31 -> 150.16218 | I31: =G31-F31 -> -5692.89 | J31: =I31/F31 -> -0.13645741 | K31: 45208 | L31: 45219 | M31: =DAYS360(K31,L31) -> 11 | O31: Blew through my stop in a matter of an hour on Thurs. Sold Friday when it didn't recover early.
A32: AIT | B32: Long | C32: Applied Ind Tec | D32: 266.8733 | E32: =F32/D32 -> 151.47948 | F32: 40425.83 | G32: 40616.77 | H32: =G32/D32 -> 152.19496 | I32: =G32-F32 -> 190.94 | J32: =I32/F32 -> 0.0047232178 | K32: 45153 | L32: 45224 | M32: =DAYS360(K32,L32) -> 70 | O32: Sold to protect my cost.
I33: =SUM(I24:I32) -> -21422.57 | J33: Avg
H34: # of losses | I34: 7 | J34: -0.0808
H35: # of wins | I35: 1 | J35: 0.0105

Sheet 11-03-23
C1: 45233
C3: MANAGED ACCT | X3: Current | AC3: IBD
H4: Cost | J4: P/L | N4: Group | P4: EPS | R4: pivot | S4: last | W4: cost | X4: Stop | Y4: Stop | Z4: % | AB4: EPS | AC4: Comp
A5: Symbol | B5: Position | C5: Name | D5: Qty | E5: Current | F5: Value | G5: Cost | H5: per share | I5: P/L $ | J5: per sh | K5: Date purch | L5: days held | M5: % incr | N5: Rank | O5: RS | P5: RS | Q5: pivot | R5: -0.07 | S5: low | T5: 0.25 | U5: 0.5 | V5: 1 | W5: -0.07 | X5: Loss | Y5: Loss% | Z5: of port | AB5: Due | AC5: Rank
A7: MNSO | B7: Long | C7: Minoso | D7: =1211.7123+804.6763 -> 2016.3886 | E7: 26.64 | F7: =E7*D7 -> 53716.592 | G7: =25318.9+15999 -> 41317.9 | H7: =G7/D7 -> 20.49104 | I7: =F7-G7 -> 12398.692 | J7: =E7-H7 -> 6.1489597 | K7: 45135 | L7: =DAYS360(K7,$C$1) -> 95 | M7: =(I7/G7) -> 0.30008041 | N7: 159 | O7: 99 | P7: 99 | Q7: 19.48 | R7: =Q7*0.93 -> 18.1164 | S7: 23.61 | T7: =Q7*1.25 -> 24.35 | U7: =Q7*1.5 -> 29.22 | V7: =Q7*2 -> 38.96 | W7: =H7-(H7*0.07) -> 19.056667 | X7: 26 | Y7: =(X7-H7)/H7 -> 0.26884725 | Z7: =F7/F$17 -> 0.10536985 | AB7: 45245 | AC7: 98 | AD7: Bought after 07/24 b/o. Added at the 21dema.
A8: TS | B8: Long | C8: Tenaris | D8: 1166.935 | E8: 34.82 | F8: =E8*D8 -> 40632.677 | G8: 40941.92 | H8: =G8/D8 -> 35.085005 | I8: =F8-G8 -> -309.2433 | J8: =E8-H8 -> -0.26500473 | K8: 45233 | L8: =DAYS360(K8,$C$1) -> 0 | M8: =(I8/G8) -> -0.0075532193 | N8: 58 | O8: 87 | P8: 69 | Q8: 34.2 | R8: =Q8*0.93 -> 31.806 | S8: 31.07 | T8: =Q8*1.25 -> 42.75 | U8: =Q8*1.5 -> 51.3 | V8: =Q8*2 -> 68.4 | W8: =H8-(H8*0.07) -> 32.629054 | X8: 32.75 | Y8: =(X8-H8)/H8 -> -0.066552784 | Z8: =F8/F$17 -> 0.079704595 | AB8: 45343
F9: =E9*D9 -> 0 | H9: =G9/D9 -> #DIV/0! | I9: =F9-G9 -> 0 | J9: =E9-H9 -> #DIV/0! | M9: =(I9/G9) -> #DIV/0! | R9: =Q9*0.93 -> 0 | T9: =Q9*1.25 -> 0 | U9: =Q9*1.5 -> 0 | V9: =Q9*2 -> 0 | W9: =H9-(H9*0.07) -> #DIV/0! | Y9: =(X9-H9)/H9 -> #DIV/0! | Z9: =F9/F$17 -> 0
F10: =E10*D10 -> 0 | H10: =G10/D10 -> #DIV/0! | I10: =F10-G10 -> 0 | J10: =E10-H10 -> #DIV/0! | M10: =(I10/G10) -> #DIV/0! | R10: =Q10*0.93 -> 0 | T10: =Q10*1.25 -> 0 | U10: =Q10*1.5 -> 0 | V10: =Q10*2 -> 0 | W10: =H10-(H10*0.07) -> #DIV/0! | Y10: =(X10-H10)/H10 -> #DIV/0! | Z10: =F10/F$17 -> 0
F11: =E11*D11 -> 0 | H11: =G11/D11 -> #DIV/0! | I11: =F11-G11 -> 0 | J11: =E11-H11 -> #DIV/0! | M11: =(I11/G11) -> #DIV/0! | R11: =Q11*0.93 -> 0 | T11: =Q11*1.25 -> 0 | U11: =Q11*1.5 -> 0 | V11: =Q11*2 -> 0 | W11: =H11-(H11*0.07) -> #DIV/0! | Y11: =(X11-H11)/H11 -> #DIV/0! | Z11: =F11/F$17 -> 0
A12: BIL | B12: Long | C12: Tbill ETF | D12: 2778.4118 | E12: 91.48 | F12: =E12*D12 -> 254169.11 | G12: 254613.66 | H12: =G12/D12 -> 91.640001 | I12: =F12-G12 -> -444.54854 | J12: =E12-H12 -> -0.16000095 | M12: =(I12/G12) -> -0.0017459728 | R12: =Q12*0.93 -> 0 | T12: =Q12*1.25 -> 0 | U12: =Q12*1.5 -> 0 | V12: =Q12*2 -> 0 | W12: =H12-(H12*0.07) -> 85.225201 | Y12: =(X12-H12)/H12 -> -1 | Z12: =F12/F$17 -> 0.49857523
A13: SQQQ | B13: Long | C13: QQQ Triple short | D13: 511.2918 | E13: 18.82 | F13: =E13*D13 -> 9622.5117 | G13: 24797.66 | H13: =G13/D13 -> 48.500015 | I13: =F13-G13 -> -15175.148 | J13: =E13-H13 -> -29.680015 | M13: =(I13/G13) -> -0.61195888 | R13: =Q13*0.93 -> 0 | T13: =Q13*1.25 -> 0 | U13: =Q13*1.5 -> 0 | V13: =Q13*2 -> 0 | W13: =H13-(H13*0.07) -> 45.105014 | Y13: =(X13-H13)/H13 -> -1 | Z13: =F13/F$17 -> 0.018875409
F14: =E14*D14 -> 0 | H14: =G14/D14 -> #DIV/0! | I14: =F14-G14 -> 0 | J14: =E14-H14 -> #DIV/0! | L14: =DAYS360(K14,$C$1) -> 44583 | M14: =(I14/G14) -> #DIV/0! | R14: =Q14*0.93 -> 0 | T14: =Q14*1.25 -> 0 | U14: =Q14*1.5 -> 0 | V14: =Q14*2 -> 0 | W14: =H14-(H14*0.07) -> #DIV/0! | Y14: =(X14-H14)/H14 -> #DIV/0! | Z14: =F14/F$17 -> 0
A15: Sub-Total | F15: =SUM(F6:F14) -> 358140.89 | G15: =SUM(G6:G14) -> 361671.14 | I15: =SUM(I6:I14) -> -3530.2479
D16: Cash, other | F16: 151650 | G16: =F16/F17 -> 0.29747491
D17: Total | F17: =SUM(F15:F16) -> 509790.89
H18: Last week's close | I18: ='10-27-23'!F17 -> 510908.14 | K18: 45107 | L18: 509801
H19: Week's change | I19: =(F17-I18)/I18 -> -0.0021867946 | K19: chg % | L19: =(F17-L18)/L18 -> -1.9827062e-05
M21: days
A22: 2023 Closed Trades - Managed Acct | D22: Qty | E22: Cost/sh | F22: $ cost | G22: $Proc | H22: Proc/sh | I22: Profit/loss | J22: % | K22: Date purch | L22: Date sold | M22: held | P22: Comments
A24: HXL | B24: Long | C24: Hexcel | D24: 665.9739 | E24: =F24/D24 -> 76.621621 | F24: 51028 | G24: 45324.79 | H24: =G24/D24 -> 68.057907 | I24: =G24-F24 -> -5703.21 | J24: =I24/F24 -> -0.11176629 | K24: 45106 | L24: 45132 | M24: =DAYS360(K24,L24) -> 26 | O24: Bad reaction to EPS report. Stopped out.
A25: MCK | B25: Long | C25: McKesson | D25: 123.3931 | E25: =F25/D25 -> 413.24004 | F25: 50990.97 | G25: 48894.94 | H25: =G25/D25 -> 396.25344 | I25: =G25-F25 -> -2096.03 | J25: =I25/F25 -> -0.041105906 | K25: 45104 | L25: 45138 | M25: =DAYS360(K25,L25) -> 34 | O25: Broke original stop and 50dma. EPS coming in a few days.
A26: DXCM | B26: Long | C26: DexCom | D26: 278.2008 | E26: =F26/D26 -> 128.41002 | F26: 35723.77 | G26: 34855.72 | H26: =G26/D26 -> 125.28979 | I26: =G26-F26 -> -868.05 | J26: =I26/F26 -> -0.024298947 | K26: 45106 | L26: 45138 | M26: =DAYS360(K26,L26) -> 32 | O26: The positive reaction to EPS report was rejected at the old high and reversed. Didn't like the action.
A27: IONQ | B27: Long | C27: IonQ | D27: 1007.1459 | E27: =F27/D27 -> 20.954908 | F27: 21104.65 | G27: 18099.32 | H27: =G27/D27 -> 17.970902 | I27: =G27-F27 -> -3005.33 | J27: =I27/F27 -> -0.14240132 | K27: 45181 | L27: 45183 | M27: =DAYS360(K27,L27) -> 2 | O27: Breakout failure. Only 4% position. Only .6% hit to total.
A28: SNPS | B28: Long | C28: Synopsys | D28: 115.8536 | E28: =F28/D28 -> 442.16002 | F28: 51225.83 | G28: 52055.28 | H28: =G28/D28 -> 449.31949 | I28: =G28-F28 -> 829.45 | J28: =I28/F28 -> 0.016192027 | K28: 45117 | L28: 45184 | M28: =DAYS360(K28,L28) -> 65 | O28: Sold to protect capital on an ugly day.
A29: MTSI | B29: Long | C29: MACOM Tech Sol | D29: 507.0754 | E29: =F29/D29 -> 81.153611 | F29: 41151 | G29: 38871.01 | H29: =G29/D29 -> 76.657258 | I29: =G29-F29 -> -2279.99 | J29: =I29/F29 -> -0.055405458 | K29: 45167 | L29: 45216 | M29: =DAYS360(K29,L29) -> 48 | O29: Lost the 50dma in above avg vol. Sold prior to stop.
A30: ZS | B30: Long | C30: Zscaler | D30: 306.1703 | E30: =F30/D30 -> 170.32671 | F30: 52148.98 | G30: 49351.52 | H30: =G30/D30 -> 161.18977 | I30: =G30-F30 -> -2797.46 | J30: =I30/F30 -> -0.053643619 | K30: 45208 | L30: 45219 | M30: =DAYS360(K30,L30) -> 11 | O30: Lost the pivot in heavy vol. Sold prior to stop.
A31: DUOL | B31: Long | C31: Duolingo | D31: 239.9158 | E31: =F31/D31 -> 173.89088 | F31: 41719.17 | G31: 36026.28 | H31: =G31/D31 -> 150.16218 | I31: =G31-F31 -> -5692.89 | J31: =I31/F31 -> -0.13645741 | K31: 45208 | L31: 45219 | M31: =DAYS360(K31,L31) -> 11 | O31: Blew through my stop in a matter of an hour on Thurs. Sold Friday when it didn't recover early.
A32: AIT | B32: Long | C32: Applied Ind Tec | D32: 266.8733 | E32: =F32/D32 -> 151.47948 | F32: 40425.83 | G32: 40616.77 | H32: =G32/D32 -> 152.19496 | I32: =G32-F32 -> 190.94 | J32: =I32/F32 -> 0.0047232178 | K32: 45153 | L32: 45224 | M32: =DAYS360(K32,L32) -> 70 | O32: Sold to protect my cost.
I33: =SUM(I24:I32) -> -21422.57 | J33: Avg
H34: # of losses | I34: 7 | J34: -0.0808
H35: # of wins | I35: 2 | J35: 0.0105

Sheet 11-10-23
C1: 45240
C3: MANAGED ACCT | X3: Current | AC3: IBD
H4: Cost | J4: P/L | N4: Group | P4: EPS | R4: pivot | S4: last | W4: cost | X4: Stop | Y4: Stop | Z4: % | AB4: EPS | AC4: Comp
A5: Symbol | B5: Position | C5: Name | D5: Qty | E5: Current | F5: Value | G5: Cost | H5: per share | I5: P/L $ | J5: per sh | K5: Date purch | L5: days held | M5: % incr | N5: Rank | O5: RS | P5: RS | Q5: pivot | R5: -0.07 | S5: low | T5: 0.25 | U5: 0.5 | V5: 1 | W5: -0.07 | X5: Loss | Y5: Loss% | Z5: of port | AB5: Due | AC5: Rank
A7: MNSO | B7: Long | C7: Minoso | D7: =1211.7123+804.6763 -> 2016.3886 | E7: 25.78 | F7: =E7*D7 -> 51982.498 | G7: =25318.9+15999 -> 41317.9 | H7: =G7/D7 -> 20.49104 | I7: =F7-G7 -> 10664.598 | J7: =E7-H7 -> 5.2889597 | K7: 45135 | L7: =DAYS360(K7,$C$1) -> 102 | M7: =(I7/G7) -> 0.25811085 | N7: 159 | O7: 99 | P7: 99 | Q7: 19.48 | R7: =Q7*0.93 -> 18.1164 | S7: 23.61 | T7: =Q7*1.25 -> 24.35 | U7: =Q7*1.5 -> 29.22 | V7: =Q7*2 -> 38.96 | W7: =H7-(H7*0.07) -> 19.056667 | X7: 26 | Y7: =(X7-H7)/H7 -> 0.26884725 | Z7: =F7/F$17 -> 0.10271524 | AB7: 45251 | AC7: 97 | AD7: Bought after 07/24 b/o. Added at the 21dema.
A8: TS | B8: Long | C8: Tenaris | D8: 1166.935 | E8: 34.65 | F8: =E8*D8 -> 40434.298 | G8: 40941.92 | H8: =G8/D8 -> 35.085005 | I8: =F8-G8 -> -507.62225 | J8: =E8-H8 -> -0.43500473 | K8: 45233 | L8: =DAYS360(K8,$C$1) -> 7 | M8: =(I8/G8) -> -0.012398594 | N8: 55 | O8: 86 | P8: 68 | Q8: 34.2 | R8: =Q8*0.93 -> 31.806 | S8: 31.07 | T8: =Q8*1.25 -> 42.75 | U8: =Q8*1.5 -> 51.3 | V8: =Q8*2 -> 68.4 | W8: =H8-(H8*0.07) -> 32.629054 | X8: 32.75 | Y8: =(X8-H8)/H8 -> -0.066552784 | Z8: =F8/F$17 -> 0.07989648 | AB8: 45343 | AC8: 92 | AD8: Bought day after gapping out of base.
A9: AXON | B9: Long | C9: Axon Enterprise | D9: 267.8431 | E9: 217.94 | F9: =E9*D9 -> 58373.725 | G9: 61166.24 | H9: =G9/D9 -> 228.36594 | I9: =F9-G9 -> -2792.5148 | J9: =E9-H9 -> -10.425935 | K9: 45238 | L9: =DAYS360(K9,$C$1) -> 2 | M9: =(I9/G9) -> -0.045654511 | N9: 74 | O9: 88 | P9: 99 | Q9: 223.3 | R9: =Q9*0.93 -> 207.669 | S9: 199.29 | T9: =Q9*1.25 -> 279.125 | U9: =Q9*1.5 -> 334.95 | V9: =Q9*2 -> 446.6 | W9: =H9-(H9*0.07) -> 212.38032 | X9: 212 | Y9: =(X9-H9)/H9 -> -0.071665396 | Z9: =F9/F$17 -> 0.11534404 | AB9: 45349 | AC9: 99 | AD9: Bought as it gapped out of base on EPS.
F10: =E10*D10 -> 0 | H10: =G10/D10 -> #DIV/0! | I10: =F10-G10 -> 0 | J10: =E10-H10 -> #DIV/0! | M10: =(I10/G10) -> #DIV/0! | R10: =Q10*0.93 -> 0 | T10: =Q10*1.25 -> 0 | U10: =Q10*1.5 -> 0 | V10: =Q10*2 -> 0 | W10: =H10-(H10*0.07) -> #DIV/0! | Y10: =(X10-H10)/H10 -> #DIV/0! | Z10: =F10/F$17 -> 0
F11: =E11*D11 -> 0 | H11: =G11/D11 -> #DIV/0! | I11: =F11-G11 -> 0 | J11: =E11-H11 -> #DIV/0! | M11: =(I11/G11) -> #DIV/0! | R11: =Q11*0.93 -> 0 | T11: =Q11*1.25 -> 0 | U11: =Q11*1.5 -> 0 | V11: =Q11*2 -> 0 | W11: =H11-(H11*0.07) -> #DIV/0! | Y11: =(X11-H11)/H11 -> #DIV/0! | Z11: =F11/F$17 -> 0
A12: BIL | B12: Long | C12: Tbill ETF | D12: 2778.4118 | E12: 91.58 | F12: =E12*D12 -> 254446.95 | G12: 254613.66 | H12: =G12/D12 -> 91.640001 | I12: =F12-G12 -> -166.70736 | J12: =E12-H12 -> -0.060000953 | M12: =(I12/G12) -> -0.00065474632 | R12: =Q12*0.93 -> 0 | T12: =Q12*1.25 -> 0 | U12: =Q12*1.5 -> 0 | V12: =Q12*2 -> 0 | W12: =H12-(H12*0.07) -> 85.225201 | Y12: =(X12-H12)/H12 -> -1 | Z12: =F12/F$17 -> 0.50277653
A13: SQQQ | B13: Long | C13: QQQ Triple short | D13: 511.2918 | E13: 17.28 | F13: =E13*D13 -> 8835.1223 | G13: 24797.66 | H13: =G13/D13 -> 48.500015 | I13: =F13-G13 -> -15962.538 | J13: =E13-H13 -> -31.220015 | M13: =(I13/G13) -> -0.64371145 | R13: =Q13*0.93 -> 0 | T13: =Q13*1.25 -> 0 | U13: =Q13*1.5 -> 0 | V13: =Q13*2 -> 0 | W13: =H13-(H13*0.07) -> 45.105014 | Y13: =(X13-H13)/H13 -> -1 | Z13: =F13/F$17 -> 0.017457832
F14: =E14*D14 -> 0 | H14: =G14/D14 -> #DIV/0! | I14: =F14-G14 -> 0 | J14: =E14-H14 -> #DIV/0! | L14: =DAYS360(K14,$C$1) -> 44590 | M14: =(I14/G14) -> #DIV/0! | R14: =Q14*0.93 -> 0 | T14: =Q14*1.25 -> 0 | U14: =Q14*1.5 -> 0 | V14: =Q14*2 -> 0 | W14: =H14-(H14*0.07) -> #DIV/0! | Y14: =(X14-H14)/H14 -> #DIV/0! | Z14: =F14/F$17 -> 0
A15: Sub-Total | F15: =SUM(F6:F14) -> 414072.6 | G15: =SUM(G6:G14) -> 422837.38 | I15: =SUM(I6:I14) -> -8764.784
D16: Cash, other | F16: 92011 | G16: =F16/F17 -> 0.18180988
D17: Total | F17: =SUM(F15:F16) -> 506083.6
H18: Last week's close | I18: ='11-03-23'!F17 -> 509790.89 | K18: 45107 | L18: 509801
H19: Week's change | I19: =(F17-I18)/I18 -> -0.0072721898 | K19: chg % | L19: =(F17-L18)/L18 -> -0.0072918727
M21: days
A22: 2023 Closed Trades - Managed Acct | D22: Qty | E22: Cost/sh | F22: $ cost | G22: $Proc | H22: Proc/sh | I22: Profit/loss | J22: % | K22: Date purch | L22: Date sold | M22: held | P22: Comments
A24: HXL | B24: Long | C24: Hexcel | D24: 665.9739 | E24: =F24/D24 -> 76.621621 | F24: 51028 | G24: 45324.79 | H24: =G24/D24 -> 68.057907 | I24: =G24-F24 -> -5703.21 | J24: =I24/F24 -> -0.11176629 | K24: 45106 | L24: 45132 | M24: =DAYS360(K24,L24) -> 26 | O24: Bad reaction to EPS report. Stopped out.
A25: MCK | B25: Long | C25: McKesson | D25: 123.3931 | E25: =F25/D25 -> 413.24004 | F25: 50990.97 | G25: 48894.94 | H25: =G25/D25 -> 396.25344 | I25: =G25-F25 -> -2096.03 | J25: =I25/F25 -> -0.041105906 | K25: 45104 | L25: 45138 | M25: =DAYS360(K25,L25) -> 34 | O25: Broke original stop and 50dma. EPS coming in a few days.
A26: DXCM | B26: Long | C26: DexCom | D26: 278.2008 | E26: =F26/D26 -> 128.41002 | F26: 35723.77 | G26: 34855.72 | H26: =G26/D26 -> 125.28979 | I26: =G26-F26 -> -868.05 | J26: =I26/F26 -> -0.024298947 | K26: 45106 | L26: 45138 | M26: =DAYS360(K26,L26) -> 32 | O26: The positive reaction to EPS report was rejected at the old high and reversed. Didn't like the action.
A27: IONQ | B27: Long | C27: IonQ | D27: 1007.1459 | E27: =F27/D27 -> 20.954908 | F27: 21104.65 | G27: 18099.32 | H27: =G27/D27 -> 17.970902 | I27: =G27-F27 -> -3005.33 | J27: =I27/F27 -> -0.14240132 | K27: 45181 | L27: 45183 | M27: =DAYS360(K27,L27) -> 2 | O27: Breakout failure. Only 4% position. Only .6% hit to total.
A28: SNPS | B28: Long | C28: Synopsys | D28: 115.8536 | E28: =F28/D28 -> 442.16002 | F28: 51225.83 | G28: 52055.28 | H28: =G28/D28 -> 449.31949 | I28: =G28-F28 -> 829.45 | J28: =I28/F28 -> 0.016192027 | K28: 45117 | L28: 45184 | M28: =DAYS360(K28,L28) -> 65 | O28: Sold to protect capital on an ugly day.
A29: MTSI | B29: Long | C29: MACOM Tech Sol | D29: 507.0754 | E29: =F29/D29 -> 81.153611 | F29: 41151 | G29: 38871.01 | H29: =G29/D29 -> 76.657258 | I29: =G29-F29 -> -2279.99 | J29: =I29/F29 -> -0.055405458 | K29: 45167 | L29: 45216 | M29: =DAYS360(K29,L29) -> 48 | O29: Lost the 50dma in above avg vol. Sold prior to stop.
A30: ZS | B30: Long | C30: Zscaler | D30: 306.1703 | E30: =F30/D30 -> 170.32671 | F30: 52148.98 | G30: 49351.52 | H30: =G30/D30 -> 161.18977 | I30: =G30-F30 -> -2797.46 | J30: =I30/F30 -> -0.053643619 | K30: 45208 | L30: 45219 | M30: =DAYS360(K30,L30) -> 11 | O30: Lost the pivot in heavy vol. Sold prior to stop.
A31: DUOL | B31: Long | C31: Duolingo | D31: 239.9158 | E31: =F31/D31 -> 173.89088 | F31: 41719.17 | G31: 36026.28 | H31: =G31/D31 -> 150.16218 | I31: =G31-F31 -> -5692.89 | J31: =I31/F31 -> -0.13645741 | K31: 45208 | L31: 45219 | M31: =DAYS360(K31,L31) -> 11 | O31: Blew through my stop in a matter of an hour on Thurs. Sold Friday when it didn't recover early.
A32: AIT | B32: Long | C32: Applied Ind Tec | D32: 266.8733 | E32: =F32/D32 -> 151.47948 | F32: 40425.83 | G32: 40616.77 | H32: =G32/D32 -> 152.19496 | I32: =G32-F32 -> 190.94 | J32: =I32/F32 -> 0.0047232178 | K32: 45153 | L32: 45224 | M32: =DAYS360(K32,L32) -> 70 | O32: Sold to protect my cost.
I33: =SUM(I24:I32) -> -21422.57 | J33: Avg
H34: # of losses | I34: 7 | J34: -0.0808
H35: # of wins | I35: 2 | J35: 0.0105

Sheet 11-17-23
C1: 45247
C3: MANAGED ACCT | X3: Current | AC3: IBD
H4: Cost | J4: P/L | N4: Group | P4: EPS | R4: pivot | S4: last | W4: cost | X4: Stop | Y4: Stop | Z4: % | AB4: EPS | AC4: Comp
A5: Symbol | B5: Position | C5: Name | D5: Qty | E5: Current | F5: Value | G5: Cost | H5: per share | I5: P/L $ | J5: per sh | K5: Date purch | L5: days held | M5: % incr | N5: Rank | O5: RS | P5: RS | Q5: pivot | R5: -0.07 | S5: low | T5: 0.25 | U5: 0.5 | V5: 1 | W5: -0.07 | X5: Loss | Y5: Loss% | Z5: of port | AB5: Due | AC5: Rank
A7: MNSO | B7: Long | C7: Minoso | D7: =1211.7123+804.6763 -> 2016.3886 | E7: 26.65 | F7: =E7*D7 -> 53736.756 | G7: =25318.9+15999 -> 41317.9 | H7: =G7/D7 -> 20.49104 | I7: =F7-G7 -> 12418.856 | J7: =E7-H7 -> 6.1589597 | K7: 45135 | L7: =DAYS360(K7,$C$1) -> 109 | M7: =(I7/G7) -> 0.30056843 | N7: 138 | O7: 99 | P7: 99 | Q7: 19.48 | R7: =Q7*0.93 -> 18.1164 | S7: 23.61 | T7: =Q7*1.25 -> 24.35 | U7: =Q7*1.5 -> 29.22 | V7: =Q7*2 -> 38.96 | W7: =H7-(H7*0.07) -> 19.056667 | X7: 26 | Y7: =(X7-H7)/H7 -> 0.26884725 | Z7: =F7/F$18 -> 0.10569577 | AB7: 45251 | AC7: 98 | AD7: Bought after 07/24 b/o. Added at the 21dema.
A8: TS | B8: Long | C8: Tenaris | D8: 1166.935 | E8: 34.3 | F8: =E8*D8 -> 40025.87 | G8: 40941.92 | H8: =G8/D8 -> 35.085005 | I8: =F8-G8 -> -916.0495 | J8: =E8-H8 -> -0.78500473 | K8: 45233 | L8: =DAYS360(K8,$C$1) -> 14 | M8: =(I8/G8) -> -0.022374366 | N8: 52 | O8: 74 | P8: 69 | Q8: 34.2 | R8: =Q8*0.93 -> 31.806 | S8: 31.07 | T8: =Q8*1.25 -> 42.75 | U8: =Q8*1.5 -> 51.3 | V8: =Q8*2 -> 68.4 | W8: =H8-(H8*0.07) -> 32.629054 | X8: 32.75 | Y8: =(X8-H8)/H8 -> -0.066552784 | Z8: =F8/F$18 -> 0.078727591 | AB8: 45343 | AC8: 90 | AD8: Bought day after gapping out of base.
A9: AXON | B9: Long | C9: Axon Enterprise | D9: 267.8431 | E9: 223.48 | F9: =E9*D9 -> 59857.576 | G9: 61166.24 | H9: =G9/D9 -> 228.36594 | I9: =F9-G9 -> -1308.664 | J9: =E9-H9 -> -4.8859351 | K9: 45238 | L9: =DAYS360(K9,$C$1) -> 9 | M9: =(I9/G9) -> -0.021395201 | N9: 55 | O9: 88 | P9: 99 | Q9: 223.3 | R9: =Q9*0.93 -> 207.669 | S9: 199.29 | T9: =Q9*1.25 -> 279.125 | U9: =Q9*1.5 -> 334.95 | V9: =Q9*2 -> 446.6 | W9: =H9-(H9*0.07) -> 212.38032 | X9: 212 | Y9: =(X9-H9)/H9 -> -0.071665396 | Z9: =F9/F$18 -> 0.11773492 | AB9: 45349 | AC9: 99 | AD9: Bought as it gapped out of base on EPS.
A10: KD | B10: Long | C10: Kyndryl Hldgs | D10: 1160.2602 | E10: 18.22 | F10: =E10*D10 -> 21139.941 | G10: 20288.83 | H10: =G10/D10 -> 17.486448 | I10: =F10-G10 -> 851.11084 | J10: =E10-H10 -> 0.7335517 | K10: 45243 | L10: =DAYS360(K10,$C$1) -> 4 | M10: =(I10/G10) -> 0.041949725 | N10: 51 | O10: 96 | P10: 74 | Q10: 17.32 | R10: =Q10*0.93 -> 16.1076 | S10: 17.15 | T10: =Q10*1.25 -> 21.65 | U10: =Q10*1.5 -> 25.98 | V10: =Q10*2 -> 34.64 | W10: =H10-(H10*0.07) -> 16.262397 | X10: 16.5 | Y10: =(X10-H10)/H10 -> -0.056412159 | Z10: =F10/F$18 -> 0.041580523 | AB10: 45350 | AC10: 88 | AD10: Bought after 11/08 b/o. Trading tightly here.
A11: APPF | B11: Long | C11: AppFolio | D11: 247.9038 | E11: 200.56 | F11: =E11*D11 -> 49719.586 | G11: 50927.29 | H11: =G11/D11 -> 205.43166 | I11: =F11-G11 -> -1207.7039 | J11: =E11-H11 -> -4.8716634 | K11: 45244 | L11: =DAYS360(K11,$C$1) -> 3 | M11: =(I11/G11) -> -0.023714277 | N11: 115 | O11: 97 | P11: 83 | Q11: 201.91 | R11: =Q11*0.93 -> 187.7763 | S11: 182.26 | T11: =Q11*1.25 -> 252.3875 | U11: =Q11*1.5 -> 302.865 | V11: =Q11*2 -> 403.82 | W11: =H11-(H11*0.07) -> 191.05145 | X11: 190 | Y11: =(X11-H11)/H11 -> -0.075118232 | Z11: =F11/F$18 -> 0.097794331 | AB11: 45348 | AC11: 92 | AD11: B/o at the open.
A12: PLTR | B12: Long | C12: Palantir | D12: 1006.8806 | E12: 20.49 | F12: =E12*D12 -> 20630.983 | G12: 20479.95 | H12: =G12/D12 -> 20.339999 | I12: =F12-G12 -> 151.03349 | J12: =E12-H12 -> 0.15000139 | K12: 45245 | L12: =DAYS360(K12,$C$1) -> 2 | M12: =(I12/G12) -> 0.0073747003 | N12: 51 | O12: 99 | P12: 84 | Q12: 19.17 | R12: =Q12*0.93 -> 17.8281 | S12: 18.06 | T12: =Q12*1.25 -> 23.9625 | U12: =Q12*1.5 -> 28.755 | V12: =Q12*2 -> 38.34 | W12: =H12-(H12*0.07) -> 18.916199 | X12: 18.75 | Y12: =(X12-H12)/H12 -> -0.078171028 | Z12: =F12/F$18 -> 0.040579446 | AB12: 45336 | AC12: 98
A13: BIL | B13: Long | C13: Tbill ETF | D13: 2223.78 | E13: 91.68 | F13: =E13*D13 -> 203876.15 | G13: 203698.25 | H13: =G13/D13 -> 91.600001 | I13: =F13-G13 -> 177.9004 | J13: =E13-H13 -> 0.079999101 | M13: =(I13/G13) -> 0.00087335262 | R13: =Q13*0.93 -> 0 | T13: =Q13*1.25 -> 0 | U13: =Q13*1.5 -> 0 | V13: =Q13*2 -> 0 | W13: =H13-(H13*0.07) -> 85.188001 | Y13: =(X13-H13)/H13 -> -1 | Z13: =F13/F$18 -> 0.4010076
A14: SQQQ | B14: Long | C14: QQQ Triple short | D14: 511.2918 | E14: 16.28 | F14: =E14*D14 -> 8323.8305 | G14: 24797.66 | H14: =G14/D14 -> 48.500015 | I14: =F14-G14 -> -16473.829 | J14: =E14-H14 -> -32.220015 | M14: =(I14/G14) -> -0.66433 | R14: =Q14*0.93 -> 0 | T14: =Q14*1.25 -> 0 | U14: =Q14*1.5 -> 0 | V14: =Q14*2 -> 0 | W14: =H14-(H14*0.07) -> 45.105014 | Y14: =(X14-H14)/H14 -> -1 | Z14: =F14/F$18 -> 0.016372289
F15: =E15*D15 -> 0 | H15: =G15/D15 -> #DIV/0! | I15: =F15-G15 -> 0 | J15: =E15-H15 -> #DIV/0! | L15: =DAYS360(K15,$C$1) -> 44597 | M15: =(I15/G15) -> #DIV/0! | R15: =Q15*0.93 -> 0 | T15: =Q15*1.25 -> 0 | U15: =Q15*1.5 -> 0 | V15: =Q15*2 -> 0 | W15: =H15-(H15*0.07) -> #DIV/0! | Y15: =(X15-H15)/H15 -> #DIV/0! | Z15: =F15/F$18 -> 0
A16: Sub-Total | F16: =SUM(F6:F15) -> 457310.69 | G16: =SUM(G6:G15) -> 463618.04 | I16: =SUM(I6:I15) -> -6307.346
D17: Cash, other | F17: 51099 | G17: =F17/F18 -> 0.10050752
D18: Total | F18: =SUM(F16:F17) -> 508409.69
H19: Last week's close | I19: ='11-10-23'!F17 -> 506083.6 | K19: 45107 | L19: 509801
H20: Week's change | I20: =(F18-I19)/I19 -> 0.0045962723 | K20: chg % | L20: =(F18-L19)/L19 -> -0.0027291158
M22: days
A23: 2023 Closed Trades - Managed Acct | D23: Qty | E23: Cost/sh | F23: $ cost | G23: $Proc | H23: Proc/sh | I23: Profit/loss | J23: % | K23: Date purch | L23: Date sold | M23: held | P23: Comments
A25: HXL | B25: Long | C25: Hexcel | D25: 665.9739 | E25: =F25/D25 -> 76.621621 | F25: 51028 | G25: 45324.79 | H25: =G25/D25 -> 68.057907 | I25: =G25-F25 -> -5703.21 | J25: =I25/F25 -> -0.11176629 | K25: 45106 | L25: 45132 | M25: =DAYS360(K25,L25) -> 26 | O25: Bad reaction to EPS report. Stopped out.
A26: MCK | B26: Long | C26: McKesson | D26: 123.3931 | E26: =F26/D26 -> 413.24004 | F26: 50990.97 | G26: 48894.94 | H26: =G26/D26 -> 396.25344 | I26: =G26-F26 -> -2096.03 | J26: =I26/F26 -> -0.041105906 | K26: 45104 | L26: 45138 | M26: =DAYS360(K26,L26) -> 34 | O26: Broke original stop and 50dma. EPS coming in a few days.
A27: DXCM | B27: Long | C27: DexCom | D27: 278.2008 | E27: =F27/D27 -> 128.41002 | F27: 35723.77 | G27: 34855.72 | H27: =G27/D27 -> 125.28979 | I27: =G27-F27 -> -868.05 | J27: =I27/F27 -> -0.024298947 | K27: 45106 | L27: 45138 | M27: =DAYS360(K27,L27) -> 32 | O27: The positive reaction to EPS report was rejected at the old high and reversed. Didn't like the action.
A28: IONQ | B28: Long | C28: IonQ | D28: 1007.1459 | E28: =F28/D28 -> 20.954908 | F28: 21104.65 | G28: 18099.32 | H28: =G28/D28 -> 17.970902 | I28: =G28-F28 -> -3005.33 | J28: =I28/F28 -> -0.14240132 | K28: 45181 | L28: 45183 | M28: =DAYS360(K28,L28) -> 2 | O28: Breakout failure. Only 4% position. Only .6% hit to total.
A29: SNPS | B29: Long | C29: Synopsys | D29: 115.8536 | E29: =F29/D29 -> 442.16002 | F29: 51225.83 | G29: 52055.28 | H29: =G29/D29 -> 449.31949 | I29: =G29-F29 -> 829.45 | J29: =I29/F29 -> 0.016192027 | K29: 45117 | L29: 45184 | M29: =DAYS360(K29,L29) -> 65 | O29: Sold to protect capital on an ugly day.
A30: MTSI | B30: Long | C30: MACOM Tech Sol | D30: 507.0754 | E30: =F30/D30 -> 81.153611 | F30: 41151 | G30: 38871.01 | H30: =G30/D30 -> 76.657258 | I30: =G30-F30 -> -2279.99 | J30: =I30/F30 -> -0.055405458 | K30: 45167 | L30: 45216 | M30: =DAYS360(K30,L30) -> 48 | O30: Lost the 50dma in above avg vol. Sold prior to stop.
A31: ZS | B31: Long | C31: Zscaler | D31: 306.1703 | E31: =F31/D31 -> 170.32671 | F31: 52148.98 | G31: 49351.52 | H31: =G31/D31 -> 161.18977 | I31: =G31-F31 -> -2797.46 | J31: =I31/F31 -> -0.053643619 | K31: 45208 | L31: 45219 | M31: =DAYS360(K31,L31) -> 11 | O31: Lost the pivot in heavy vol. Sold prior to stop.
A32: DUOL | B32: Long | C32: Duolingo | D32: 239.9158 | E32: =F32/D32 -> 173.89088 | F32: 41719.17 | G32: 36026.28 | H32: =G32/D32 -> 150.16218 | I32: =G32-F32 -> -5692.89 | J32: =I32/F32 -> -0.13645741 | K32: 45208 | L32: 45219 | M32: =DAYS360(K32,L32) -> 11 | O32: Blew through my stop in a matter of an hour on Thurs. Sold Friday when it didn't recover early.
A33: AIT | B33: Long | C33: Applied Ind Tec | D33: 266.8733 | E33: =F33/D33 -> 151.47948 | F33: 40425.83 | G33: 40616.77 | H33: =G33/D33 -> 152.19496 | I33: =G33-F33 -> 190.94 | J33: =I33/F33 -> 0.0047232178 | K33: 45153 | L33: 45224 | M33: =DAYS360(K33,L33) -> 70 | O33: Sold to protect my cost.
I34: =SUM(I25:I33) -> -21422.57 | J34: Avg
H35: # of losses | I35: 7 | J35: -0.0808
H36: # of wins | I36: 2 | J36: 0.0105

Sheet 11-24-23
C1: 45254
C3: MANAGED ACCT | X3: Current | AC3: IBD
H4: Cost | J4: P/L | N4: Group | P4: EPS | R4: pivot | S4: last | W4: cost | X4: Stop | Y4: Stop | Z4: % | AB4: EPS | AC4: Comp
A5: Symbol | B5: Position | C5: Name | D5: Qty | E5: Current | F5: Value | G5: Cost | H5: per share | I5: P/L $ | J5: per sh | K5: Date purch | L5: days held | M5: % incr | N5: Rank | O5: RS | P5: RS | Q5: pivot | R5: -0.07 | S5: low | T5: 0.25 | U5: 0.5 | V5: 1 | W5: -0.07 | X5: Loss | Y5: Loss% | Z5: of port | AB5: Due | AC5: Rank
A7: MNSO | B7: Long | C7: Minoso | D7: =1211.7123+804.6763 -> 2016.3886 | E7: 25.16 | F7: =E7*D7 -> 50732.337 | G7: =25318.9+15999 -> 41317.9 | H7: =G7/D7 -> 20.49104 | I7: =F7-G7 -> 9414.4372 | J7: =E7-H7 -> 4.6689597 | K7: 45135 | L7: =DAYS360(K7,$C$1) -> 116 | M7: =(I7/G7) -> 0.22785372 | N7: 90 | O7: 98 | P7: 98 | Q7: 19.48 | R7: =Q7*0.93 -> 18.1164 | S7: 23.61 | T7: =Q7*1.25 -> 24.35 | U7: =Q7*1.5 -> 29.22 | V7: =Q7*2 -> 38.96 | W7: =H7-(H7*0.07) -> 19.056667 | X7: 26 | Y7: =(X7-H7)/H7 -> 0.26884725 | Z7: =F7/F$18 -> 0.10084377 | AB7: 45350 | AC7: 98 | AD7: Bought after 07/24 b/o. Added at the 21dema.
A8: TS | B8: Long | C8: Tenaris | D8: 1166.935 | E8: 34 | F8: =E8*D8 -> 39675.79 | G8: 40941.92 | H8: =G8/D8 -> 35.085005 | I8: =F8-G8 -> -1266.13 | J8: =E8-H8 -> -1.0850047 | K8: 45233 | L8: =DAYS360(K8,$C$1) -> 21 | M8: =(I8/G8) -> -0.030925027 | N8: 24 | O8: 81 | P8: 69 | Q8: 34.2 | R8: =Q8*0.93 -> 31.806 | S8: 31.07 | T8: =Q8*1.25 -> 42.75 | U8: =Q8*1.5 -> 51.3 | V8: =Q8*2 -> 68.4 | W8: =H8-(H8*0.07) -> 32.629054 | X8: 32.75 | Y8: =(X8-H8)/H8 -> -0.066552784 | Z8: =F8/F$18 -> 0.078865995 | AB8: 45343 | AC8: 91 | AD8: Bought day after gapping out of base.
A9: AXON | B9: Long | C9: Axon Enterprise | D9: 267.8431 | E9: 228.42 | F9: =E9*D9 -> 61180.721 | G9: 61166.24 | H9: =G9/D9 -> 228.36594 | I9: =F9-G9 -> 14.480902 | J9: =E9-H9 -> 0.054064869 | K9: 45238 | L9: =DAYS360(K9,$C$1) -> 16 | M9: =(I9/G9) -> 0.00023674664 | N9: 52 | O9: 89 | P9: 99 | Q9: 223.3 | R9: =Q9*0.93 -> 207.669 | S9: 199.29 | T9: =Q9*1.25 -> 279.125 | U9: =Q9*1.5 -> 334.95 | V9: =Q9*2 -> 446.6 | W9: =H9-(H9*0.07) -> 212.38032 | X9: 212 | Y9: =(X9-H9)/H9 -> -0.071665396 | Z9: =F9/F$18 -> 0.12161266 | AB9: 45349 | AC9: 99 | AD9: Bought as it gapped out of base on EPS.
A10: KD | B10: Long | C10: Kyndryl Hldgs | D10: 1160.2602 | E10: 18.08 | F10: =E10*D10 -> 20977.504 | G10: 20288.83 | H10: =G10/D10 -> 17.486448 | I10: =F10-G10 -> 688.67442 | J10: =E10-H10 -> 0.5935517 | K10: 45243 | L10: =DAYS360(K10,$C$1) -> 11 | M10: =(I10/G10) -> 0.033943525 | N10: 73 | O10: 94 | P10: 74 | Q10: 17.32 | R10: =Q10*0.93 -> 16.1076 | S10: 17.15 | T10: =Q10*1.25 -> 21.65 | U10: =Q10*1.5 -> 25.98 | V10: =Q10*2 -> 34.64 | W10: =H10-(H10*0.07) -> 16.262397 | X10: 16.5 | Y10: =(X10-H10)/H10 -> -0.056412159 | Z10: =F10/F$18 -> 0.041698269 | AB10: 45350 | AC10: 84 | AD10: Bought after 11/08 b/o. Trading tightly here.
A11: APPF | B11: Long | C11: AppFolio | D11: 247.9038 | E11: 193.21 | F11: =E11*D11 -> 47897.493 | G11: 50927.29 | H11: =G11/D11 -> 205.43166 | I11: =F11-G11 -> -3029.7968 | J11: =E11-H11 -> -12.221663 | K11: 45244 | L11: =DAYS360(K11,$C$1) -> 10 | M11: =(I11/G11) -> -0.059492598 | N11: 141 | O11: 94 | P11: 83 | Q11: 201.91 | R11: =Q11*0.93 -> 187.7763 | S11: 182.26 | T11: =Q11*1.25 -> 252.3875 | U11: =Q11*1.5 -> 302.865 | V11: =Q11*2 -> 403.82 | W11: =H11-(H11*0.07) -> 191.05145 | X11: 190 | Y11: =(X11-H11)/H11 -> -0.075118232 | Z11: =F11/F$18 -> 0.095208777 | AB11: 45348 | AC11: 89 | AD11: B/o at the open.
A12: PLTR | B12: Long | C12: Palantir | D12: 1006.8806 | E12: 19.2 | F12: =E12*D12 -> 19332.108 | G12: 20479.95 | H12: =G12/D12 -> 20.339999 | I12: =F12-G12 -> -1147.8425 | J12: =E12-H12 -> -1.1399986 | K12: 45245 | L12: =DAYS360(K12,$C$1) -> 9 | M12: =(I12/G12) -> -0.056047133 | N12: 73 | O12: 98 | P12: 84 | Q12: 19.17 | R12: =Q12*0.93 -> 17.8281 | S12: 18.06 | T12: =Q12*1.25 -> 23.9625 | U12: =Q12*1.5 -> 28.755 | V12: =Q12*2 -> 38.34 | W12: =H12-(H12*0.07) -> 18.916199 | X12: 18.75 | Y12: =(X12-H12)/H12 -> -0.078171028 | Z12: =F12/F$18 -> 0.038427613 | AB12: 45336 | AC12: 97
A13: BIL | B13: Long | C13: Tbill ETF | D13: 2223.78 | E13: 91.76 | F13: =E13*D13 -> 204054.05 | G13: 203698.25 | H13: =G13/D13 -> 91.600001 | I13: =F13-G13 -> 355.8028 | J13: =E13-H13 -> 0.1599991 | M13: =(I13/G13) -> 0.0017467151 | R13: =Q13*0.93 -> 0 | T13: =Q13*1.25 -> 0 | U13: =Q13*1.5 -> 0 | V13: =Q13*2 -> 0 | W13: =H13-(H13*0.07) -> 85.188001 | Y13: =(X13-H13)/H13 -> -1 | Z13: =F13/F$18 -> 0.40561072
A14: SQQQ | B14: Long | C14: QQQ Triple short | D14: 511.2918 | E14: 15.9 | F14: =E14*D14 -> 8129.5396 | G14: 24797.66 | H14: =G14/D14 -> 48.500015 | I14: =F14-G14 -> -16668.12 | J14: =E14-H14 -> -32.600015 | M14: =(I14/G14) -> -0.67216505 | R14: =Q14*0.93 -> 0 | T14: =Q14*1.25 -> 0 | U14: =Q14*1.5 -> 0 | V14: =Q14*2 -> 0 | W14: =H14-(H14*0.07) -> 45.105014 | Y14: =(X14-H14)/H14 -> -1 | Z14: =F14/F$18 -> 0.016159583
F15: =E15*D15 -> 0 | H15: =G15/D15 -> #DIV/0! | I15: =F15-G15 -> 0 | J15: =E15-H15 -> #DIV/0! | L15: =DAYS360(K15,$C$1) -> 44604 | M15: =(I15/G15) -> #DIV/0! | R15: =Q15*0.93 -> 0 | T15: =Q15*1.25 -> 0 | U15: =Q15*1.5 -> 0 | V15: =Q15*2 -> 0 | W15: =H15-(H15*0.07) -> #DIV/0! | Y15: =(X15-H15)/H15 -> #DIV/0! | Z15: =F15/F$18 -> 0
A16: Sub-Total | F16: =SUM(F6:F15) -> 451979.55 | G16: =SUM(G6:G15) -> 463618.04 | I16: =SUM(I6:I15) -> -11638.494
D17: Cash, other | F17: 51099 | G17: =F17/F18 -> 0.10157261
D18: Total | F18: =SUM(F16:F17) -> 503078.55
H19: Last week's close | I19: ='11-17-23'!F18 -> 508409.69 | K19: 45107 | L19: 509801
H20: Week's change | I20: =(F18-I19)/I19 -> -0.01048593 | K20: chg % | L20: =(F18-L19)/L19 -> -0.013186428
M22: days
A23: 2023 Closed Trades - Managed Acct | D23: Qty | E23: Cost/sh | F23: $ cost | G23: $Proc | H23: Proc/sh | I23: Profit/loss | J23: % | K23: Date purch | L23: Date sold | M23: held | P23: Comments
A25: HXL | B25: Long | C25: Hexcel | D25: 665.9739 | E25: =F25/D25 -> 76.621621 | F25: 51028 | G25: 45324.79 | H25: =G25/D25 -> 68.057907 | I25: =G25-F25 -> -5703.21 | J25: =I25/F25 -> -0.11176629 | K25: 45106 | L25: 45132 | M25: =DAYS360(K25,L25) -> 26 | O25: Bad reaction to EPS report. Stopped out.
A26: MCK | B26: Long | C26: McKesson | D26: 123.3931 | E26: =F26/D26 -> 413.24004 | F26: 50990.97 | G26: 48894.94 | H26: =G26/D26 -> 396.25344 | I26: =G26-F26 -> -2096.03 | J26: =I26/F26 -> -0.041105906 | K26: 45104 | L26: 45138 | M26: =DAYS360(K26,L26) -> 34 | O26: Broke original stop and 50dma. EPS coming in a few days.
A27: DXCM | B27: Long | C27: DexCom | D27: 278.2008 | E27: =F27/D27 -> 128.41002 | F27: 35723.77 | G27: 34855.72 | H27: =G27/D27 -> 125.28979 | I27: =G27-F27 -> -868.05 | J27: =I27/F27 -> -0.024298947 | K27: 45106 | L27: 45138 | M27: =DAYS360(K27,L27) -> 32 | O27: The positive reaction to EPS report was rejected at the old high and reversed. Didn't like the action.
A28: IONQ | B28: Long | C28: IonQ | D28: 1007.1459 | E28: =F28/D28 -> 20.954908 | F28: 21104.65 | G28: 18099.32 | H28: =G28/D28 -> 17.970902 | I28: =G28-F28 -> -3005.33 | J28: =I28/F28 -> -0.14240132 | K28: 45181 | L28: 45183 | M28: =DAYS360(K28,L28) -> 2 | O28: Breakout failure. Only 4% position. Only .6% hit to total.
A29: SNPS | B29: Long | C29: Synopsys | D29: 115.8536 | E29: =F29/D29 -> 442.16002 | F29: 51225.83 | G29: 52055.28 | H29: =G29/D29 -> 449.31949 | I29: =G29-F29 -> 829.45 | J29: =I29/F29 -> 0.016192027 | K29: 45117 | L29: 45184 | M29: =DAYS360(K29,L29) -> 65 | O29: Sold to protect capital on an ugly day.
A30: MTSI | B30: Long | C30: MACOM Tech Sol | D30: 507.0754 | E30: =F30/D30 -> 81.153611 | F30: 41151 | G30: 38871.01 | H30: =G30/D30 -> 76.657258 | I30: =G30-F30 -> -2279.99 | J30: =I30/F30 -> -0.055405458 | K30: 45167 | L30: 45216 | M30: =DAYS360(K30,L30) -> 48 | O30: Lost the 50dma in above avg vol. Sold prior to stop.
A31: ZS | B31: Long | C31: Zscaler | D31: 306.1703 | E31: =F31/D31 -> 170.32671 | F31: 52148.98 | G31: 49351.52 | H31: =G31/D31 -> 161.18977 | I31: =G31-F31 -> -2797.46 | J31: =I31/F31 -> -0.053643619 | K31: 45208 | L31: 45219 | M31: =DAYS360(K31,L31) -> 11 | O31: Lost the pivot in heavy vol. Sold prior to stop.
A32: DUOL | B32: Long | C32: Duolingo | D32: 239.9158 | E32: =F32/D32 -> 173.89088 | F32: 41719.17 | G32: 36026.28 | H32: =G32/D32 -> 150.16218 | I32: =G32-F32 -> -5692.89 | J32: =I32/F32 -> -0.13645741 | K32: 45208 | L32: 45219 | M32: =DAYS360(K32,L32) -> 11 | O32: Blew through my stop in a matter of an hour on Thurs. Sold Friday when it didn't recover early.
A33: AIT | B33: Long | C33: Applied Ind Tec | D33: 266.8733 | E33: =F33/D33 -> 151.47948 | F33: 40425.83 | G33: 40616.77 | H33: =G33/D33 -> 152.19496 | I33: =G33-F33 -> 190.94 | J33: =I33/F33 -> 0.0047232178 | K33: 45153 | L33: 45224 | M33: =DAYS360(K33,L33) -> 70 | O33: Sold to protect my cost.
I34: =SUM(I25:I33) -> -21422.57 | J34: Avg
H35: # of losses | I35: 7 | J35: -0.0808
H36: # of wins | I36: 2 | J36: 0.0105

Sheet 12-01-23
C1: 45261
C3: MANAGED ACCT | X3: Current | AC3: IBD
H4: Cost | J4: P/L | N4: Group | P4: EPS | R4: pivot | S4: last | W4: cost | X4: Stop | Y4: Stop | Z4: % | AB4: EPS | AC4: Comp
A5: Symbol | B5: Position | C5: Name | D5: Qty | E5: Current | F5: Value | G5: Cost | H5: per share | I5: P/L $ | J5: per sh | K5: Date purch | L5: days held | M5: % incr | N5: Rank | O5: RS | P5: RS | Q5: pivot | R5: -0.07 | S5: low | T5: 0.25 | U5: 0.5 | V5: 1 | W5: -0.07 | X5: Loss | Y5: Loss% | Z5: of port | AB5: Due | AC5: Rank
A7: MNSO | B7: Long | C7: Minoso | D7: =1211.7123+804.6763 -> 2016.3886 | E7: 24.24 | F7: =E7*D7 -> 48877.26 | G7: =25318.9+15999 -> 41317.9 | H7: =G7/D7 -> 20.49104 | I7: =F7-G7 -> 7559.3597 | J7: =E7-H7 -> 3.7489597 | K7: 45135 | L7: =DAYS360(K7,$C$1) -> 123 | M7: =(I7/G7) -> 0.18295605 | N7: 96 | O7: 95 | P7: 98 | Q7: 19.48 | R7: =Q7*0.93 -> 18.1164 | S7: 23.61 | T7: =Q7*1.25 -> 24.35 | U7: =Q7*1.5 -> 29.22 | V7: =Q7*2 -> 38.96 | W7: =H7-(H7*0.07) -> 19.056667 | X7: 26 | Y7: =(X7-H7)/H7 -> 0.26884725 | Z7: =F7/F$18 -> 0.096849243 | AB7: 45350 | AC7: 97 | AD7: Bought after 07/24 b/o. Added at the 21dema.
A8: TS | B8: Long | C8: Tenaris | D8: 1166.935 | E8: 34.87 | F8: =E8*D8 -> 40691.023 | G8: 40941.92 | H8: =G8/D8 -> 35.085005 | I8: =F8-G8 -> -250.89655 | J8: =E8-H8 -> -0.21500473 | K8: 45233 | L8: =DAYS360(K8,$C$1) -> 28 | M8: =(I8/G8) -> -0.006128109 | N8: 28 | O8: 83 | P8: 69 | Q8: 34.2 | R8: =Q8*0.93 -> 31.806 | S8: 31.07 | T8: =Q8*1.25 -> 42.75 | U8: =Q8*1.5 -> 51.3 | V8: =Q8*2 -> 68.4 | W8: =H8-(H8*0.07) -> 32.629054 | X8: 32.75 | Y8: =(X8-H8)/H8 -> -0.066552784 | Z8: =F8/F$18 -> 0.080628392 | AB8: 45343 | AC8: 93 | AD8: Bought day after gapping out of base.
A9: AXON | B9: Long | C9: Axon Enterprise | D9: 267.8431 | E9: 231.51 | F9: =E9*D9 -> 62008.356 | G9: 61166.24 | H9: =G9/D9 -> 228.36594 | I9: =F9-G9 -> 842.11608 | J9: =E9-H9 -> 3.1440649 | K9: 45238 | L9: =DAYS360(K9,$C$1) -> 23 | M9: =(I9/G9) -> 0.013767661 | N9: 35 | O9: 85 | P9: 99 | Q9: 223.3 | R9: =Q9*0.93 -> 207.669 | S9: 199.29 | T9: =Q9*1.25 -> 279.125 | U9: =Q9*1.5 -> 334.95 | V9: =Q9*2 -> 446.6 | W9: =H9-(H9*0.07) -> 212.38032 | X9: 212 | Y9: =(X9-H9)/H9 -> -0.071665396 | Z9: =F9/F$18 -> 0.12286823 | AB9: 45349 | AC9: 99 | AD9: Bought as it gapped out of base on EPS.
A10: KD | B10: Long | C10: Kyndryl Hldgs | D10: =1160.2602+1046.0778 -> 2206.338 | E10: 18.5 | F10: =E10*D10 -> 40817.253 | G10: =20288.83+19170.47 -> 39459.3 | H10: =G10/D10 -> 17.884522 | I10: =F10-G10 -> 1357.953 | J10: =E10-H10 -> 0.61547823 | K10: 45243 | L10: =DAYS360(K10,$C$1) -> 18 | M10: =(I10/G10) -> 0.034414016 | N10: 51 | O10: 93 | P10: 74 | Q10: 17.32 | R10: =Q10*0.93 -> 16.1076 | S10: 17.15 | T10: =Q10*1.25 -> 21.65 | U10: =Q10*1.5 -> 25.98 | V10: =Q10*2 -> 34.64 | W10: =H10-(H10*0.07) -> 16.632605 | X10: 16.5 | Y10: =(X10-H10)/H10 -> -0.077414526 | Z10: =F10/F$18 -> 0.080878513 | AB10: 45350 | AC10: 86 | AD10: Bought after 11/08 b/o. Trading tightly here.
A11: APPF | B11: Long | C11: AppFolio | D11: 247.9038 | E11: 187.83 | F11: =E11*D11 -> 46563.771 | G11: 50927.29 | H11: =G11/D11 -> 205.43166 | I11: =F11-G11 -> -4363.5192 | J11: =E11-H11 -> -17.601663 | K11: 45244 | L11: =DAYS360(K11,$C$1) -> 17 | M11: =(I11/G11) -> -0.085681356 | N11: 149 | O11: 92 | P11: 83 | Q11: 201.91 | R11: =Q11*0.93 -> 187.7763 | S11: 182.26 | T11: =Q11*1.25 -> 252.3875 | U11: =Q11*1.5 -> 302.865 | V11: =Q11*2 -> 403.82 | W11: =H11-(H11*0.07) -> 191.05145 | X11: 190 | Y11: =(X11-H11)/H11 -> -0.075118232 | Z11: =F11/F$18 -> 0.092265115 | AB11: 45348 | AC11: 85 | AD11: B/o at the open.
A12: PLTR | B12: Long | C12: Palantir | D12: =1006.8806+1065.4202 -> 2072.3008 | E12: 20.27 | F12: =E12*D12 -> 42005.537 | G12: =20479.95+20765.04 -> 41244.99 | H12: =G12/D12 -> 19.902994 | I12: =F12-G12 -> 760.54722 | J12: =E12-H12 -> 0.36700619 | K12: 45245 | L12: =DAYS360(K12,$C$1) -> 16 | M12: =(I12/G12) -> 0.018439748 | N12: 51 | O12: 99 | P12: 84 | Q12: 19.17 | R12: =Q12*0.93 -> 17.8281 | S12: 18.06 | T12: =Q12*1.25 -> 23.9625 | U12: =Q12*1.5 -> 28.755 | V12: =Q12*2 -> 38.34 | W12: =H12-(H12*0.07) -> 18.509784 | X12: 18.75 | Y12: =(X12-H12)/H12 -> -0.057930672 | Z12: =F12/F$18 -> 0.083233072 | AB12: 45336 | AC12: 98
A13: BIL | B13: Long | C13: Tbill ETF | D13: 2223.78 | E13: 91.44 | F13: =E13*D13 -> 203342.44 | G13: 203698.25 | H13: =G13/D13 -> 91.600001 | I13: =F13-G13 -> -355.8068 | J13: =E13-H13 -> -0.1600009 | M13: =(I13/G13) -> -0.0017467347 | R13: =Q13*0.93 -> 0 | T13: =Q13*1.25 -> 0 | U13: =Q13*1.5 -> 0 | V13: =Q13*2 -> 0 | W13: =H13-(H13*0.07) -> 85.188001 | Y13: =(X13-H13)/H13 -> -1 | Z13: =F13/F$18 -> 0.4029187
A14: SQQQ | B14: Long | C14: QQQ Triple short | D14: 511.2918 | E14: 15.94 | F14: =E14*D14 -> 8149.9913 | G14: 24797.66 | H14: =G14/D14 -> 48.500015 | I14: =F14-G14 -> -16647.669 | J14: =E14-H14 -> -32.560015 | M14: =(I14/G14) -> -0.67134031 | R14: =Q14*0.93 -> 0 | T14: =Q14*1.25 -> 0 | U14: =Q14*1.5 -> 0 | V14: =Q14*2 -> 0 | W14: =H14-(H14*0.07) -> 45.105014 | Y14: =(X14-H14)/H14 -> -1 | Z14: =F14/F$18 -> 0.016149033
F15: =E15*D15 -> 0 | H15: =G15/D15 -> #DIV/0! | I15: =F15-G15 -> 0 | J15: =E15-H15 -> #DIV/0! | L15: =DAYS360(K15,$C$1) -> 44611 | M15: =(I15/G15) -> #DIV/0! | R15: =Q15*0.93 -> 0 | T15: =Q15*1.25 -> 0 | U15: =Q15*1.5 -> 0 | V15: =Q15*2 -> 0 | W15: =H15-(H15*0.07) -> #DIV/0! | Y15: =(X15-H15)/H15 -> #DIV/0! | Z15: =F15/F$18 -> 0
A16: Sub-Total | F16: =SUM(F6:F15) -> 492455.63 | G16: =SUM(G6:G15) -> 503553.55 | I16: =SUM(I6:I15) -> -11097.915
D17: Cash, other | F17: 12218 | G17: =F17/F18 -> 0.024209705
D18: Total | F18: =SUM(F16:F17) -> 504673.63
H19: Last week's close | I19: ='11-24-23'!F18 -> 503078.55 | K19: 45107 | L19: 509801
H20: Week's change | I20: =(F18-I19)/I19 -> 0.003170656 | K20: chg % | L20: =(F18-L19)/L19 -> -0.010057582
M22: days
A23: 2023 Closed Trades - Managed Acct | D23: Qty | E23: Cost/sh | F23: $ cost | G23: $Proc | H23: Proc/sh | I23: Profit/loss | J23: % | K23: Date purch | L23: Date sold | M23: held | P23: Comments
A25: HXL | B25: Long | C25: Hexcel | D25: 665.9739 | E25: =F25/D25 -> 76.621621 | F25: 51028 | G25: 45324.79 | H25: =G25/D25 -> 68.057907 | I25: =G25-F25 -> -5703.21 | J25: =I25/F25 -> -0.11176629 | K25: 45106 | L25: 45132 | M25: =DAYS360(K25,L25) -> 26 | O25: Bad reaction to EPS report. Stopped out.
A26: MCK | B26: Long | C26: McKesson | D26: 123.3931 | E26: =F26/D26 -> 413.24004 | F26: 50990.97 | G26: 48894.94 | H26: =G26/D26 -> 396.25344 | I26: =G26-F26 -> -2096.03 | J26: =I26/F26 -> -0.041105906 | K26: 45104 | L26: 45138 | M26: =DAYS360(K26,L26) -> 34 | O26: Broke original stop and 50dma. EPS coming in a few days.
A27: DXCM | B27: Long | C27: DexCom | D27: 278.2008 | E27: =F27/D27 -> 128.41002 | F27: 35723.77 | G27: 34855.72 | H27: =G27/D27 -> 125.28979 | I27: =G27-F27 -> -868.05 | J27: =I27/F27 -> -0.024298947 | K27: 45106 | L27: 45138 | M27: =DAYS360(K27,L27) -> 32 | O27: The positive reaction to EPS report was rejected at the old high and reversed. Didn't like the action.
A28: IONQ | B28: Long | C28: IonQ | D28: 1007.1459 | E28: =F28/D28 -> 20.954908 | F28: 21104.65 | G28: 18099.32 | H28: =G28/D28 -> 17.970902 | I28: =G28-F28 -> -3005.33 | J28: =I28/F28 -> -0.14240132 | K28: 45181 | L28: 45183 | M28: =DAYS360(K28,L28) -> 2 | O28: Breakout failure. Only 4% position. Only .6% hit to total.
A29: SNPS | B29: Long | C29: Synopsys | D29: 115.8536 | E29: =F29/D29 -> 442.16002 | F29: 51225.83 | G29: 52055.28 | H29: =G29/D29 -> 449.31949 | I29: =G29-F29 -> 829.45 | J29: =I29/F29 -> 0.016192027 | K29: 45117 | L29: 45184 | M29: =DAYS360(K29,L29) -> 65 | O29: Sold to protect capital on an ugly day.
A30: MTSI | B30: Long | C30: MACOM Tech Sol | D30: 507.0754 | E30: =F30/D30 -> 81.153611 | F30: 41151 | G30: 38871.01 | H30: =G30/D30 -> 76.657258 | I30: =G30-F30 -> -2279.99 | J30: =I30/F30 -> -0.055405458 | K30: 45167 | L30: 45216 | M30: =DAYS360(K30,L30) -> 48 | O30: Lost the 50dma in above avg vol. Sold prior to stop.
A31: ZS | B31: Long | C31: Zscaler | D31: 306.1703 | E31: =F31/D31 -> 170.32671 | F31: 52148.98 | G31: 49351.52 | H31: =G31/D31 -> 161.18977 | I31: =G31-F31 -> -2797.46 | J31: =I31/F31 -> -0.053643619 | K31: 45208 | L31: 45219 | M31: =DAYS360(K31,L31) -> 11 | O31: Lost the pivot in heavy vol. Sold prior to stop.
A32: DUOL | B32: Long | C32: Duolingo | D32: 239.9158 | E32: =F32/D32 -> 173.89088 | F32: 41719.17 | G32: 36026.28 | H32: =G32/D32 -> 150.16218 | I32: =G32-F32 -> -5692.89 | J32: =I32/F32 -> -0.13645741 | K32: 45208 | L32: 45219 | M32: =DAYS360(K32,L32) -> 11 | O32: Blew through my stop in a matter of an hour on Thurs. Sold Friday when it didn't recover early.
A33: AIT | B33: Long | C33: Applied Ind Tec | D33: 266.8733 | E33: =F33/D33 -> 151.47948 | F33: 40425.83 | G33: 40616.77 | H33: =G33/D33 -> 152.19496 | I33: =G33-F33 -> 190.94 | J33: =I33/F33 -> 0.0047232178 | K33: 45153 | L33: 45224 | M33: =DAYS360(K33,L33) -> 70 | O33: Sold to protect my cost.
I34: =SUM(I25:I33) -> -21422.57 | J34: Avg
H35: # of losses | I35: 7 | J35: -0.0808
H36: # of wins | I36: 2 | J36: 0.0105

Sheet 12-15-23
C1: 45275
C3: MANAGED ACCT | X3: Current | AC3: IBD
H4: Cost | J4: P/L | N4: Group | P4: EPS | R4: pivot | S4: last | W4: cost | X4: Stop | Y4: Stop | Z4: % | AB4: EPS | AC4: Comp
A5: Symbol | B5: Position | C5: Name | D5: Qty | E5: Current | F5: Value | G5: Cost | H5: per share | I5: P/L $ | J5: per sh | K5: Date purch | L5: days held | M5: % incr | N5: Rank | O5: RS | P5: RS | Q5: pivot | R5: -0.07 | S5: low | T5: 0.25 | U5: 0.5 | V5: 1 | W5: -0.07 | X5: Loss | Y5: Loss% | Z5: of port | AB5: Due | AC5: Rank
A7: MNSO | F7: =E7*D7 -> 0 | H7: =G7/D7 -> #DIV/0! | I7: =F7-G7 -> 0 | J7: =E7-H7 -> #DIV/0! | L7: =DAYS360(K7,$C$1) -> 44625 | M7: =(I7/G7) -> #DIV/0! | R7: =Q7*0.93 -> 0 | T7: =Q7*1.25 -> 0 | U7: =Q7*1.5 -> 0 | V7: =Q7*2 -> 0 | W7: =H7-(H7*0.07) -> #DIV/0! | Y7: =(X7-H7)/H7 -> #DIV/0! | Z7: =F7/F$18 -> 0
A8: TS | B8: Long | C8: Minoso | D8: =1211.7123+804.6763 -> 2016.3886 | E8: 19.14 | F8: =E8*D8 -> 38593.678 | G8: =25318.9+15999 -> 41317.9 | H8: =G8/D8 -> 20.49104 | I8: =F8-G8 -> -2724.2222 | J8: =E8-H8 -> -1.3510403 | K8: 45135 | L8: =DAYS360(K8,$C$1) -> 137 | M8: =(I8/G8) -> -0.06593322 | N8: 145 | O8: 33 | P8: 98 | Q8: 19.48 | R8: =Q8*0.93 -> 18.1164 | S8: 23.61 | T8: =Q8*1.25 -> 24.35 | U8: =Q8*1.5 -> 29.22 | V8: =Q8*2 -> 38.96 | W8: =H8-(H8*0.07) -> 19.056667 | X8: 26 | Y8: =(X8-H8)/H8 -> 0.26884725 | Z8: =F8/F$18 -> 0.081395448 | AB8: 45350 | AC8: 66 | AD8: Bought after 07/24 b/o. Added at the 21dema.
A9: AXON | B9: Long | C9: Tenaris | D9: 1166.935 | E9: 34.13 | F9: =E9*D9 -> 39827.492 | G9: 40941.92 | H9: =G9/D9 -> 35.085005 | I9: =F9-G9 -> -1114.4284 | J9: =E9-H9 -> -0.95500473 | K9: 45233 | L9: =DAYS360(K9,$C$1) -> 42 | M9: =(I9/G9) -> -0.027219741 | N9: 58 | O9: 73 | P9: 69 | Q9: 34.2 | R9: =Q9*0.93 -> 31.806 | S9: 31.07 | T9: =Q9*1.25 -> 42.75 | U9: =Q9*1.5 -> 51.3 | V9: =Q9*2 -> 68.4 | W9: =H9-(H9*0.07) -> 32.629054 | X9: 32.75 | Y9: =(X9-H9)/H9 -> -0.066552784 | Z9: =F9/F$18 -> 0.083997605 | AB9: 45343 | AC9: 83 | AD9: Bought day after gapping out of base.
A10: KD | B10: Long | C10: Axon Enterprise | D10: 267.8431 | E10: 255.98 | F10: =E10*D10 -> 68562.477 | G10: 61166.24 | H10: =G10/D10 -> 228.36594 | I10: =F10-G10 -> 7396.2367 | J10: =E10-H10 -> 27.614065 | K10: 45238 | L10: =DAYS360(K10,$C$1) -> 37 | M10: =(I10/G10) -> 0.12092025 | N10: 57 | O10: 89 | P10: 99 | Q10: 223.3 | R10: =Q10*0.93 -> 207.669 | S10: 199.29 | T10: =Q10*1.25 -> 279.125 | U10: =Q10*1.5 -> 334.95 | V10: =Q10*2 -> 446.6 | W10: =H10-(H10*0.07) -> 212.38032 | X10: 212 | Y10: =(X10-H10)/H10 -> -0.071665396 | Z10: =F10/F$18 -> 0.14460072 | AB10: 45349 | AC10: 99 | AD10: Bought as it gapped out of base on EPS.
B11: Long | C11: Kyndryl Hldgs | D11: =1160.2602+1046.0778 -> 2206.338 | E11: 18.37 | F11: =E11*D11 -> 40530.429 | G11: =20288.83+19170.47 -> 39459.3 | H11: =G11/D11 -> 17.884522 | I11: =F11-G11 -> 1071.1291 | J11: =E11-H11 -> 0.48547823 | K11: 45243 | L11: =DAYS360(K11,$C$1) -> 32 | M11: =(I11/G11) -> 0.027145161 | N11: 50 | O11: 92 | P11: 74 | Q11: 17.32 | R11: =Q11*0.93 -> 16.1076 | S11: 17.15 | T11: =Q11*1.25 -> 21.65 | U11: =Q11*1.5 -> 25.98 | V11: =Q11*2 -> 34.64 | W11: =H11-(H11*0.07) -> 16.632605 | X11: 16.5 | Y11: =(X11-H11)/H11 -> -0.077414526 | Z11: =F11/F$18 -> 0.085480126 | AB11: 45350 | AC11: 81 | AD11: Bought after 11/08 b/o. Trading tightly here.
A12: PLTR | B12: Long | C12: Palantir | D12: =1006.8806+1065.4202 -> 2072.3008 | E12: 18.2 | F12: =E12*D12 -> 37715.875 | G12: =20479.95+20765.04 -> 41244.99 | H12: =G12/D12 -> 19.902994 | I12: =F12-G12 -> -3529.1154 | J12: =E12-H12 -> -1.7029938 | K12: 45245 | L12: =DAYS360(K12,$C$1) -> 30 | M12: =(I12/G12) -> -0.085564706 | N12: 50 | O12: 97 | P12: 84 | Q12: 19.17 | R12: =Q12*0.93 -> 17.8281 | S12: 18.06 | T12: =Q12*1.25 -> 23.9625 | U12: =Q12*1.5 -> 28.755 | V12: =Q12*2 -> 38.34 | W12: =H12-(H12*0.07) -> 18.509784 | X12: 18.75 | Y12: =(X12-H12)/H12 -> -0.057930672 | Z12: =F12/F$18 -> 0.07954413 | AB12: 45336 | AC12: 94
A13: BIL | B13: Long | C13: Tbill ETF | D13: =2223.78-868.0181 -> 1355.7619 | E13: 91.63 | F13: =E13*D13 -> 124228.46 | G13: =203698.25-79510.46 -> 124187.79 | H13: =G13/D13 -> 91.6 | I13: =F13-G13 -> 40.672897 | J13: =E13-H13 -> 0.03000003 | M13: =(I13/G13) -> 0.00032751124 | R13: =Q13*0.93 -> 0 | T13: =Q13*1.25 -> 0 | U13: =Q13*1.5 -> 0 | V13: =Q13*2 -> 0 | W13: =H13-(H13*0.07) -> 85.188 | Y13: =(X13-H13)/H13 -> -1 | Z13: =F13/F$18 -> 0.26200228
A14: SQQQ | B14: Long | C14: QQQ Triple short | D14: 511.2918 | E14: 14.25 | F14: =E14*D14 -> 7285.9082 | G14: 24797.66 | H14: =G14/D14 -> 48.500015 | I14: =F14-G14 -> -17511.752 | J14: =E14-H14 -> -34.250015 | M14: =(I14/G14) -> -0.70618566 | R14: =Q14*0.93 -> 0 | T14: =Q14*1.25 -> 0 | U14: =Q14*1.5 -> 0 | V14: =Q14*2 -> 0 | W14: =H14-(H14*0.07) -> 45.105014 | Y14: =(X14-H14)/H14 -> -1 | Z14: =F14/F$18 -> 0.015366241
F15: =E15*D15 -> 0 | H15: =G15/D15 -> #DIV/0! | I15: =F15-G15 -> 0 | J15: =E15-H15 -> #DIV/0! | L15: =DAYS360(K15,$C$1) -> 44625 | M15: =(I15/G15) -> #DIV/0! | R15: =Q15*0.93 -> 0 | T15: =Q15*1.25 -> 0 | U15: =Q15*1.5 -> 0 | V15: =Q15*2 -> 0 | W15: =H15-(H15*0.07) -> #DIV/0! | Y15: =(X15-H15)/H15 -> #DIV/0! | Z15: =F15/F$18 -> 0
A16: Sub-Total | F16: =SUM(F6:F15) -> 356744.32 | G16: =SUM(G6:G15) -> 373115.8 | I16: =SUM(I6:I15) -> -16371.479
D17: Cash, other | F17: 117406 | G17: =F17/F18 -> 0.24761346
D18: Total | F18: =SUM(F16:F17) -> 474150.32
H19: Last week's close | I19: ='12-01-23'!F18-20351 -> 484322.63 | K19: 45107 | L19: =509801-20351 -> 489450
H20: Week's change | I20: =(F18-I19)/I19 -> -0.021003177 | K20: chg % | L20: =(F18-L19)/L19 -> -0.031258922
M22: days
A23: 2023 Closed Trades - Managed Acct | D23: Qty | E23: Cost/sh | F23: $ cost | G23: $Proc | H23: Proc/sh | I23: Profit/loss | J23: % | K23: Date purch | L23: Date sold | M23: held | P23: Comments
A25: HXL | B25: Long | C25: Hexcel | D25: 665.9739 | E25: =F25/D25 -> 76.621621 | F25: 51028 | G25: 45324.79 | H25: =G25/D25 -> 68.057907 | I25: =G25-F25 -> -5703.21 | J25: =I25/F25 -> -0.11176629 | K25: 45106 | L25: 45132 | M25: =DAYS360(K25,L25) -> 26 | O25: Bad reaction to EPS report. Stopped out.
A26: MCK | B26: Long | C26: McKesson | D26: 123.3931 | E26: =F26/D26 -> 413.24004 | F26: 50990.97 | G26: 48894.94 | H26: =G26/D26 -> 396.25344 | I26: =G26-F26 -> -2096.03 | J26: =I26/F26 -> -0.041105906 | K26: 45104 | L26: 45138 | M26: =DAYS360(K26,L26) -> 34 | O26: Broke original stop and 50dma. EPS coming in a few days.
A27: DXCM | B27: Long | C27: DexCom | D27: 278.2008 | E27: =F27/D27 -> 128.41002 | F27: 35723.77 | G27: 34855.72 | H27: =G27/D27 -> 125.28979 | I27: =G27-F27 -> -868.05 | J27: =I27/F27 -> -0.024298947 | K27: 45106 | L27: 45138 | M27: =DAYS360(K27,L27) -> 32 | O27: The positive reaction to EPS report was rejected at the old high and reversed. Didn't like the action.
A28: IONQ | B28: Long | C28: IonQ | D28: 1007.1459 | E28: =F28/D28 -> 20.954908 | F28: 21104.65 | G28: 18099.32 | H28: =G28/D28 -> 17.970902 | I28: =G28-F28 -> -3005.33 | J28: =I28/F28 -> -0.14240132 | K28: 45181 | L28: 45183 | M28: =DAYS360(K28,L28) -> 2 | O28: Breakout failure. Only 4% position. Only .6% hit to total.
A29: SNPS | B29: Long | C29: Synopsys | D29: 115.8536 | E29: =F29/D29 -> 442.16002 | F29: 51225.83 | G29: 52055.28 | H29: =G29/D29 -> 449.31949 | I29: =G29-F29 -> 829.45 | J29: =I29/F29 -> 0.016192027 | K29: 45117 | L29: 45184 | M29: =DAYS360(K29,L29) -> 65 | O29: Sold to protect capital on an ugly day.
A30: MTSI | B30: Long | C30: MACOM Tech Sol | D30: 507.0754 | E30: =F30/D30 -> 81.153611 | F30: 41151 | G30: 38871.01 | H30: =G30/D30 -> 76.657258 | I30: =G30-F30 -> -2279.99 | J30: =I30/F30 -> -0.055405458 | K30: 45167 | L30: 45216 | M30: =DAYS360(K30,L30) -> 48 | O30: Lost the 50dma in above avg vol. Sold prior to stop.
A31: ZS | B31: Long | C31: Zscaler | D31: 306.1703 | E31: =F31/D31 -> 170.32671 | F31: 52148.98 | G31: 49351.52 | H31: =G31/D31 -> 161.18977 | I31: =G31-F31 -> -2797.46 | J31: =I31/F31 -> -0.053643619 | K31: 45208 | L31: 45219 | M31: =DAYS360(K31,L31) -> 11 | O31: Lost the pivot in heavy vol. Sold prior to stop.
A32: DUOL | B32: Long | C32: Duolingo | D32: 239.9158 | E32: =F32/D32 -> 173.89088 | F32: 41719.17 | G32: 36026.28 | H32: =G32/D32 -> 150.16218 | I32: =G32-F32 -> -5692.89 | J32: =I32/F32 -> -0.13645741 | K32: 45208 | L32: 45219 | M32: =DAYS360(K32,L32) -> 11 | O32: Blew through my stop in a matter of an hour on Thurs. Sold Friday when it didn't recover early.
A33: AIT | B33: Long | C33: Applied Ind Tec | D33: 266.8733 | E33: =F33/D33 -> 151.47948 | F33: 40425.83 | G33: 40616.77 | H33: =G33/D33 -> 152.19496 | I33: =G33-F33 -> 190.94 | J33: =I33/F33 -> 0.0047232178 | K33: 45153 | L33: 45224 | M33: =DAYS360(K33,L33) -> 70 | O33: Sold to protect my cost.
A34: APPF | B34: Long | C34: AppFolio | D34: 247.9038 | E34: =F34/D34 -> 205.43166 | F34: 50927.29 | G34: 45926.83 | H34: =G34/D34 -> 185.26069 | I34: =G34-F34 -> -5000.46 | J34: =I34/F34 -> -0.098188221 | K34: 45244 | L34: 45267 | M34: =DAYS360(K34,L34) -> 23 | O34: Broke the 50dma.
I38: =SUM(I25:I37) -> -26423.03 | J38: Avg
H39: # of losses | I39: 8 | J39: -0.083
H40: # of wins | I40: 2 | J40: 0.0105

Sheet 12-22-23
C1: 45282
C3: MANAGED ACCT | X3: Current | AC3: IBD
H4: Cost | J4: P/L | N4: Group | P4: EPS | R4: pivot | S4: last | W4: cost | X4: Stop | Y4: Stop | Z4: % | AB4: EPS | AC4: Comp
A5: Symbol | B5: Position | C5: Name | D5: Qty | E5: Current | F5: Value | G5: Cost | H5: per share | I5: P/L $ | J5: per sh | K5: Date purch | L5: days held | M5: % incr | N5: Rank | O5: RS | P5: RS | Q5: pivot | R5: -0.07 | S5: low | T5: 0.25 | U5: 0.5 | V5: 1 | W5: -0.07 | X5: Loss | Y5: Loss% | Z5: of port | AB5: Due | AC5: Rank
F7: =E7*D7 -> 0 | H7: =G7/D7 -> #DIV/0! | I7: =F7-G7 -> 0 | J7: =E7-H7 -> #DIV/0! | L7: =DAYS360(K7,$C$1) -> 44632 | M7: =(I7/G7) -> #DIV/0! | R7: =Q7*0.93 -> 0 | T7: =Q7*1.25 -> 0 | U7: =Q7*1.5 -> 0 | V7: =Q7*2 -> 0 | W7: =H7-(H7*0.07) -> #DIV/0! | Y7: =(X7-H7)/H7 -> #DIV/0! | Z7: =F7/F$18 -> 0
A8: MNSO | B8: Long | C8: Minoso | D8: =1211.7123+804.6763 -> 2016.3886 | E8: 19.64 | F8: =E8*D8 -> 39601.872 | G8: =25318.9+15999 -> 41317.9 | H8: =G8/D8 -> 20.49104 | I8: =F8-G8 -> -1716.0279 | J8: =E8-H8 -> -0.85104027 | K8: 45135 | L8: =DAYS360(K8,$C$1) -> 144 | M8: =(I8/G8) -> -0.041532312 | N8: 164 | O8: 69 | P8: 98 | Q8: 19.48 | R8: =Q8*0.93 -> 18.1164 | S8: 18.27 | T8: =Q8*1.25 -> 24.35 | U8: =Q8*1.5 -> 29.22 | V8: =Q8*2 -> 38.96 | W8: =H8-(H8*0.07) -> 19.056667 | X8: 26 | Y8: =(X8-H8)/H8 -> 0.26884725 | Z8: =F8/F$18 -> 0.083353379 | AB8: 45350 | AC8: 79 | AD8: Bought after 07/24 b/o. Added at the 21dema.
A9: TS | B9: Long | C9: Tenaris | D9: 1166.935 | E9: 35.25 | F9: =E9*D9 -> 41134.459 | G9: 40941.92 | H9: =G9/D9 -> 35.085005 | I9: =F9-G9 -> 192.53875 | J9: =E9-H9 -> 0.16499527 | K9: 45233 | L9: =DAYS360(K9,$C$1) -> 49 | M9: =(I9/G9) -> 0.0047027289 | N9: 62 | O9: 77 | P9: 69 | Q9: 34.2 | R9: =Q9*0.93 -> 31.806 | S9: 32.69 | T9: =Q9*1.25 -> 42.75 | U9: =Q9*1.5 -> 51.3 | V9: =Q9*2 -> 68.4 | W9: =H9-(H9*0.07) -> 32.629054 | X9: 32.75 | Y9: =(X9-H9)/H9 -> -0.066552784 | Z9: =F9/F$18 -> 0.086579143 | AB9: 45343 | AC9: 84 | AD9: Bought day after gapping out of base.
A10: AXON | B10: Long | C10: Axon Enterprise | D10: 267.8431 | E10: 259.03 | F10: =E10*D10 -> 69379.398 | G10: 61166.24 | H10: =G10/D10 -> 228.36594 | I10: =F10-G10 -> 8213.1582 | J10: =E10-H10 -> 30.664065 | K10: 45238 | L10: =DAYS360(K10,$C$1) -> 44 | M10: =(I10/G10) -> 0.134276 | N10: 24 | O10: 90 | P10: 99 | Q10: 223.3 | R10: =Q10*0.93 -> 207.669 | S10: 224.28 | T10: =Q10*1.25 -> 279.125 | U10: =Q10*1.5 -> 334.95 | V10: =Q10*2 -> 446.6 | W10: =H10-(H10*0.07) -> 212.38032 | X10: 234 | Y10: =(X10-H10)/H10 -> 0.024671214 | Z10: =F10/F$18 -> 0.14602863 | AB10: 45349 | AC10: 99 | AD10: Bought as it gapped out of base on EPS.
A11: KD | B11: Long | C11: Kyndryl Hldgs | D11: =1160.2602+1046.0778 -> 2206.338 | E11: 20.4 | F11: =E11*D11 -> 45009.295 | G11: =20288.83+19170.47 -> 39459.3 | H11: =G11/D11 -> 17.884522 | I11: =F11-G11 -> 5549.9952 | J11: =E11-H11 -> 2.5154782 | K11: 45243 | L11: =DAYS360(K11,$C$1) -> 39 | M11: =(I11/G11) -> 0.14065113 | N11: 38 | O11: 94 | P11: 73 | Q11: 17.32 | R11: =Q11*0.93 -> 16.1076 | S11: 18.05 | T11: =Q11*1.25 -> 21.65 | U11: =Q11*1.5 -> 25.98 | V11: =Q11*2 -> 34.64 | W11: =H11-(H11*0.07) -> 16.632605 | X11: 18 | Y11: =(X11-H11)/H11 -> 0.0064568809 | Z11: =F11/F$18 -> 0.094734836 | AB11: 45350 | AC11: 81 | AD11: Bought after 11/08 b/o. Trading tightly here.
A12: PLTR | B12: Long | C12: Palantir | D12: =1006.8806+1065.4202 -> 2072.3008 | E12: 17.41 | F12: =E12*D12 -> 36078.757 | G12: =20479.95+20765.04 -> 41244.99 | H12: =G12/D12 -> 19.902994 | I12: =F12-G12 -> -5166.2331 | J12: =E12-H12 -> -2.4929938 | K12: 45245 | L12: =DAYS360(K12,$C$1) -> 37 | M12: =(I12/G12) -> -0.12525723 | N12: 38 | O12: 97 | P12: 84 | Q12: 19.17 | R12: =Q12*0.93 -> 17.8281 | S12: 17.05 | T12: =Q12*1.25 -> 23.9625 | U12: =Q12*1.5 -> 28.755 | V12: =Q12*2 -> 38.34 | W12: =H12-(H12*0.07) -> 18.509784 | X12: 18.75 | Y12: =(X12-H12)/H12 -> -0.057930672 | Z12: =F12/F$18 -> 0.075937983 | AB12: 45336 | AC12: 97
A13: BIL | B13: Long | C13: Tbill ETF | D13: =2223.78-868.0181 -> 1355.7619 | E13: 91.31 | F13: =E13*D13 -> 123794.62 | G13: =203698.25-79510.46 -> 124187.79 | H13: =G13/D13 -> 91.6 | I13: =F13-G13 -> -393.17091 | J13: =E13-H13 -> -0.28999997 | M13: =(I13/G13) -> -0.0031659385 | R13: =Q13*0.93 -> 0 | T13: =Q13*1.25 -> 0 | U13: =Q13*1.5 -> 0 | V13: =Q13*2 -> 0 | W13: =H13-(H13*0.07) -> 85.188 | Y13: =(X13-H13)/H13 -> -1 | Z13: =F13/F$18 -> 0.26056091
A14: SQQQ | B14: Long | C14: QQQ Triple short | D14: 511.2918 | E14: 13.53 | F14: =E14*D14 -> 6917.7781 | G14: 24797.66 | H14: =G14/D14 -> 48.500015 | I14: =F14-G14 -> -17879.882 | J14: =E14-H14 -> -34.970015 | M14: =(I14/G14) -> -0.72103101 | R14: =Q14*0.93 -> 0 | T14: =Q14*1.25 -> 0 | U14: =Q14*1.5 -> 0 | V14: =Q14*2 -> 0 | W14: =H14-(H14*0.07) -> 45.105014 | Y14: =(X14-H14)/H14 -> -1 | Z14: =F14/F$18 -> 0.014560427
F15: =E15*D15 -> 0 | H15: =G15/D15 -> #DIV/0! | I15: =F15-G15 -> 0 | J15: =E15-H15 -> #DIV/0! | L15: =DAYS360(K15,$C$1) -> 44632 | M15: =(I15/G15) -> #DIV/0! | R15: =Q15*0.93 -> 0 | T15: =Q15*1.25 -> 0 | U15: =Q15*1.5 -> 0 | V15: =Q15*2 -> 0 | W15: =H15-(H15*0.07) -> #DIV/0! | Y15: =(X15-H15)/H15 -> #DIV/0! | Z15: =F15/F$18 -> 0
A16: Sub-Total | F16: =SUM(F6:F15) -> 361916.18 | G16: =SUM(G6:G15) -> 373115.8 | I16: =SUM(I6:I15) -> -11199.622
D17: Cash, other | F17: 113192 | G17: =F17/F18 -> 0.23824469
D18: Total | F18: =SUM(F16:F17) -> 475108.18
H19: Last week's close | I19: ='12-15-23'!F18 -> 474150.32 | K19: 45107 | L19: =509801-21683 -> 488118
H20: Week's change | I20: =(F18-I19)/I19 -> 0.0020201559 | K20: chg % | L20: =(F18-L19)/L19 -> -0.026653026
M22: days
A23: 2023 Closed Trades - Managed Acct | D23: Qty | E23: Cost/sh | F23: $ cost | G23: $Proc | H23: Proc/sh | I23: Profit/loss | J23: % | K23: Date purch | L23: Date sold | M23: held | P23: Comments
A25: HXL | B25: Long | C25: Hexcel | D25: 665.9739 | E25: =F25/D25 -> 76.621621 | F25: 51028 | G25: 45324.79 | H25: =G25/D25 -> 68.057907 | I25: =G25-F25 -> -5703.21 | J25: =I25/F25 -> -0.11176629 | K25: 45106 | L25: 45132 | M25: =DAYS360(K25,L25) -> 26 | O25: Bad reaction to EPS report. Stopped out.
A26: MCK | B26: Long | C26: McKesson | D26: 123.3931 | E26: =F26/D26 -> 413.24004 | F26: 50990.97 | G26: 48894.94 | H26: =G26/D26 -> 396.25344 | I26: =G26-F26 -> -2096.03 | J26: =I26/F26 -> -0.041105906 | K26: 45104 | L26: 45138 | M26: =DAYS360(K26,L26) -> 34 | O26: Broke original stop and 50dma. EPS coming in a few days.
A27: DXCM | B27: Long | C27: DexCom | D27: 278.2008 | E27: =F27/D27 -> 128.41002 | F27: 35723.77 | G27: 34855.72 | H27: =G27/D27 -> 125.28979 | I27: =G27-F27 -> -868.05 | J27: =I27/F27 -> -0.024298947 | K27: 45106 | L27: 45138 | M27: =DAYS360(K27,L27) -> 32 | O27: The positive reaction to EPS report was rejected at the old high and reversed. Didn't like the action.
A28: IONQ | B28: Long | C28: IonQ | D28: 1007.1459 | E28: =F28/D28 -> 20.954908 | F28: 21104.65 | G28: 18099.32 | H28: =G28/D28 -> 17.970902 | I28: =G28-F28 -> -3005.33 | J28: =I28/F28 -> -0.14240132 | K28: 45181 | L28: 45183 | M28: =DAYS360(K28,L28) -> 2 | O28: Breakout failure. Only 4% position. Only .6% hit to total.
A29: SNPS | B29: Long | C29: Synopsys | D29: 115.8536 | E29: =F29/D29 -> 442.16002 | F29: 51225.83 | G29: 52055.28 | H29: =G29/D29 -> 449.31949 | I29: =G29-F29 -> 829.45 | J29: =I29/F29 -> 0.016192027 | K29: 45117 | L29: 45184 | M29: =DAYS360(K29,L29) -> 65 | O29: Sold to protect capital on an ugly day.
A30: MTSI | B30: Long | C30: MACOM Tech Sol | D30: 507.0754 | E30: =F30/D30 -> 81.153611 | F30: 41151 | G30: 38871.01 | H30: =G30/D30 -> 76.657258 | I30: =G30-F30 -> -2279.99 | J30: =I30/F30 -> -0.055405458 | K30: 45167 | L30: 45216 | M30: =DAYS360(K30,L30) -> 48 | O30: Lost the 50dma in above avg vol. Sold prior to stop.
A31: ZS | B31: Long | C31: Zscaler | D31: 306.1703 | E31: =F31/D31 -> 170.32671 | F31: 52148.98 | G31: 49351.52 | H31: =G31/D31 -> 161.18977 | I31: =G31-F31 -> -2797.46 | J31: =I31/F31 -> -0.053643619 | K31: 45208 | L31: 45219 | M31: =DAYS360(K31,L31) -> 11 | O31: Lost the pivot in heavy vol. Sold prior to stop.
A32: DUOL | B32: Long | C32: Duolingo | D32: 239.9158 | E32: =F32/D32 -> 173.89088 | F32: 41719.17 | G32: 36026.28 | H32: =G32/D32 -> 150.16218 | I32: =G32-F32 -> -5692.89 | J32: =I32/F32 -> -0.13645741 | K32: 45208 | L32: 45219 | M32: =DAYS360(K32,L32) -> 11 | O32: Blew through my stop in a matter of an hour on Thurs. Sold Friday when it didn't recover early.
A33: AIT | B33: Long | C33: Applied Ind Tec | D33: 266.8733 | E33: =F33/D33 -> 151.47948 | F33: 40425.83 | G33: 40616.77 | H33: =G33/D33 -> 152.19496 | I33: =G33-F33 -> 190.94 | J33: =I33/F33 -> 0.0047232178 | K33: 45153 | L33: 45224 | M33: =DAYS360(K33,L33) -> 70 | O33: Sold to protect my cost.
A34: APPF | B34: Long | C34: AppFolio | D34: 247.9038 | E34: =F34/D34 -> 205.43166 | F34: 50927.29 | G34: 45926.83 | H34: =G34/D34 -> 185.26069 | I34: =G34-F34 -> -5000.46 | J34: =I34/F34 -> -0.098188221 | K34: 45244 | L34: 45267 | M34: =DAYS360(K34,L34) -> 23 | O34: Broke the 50dma.
A35: SMCI | B35: Long | C35: Super Micro Comp | D35: 179.9328 | E35: =F35/D35 -> 320.36577 | F35: 57644.31 | G35: 52870.41 | H35: =G35/D35 -> 293.8342 | I35: =G35-F35 -> -4773.9 | J35: =I35/F35 -> -0.0828165 | K35: 45279 | L35: 45282 | M35: =DAYS360(K35,L35) -> 3 | O35: B/O failed.
I38: =SUM(I25:I37) -> -31196.93 | J38: Avg
H39: # of losses | I39: 9 | J39: -0.0829
H40: # of wins | I40: 2 | J40: 0.0105

Sheet 12-29-23
C1: 45289
C3: MANAGED ACCT | X3: Current | AC3: IBD
H4: Cost | J4: P/L | N4: Group | P4: EPS | R4: pivot | S4: last | W4: cost | X4: Stop | Y4: Stop | Z4: % | AB4: EPS | AC4: Comp
A5: Symbol | B5: Position | C5: Name | D5: Qty | E5: Current | F5: Value | G5: Cost | H5: per share | I5: P/L $ | J5: per sh | K5: Date purch | L5: days held | M5: % incr | N5: Rank | O5: RS | P5: RS | Q5: pivot | R5: -0.07 | S5: low | T5: 0.25 | U5: 0.5 | V5: 1 | W5: -0.07 | X5: Loss | Y5: Loss% | Z5: of port | AB5: Due | AC5: Rank
A7: MNSO | B7: Long | C7: Minoso | D7: =1211.7123+804.6763 -> 2016.3886 | E7: 20.41 | F7: =E7*D7 -> 41154.491 | G7: =25318.9+15999 -> 41317.9 | H7: =G7/D7 -> 20.49104 | I7: =F7-G7 -> -163.40867 | J7: =E7-H7 -> -0.081040269 | K7: 45135 | L7: =DAYS360(K7,$C$1) -> 151 | M7: =(I7/G7) -> -0.0039549124 | N7: 137 | O7: 74 | P7: 98 | Q7: 19.48 | R7: =Q7*0.93 -> 18.1164 | S7: 18.27 | T7: =Q7*1.25 -> 24.35 | U7: =Q7*1.5 -> 29.22 | V7: =Q7*2 -> 38.96 | W7: =H7-(H7*0.07) -> 19.056667 | X7: 26 | Y7: =(X7-H7)/H7 -> 0.26884725 | Z7: =F7/F$19 -> 0.086429855 | AB7: 45350 | AC7: 84 | AD7: Bought after 07/24 b/o. Added at the 21dema.
A8: TS | B8: Long | C8: Tenaris | D8: 1166.935 | E8: 34.76 | F8: =E8*D8 -> 40562.661 | G8: 40941.92 | H8: =G8/D8 -> 35.085005 | I8: =F8-G8 -> -379.2594 | J8: =E8-H8 -> -0.32500473 | K8: 45233 | L8: =DAYS360(K8,$C$1) -> 56 | M8: =(I8/G8) -> -0.0092633516 | N8: 74 | O8: 67 | P8: 69 | Q8: 34.2 | R8: =Q8*0.93 -> 31.806 | S8: 32.69 | T8: =Q8*1.25 -> 42.75 | U8: =Q8*1.5 -> 51.3 | V8: =Q8*2 -> 68.4 | W8: =H8-(H8*0.07) -> 32.629054 | X8: 32.75 | Y8: =(X8-H8)/H8 -> -0.066552784 | Z8: =F8/F$19 -> 0.085186932 | AB8: 45343 | AC8: 80 | AD8: Bought day after gapping out of base.
A9: AXON | B9: Long | C9: Axon Enterprise | D9: 267.8431 | E9: 258.33 | F9: =E9*D9 -> 69191.908 | G9: 61166.24 | H9: =G9/D9 -> 228.36594 | I9: =F9-G9 -> 8025.668 | J9: =E9-H9 -> 29.964065 | K9: 45238 | L9: =DAYS360(K9,$C$1) -> 51 | M9: =(I9/G9) -> 0.13121075 | N9: 42 | O9: 90 | P9: 99 | Q9: 223.3 | R9: =Q9*0.93 -> 207.669 | S9: 224.28 | T9: =Q9*1.25 -> 279.125 | U9: =Q9*1.5 -> 334.95 | V9: =Q9*2 -> 446.6 | W9: =H9-(H9*0.07) -> 212.38032 | X9: 234 | Y9: =(X9-H9)/H9 -> 0.024671214 | Z9: =F9/F$19 -> 0.14531212 | AB9: 45349 | AC9: 99 | AD9: Bought as it gapped out of base on EPS.
A10: KD | B10: Long | C10: Kyndryl Hldgs | D10: =1160.2602+1046.0778 -> 2206.338 | E10: 20.78 | F10: =E10*D10 -> 45847.704 | G10: =20288.83+19170.47 -> 39459.3 | H10: =G10/D10 -> 17.884522 | I10: =F10-G10 -> 6388.4036 | J10: =E10-H10 -> 2.8954782 | K10: 45243 | L10: =DAYS360(K10,$C$1) -> 46 | M10: =(I10/G10) -> 0.16189855 | N10: 41 | O10: 95 | P10: 73 | Q10: 17.32 | R10: =Q10*0.93 -> 16.1076 | S10: 18.05 | T10: =Q10*1.25 -> 21.65 | U10: =Q10*1.5 -> 25.98 | V10: =Q10*2 -> 34.64 | W10: =H10-(H10*0.07) -> 16.632605 | X10: 18 | Y10: =(X10-H10)/H10 -> 0.0064568809 | Z10: =F10/F$19 -> 0.096286219 | AB10: 45350 | AC10: 87 | AD10: Bought after 11/08 b/o. Trading tightly here.
A11: DDOG | B11: Long | C11: Datadog | D11: 308.2955 | E11: 121.38 | F11: =E11*D11 -> 37420.908 | G11: 38082.35 | H11: =G11/D11 -> 123.52548 | I11: =F11-G11 -> -661.44221 | J11: =E11-H11 -> -2.1454812 | K11: 45286 | L11: =DAYS360(K11,$C$1) -> 3 | M11: =(I11/G11) -> -0.017368734 | N11: 41 | O11: 94 | P11: 99 | Q11: 120.26 | R11: =Q11*0.93 -> 111.8418 | S11: 112.25 | T11: =Q11*1.25 -> 150.325 | U11: =Q11*1.5 -> 180.39 | V11: =Q11*2 -> 240.52 | W11: =H11-(H11*0.07) -> 114.8787 | X11: 116 | Y11: =(X11-H11)/H11 -> -0.060922501 | Z11: =F11/F$19 -> 0.078588837 | AB11: 45337 | AC11: 99 | AD11: Trading tightly since b/o.
A12: YELP | B12: Long | C12: Yelp Inc | D12: 808.573 | E12: 47.34 | F12: =E12*D12 -> 38277.846 | G12: 38349.05 | H12: =G12/D12 -> 47.428062 | I12: =F12-G12 -> -71.20418 | J12: =E12-H12 -> -0.088061536 | K12: 45288 | L12: =DAYS360(K12,$C$1) -> 1 | M12: =(I12/G12) -> -0.0018567391 | N12: 62 | O12: 91 | P12: 82 | Q12: 47 | R12: =Q12*0.93 -> 43.71 | S12: 42.57 | T12: =Q12*1.25 -> 58.75 | U12: =Q12*1.5 -> 70.5 | V12: =Q12*2 -> 94 | W12: =H12-(H12*0.07) -> 44.108097 | X12: 45.75 | Y12: =(X12-H12)/H12 -> -0.035381196 | Z12: =F12/F$19 -> 0.08038852 | AB12: 45330 | AC12: 95 | AD12: Bought the pivot test.
F13: =E13*D13 -> 0 | H13: =G13/D13 -> #DIV/0! | I13: =F13-G13 -> 0 | J13: =E13-H13 -> #DIV/0! | L13: =DAYS360(K13,$C$1) -> 44639 | M13: =(I13/G13) -> #DIV/0! | R13: =Q13*0.93 -> 0 | T13: =Q13*1.25 -> 0 | U13: =Q13*1.5 -> 0 | V13: =Q13*2 -> 0 | W13: =H13-(H13*0.07) -> #DIV/0! | Y13: =(X13-H13)/H13 -> #DIV/0! | Z13: =F13/F$19 -> 0
A14: BIL | B14: Long | C14: Tbill ETF | D14: =2223.78-868.0181 -> 1355.7619 | E14: 91.39 | F14: =E14*D14 -> 123903.08 | G14: =203698.25-79510.46 -> 124187.79 | H14: =G14/D14 -> 91.6 | I14: =F14-G14 -> -284.70996 | J14: =E14-H14 -> -0.20999997 | M14: =(I14/G14) -> -0.0022925761 | R14: =Q14*0.93 -> 0 | T14: =Q14*1.25 -> 0 | U14: =Q14*1.5 -> 0 | V14: =Q14*2 -> 0 | W14: =H14-(H14*0.07) -> 85.188 | Y14: =(X14-H14)/H14 -> -1 | Z14: =F14/F$19 -> 0.2602128
F15: =E15*D15 -> 0 | H15: =G15/D15 -> #DIV/0! | I15: =F15-G15 -> 0 | J15: =E15-H15 -> #DIV/0! | M15: =(I15/G15) -> #DIV/0! | R15: =Q15*0.93 -> 0 | T15: =Q15*1.25 -> 0 | U15: =Q15*1.5 -> 0 | V15: =Q15*2 -> 0 | W15: =H15-(H15*0.07) -> #DIV/0! | Y15: =(X15-H15)/H15 -> #DIV/0! | Z15: =F15/F$19 -> 0
F16: =E16*D16 -> 0 | H16: =G16/D16 -> #DIV/0! | I16: =F16-G16 -> 0 | J16: =E16-H16 -> #DIV/0! | L16: =DAYS360(K16,$C$1) -> 44639 | M16: =(I16/G16) -> #DIV/0! | R16: =Q16*0.93 -> 0 | T16: =Q16*1.25 -> 0 | U16: =Q16*1.5 -> 0 | V16: =Q16*2 -> 0 | W16: =H16-(H16*0.07) -> #DIV/0! | Y16: =(X16-H16)/H16 -> #DIV/0! | Z16: =F16/F$19 -> 0
A17: Sub-Total | F17: =SUM(F6:F16) -> 396358.6 | G17: =SUM(G6:G16) -> 383504.55 | I17: =SUM(I6:I16) -> 12854.047
D18: Cash, other | F18: 79802 | G18: =F18/F19 -> 0.16759472
D19: Total | F19: =SUM(F17:F18) -> 476160.6
H20: Last week's close | I20: ='12-22-23'!F18 -> 475108.18 | K20: 45107 | L20: =509801-21683 -> 488118
H21: Week's change | I21: =(F19-I20)/I20 -> 0.0022151143 | K21: chg % | L21: =(F19-L20)/L20 -> -0.024496951
M23: days
A24: 2023 Closed Trades - Managed Acct | D24: Qty | E24: Cost/sh | F24: $ cost | G24: $Proc | H24: Proc/sh | I24: Profit/loss | J24: % | K24: Date purch | L24: Date sold | M24: held | P24: Comments
A26: HXL | B26: Long | C26: Hexcel | D26: 665.9739 | E26: =F26/D26 -> 76.621621 | F26: 51028 | G26: 45324.79 | H26: =G26/D26 -> 68.057907 | I26: =G26-F26 -> -5703.21 | J26: =I26/F26 -> -0.11176629 | K26: 45106 | L26: 45132 | M26: =DAYS360(K26,L26) -> 26 | O26: Bad reaction to EPS report. Stopped out.
A27: MCK | B27: Long | C27: McKesson | D27: 123.3931 | E27: =F27/D27 -> 413.24004 | F27: 50990.97 | G27: 48894.94 | H27: =G27/D27 -> 396.25344 | I27: =G27-F27 -> -2096.03 | J27: =I27/F27 -> -0.041105906 | K27: 45104 | L27: 45138 | M27: =DAYS360(K27,L27) -> 34 | O27: Broke original stop and 50dma. EPS coming in a few days.
A28: DXCM | B28: Long | C28: DexCom | D28: 278.2008 | E28: =F28/D28 -> 128.41002 | F28: 35723.77 | G28: 34855.72 | H28: =G28/D28 -> 125.28979 | I28: =G28-F28 -> -868.05 | J28: =I28/F28 -> -0.024298947 | K28: 45106 | L28: 45138 | M28: =DAYS360(K28,L28) -> 32 | O28: The positive reaction to EPS report was rejected at the old high and reversed. Didn't like the action.
A29: IONQ | B29: Long | C29: IonQ | D29: 1007.1459 | E29: =F29/D29 -> 20.954908 | F29: 21104.65 | G29: 18099.32 | H29: =G29/D29 -> 17.970902 | I29: =G29-F29 -> -3005.33 | J29: =I29/F29 -> -0.14240132 | K29: 45181 | L29: 45183 | M29: =DAYS360(K29,L29) -> 2 | O29: Breakout failure. Only 4% position. Only .6% hit to total.
A30: SNPS | B30: Long | C30: Synopsys | D30: 115.8536 | E30: =F30/D30 -> 442.16002 | F30: 51225.83 | G30: 52055.28 | H30: =G30/D30 -> 449.31949 | I30: =G30-F30 -> 829.45 | J30: =I30/F30 -> 0.016192027 | K30: 45117 | L30: 45184 | M30: =DAYS360(K30,L30) -> 65 | O30: Sold to protect capital on an ugly day.
A31: MTSI | B31: Long | C31: MACOM Tech Sol | D31: 507.0754 | E31: =F31/D31 -> 81.153611 | F31: 41151 | G31: 38871.01 | H31: =G31/D31 -> 76.657258 | I31: =G31-F31 -> -2279.99 | J31: =I31/F31 -> -0.055405458 | K31: 45167 | L31: 45216 | M31: =DAYS360(K31,L31) -> 48 | O31: Lost the 50dma in above avg vol. Sold prior to stop.
A32: ZS | B32: Long | C32: Zscaler | D32: 306.1703 | E32: =F32/D32 -> 170.32671 | F32: 52148.98 | G32: 49351.52 | H32: =G32/D32 -> 161.18977 | I32: =G32-F32 -> -2797.46 | J32: =I32/F32 -> -0.053643619 | K32: 45208 | L32: 45219 | M32: =DAYS360(K32,L32) -> 11 | O32: Lost the pivot in heavy vol. Sold prior to stop.
A33: DUOL | B33: Long | C33: Duolingo | D33: 239.9158 | E33: =F33/D33 -> 173.89088 | F33: 41719.17 | G33: 36026.28 | H33: =G33/D33 -> 150.16218 | I33: =G33-F33 -> -5692.89 | J33: =I33/F33 -> -0.13645741 | K33: 45208 | L33: 45219 | M33: =DAYS360(K33,L33) -> 11 | O33: Blew through my stop in a matter of an hour on Thurs. Sold Friday when it didn't recover early.
A34: AIT | B34: Long | C34: Applied Ind Tec | D34: 266.8733 | E34: =F34/D34 -> 151.47948 | F34: 40425.83 | G34: 40616.77 | H34: =G34/D34 -> 152.19496 | I34: =G34-F34 -> 190.94 | J34: =I34/F34 -> 0.0047232178 | K34: 45153 | L34: 45224 | M34: =DAYS360(K34,L34) -> 70 | O34: Sold to protect my cost.
A35: APPF | B35: Long | C35: AppFolio | D35: 247.9038 | E35: =F35/D35 -> 205.43166 | F35: 50927.29 | G35: 45926.83 | H35: =G35/D35 -> 185.26069 | I35: =G35-F35 -> -5000.46 | J35: =I35/F35 -> -0.098188221 | K35: 45244 | L35: 45267 | M35: =DAYS360(K35,L35) -> 23 | O35: Broke the 50dma.
A36: SMCI | B36: Long | C36: Super Micro Comp | D36: 179.9328 | E36: =F36/D36 -> 320.36577 | F36: 57644.31 | G36: 52870.41 | H36: =G36/D36 -> 293.8342 | I36: =G36-F36 -> -4773.9 | J36: =I36/F36 -> -0.0828165 | K36: 45279 | L36: 45282 | M36: =DAYS360(K36,L36) -> 3 | O36: B/O failed.
A37: PLTR | B37: Long | C37: Palantir | D37: =1006.8806+1065.4202 -> 2072.3008 | E37: =F37/D37 -> 19.902994 | F37: =20479.95+20765.04 -> 41244.99 | G37: 35809.9 | H37: =G37/D37 -> 17.280262 | I37: =G37-F37 -> -5435.09 | J37: =I37/F37 -> -0.13177576 | K37: 45245 | L37: 45289 | M37: =DAYS360(K37,L37) -> 44
A38: SQQQ | B38: Long | C38: QQQ Triple short | D38: 511.2918 | E38: =F38/D38 -> 48.500015 | F38: 24797.66 | G38: 6812.97 | H38: =G38/D38 -> 13.325013 | I38: =G38-F38 -> -17984.69 | J38: =I38/F38 -> -0.72525754
I39: =SUM(I26:I38) -> -54616.71 | J39: Avg
H40: # of losses | I40: 9 | J40: -0.0829
H41: # of wins | I41: 2 | J41: 0.0105
