Workbook

Sheet 01-05-24
C1: 45296
C3: MANAGED ACCT | X3: Current | AC3: IBD
H4: Cost | J4: P/L | N4: Group | P4: EPS | R4: pivot | S4: last | W4: cost | X4: Stop | Y4: Stop | Z4: % | AB4: EPS | AC4: Comp
A5: Symbol | B5: Position | C5: Name | D5: Qty | E5: Current | F5: Value | G5: Cost | H5: per share | I5: P/L $ | J5: per sh | K5: Date purch | L5: days held | M5: % incr | N5: Rank | O5: RS | P5: RS | Q5: pivot | R5: -0.07 | S5: low | T5: 0.25 | U5: 0.5 | V5: 1 | W5: -0.07 | X5: Loss | Y5: Loss% | Z5: of port | AB5: Due | AC5: Rank
A7: MNSO | B7: Long | C7: Minoso | D7: =1211.7123+804.6763 -> 2016.3886 | E7: 21.38 | F7: =E7*D7 -> 43110.388 | G7: =25318.9+15999 -> 41317.9 | H7: =G7/D7 -> 20.49104 | I7: =F7-G7 -> 1792.4883 | J7: =E7-H7 -> 0.88895973 | K7: 45135 | L7: =DAYS360(K7,$C$1) -> 157 | M7: =(I7/G7) -> 0.04338285 | N7: 163 | O7: 84 | P7: 98 | Q7: 19.48 | R7: =Q7*0.93 -> 18.1164 | S7: 18.27 | T7: =Q7*1.25 -> 24.35 | U7: =Q7*1.5 -> 29.22 | V7: =Q7*2 -> 38.96 | W7: =H7-(H7*0.07) -> 19.056667 | X7: 26 | Y7: =(X7-H7)/H7 -> 0.26884725 | Z7: =F7/F$19 -> 0.092164222 | AB7: 45350 | AC7: 90 | AD7: Bought after 07/24 b/o. Added at the 21dema.
A8: TS | B8: Long | C8: Tenaris | D8: 1166.935 | E8: 33.95 | F8: =E8*D8 -> 39617.443 | G8: 40941.92 | H8: =G8/D8 -> 35.085005 | I8: =F8-G8 -> -1324.4767 | J8: =E8-H8 -> -1.1350047 | K8: 45233 | L8: =DAYS360(K8,$C$1) -> 62 | M8: =(I8/G8) -> -0.032350138 | N8: 69 | O8: 71 | P8: 69 | Q8: 34.2 | R8: =Q8*0.93 -> 31.806 | S8: 32.69 | T8: =Q8*1.25 -> 42.75 | U8: =Q8*1.5 -> 51.3 | V8: =Q8*2 -> 68.4 | W8: =H8-(H8*0.07) -> 32.629054 | X8: 32.75 | Y8: =(X8-H8)/H8 -> -0.066552784 | Z8: =F8/F$19 -> 0.084696775 | AB8: 45343 | AC8: 80 | AD8: Bought day after gapping out of base.
A9: AXON | B9: Long | C9: Axon Enterprise | D9: 267.8431 | E9: 244.21 | F9: =E9*D9 -> 65409.963 | G9: 61166.24 | H9: =G9/D9 -> 228.36594 | I9: =F9-G9 -> 4243.7235 | J9: =E9-H9 -> 15.844065 | K9: 45238 | L9: =DAYS360(K9,$C$1) -> 57 | M9: =(I9/G9) -> 0.069380159 | N9: 33 | O9: 88 | P9: 99 | Q9: 223.3 | R9: =Q9*0.93 -> 207.669 | S9: 224.28 | T9: =Q9*1.25 -> 279.125 | U9: =Q9*1.5 -> 334.95 | V9: =Q9*2 -> 446.6 | W9: =H9-(H9*0.07) -> 212.38032 | X9: 234 | Y9: =(X9-H9)/H9 -> 0.024671214 | Z9: =F9/F$19 -> 0.13983772 | AB9: 45349 | AC9: 99 | AD9: Bought as it gapped out of base on EPS.
A10: KD | B10: Long | C10: Kyndryl Hldgs | D10: =1160.2602+1046.0778 -> 2206.338 | E10: 19.59 | F10: =E10*D10 -> 43222.161 | G10: =20288.83+19170.47 -> 39459.3 | H10: =G10/D10 -> 17.884522 | I10: =F10-G10 -> 3762.8614 | J10: =E10-H10 -> 1.7054782 | K10: 45243 | L10: =DAYS360(K10,$C$1) -> 52 | M10: =(I10/G10) -> 0.095360572 | N10: 44 | O10: 93 | P10: 73 | Q10: 17.32 | R10: =Q10*0.93 -> 16.1076 | S10: 18.05 | T10: =Q10*1.25 -> 21.65 | U10: =Q10*1.5 -> 25.98 | V10: =Q10*2 -> 34.64 | W10: =H10-(H10*0.07) -> 16.632605 | X10: 18 | Y10: =(X10-H10)/H10 -> 0.0064568809 | Z10: =F10/F$19 -> 0.092403178 | AB10: 45350 | AC10: 86 | AD10: Bought after 11/08 b/o. Trading tightly here.
A11: DDOG | B11: Long | C11: Datadog | D11: 308.2955 | E11: 115.99 | F11: =E11*D11 -> 35759.195 | G11: 38082.35 | H11: =G11/D11 -> 123.52548 | I11: =F11-G11 -> -2323.155 | J11: =E11-H11 -> -7.5354812 | K11: 45286 | L11: =DAYS360(K11,$C$1) -> 9 | M11: =(I11/G11) -> -0.061003456 | N11: 44 | O11: 94 | P11: 99 | Q11: 120.26 | R11: =Q11*0.93 -> 111.8418 | S11: 110.7 | T11: =Q11*1.25 -> 150.325 | U11: =Q11*1.5 -> 180.39 | V11: =Q11*2 -> 240.52 | W11: =H11-(H11*0.07) -> 114.8787 | X11: 116 | Y11: =(X11-H11)/H11 -> -0.060922501 | Z11: =F11/F$19 -> 0.076448358 | AB11: 45337 | AC11: 99 | AD11: Trading tightly since b/o.
A12: YELP | B12: Long | C12: Yelp Inc | D12: 808.573 | E12: 44.97 | F12: =E12*D12 -> 36361.528 | G12: 38349.05 | H12: =G12/D12 -> 47.428062 | I12: =F12-G12 -> -1987.5222 | J12: =E12-H12 -> -2.4580615 | K12: 45288 | L12: =DAYS360(K12,$C$1) -> 7 | M12: =(I12/G12) -> -0.051827156 | N12: 61 | O12: 89 | P12: 83 | Q12: 47 | R12: =Q12*0.93 -> 43.71 | S12: 42.57 | T12: =Q12*1.25 -> 58.75 | U12: =Q12*1.5 -> 70.5 | V12: =Q12*2 -> 94 | W12: =H12-(H12*0.07) -> 44.108097 | X12: 45.75 | Y12: =(X12-H12)/H12 -> -0.035381196 | Z12: =F12/F$19 -> 0.077736065 | AB12: 45330 | AC12: 96 | AD12: Bought the pivot test.
F13: =E13*D13 -> 0 | H13: =G13/D13 -> #DIV/0! | I13: =F13-G13 -> 0 | J13: =E13-H13 -> #DIV/0! | L13: =DAYS360(K13,$C$1) -> 44645 | M13: =(I13/G13) -> #DIV/0! | R13: =Q13*0.93 -> 0 | T13: =Q13*1.25 -> 0 | U13: =Q13*1.5 -> 0 | V13: =Q13*2 -> 0 | W13: =H13-(H13*0.07) -> #DIV/0! | Y13: =(X13-H13)/H13 -> #DIV/0! | Z13: =F13/F$19 -> 0
A14: BIL | B14: Long | C14: Tbill ETF | D14: =2223.78-868.0181 -> 1355.7619 | E14: 91.47 | F14: =E14*D14 -> 124011.54 | G14: =203698.25-79510.46 -> 124187.79 | H14: =G14/D14 -> 91.6 | I14: =F14-G14 -> -176.24901 | J14: =E14-H14 -> -0.12999997 | M14: =(I14/G14) -> -0.0014192137 | R14: =Q14*0.93 -> 0 | T14: =Q14*1.25 -> 0 | U14: =Q14*1.5 -> 0 | V14: =Q14*2 -> 0 | W14: =H14-(H14*0.07) -> 85.188 | Y14: =(X14-H14)/H14 -> -1 | Z14: =F14/F$19 -> 0.26512003
F15: =E15*D15 -> 0 | H15: =G15/D15 -> #DIV/0! | I15: =F15-G15 -> 0 | J15: =E15-H15 -> #DIV/0! | M15: =(I15/G15) -> #DIV/0! | R15: =Q15*0.93 -> 0 | T15: =Q15*1.25 -> 0 | U15: =Q15*1.5 -> 0 | V15: =Q15*2 -> 0 | W15: =H15-(H15*0.07) -> #DIV/0! | Y15: =(X15-H15)/H15 -> #DIV/0! | Z15: =F15/F$19 -> 0
F16: =E16*D16 -> 0 | H16: =G16/D16 -> #DIV/0! | I16: =F16-G16 -> 0 | J16: =E16-H16 -> #DIV/0! | L16: =DAYS360(K16,$C$1) -> 44645 | M16: =(I16/G16) -> #DIV/0! | R16: =Q16*0.93 -> 0 | T16: =Q16*1.25 -> 0 | U16: =Q16*1.5 -> 0 | V16: =Q16*2 -> 0 | W16: =H16-(H16*0.07) -> #DIV/0! | Y16: =(X16-H16)/H16 -> #DIV/0! | Z16: =F16/F$19 -> 0
A17: Sub-Total | F17: =SUM(F6:F16) -> 387492.22 | G17: =SUM(G6:G16) -> 383504.55 | I17: =SUM(I6:I16) -> 3987.6702
D18: Cash, other | F18: 80264 | G18: =F18/F19 -> 0.17159366
D19: Total | F19: =SUM(F17:F18) -> 467756.22
H20: Last week's close | I20: 476160.6 | K20: 45291 | L20: 476160.6
A21: * | H21: Week's change | I21: =(F19-I20)/I20 -> -0.017650305 | K21: chg % | L21: =(F19-L20)/L20 -> -0.017650305
M23: days
A24: 2024 Closed Trades - Managed Acct | D24: Qty | E24: Cost/sh | F24: $ cost | G24: $Proc | H24: Proc/sh | I24: Profit/loss | J24: % | K24: Date purch | L24: Date sold | M24: held | P24: Comments
I39: =SUM(I26:I38) -> 0 | J39: Avg
H40: # of losses
H41: # of wins

Sheet 01-12-24
C1: 45303
C3: MANAGED ACCT | X3: Current | AC3: IBD
H4: Cost | J4: P/L | N4: Group | P4: EPS | R4: pivot | S4: last | W4: cost | X4: Stop | Y4: Stop | Z4: % | AB4: EPS | AC4: Comp
A5: Symbol | B5: Position | C5: Name | D5: Qty | E5: Current | F5: Value | G5: Cost | H5: per share | I5: P/L $ | J5: per sh | K5: Date purch | L5: days held | M5: % incr | N5: Rank | O5: RS | P5: RS | Q5: pivot | R5: -0.07 | S5: low | T5: 0.25 | U5: 0.5 | V5: 1 | W5: -0.07 | X5: Loss | Y5: Loss% | Z5: of port | AB5: Due | AC5: Rank
A7: MNSO | B7: Long | C7: Minoso | D7: =1211.7123+804.6763 -> 2016.3886 | E7: 22.49 | F7: =E7*D7 -> 45348.58 | G7: =25318.9+15999 -> 41317.9 | H7: =G7/D7 -> 20.49104 | I7: =F7-G7 -> 4030.6796 | J7: =E7-H7 -> 1.9989597 | K7: 45135 | L7: =DAYS360(K7,$C$1) -> 164 | M7: =(I7/G7) -> 0.097552867 | N7: 178 | O7: 83 | P7: 98 | Q7: 19.48 | R7: =Q7*0.93 -> 18.1164 | S7: 18.27 | T7: =Q7*1.25 -> 24.35 | U7: =Q7*1.5 -> 29.22 | V7: =Q7*2 -> 38.96 | W7: =H7-(H7*0.07) -> 19.056667 | X7: 26 | Y7: =(X7-H7)/H7 -> 0.26884725 | Z7: =F7/F$19 -> 0.095391952 | AB7: 45350 | AC7: 89 | AD7: Bought after 07/24 b/o. Added at the 21dema.
A8: TS | B8: Long | C8: Tenaris | D8: 1166.935 | E8: 32.31 | F8: =E8*D8 -> 37703.67 | G8: 40941.92 | H8: =G8/D8 -> 35.085005 | I8: =F8-G8 -> -3238.2501 | J8: =E8-H8 -> -2.7750047 | K8: 45233 | L8: =DAYS360(K8,$C$1) -> 69 | M8: =(I8/G8) -> -0.079093754 | N8: 111 | O8: 35 | P8: 69 | Q8: 34.2 | R8: =Q8*0.93 -> 31.806 | S8: 32.69 | T8: =Q8*1.25 -> 42.75 | U8: =Q8*1.5 -> 51.3 | V8: =Q8*2 -> 68.4 | W8: =H8-(H8*0.07) -> 32.629054 | X8: 32.75 | Y8: =(X8-H8)/H8 -> -0.066552784 | Z8: =F8/F$19 -> 0.07931068 | AB8: 45343 | AC8: 58 | AD8: Bought day after gapping out of base.
A9: AXON | B9: Long | C9: Axon Enterprise | D9: 267.8431 | E9: 250.69 | F9: =E9*D9 -> 67145.587 | G9: 61166.24 | H9: =G9/D9 -> 228.36594 | I9: =F9-G9 -> 5979.3467 | J9: =E9-H9 -> 22.324065 | K9: 45238 | L9: =DAYS360(K9,$C$1) -> 64 | M9: =(I9/G9) -> 0.097755669 | N9: 29 | O9: 87 | P9: 99 | Q9: 223.3 | R9: =Q9*0.93 -> 207.669 | S9: 224.28 | T9: =Q9*1.25 -> 279.125 | U9: =Q9*1.5 -> 334.95 | V9: =Q9*2 -> 446.6 | W9: =H9-(H9*0.07) -> 212.38032 | X9: 234 | Y9: =(X9-H9)/H9 -> 0.024671214 | Z9: =F9/F$19 -> 0.14124254 | AB9: 45349 | AC9: 99 | AD9: Bought as it gapped out of base on EPS.
A10: KD | B10: Long | C10: Kyndryl Hldgs | D10: =1160.2602+1046.0778 -> 2206.338 | E10: 21.08 | F10: =E10*D10 -> 46509.605 | G10: =20288.83+19170.47 -> 39459.3 | H10: =G10/D10 -> 17.884522 | I10: =F10-G10 -> 7050.305 | J10: =E10-H10 -> 3.1954782 | K10: 45243 | L10: =DAYS360(K10,$C$1) -> 59 | M10: =(I10/G10) -> 0.17867284 | N10: 34 | O10: 93 | P10: 73 | Q10: 17.32 | R10: =Q10*0.93 -> 16.1076 | S10: 18.05 | T10: =Q10*1.25 -> 21.65 | U10: =Q10*1.5 -> 25.98 | V10: =Q10*2 -> 34.64 | W10: =H10-(H10*0.07) -> 16.632605 | X10: 18 | Y10: =(X10-H10)/H10 -> 0.0064568809 | Z10: =F10/F$19 -> 0.0978342 | AB10: 45328 | AC10: 90 | AD10: Bought after 11/08 b/o. Trading tightly here.
A11: DDOG | B11: Long | C11: Datadog | D11: 308.2955 | E11: 123 | F11: =E11*D11 -> 37920.346 | G11: 38082.35 | H11: =G11/D11 -> 123.52548 | I11: =F11-G11 -> -162.0035 | J11: =E11-H11 -> -0.52548123 | K11: 45286 | L11: =DAYS360(K11,$C$1) -> 16 | M11: =(I11/G11) -> -0.0042540311 | N11: 34 | O11: 95 | P11: 99 | Q11: 120.26 | R11: =Q11*0.93 -> 111.8418 | S11: 110.7 | T11: =Q11*1.25 -> 150.325 | U11: =Q11*1.5 -> 180.39 | V11: =Q11*2 -> 240.52 | W11: =H11-(H11*0.07) -> 114.8787 | X11: 116 | Y11: =(X11-H11)/H11 -> -0.060922501 | Z11: =F11/F$19 -> 0.079766465 | AB11: 45337 | AC11: 99 | AD11: Trading tightly since b/o.
F12: =E12*D12 -> 0 | H12: =G12/D12 -> #DIV/0! | I12: =F12-G12 -> 0 | J12: =E12-H12 -> #DIV/0! | L12: =DAYS360(K12,$C$1) -> 44652 | M12: =(I12/G12) -> #DIV/0! | R12: =Q12*0.93 -> 0 | T12: =Q12*1.25 -> 0 | U12: =Q12*1.5 -> 0 | V12: =Q12*2 -> 0 | W12: =H12-(H12*0.07) -> #DIV/0! | Y12: =(X12-H12)/H12 -> #DIV/0! | Z12: =F12/F$19 -> 0
A13: ACMR | B13: Long | C13: ACM Research | D13: 1339.9646 | E13: 21.81 | F13: =E13*D13 -> 29224.628 | G13: 28457.8 | H13: =G13/D13 -> 21.237725 | I13: =F13-G13 -> 766.82793 | J13: =E13-H13 -> 0.57227476 | K13: 45302 | L13: =DAYS360(K13,$C$1) -> 1 | M13: =(I13/G13) -> 0.026946142 | N13: 85 | O13: 95 | P13: 99 | Q13: 20.43 | R13: =Q13*0.93 -> 18.9999 | S13: 16.66 | T13: =Q13*1.25 -> 25.5375 | U13: =Q13*1.5 -> 30.645 | V13: =Q13*2 -> 40.86 | W13: =H13-(H13*0.07) -> 19.751084 | X13: 19.75 | Y13: =(X13-H13)/H13 -> -0.070051063 | Z13: =F13/F$19 -> 0.061474788 | AB13: 45345 | AC13: 98 | AD13: B/o Jan 10in big vol.
A14: BIL | B14: Long | C14: Tbill ETF | D14: =2223.78-868.0181 -> 1355.7619 | E14: 91.58 | F14: =E14*D14 -> 124160.67 | G14: =203698.25-79510.46 -> 124187.79 | H14: =G14/D14 -> 91.6 | I14: =F14-G14 -> -27.115198 | J14: =E14-H14 -> -0.01999997 | M14: =(I14/G14) -> -0.00021834029 | R14: =Q14*0.93 -> 0 | T14: =Q14*1.25 -> 0 | U14: =Q14*1.5 -> 0 | V14: =Q14*2 -> 0 | W14: =H14-(H14*0.07) -> 85.188 | Y14: =(X14-H14)/H14 -> -1 | Z14: =F14/F$19 -> 0.26117531
F15: =E15*D15 -> 0 | H15: =G15/D15 -> #DIV/0! | I15: =F15-G15 -> 0 | J15: =E15-H15 -> #DIV/0! | M15: =(I15/G15) -> #DIV/0! | R15: =Q15*0.93 -> 0 | T15: =Q15*1.25 -> 0 | U15: =Q15*1.5 -> 0 | V15: =Q15*2 -> 0 | W15: =H15-(H15*0.07) -> #DIV/0! | Y15: =(X15-H15)/H15 -> #DIV/0! | Z15: =F15/F$19 -> 0
F16: =E16*D16 -> 0 | H16: =G16/D16 -> #DIV/0! | I16: =F16-G16 -> 0 | J16: =E16-H16 -> #DIV/0! | L16: =DAYS360(K16,$C$1) -> 44652 | M16: =(I16/G16) -> #DIV/0! | R16: =Q16*0.93 -> 0 | T16: =Q16*1.25 -> 0 | U16: =Q16*1.5 -> 0 | V16: =Q16*2 -> 0 | W16: =H16-(H16*0.07) -> #DIV/0! | Y16: =(X16-H16)/H16 -> #DIV/0! | Z16: =F16/F$19 -> 0
A17: Sub-Total | F17: =SUM(F6:F16) -> 388013.09 | G17: =SUM(G6:G16) -> 373613.3 | I17: =SUM(I6:I16) -> 14399.79
D18: Cash, other | F18: 87379 | G18: =F18/F19 -> 0.18380407
D19: Total | F19: =SUM(F17:F18) -> 475392.09
H20: Last week's close | I20: ='01-05-24'!F19 -> 467756.22 | K20: 45291 | L20: 476160.6
A21: * | H21: Week's change | I21: =(F19-I20)/I20 -> 0.016324465 | K21: chg % | L21: =(F19-L20)/L20 -> -0.0016139713
M23: days
A24: 2024 Closed Trades - Managed Acct | D24: Qty | E24: Cost/sh | F24: $ cost | G24: $Proc | H24: Proc/sh | I24: Profit/loss | J24: % | K24: Date purch | L24: Date sold | M24: held | P24: Comments
A25: YELP | B25: Long | C25: Yelp Inc | D25: 808.573 | E25: =F25/D25 -> 47.428062 | F25: 38349.05 | G25: 35186.18 | H25: =G25/D25 -> 43.516392 | I25: =G25-F25 -> -3162.87 | J25: =I25/F25 -> -0.082475837 | K25: 45286 | L25: 45302 | M25: =DAYS360(K25,L25) -> 15 | O25: Closed below stop for 2 days.
I39: =SUM(I26:I38) -> 0 | J39: Avg
H40: # of losses
H41: # of wins

Sheet 01-19-24
C1: 45310
C3: MANAGED ACCT | X3: Current | AC3: IBD
H4: Cost | J4: P/L | N4: Group | P4: EPS | R4: pivot | S4: last | W4: cost | X4: Stop | Y4: Stop | Z4: % | AB4: EPS | AC4: Comp
A5: Symbol | B5: Position | C5: Name | D5: Qty | E5: Current | F5: Value | G5: Cost | H5: per share | I5: P/L $ | J5: per sh | K5: Date purch | L5: days held | M5: % incr | N5: Rank | O5: RS | P5: RS | Q5: pivot | R5: -0.07 | S5: low | T5: 0.25 | U5: 0.5 | V5: 1 | W5: -0.07 | X5: Loss | Y5: Loss% | Z5: of port | AB5: Due | AC5: Rank
A7: AXON | B7: Long | C7: Axon Enterprise | D7: 267.8431 | E7: 256.79 | F7: =E7*D7 -> 68779.43 | G7: 61166.24 | H7: =G7/D7 -> 228.36594 | I7: =F7-G7 -> 7613.1896 | J7: =E7-H7 -> 28.424065 | K7: 45238 | L7: =DAYS360(K7,$C$1) -> 71 | M7: =(I7/G7) -> 0.12446718 | N7: 25 | O7: 89 | P7: 99 | Q7: 223.3 | R7: =Q7*0.93 -> 207.669 | S7: 224.28 | T7: =Q7*1.25 -> 279.125 | U7: =Q7*1.5 -> 334.95 | V7: =Q7*2 -> 446.6 | W7: =H7-(H7*0.07) -> 212.38032 | X7: 234 | Y7: =(X7-H7)/H7 -> 0.024671214 | Z7: =F7/F$19 -> 0.14531856 | AB7: 45349 | AC7: 99 | AD7: Bought as it gapped out of base on EPS.
A8: KD | B8: Long | C8: Kyndryl Hldgs | D8: =1160.2602+1046.0778 -> 2206.338 | E8: 20.88 | F8: =E8*D8 -> 46068.337 | G8: =20288.83+19170.47 -> 39459.3 | H8: =G8/D8 -> 17.884522 | I8: =F8-G8 -> 6609.0374 | J8: =E8-H8 -> 2.9954782 | K8: 45243 | L8: =DAYS360(K8,$C$1) -> 66 | M8: =(I8/G8) -> 0.16748998 | N8: 28 | O8: 95 | P8: 74 | Q8: 17.32 | R8: =Q8*0.93 -> 16.1076 | S8: 18.05 | T8: =Q8*1.25 -> 21.65 | U8: =Q8*1.5 -> 25.98 | V8: =Q8*2 -> 34.64 | W8: =H8-(H8*0.07) -> 16.632605 | X8: 19 | Y8: =(X8-H8)/H8 -> 0.062371152 | Z8: =F8/F$19 -> 0.097334108 | AB8: 45328 | AC8: 91 | AD8: Bought after 11/08 b/o. Trading tightly here.
A9: DDOG | B9: Long | C9: Datadog | D9: 308.2955 | E9: 130.31 | F9: =E9*D9 -> 40173.987 | G9: 38082.35 | H9: =G9/D9 -> 123.52548 | I9: =F9-G9 -> 2091.6366 | J9: =E9-H9 -> 6.7845188 | K9: 45286 | L9: =DAYS360(K9,$C$1) -> 23 | M9: =(I9/G9) -> 0.054924042 | N9: 28 | O9: 96 | P9: 99 | Q9: 120.26 | R9: =Q9*0.93 -> 111.8418 | S9: 110.7 | T9: =Q9*1.25 -> 150.325 | U9: =Q9*1.5 -> 180.39 | V9: =Q9*2 -> 240.52 | W9: =H9-(H9*0.07) -> 114.8787 | X9: 116 | Y9: =(X9-H9)/H9 -> -0.060922501 | Z9: =F9/F$19 -> 0.084880405 | AB9: 45335 | AC9: 99 | AD9: Trading tightly since b/o.
A10: ACMR | B10: Long | C10: ACM Research | D10: 1339.9646 | E10: 20.46 | F10: =E10*D10 -> 27415.676 | G10: 28457.8 | H10: =G10/D10 -> 21.237725 | I10: =F10-G10 -> -1042.1243 | J10: =E10-H10 -> -0.77772524 | K10: 45302 | L10: =DAYS360(K10,$C$1) -> 8 | M10: =(I10/G10) -> -0.036619988 | N10: 23 | O10: 95 | P10: 99 | Q10: 20.43 | R10: =Q10*0.93 -> 18.9999 | S10: 16.66 | T10: =Q10*1.25 -> 25.5375 | U10: =Q10*1.5 -> 30.645 | V10: =Q10*2 -> 40.86 | W10: =H10-(H10*0.07) -> 19.751084 | X10: 19.75 | Y10: =(X10-H10)/H10 -> -0.070051063 | Z10: =F10/F$19 -> 0.05792439 | AB10: 45345 | AC10: 99 | AD10: B/o Jan 10in big vol.
A11: VKTX | B11: Long | C11: Viking Therap | D11: =1286.8297+948.5633 -> 2235.393 | E11: 21.77 | F11: =E11*D11 -> 48664.506 | G11: =28174.78+19947.6 -> 48122.38 | H11: =G11/D11 -> 21.527481 | I11: =F11-G11 -> 542.12561 | J11: =E11-H11 -> 0.24251915 | K11: 45309 | L11: =DAYS360(K11,$C$1) -> 1 | M11: =(I11/G11) -> 0.011265561 | N11: 4 | O11: 98 | P11: 22 | Q11: 20.03 | R11: =Q11*0.93 -> 18.6279 | S11: 20.28 | T11: =Q11*1.25 -> 25.0375 | U11: =Q11*1.5 -> 30.045 | V11: =Q11*2 -> 40.06 | W11: =H11-(H11*0.07) -> 20.020557 | X11: 19.75 | Y11: =(X11-H11)/H11 -> -0.082567991 | Z11: =F11/F$19 -> 0.10281934 | AB11: 45329 | AC11: 74 | AD11: Bought after pivot test.
F12: =E12*D12 -> 0 | H12: =G12/D12 -> #DIV/0! | I12: =F12-G12 -> 0 | J12: =E12-H12 -> #DIV/0! | L12: =DAYS360(K12,$C$1) -> 44659 | M12: =(I12/G12) -> #DIV/0! | R12: =Q12*0.93 -> 0 | T12: =Q12*1.25 -> 0 | U12: =Q12*1.5 -> 0 | V12: =Q12*2 -> 0 | W12: =H12-(H12*0.07) -> #DIV/0! | Y12: =(X12-H12)/H12 -> #DIV/0! | Z12: =F12/F$19 -> 0
F13: =E13*D13 -> 0 | H13: =G13/D13 -> #DIV/0! | I13: =F13-G13 -> 0 | J13: =E13-H13 -> #DIV/0! | L13: =DAYS360(K13,$C$1) -> 44659 | M13: =(I13/G13) -> #DIV/0! | R13: =Q13*0.93 -> 0 | T13: =Q13*1.25 -> 0 | U13: =Q13*1.5 -> 0 | V13: =Q13*2 -> 0 | W13: =H13-(H13*0.07) -> #DIV/0! | Y13: =(X13-H13)/H13 -> #DIV/0! | Z13: =F13/F$19 -> 0
A14: BIL | B14: Long | C14: Tbill ETF | D14: =2223.78-868.0181 -> 1355.7619 | E14: 91.66 | F14: =E14*D14 -> 124269.14 | G14: =203698.25-79510.46 -> 124187.79 | H14: =G14/D14 -> 91.6 | I14: =F14-G14 -> 81.345754 | J14: =E14-H14 -> 0.06000003 | M14: =(I14/G14) -> 0.00065502216 | R14: =Q14*0.93 -> 0 | T14: =Q14*1.25 -> 0 | U14: =Q14*1.5 -> 0 | V14: =Q14*2 -> 0 | W14: =H14-(H14*0.07) -> 85.188 | Y14: =(X14-H14)/H14 -> -1 | Z14: =F14/F$19 -> 0.26255832
F15: =E15*D15 -> 0 | H15: =G15/D15 -> #DIV/0! | I15: =F15-G15 -> 0 | J15: =E15-H15 -> #DIV/0! | M15: =(I15/G15) -> #DIV/0! | R15: =Q15*0.93 -> 0 | T15: =Q15*1.25 -> 0 | U15: =Q15*1.5 -> 0 | V15: =Q15*2 -> 0 | W15: =H15-(H15*0.07) -> #DIV/0! | Y15: =(X15-H15)/H15 -> #DIV/0! | Z15: =F15/F$19 -> 0
F16: =E16*D16 -> 0 | H16: =G16/D16 -> #DIV/0! | I16: =F16-G16 -> 0 | J16: =E16-H16 -> #DIV/0! | L16: =DAYS360(K16,$C$1) -> 44659 | M16: =(I16/G16) -> #DIV/0! | R16: =Q16*0.93 -> 0 | T16: =Q16*1.25 -> 0 | U16: =Q16*1.5 -> 0 | V16: =Q16*2 -> 0 | W16: =H16-(H16*0.07) -> #DIV/0! | Y16: =(X16-H16)/H16 -> #DIV/0! | Z16: =F16/F$19 -> 0
A17: Sub-Total | F17: =SUM(F6:F16) -> 355371.07 | G17: =SUM(G6:G16) -> 339475.86 | I17: =SUM(I6:I16) -> 15895.211
D18: Cash, other | F18: 117930 | G18: =F18/F19 -> 0.24916487
D19: Total | F19: =SUM(F17:F18) -> 473301.07
H20: Last week's close | I20: ='01-12-24'!F19 -> 475392.09 | K20: 45291 | L20: 476160.6
A21: * | H21: Week's change | I21: =(F19-I20)/I20 -> -0.004398516 | K21: chg % | L21: =(F19-L20)/L20 -> -0.0060053882
M23: days
A24: 2024 Closed Trades - Managed Acct | D24: Qty | E24: Cost/sh | F24: $ cost | G24: $Proc | H24: Proc/sh | I24: Profit/loss | J24: % | K24: Date purch | L24: Date sold | M24: held | P24: Comments
A25: YELP | B25: Long | C25: Yelp Inc | D25: 808.573 | E25: =F25/D25 -> 47.428062 | F25: 38349.05 | G25: 35186.18 | H25: =G25/D25 -> 43.516392 | I25: =G25-F25 -> -3162.87 | J25: =I25/F25 -> -0.082475837 | K25: 45286 | L25: 45302 | M25: =DAYS360(K25,L25) -> 15 | O25: Closed below stop for 2 days.
A26: TS | B26: Long | C26: Tenaris | D26: 1166.935 | E26: =F26/D26 -> 35.085005 | F26: 40941.92 | G26: 36634.59 | H26: =G26/D26 -> 31.393857 | I26: =G26-F26 -> -4307.33 | J26: =I26/F26 -> -0.10520586 | K26: 45233 | L26: 45307 | M26: =DAYS360(K26,L26) -> 73
B27: Long | C27: Minoso | D27: =1211.7123+804.6763 -> 2016.3886 | E27: =F27/D27 -> 20.49104 | F27: 41317.9 | G27: 42071.53 | H27: =G27/D27 -> 20.864793 | I27: =G27-F27 -> 753.63 | J27: =I27/F27 -> 0.018239794 | K27: 45135 | L27: 45308 | M27: =DAYS360(K27,L27) -> 169 | O27: Totally blew this trade. Had a nearly 50% profit.
I39: =SUM(I26:I38) -> -3553.7 | J39: Avg
H40: # of losses
H41: # of wins

Sheet 01-26-24
C1: 45317
C3: MANAGED ACCT | X3: Current | AC3: IBD
H4: Cost | J4: P/L | N4: Group | P4: EPS | R4: pivot | S4: last | W4: cost | X4: Stop | Y4: Stop | Z4: % | AB4: EPS | AC4: Comp
A5: Symbol | B5: Position | C5: Name | D5: Qty | E5: Current | F5: Value | G5: Cost | H5: per share | I5: P/L $ | J5: per sh | K5: Date purch | L5: days held | M5: % incr | N5: Rank | O5: RS | P5: RS | Q5: pivot | R5: -0.07 | S5: low | T5: 0.25 | U5: 0.5 | V5: 1 | W5: -0.07 | X5: Loss | Y5: Loss% | Z5: of port | AB5: Due | AC5: Rank
A7: AXON | B7: Long | C7: Axon Enterprise | D7: 267.8431 | E7: 251.36 | F7: =E7*D7 -> 67325.042 | G7: 61166.24 | H7: =G7/D7 -> 228.36594 | I7: =F7-G7 -> 6158.8016 | J7: =E7-H7 -> 22.994065 | K7: 45238 | L7: =DAYS360(K7,$C$1) -> 78 | M7: =(I7/G7) -> 0.10068956 | N7: 27 | O7: 87 | P7: 99 | Q7: 223.3 | R7: =Q7*0.93 -> 207.669 | S7: 241.72 | T7: =Q7*1.25 -> 279.125 | U7: =Q7*1.5 -> 334.95 | V7: =Q7*2 -> 446.6 | W7: =H7-(H7*0.07) -> 212.38032 | X7: 234 | Y7: =(X7-H7)/H7 -> 0.024671214 | Z7: =F7/F$19 -> 0.144941 | AB7: 45349 | AC7: 99 | AD7: Bought as it gapped out of base on EPS.
A8: KD | B8: Long | C8: Kyndryl Hldgs | D8: =1160.2602+1046.0778 -> 2206.338 | E8: 21.21 | F8: =E8*D8 -> 46796.429 | G8: =20288.83+19170.47 -> 39459.3 | H8: =G8/D8 -> 17.884522 | I8: =F8-G8 -> 7337.129 | J8: =E8-H8 -> 3.3254782 | K8: 45243 | L8: =DAYS360(K8,$C$1) -> 73 | M8: =(I8/G8) -> 0.18594169 | N8: 26 | O8: 95 | P8: 74 | Q8: 17.32 | R8: =Q8*0.93 -> 16.1076 | S8: 18.05 | T8: =Q8*1.25 -> 21.65 | U8: =Q8*1.5 -> 25.98 | V8: =Q8*2 -> 34.64 | W8: =H8-(H8*0.07) -> 16.632605 | X8: 19 | Y8: =(X8-H8)/H8 -> 0.062371152 | Z8: =F8/F$19 -> 0.10074589 | AB8: 45328 | AC8: 90 | AD8: Bought after 11/08 b/o. Trading tightly here.
A9: DDOG | B9: Long | C9: Datadog | D9: =308.2955+142.5312 -> 450.8267 | E9: 123.95 | F9: =E9*D9 -> 55879.969 | G9: =38082.35+18004.55 -> 56086.9 | H9: =G9/D9 -> 124.409 | I9: =F9-G9 -> -206.93053 | J9: =E9-H9 -> -0.45900239 | K9: 45286 | L9: =DAYS360(K9,$C$1) -> 30 | M9: =(I9/G9) -> -0.0036894629 | N9: 26 | O9: 94 | P9: 99 | Q9: 120.26 | R9: =Q9*0.93 -> 111.8418 | S9: 110.7 | T9: =Q9*1.25 -> 150.325 | U9: =Q9*1.5 -> 180.39 | V9: =Q9*2 -> 240.52 | W9: =H9-(H9*0.07) -> 115.70037 | X9: 116 | Y9: =(X9-H9)/H9 -> -0.067591591 | Z9: =F9/F$19 -> 0.12030143 | AB9: 45335 | AC9: 99 | AD9: Trading tightly since b/o.
A10: ACMR | B10: Long | C10: ACM Research | D10: =1339.9646+918.07 -> 2258.0346 | E10: 18.98 | F10: =E10*D10 -> 42857.497 | G10: =28457.8+19398.39 -> 47856.19 | H10: =G10/D10 -> 21.193736 | I10: =F10-G10 -> -4998.6933 | J10: =E10-H10 -> -2.2137364 | K10: 45302 | L10: =DAYS360(K10,$C$1) -> 15 | M10: =(I10/G10) -> -0.10445239 | N10: 23 | O10: 95 | P10: 99 | Q10: 20.43 | R10: =Q10*0.93 -> 18.9999 | S10: 16.66 | T10: =Q10*1.25 -> 25.5375 | U10: =Q10*1.5 -> 30.645 | V10: =Q10*2 -> 40.86 | W10: =H10-(H10*0.07) -> 19.710175 | X10: 19.75 | Y10: =(X10-H10)/H10 -> -0.068120898 | Z10: =F10/F$19 -> 0.092265941 | AB10: 45345 | AC10: 99 | AD10: B/o Jan 10in big vol.
A11: VKTX | B11: Long | C11: Viking Therap | D11: =1286.8297+948.5633 -> 2235.393 | E11: 21.37 | F11: =E11*D11 -> 47770.348 | G11: =28174.78+19947.6 -> 48122.38 | H11: =G11/D11 -> 21.527481 | I11: =F11-G11 -> -352.03159 | J11: =E11-H11 -> -0.15748085 | K11: 45309 | L11: =DAYS360(K11,$C$1) -> 8 | M11: =(I11/G11) -> -0.0073153404 | N11: 3 | O11: 98 | P11: 23 | Q11: 20.03 | R11: =Q11*0.93 -> 18.6279 | S11: 20.28 | T11: =Q11*1.25 -> 25.0375 | U11: =Q11*1.5 -> 30.045 | V11: =Q11*2 -> 40.06 | W11: =H11-(H11*0.07) -> 20.020557 | X11: 19.75 | Y11: =(X11-H11)/H11 -> -0.082567991 | Z11: =F11/F$19 -> 0.10284259 | AB11: 45329 | AC11: 74 | AD11: Bought after pivot test.
A12: AAON | B12: Long | C12: AAON | D12: 532.4164 | E12: 69.94 | F12: =E12*D12 -> 37237.203 | G12: 38270.34 | H12: =G12/D12 -> 71.880468 | I12: =F12-G12 -> -1033.137 | J12: =E12-H12 -> -1.940468 | K12: 45313 | L12: =DAYS360(K12,$C$1) -> 4 | M12: =(I12/G12) -> -0.026995762 | N12: 42 | O12: 84 | P12: 98 | Q12: 71.39 | R12: =Q12*0.93 -> 66.3927 | S12: 70.32 | T12: =Q12*1.25 -> 89.2375 | U12: =Q12*1.5 -> 107.085 | V12: =Q12*2 -> 142.78 | W12: =H12-(H12*0.07) -> 66.848835 | X12: 67.5 | Y12: =(X12-H12)/H12 -> -0.060941005 | Z12: =F12/F$19 -> 0.080166268 | AB12: 45351 | AC12: 99 | AD12: Bought after pivot test.
F13: =E13*D13 -> 0 | H13: =G13/D13 -> #DIV/0! | I13: =F13-G13 -> 0 | J13: =E13-H13 -> #DIV/0! | L13: =DAYS360(K13,$C$1) -> 44666 | M13: =(I13/G13) -> #DIV/0! | R13: =Q13*0.93 -> 0 | T13: =Q13*1.25 -> 0 | U13: =Q13*1.5 -> 0 | V13: =Q13*2 -> 0 | W13: =H13-(H13*0.07) -> #DIV/0! | Y13: =(X13-H13)/H13 -> #DIV/0! | Z13: =F13/F$19 -> 0
A14: BIL | B14: Long | C14: Tbill ETF | D14: =2223.78-868.0181 -> 1355.7619 | E14: 91.75 | F14: =E14*D14 -> 124391.15 | G14: =203698.25-79510.46 -> 124187.79 | H14: =G14/D14 -> 91.6 | I14: =F14-G14 -> 203.36433 | J14: =E14-H14 -> 0.15000003 | M14: =(I14/G14) -> 0.0016375549 | R14: =Q14*0.93 -> 0 | T14: =Q14*1.25 -> 0 | U14: =Q14*1.5 -> 0 | V14: =Q14*2 -> 0 | W14: =H14-(H14*0.07) -> 85.188 | Y14: =(X14-H14)/H14 -> -1 | Z14: =F14/F$19 -> 0.26779602
F15: =E15*D15 -> 0 | H15: =G15/D15 -> #DIV/0! | I15: =F15-G15 -> 0 | J15: =E15-H15 -> #DIV/0! | M15: =(I15/G15) -> #DIV/0! | R15: =Q15*0.93 -> 0 | T15: =Q15*1.25 -> 0 | U15: =Q15*1.5 -> 0 | V15: =Q15*2 -> 0 | W15: =H15-(H15*0.07) -> #DIV/0! | Y15: =(X15-H15)/H15 -> #DIV/0! | Z15: =F15/F$19 -> 0
F16: =E16*D16 -> 0 | H16: =G16/D16 -> #DIV/0! | I16: =F16-G16 -> 0 | J16: =E16-H16 -> #DIV/0! | L16: =DAYS360(K16,$C$1) -> 44666 | M16: =(I16/G16) -> #DIV/0! | R16: =Q16*0.93 -> 0 | T16: =Q16*1.25 -> 0 | U16: =Q16*1.5 -> 0 | V16: =Q16*2 -> 0 | W16: =H16-(H16*0.07) -> #DIV/0! | Y16: =(X16-H16)/H16 -> #DIV/0! | Z16: =F16/F$19 -> 0
A17: Sub-Total | F17: =SUM(F6:F16) -> 422257.64 | G17: =SUM(G6:G16) -> 415149.14 | I17: =SUM(I6:I16) -> 7108.5025
D18: Cash, other | F18: 42242 | G18: =F18/F19 -> 0.090940867
D19: Total | F19: =SUM(F17:F18) -> 464499.64
H20: Last week's close | I20: ='01-19-24'!F19 -> 473301.07 | K20: 45291 | L20: 476160.6
A21: * | H21: Week's change | I21: =(F19-I20)/I20 -> -0.018595834 | K21: chg % | L21: =(F19-L20)/L20 -> -0.024489547
M23: days
A24: 2024 Closed Trades - Managed Acct | D24: Qty | E24: Cost/sh | F24: $ cost | G24: $Proc | H24: Proc/sh | I24: Profit/loss | J24: % | K24: Date purch | L24: Date sold | M24: held | P24: Comments
A25: YELP | B25: Long | C25: Yelp Inc | D25: 808.573 | E25: =F25/D25 -> 47.428062 | F25: 38349.05 | G25: 35186.18 | H25: =G25/D25 -> 43.516392 | I25: =G25-F25 -> -3162.87 | J25: =I25/F25 -> -0.082475837 | K25: 45286 | L25: 45302 | M25: =DAYS360(K25,L25) -> 15 | O25: Closed below stop for 2 days.
A26: TS | B26: Long | C26: Tenaris | D26: 1166.935 | E26: =F26/D26 -> 35.085005 | F26: 40941.92 | G26: 36634.59 | H26: =G26/D26 -> 31.393857 | I26: =G26-F26 -> -4307.33 | J26: =I26/F26 -> -0.10520586 | K26: 45233 | L26: 45307 | M26: =DAYS360(K26,L26) -> 73
B27: Long | C27: Minoso | D27: =1211.7123+804.6763 -> 2016.3886 | E27: =F27/D27 -> 20.49104 | F27: 41317.9 | G27: 42071.53 | H27: =G27/D27 -> 20.864793 | I27: =G27-F27 -> 753.63 | J27: =I27/F27 -> 0.018239794 | K27: 45135 | L27: 45308 | M27: =DAYS360(K27,L27) -> 169 | O27: Totally blew this trade. Had a nearly 50% profit.
I39: =SUM(I26:I38) -> -3553.7 | J39: Avg
H40: # of losses
H41: # of wins

Sheet 02-02-24
C1: 45324
C3: MANAGED ACCT | X3: Current | AC3: IBD
H4: Cost | J4: P/L | N4: Group | P4: EPS | R4: pivot | S4: last | W4: cost | X4: Stop | Y4: Stop | Z4: % | AB4: EPS | AC4: Comp
A5: Symbol | B5: Position | C5: Name | D5: Qty | E5: Current | F5: Value | G5: Cost | H5: per share | I5: P/L $ | J5: per sh | K5: Date purch | L5: days held | M5: % incr | N5: Rank | O5: RS | P5: RS | Q5: pivot | R5: -0.07 | S5: low | T5: 0.25 | U5: 0.5 | V5: 1 | W5: -0.07 | X5: Loss | Y5: Loss% | Z5: of port | AB5: Due | AC5: Rank
A7: AXON | B7: Long | C7: Axon Enterprise | D7: 267.8431 | E7: 256.99 | F7: =E7*D7 -> 68832.998 | G7: 61166.24 | H7: =G7/D7 -> 228.36594 | I7: =F7-G7 -> 7666.7583 | J7: =E7-H7 -> 28.624065 | K7: 45238 | L7: =DAYS360(K7,$C$1) -> 84 | M7: =(I7/G7) -> 0.12534297 | N7: 23 | O7: 87 | P7: 99 | Q7: 223.3 | R7: =Q7*0.93 -> 207.669 | S7: 241.72 | T7: =Q7*1.25 -> 279.125 | U7: =Q7*1.5 -> 334.95 | V7: =Q7*2 -> 446.6 | W7: =H7-(H7*0.07) -> 212.38032 | X7: 239 | Y7: =(X7-H7)/H7 -> 0.046565898 | Z7: =F7/F$19 -> 0.14537012 | AB7: 45349 | AC7: 99 | AD7: Bought as it gapped out of base on EPS.
A8: KD | B8: Long | C8: Kyndryl Hldgs | D8: =1160.2602+1046.0778 -> 2206.338 | E8: 20.9 | F8: =E8*D8 -> 46112.464 | G8: =20288.83+19170.47 -> 39459.3 | H8: =G8/D8 -> 17.884522 | I8: =F8-G8 -> 6653.1642 | J8: =E8-H8 -> 3.0154782 | K8: 45243 | L8: =DAYS360(K8,$C$1) -> 79 | M8: =(I8/G8) -> 0.16860827 | N8: 16 | O8: 95 | P8: 74 | Q8: 17.32 | R8: =Q8*0.93 -> 16.1076 | S8: 18.05 | T8: =Q8*1.25 -> 21.65 | U8: =Q8*1.5 -> 25.98 | V8: =Q8*2 -> 34.64 | W8: =H8-(H8*0.07) -> 16.632605 | X8: 19 | Y8: =(X8-H8)/H8 -> 0.062371152 | Z8: =F8/F$19 -> 0.097386063 | AB8: 45328 | AC8: 90 | AD8: Bought after 11/08 b/o. Trading tightly here.
A9: DDOG | B9: Long | C9: Datadog | D9: =308.2955+142.5312 -> 450.8267 | E9: 134.31 | F9: =E9*D9 -> 60550.534 | G9: =38082.35+18004.55 -> 56086.9 | H9: =G9/D9 -> 124.409 | I9: =F9-G9 -> 4463.6341 | J9: =E9-H9 -> 9.9009976 | K9: 45286 | L9: =DAYS360(K9,$C$1) -> 36 | M9: =(I9/G9) -> 0.079584254 | N9: 16 | O9: 95 | P9: 99 | Q9: 120.26 | R9: =Q9*0.93 -> 111.8418 | S9: 119.34 | T9: =Q9*1.25 -> 150.325 | U9: =Q9*1.5 -> 180.39 | V9: =Q9*2 -> 240.52 | W9: =H9-(H9*0.07) -> 115.70037 | X9: 119 | Y9: =(X9-H9)/H9 -> -0.04347758 | Z9: =F9/F$19 -> 0.12787818 | AB9: 45335 | AC9: 99 | AD9: Trading tightly since b/o.
A10: VKTX | B10: Long | C10: Viking Therap | D10: =1286.8297+948.5633 -> 2235.393 | E10: 23.45 | F10: =E10*D10 -> 52419.966 | G10: =28174.78+19947.6 -> 48122.38 | H10: =G10/D10 -> 21.527481 | I10: =F10-G10 -> 4297.5859 | J10: =E10-H10 -> 1.9225191 | K10: 45309 | L10: =DAYS360(K10,$C$1) -> 14 | M10: =(I10/G10) -> 0.089305347 | N10: 2 | O10: 98 | P10: 23 | Q10: 20.03 | R10: =Q10*0.93 -> 18.6279 | S10: 20.92 | T10: =Q10*1.25 -> 25.0375 | U10: =Q10*1.5 -> 30.045 | V10: =Q10*2 -> 40.06 | W10: =H10-(H10*0.07) -> 20.020557 | X10: 19.75 | Y10: =(X10-H10)/H10 -> -0.082567991 | Z10: =F10/F$19 -> 0.11070703 | AB10: 45329 | AC10: 79 | AD10: Bought after pivot test.
A11: AAON | B11: Long | C11: AAON | D11: =532.4164+77.1815 -> 609.5979 | E11: 73.32 | F11: =E11*D11 -> 44695.718 | G11: =38270.34+5640.4 -> 43910.74 | H11: =G11/D11 -> 72.032302 | I11: =F11-G11 -> 784.97803 | J11: =E11-H11 -> 1.2876981 | K11: 45313 | L11: =DAYS360(K11,$C$1) -> 10 | M11: =(I11/G11) -> 0.017876675 | N11: 36 | O11: 84 | P11: 98 | Q11: 71.39 | R11: =Q11*0.93 -> 66.3927 | S11: 68.38 | T11: =Q11*1.25 -> 89.2375 | U11: =Q11*1.5 -> 107.085 | V11: =Q11*2 -> 142.78 | W11: =H11-(H11*0.07) -> 66.990041 | X11: 67.5 | Y11: =(X11-H11)/H11 -> -0.06292041 | Z11: =F11/F$19 -> 0.094394001 | AB11: 45351 | AC11: 99 | AD11: Bought after pivot test.
A12: BLBD | B12: Long | C12: Bluebird | D12: 952.002 | E12: 30.91 | F12: =E12*D12 -> 29426.382 | G12: 28303.96 | H12: =G12/D12 -> 29.730988 | I12: =F12-G12 -> 1122.4218 | J12: =E12-H12 -> 1.179012 | K12: 45321 | L12: =DAYS360(K12,$C$1) -> 2 | M12: =(I12/G12) -> 0.039655999 | N12: 57 | O12: 97 | P12: 81 | Q12: 28.39 | R12: =Q12*0.93 -> 26.4027 | S12: 24.09 | T12: =Q12*1.25 -> 35.4875 | U12: =Q12*1.5 -> 42.585 | V12: =Q12*2 -> 56.78 | W12: =H12-(H12*0.07) -> 27.649819 | X12: 27.5 | Y12: =(X12-H12)/H12 -> -0.075039146 | Z12: =F12/F$19 -> 0.062146309 | AB12: 45329 | AC12: 99 | AD12: Bought day 2 after b/o.
F13: =E13*D13 -> 0 | H13: =G13/D13 -> #DIV/0! | I13: =F13-G13 -> 0 | J13: =E13-H13 -> #DIV/0! | L13: =DAYS360(K13,$C$1) -> 44672 | M13: =(I13/G13) -> #DIV/0! | R13: =Q13*0.93 -> 0 | T13: =Q13*1.25 -> 0 | U13: =Q13*1.5 -> 0 | V13: =Q13*2 -> 0 | W13: =H13-(H13*0.07) -> #DIV/0! | Y13: =(X13-H13)/H13 -> #DIV/0! | Z13: =F13/F$19 -> 0
A14: BIL | B14: Long | C14: Tbill ETF | D14: 1236.0085 | E14: 91.44 | F14: =E14*D14 -> 113020.62 | G14: 113020.62 | H14: =G14/D14 -> 91.440002 | I14: =F14-G14 -> -0.00276 | J14: =E14-H14 -> -2.2329944e-06 | M14: =(I14/G14) -> -2.4420323e-08 | R14: =Q14*0.93 -> 0 | T14: =Q14*1.25 -> 0 | U14: =Q14*1.5 -> 0 | V14: =Q14*2 -> 0 | W14: =H14-(H14*0.07) -> 85.039202 | Y14: =(X14-H14)/H14 -> -1 | Z14: =F14/F$19 -> 0.23869106
F15: =E15*D15 -> 0 | H15: =G15/D15 -> #DIV/0! | I15: =F15-G15 -> 0 | J15: =E15-H15 -> #DIV/0! | M15: =(I15/G15) -> #DIV/0! | R15: =Q15*0.93 -> 0 | T15: =Q15*1.25 -> 0 | U15: =Q15*1.5 -> 0 | V15: =Q15*2 -> 0 | W15: =H15-(H15*0.07) -> #DIV/0! | Y15: =(X15-H15)/H15 -> #DIV/0! | Z15: =F15/F$19 -> 0
F16: =E16*D16 -> 0 | H16: =G16/D16 -> #DIV/0! | I16: =F16-G16 -> 0 | J16: =E16-H16 -> #DIV/0! | L16: =DAYS360(K16,$C$1) -> 44672 | M16: =(I16/G16) -> #DIV/0! | R16: =Q16*0.93 -> 0 | T16: =Q16*1.25 -> 0 | U16: =Q16*1.5 -> 0 | V16: =Q16*2 -> 0 | W16: =H16-(H16*0.07) -> #DIV/0! | Y16: =(X16-H16)/H16 -> #DIV/0! | Z16: =F16/F$19 -> 0
A17: Sub-Total | F17: =SUM(F6:F16) -> 415058.68 | G17: =SUM(G6:G16) -> 390070.14 | I17: =SUM(I6:I16) -> 24988.539
D18: Cash, other | F18: 58443 | G18: =F18/F19 -> 0.12342723
D19: Total | F19: =SUM(F17:F18) -> 473501.68
H20: Last week's close | I20: ='01-26-24'!F19 -> 464499.64 | K20: 45291 | L20: 476160.6
A21: * | H21: Week's change | I21: =(F19-I20)/I20 -> 0.019380073 | K21: chg % | L21: =(F19-L20)/L20 -> -0.0055840834
M23: days
A24: 2024 Closed Trades - Managed Acct | D24: Qty | E24: Cost/sh | F24: $ cost | G24: $Proc | H24: Proc/sh | I24: Profit/loss | J24: % | K24: Date purch | L24: Date sold | M24: held | P24: Comments
A25: YELP | B25: Long | C25: Yelp Inc | D25: 808.573 | E25: =F25/D25 -> 47.428062 | F25: 38349.05 | G25: 35186.18 | H25: =G25/D25 -> 43.516392 | I25: =G25-F25 -> -3162.87 | J25: =I25/F25 -> -0.082475837 | K25: 45286 | L25: 45302 | M25: =DAYS360(K25,L25) -> 15 | O25: Closed below stop for 2 days.
A26: TS | B26: Long | C26: Tenaris | D26: 1166.935 | E26: =F26/D26 -> 35.085005 | F26: 40941.92 | G26: 36634.59 | H26: =G26/D26 -> 31.393857 | I26: =G26-F26 -> -4307.33 | J26: =I26/F26 -> -0.10520586 | K26: 45233 | L26: 45307 | M26: =DAYS360(K26,L26) -> 73
A27: MNSO | B27: Long | C27: Minoso | D27: =1211.7123+804.6763 -> 2016.3886 | E27: =F27/D27 -> 20.49104 | F27: 41317.9 | G27: 42071.53 | H27: =G27/D27 -> 20.864793 | I27: =G27-F27 -> 753.63 | J27: =I27/F27 -> 0.018239794 | K27: 45135 | L27: 45308 | M27: =DAYS360(K27,L27) -> 169 | O27: Totally blew this trade. Had a nearly 50% profit.
A28: ACMR | B28: Long | C28: ACM Research | D28: =1339.9646+918.07 -> 2258.0346 | E28: =F28/D28 -> 21.193736 | F28: =28457.8+19398.39 -> 47856.19 | G28: 39178.27 | H28: =G28/D28 -> 17.350607 | I28: =G28-F28 -> -8677.92 | J28: =I28/F28 -> -0.18133328 | K28: 45302 | L28: 45322 | M28: =DAYS360(K28,L28) -> 20
I39: =SUM(I26:I38) -> -12231.62 | J39: Avg
H40: # of losses
H41: # of wins

Sheet 02-09-24
C1: 45331
C3: MANAGED ACCT | X3: Current | AC3: IBD
H4: Cost | J4: P/L | N4: Group | P4: EPS | R4: pivot | S4: last | W4: cost | X4: Stop | Y4: Stop | Z4: % | AB4: EPS | AC4: Comp
A5: Symbol | B5: Position | C5: Name | D5: Qty | E5: Current | F5: Value | G5: Cost | H5: per share | I5: P/L $ | J5: per sh | K5: Date purch | L5: days held | M5: % incr | N5: Rank | O5: RS | P5: RS | Q5: pivot | R5: -0.07 | S5: low | T5: 0.25 | U5: 0.5 | V5: 1 | W5: -0.07 | X5: Loss | Y5: Loss% | Z5: of port | AB5: Due | AC5: Rank
A7: AXON | B7: Long | C7: Axon Enterprise | D7: 267.8431 | E7: 270.98 | F7: =E7*D7 -> 72580.123 | G7: 61166.24 | H7: =G7/D7 -> 228.36594 | I7: =F7-G7 -> 11413.883 | J7: =E7-H7 -> 42.614065 | K7: 45238 | L7: =DAYS360(K7,$C$1) -> 91 | M7: =(I7/G7) -> 0.1866043 | N7: 39 | O7: 90 | P7: 99 | Q7: 223.3 | R7: =Q7*0.93 -> 207.669 | S7: 241.72 | T7: =Q7*1.25 -> 279.125 | U7: =Q7*1.5 -> 334.95 | V7: =Q7*2 -> 446.6 | W7: =H7-(H7*0.07) -> 212.38032 | X7: 239 | Y7: =(X7-H7)/H7 -> 0.046565898 | Z7: =F7/F$19 -> 0.14273203 | AB7: 45349 | AC7: 99 | AD7: Bought as it gapped out of base on EPS.
A8: KD | B8: Long | C8: Kyndryl Hldgs | D8: =1160.2602+1046.0778 -> 2206.338 | E8: 21.96 | F8: =E8*D8 -> 48451.182 | G8: =20288.83+19170.47 -> 39459.3 | H8: =G8/D8 -> 17.884522 | I8: =F8-G8 -> 8991.8825 | J8: =E8-H8 -> 4.0754782 | K8: 45243 | L8: =DAYS360(K8,$C$1) -> 86 | M8: =(I8/G8) -> 0.22787739 | N8: 14 | O8: 91 | P8: 22 | Q8: 17.32 | R8: =Q8*0.93 -> 16.1076 | S8: 20.03 | T8: =Q8*1.25 -> 21.65 | U8: =Q8*1.5 -> 25.98 | V8: =Q8*2 -> 34.64 | W8: =H8-(H8*0.07) -> 16.632605 | X8: 19.75 | Y8: =(X8-H8)/H8 -> 0.10430686 | Z8: =F8/F$19 -> 0.095281398 | AB8: 45427 | AC8: 90 | AD8: Bought after 11/08 b/o. Trading tightly here.
A9: DDOG | B9: Long | C9: Datadog | D9: =308.2955+142.5312 -> 450.8267 | E9: 134.91 | F9: =E9*D9 -> 60821.03 | G9: =38082.35+18004.55 -> 56086.9 | H9: =G9/D9 -> 124.409 | I9: =F9-G9 -> 4734.1301 | J9: =E9-H9 -> 10.500998 | K9: 45286 | L9: =DAYS360(K9,$C$1) -> 43 | M9: =(I9/G9) -> 0.084407056 | N9: 14 | O9: 93 | P9: 99 | Q9: 120.26 | R9: =Q9*0.93 -> 111.8418 | S9: 119.34 | T9: =Q9*1.25 -> 150.325 | U9: =Q9*1.5 -> 180.39 | V9: =Q9*2 -> 240.52 | W9: =H9-(H9*0.07) -> 115.70037 | X9: 119 | Y9: =(X9-H9)/H9 -> -0.04347758 | Z9: =F9/F$19 -> 0.11960725 | AB9: 45335 | AC9: 99 | AD9: Trading tightly since b/o.
A10: VKTX | B10: Long | C10: Viking Therap | D10: =1286.8297+948.5633 -> 2235.393 | E10: 30.86 | F10: =E10*D10 -> 68984.228 | G10: =28174.78+19947.6 -> 48122.38 | H10: =G10/D10 -> 21.527481 | I10: =F10-G10 -> 20861.848 | J10: =E10-H10 -> 9.3325191 | K10: 45309 | L10: =DAYS360(K10,$C$1) -> 21 | M10: =(I10/G10) -> 0.43351655 | N10: 2 | O10: 99 | P10: 22 | Q10: 20.03 | R10: =Q10*0.93 -> 18.6279 | S10: 22.51 | T10: =Q10*1.25 -> 25.0375 | U10: =Q10*1.5 -> 30.045 | V10: =Q10*2 -> 40.06 | W10: =H10-(H10*0.07) -> 20.020557 | X10: 22 | Y10: =(X10-H10)/H10 -> 0.021949579 | Z10: =F10/F$19 -> 0.13566054 | AB10: 45406 | AC10: 82 | AD10: Bought after pivot test.
A11: AAON | B11: Long | C11: AAON | D11: =532.4164+77.1815 -> 609.5979 | E11: 81.4 | F11: =E11*D11 -> 49621.269 | G11: =38270.34+5640.4 -> 43910.74 | H11: =G11/D11 -> 72.032302 | I11: =F11-G11 -> 5710.5291 | J11: =E11-H11 -> 9.3676981 | K11: 45313 | L11: =DAYS360(K11,$C$1) -> 17 | M11: =(I11/G11) -> 0.13004857 | N11: 41 | O11: 91 | P11: 98 | Q11: 71.39 | R11: =Q11*0.93 -> 66.3927 | S11: 68.38 | T11: =Q11*1.25 -> 89.2375 | U11: =Q11*1.5 -> 107.085 | V11: =Q11*2 -> 142.78 | W11: =H11-(H11*0.07) -> 66.990041 | X11: 67.5 | Y11: =(X11-H11)/H11 -> -0.06292041 | Z11: =F11/F$19 -> 0.097582425 | AB11: 45351 | AC11: 99 | AD11: Bought after pivot test.
A12: BLBD | B12: Long | C12: Bluebird | D12: 952.002 | E12: 30.55 | F12: =E12*D12 -> 29083.661 | G12: 28303.96 | H12: =G12/D12 -> 29.730988 | I12: =F12-G12 -> 779.7011 | J12: =E12-H12 -> 0.81901204 | K12: 45321 | L12: =DAYS360(K12,$C$1) -> 9 | M12: =(I12/G12) -> 0.027547421 | N12: 45 | O12: 96 | P12: 81 | Q12: 28.39 | R12: =Q12*0.93 -> 26.4027 | S12: 24.09 | T12: =Q12*1.25 -> 35.4875 | U12: =Q12*1.5 -> 42.585 | V12: =Q12*2 -> 56.78 | W12: =H12-(H12*0.07) -> 27.649819 | X12: 27.5 | Y12: =(X12-H12)/H12 -> -0.075039146 | Z12: =F12/F$19 -> 0.057194309 | AB12: 45421 | AC12: 98 | AD12: Bought day 2 after b/o.
A13: MDB | B13: Long | C13: MongoDB | D13: 126.054 | E13: 500.9 | F13: =E13*D13 -> 63140.449 | G13: 56759.55 | H13: =G13/D13 -> 450.27964 | I13: =F13-G13 -> 6380.8986 | J13: =E13-H13 -> 50.620358 | K13: 45327 | L13: =DAYS360(K13,$C$1) -> 4 | M13: =(I13/G13) -> 0.11241982 | N13: 12 | O13: 95 | P13: 83 | Q13: 442.84 | R13: =Q13*0.93 -> 411.8412 | S13: 400.52 | T13: =Q13*1.25 -> 553.55 | U13: =Q13*1.5 -> 664.26 | V13: =Q13*2 -> 885.68 | W13: =H13-(H13*0.07) -> 418.76007 | X13: 419 | Y13: =(X13-H13)/H13 -> -0.069467147 | Z13: =F13/F$19 -> 0.12416849 | AB13: 45358 | AC13: 99 | AD13: Bought day 1 of b/o.
A14: IOT | B14: Long | C14: Samsara | D14: 846.327 | E14: 35.47 | F14: =E14*D14 -> 30019.219 | G14: 30020.93 | H14: =G14/D14 -> 35.472022 | I14: =F14-G14 -> -1.71131 | J14: =E14-H14 -> -0.0020220435 | K14: 45331 | L14: =DAYS360(K14,$C$1) -> 0 | M14: =(I14/G14) -> -5.7003897e-05 | N14: 14 | O14: 96 | P14: 81 | Q14: 32.41 | R14: =Q14*0.93 -> 30.1413 | S14: 29.8 | T14: =Q14*1.25 -> 40.5125 | U14: =Q14*1.5 -> 48.615 | V14: =Q14*2 -> 64.82 | W14: =H14-(H14*0.07) -> 32.988981 | X14: 32.75 | Y14: =(X14-H14)/H14 -> -0.076737155 | Z14: =F14/F$19 -> 0.059034124 | AB14: 45358 | AC14: 97 | AD14: Broke out of consolidation above pivot.
F15: =E15*D15 -> 0 | H15: =G15/D15 -> #DIV/0! | I15: =F15-G15 -> 0 | J15: =E15-H15 -> #DIV/0! | L15: =DAYS360(K15,$C$1) -> 44679 | M15: =(I15/G15) -> #DIV/0! | R15: =Q15*0.93 -> 0 | T15: =Q15*1.25 -> 0 | U15: =Q15*1.5 -> 0 | V15: =Q15*2 -> 0 | W15: =H15-(H15*0.07) -> #DIV/0! | Y15: =(X15-H15)/H15 -> #DIV/0! | Z15: =F15/F$19 -> 0
A16: BIL | B16: Long | C16: Tbill ETF | D16: 540.5774 | E16: 91.53 | F16: =E16*D16 -> 49479.049 | G16: 49473.64 | H16: =G16/D16 -> 91.519993 | I16: =F16-G16 -> 5.409422 | J16: =E16-H16 -> 0.010006748 | M16: =(I16/G16) -> 0.00010933948 | R16: =Q16*0.93 -> 0 | T16: =Q16*1.25 -> 0 | U16: =Q16*1.5 -> 0 | V16: =Q16*2 -> 0 | W16: =H16-(H16*0.07) -> 85.113594 | Y16: =(X16-H16)/H16 -> -1 | Z16: =F16/F$19 -> 0.097302744
A17: Sub-Total | F17: =SUM(F6:F16) -> 472180.21 | G17: =SUM(G6:G16) -> 413303.64 | I17: =SUM(I6:I16) -> 58876.571
D18: Cash, other | F18: 36326 | G18: =F18/F19 -> 0.071436689
D19: Total | F19: =SUM(F17:F18) -> 508506.21
H20: Last week's close | I20: ='02-02-24'!F19 -> 473501.68 | K20: 45291 | L20: 476160.6
A21: * | H21: Week's change | I21: =(F19-I20)/I20 -> 0.073926942 | K21: chg % | L21: =(F19-L20)/L20 -> 0.067930044
M23: days
A24: 2024 Closed Trades - Managed Acct | D24: Qty | E24: Cost/sh | F24: $ cost | G24: $Proc | H24: Proc/sh | I24: Profit/loss | J24: % | K24: Date purch | L24: Date sold | M24: held | P24: Comments
A25: YELP | B25: Long | C25: Yelp Inc | D25: 808.573 | E25: =F25/D25 -> 47.428062 | F25: 38349.05 | G25: 35186.18 | H25: =G25/D25 -> 43.516392 | I25: =G25-F25 -> -3162.87 | J25: =I25/F25 -> -0.082475837 | K25: 45286 | L25: 45302 | M25: =DAYS360(K25,L25) -> 15 | O25: Closed below stop for 2 days.
A26: TS | B26: Long | C26: Tenaris | D26: 1166.935 | E26: =F26/D26 -> 35.085005 | F26: 40941.92 | G26: 36634.59 | H26: =G26/D26 -> 31.393857 | I26: =G26-F26 -> -4307.33 | J26: =I26/F26 -> -0.10520586 | K26: 45233 | L26: 45307 | M26: =DAYS360(K26,L26) -> 73
A27: MNSO | B27: Long | C27: Minoso | D27: =1211.7123+804.6763 -> 2016.3886 | E27: =F27/D27 -> 20.49104 | F27: 41317.9 | G27: 42071.53 | H27: =G27/D27 -> 20.864793 | I27: =G27-F27 -> 753.63 | J27: =I27/F27 -> 0.018239794 | K27: 45135 | L27: 45308 | M27: =DAYS360(K27,L27) -> 169 | O27: Totally blew this trade. Had a nearly 50% profit.
A28: ACMR | B28: Long | C28: ACM Research | D28: =1339.9646+918.07 -> 2258.0346 | E28: =F28/D28 -> 21.193736 | F28: =28457.8+19398.39 -> 47856.19 | G28: 39178.27 | H28: =G28/D28 -> 17.350607 | I28: =G28-F28 -> -8677.92 | J28: =I28/F28 -> -0.18133328 | K28: 45302 | L28: 45322 | M28: =DAYS360(K28,L28) -> 20
I39: =SUM(I26:I38) -> -12231.62 | J39: Avg
H40: # of losses
H41: # of wins

Sheet 02-16-24
C1: 45338
C3: MANAGED ACCT | X3: Current | AC3: IBD
H4: Cost | J4: P/L | N4: Group | P4: EPS | R4: pivot | S4: last | W4: cost | X4: Stop | Y4: Stop | Z4: % | AB4: EPS | AC4: Comp
A5: Symbol | B5: Position | C5: Name | D5: Qty | E5: Current | F5: Value | G5: Cost | H5: per share | I5: P/L $ | J5: per sh | K5: Date purch | L5: days held | M5: % incr | N5: Rank | O5: RS | P5: RS | Q5: pivot | R5: -0.07 | S5: low | T5: 0.25 | U5: 0.5 | V5: 1 | W5: -0.07 | X5: Loss | Y5: Loss% | Z5: of port | AB5: Due | AC5: Rank
A7: AXON | B7: Long | C7: Axon Enterprise | D7: 267.8431 | E7: 269.8 | F7: =E7*D7 -> 72264.068 | G7: 61166.24 | H7: =G7/D7 -> 228.36594 | I7: =F7-G7 -> 11097.828 | J7: =E7-H7 -> 41.434065 | K7: 45238 | L7: =DAYS360(K7,$C$1) -> 98 | M7: =(I7/G7) -> 0.18143715 | N7: 33 | O7: 89 | P7: 99 | Q7: 223.3 | R7: =Q7*0.93 -> 207.669 | S7: 241.72 | T7: =Q7*1.25 -> 279.125 | U7: =Q7*1.5 -> 334.95 | V7: =Q7*2 -> 446.6 | W7: =H7-(H7*0.07) -> 212.38032 | X7: 250 | Y7: =(X7-H7)/H7 -> 0.094734203 | Z7: =F7/F$19 -> 0.1400933 | AB7: 45349 | AC7: 99 | AD7: Bought as it gapped out of base on EPS.
A8: KD | B8: Long | C8: Kyndryl Hldgs | D8: =1160.2602+1046.0778 -> 2206.338 | E8: 21.44 | F8: =E8*D8 -> 47303.887 | G8: =20288.83+19170.47 -> 39459.3 | H8: =G8/D8 -> 17.884522 | I8: =F8-G8 -> 7844.5867 | J8: =E8-H8 -> 3.5554782 | K8: 45243 | L8: =DAYS360(K8,$C$1) -> 93 | M8: =(I8/G8) -> 0.19880197 | N8: 16 | O8: 91 | P8: 22 | Q8: 17.32 | R8: =Q8*0.93 -> 16.1076 | S8: 20.03 | T8: =Q8*1.25 -> 21.65 | U8: =Q8*1.5 -> 25.98 | V8: =Q8*2 -> 34.64 | W8: =H8-(H8*0.07) -> 16.632605 | X8: 19.75 | Y8: =(X8-H8)/H8 -> 0.10430686 | Z8: =F8/F$19 -> 0.091704739 | AB8: 45427 | AC8: 67 | AD8: Bought after 11/08 b/o. Trading tightly here.
A9: DDOG | B9: Long | C9: Datadog | D9: =308.2955+142.5312 -> 450.8267 | E9: 129.74 | F9: =E9*D9 -> 58490.256 | G9: =38082.35+18004.55 -> 56086.9 | H9: =G9/D9 -> 124.409 | I9: =F9-G9 -> 2403.3561 | J9: =E9-H9 -> 5.3309976 | K9: 45286 | L9: =DAYS360(K9,$C$1) -> 50 | M9: =(I9/G9) -> 0.042850578 | N9: 16 | O9: 91 | P9: 99 | Q9: 120.26 | R9: =Q9*0.93 -> 111.8418 | S9: 119.34 | T9: =Q9*1.25 -> 150.325 | U9: =Q9*1.5 -> 180.39 | V9: =Q9*2 -> 240.52 | W9: =H9-(H9*0.07) -> 115.70037 | X9: 122 | Y9: =(X9-H9)/H9 -> -0.01936357 | Z9: =F9/F$19 -> 0.11339097 | AB9: 45414 | AC9: 99 | AD9: Trading tightly since b/o.
A10: VKTX | B10: Long | C10: Viking Therap | D10: =1286.8297+948.5633 -> 2235.393 | E10: 36.2 | F10: =E10*D10 -> 80921.227 | G10: =28174.78+19947.6 -> 48122.38 | H10: =G10/D10 -> 21.527481 | I10: =F10-G10 -> 32798.847 | J10: =E10-H10 -> 14.672519 | K10: 45309 | L10: =DAYS360(K10,$C$1) -> 28 | M10: =(I10/G10) -> 0.68157158 | N10: 2 | O10: 99 | P10: 22 | Q10: 20.03 | R10: =Q10*0.93 -> 18.6279 | S10: 22.51 | T10: =Q10*1.25 -> 25.0375 | U10: =Q10*1.5 -> 30.045 | V10: =Q10*2 -> 40.06 | W10: =H10-(H10*0.07) -> 20.020557 | X10: 26 | Y10: =(X10-H10)/H10 -> 0.20775859 | Z10: =F10/F$19 -> 0.15687633 | AB10: 45406 | AC10: 82 | AD10: Bought after pivot test.
A11: AAON | B11: Long | C11: AAON | D11: =532.4164+77.1815 -> 609.5979 | E11: 84.3 | F11: =E11*D11 -> 51389.103 | G11: =38270.34+5640.4 -> 43910.74 | H11: =G11/D11 -> 72.032302 | I11: =F11-G11 -> 7478.363 | J11: =E11-H11 -> 12.267698 | K11: 45313 | L11: =DAYS360(K11,$C$1) -> 24 | M11: =(I11/G11) -> 0.17030829 | N11: 38 | O11: 92 | P11: 98 | Q11: 71.39 | R11: =Q11*0.93 -> 66.3927 | S11: 68.38 | T11: =Q11*1.25 -> 89.2375 | U11: =Q11*1.5 -> 107.085 | V11: =Q11*2 -> 142.78 | W11: =H11-(H11*0.07) -> 66.990041 | X11: 72 | Y11: =(X11-H11)/H11 -> -0.00044843699 | Z11: =F11/F$19 -> 0.099624462 | AB11: 45350 | AC11: 99 | AD11: Bought after pivot test.
A12: BLBD | B12: Long | C12: Bluebird | D12: =952.002+512.6146 -> 1464.6166 | E12: 32.31 | F12: =E12*D12 -> 47321.762 | G12: =28303.96+15646.4 -> 43950.36 | H12: =G12/D12 -> 30.008099 | I12: =F12-G12 -> 3371.4023 | J12: =E12-H12 -> 2.301901 | K12: 45321 | L12: =DAYS360(K12,$C$1) -> 16 | M12: =(I12/G12) -> 0.076709323 | N12: 50 | O12: 96 | P12: 81 | Q12: 28.39 | R12: =Q12*0.93 -> 26.4027 | S12: 24.09 | T12: =Q12*1.25 -> 35.4875 | U12: =Q12*1.5 -> 42.585 | V12: =Q12*2 -> 56.78 | W12: =H12-(H12*0.07) -> 27.907532 | X12: 29 | Y12: =(X12-H12)/H12 -> -0.033594232 | Z12: =F12/F$19 -> 0.091739393 | AB12: 45421 | AC12: 99 | AD12: Bought day 2 after b/o.
A13: MDB | B13: Long | C13: MongoDB | D13: 126.054 | E13: 465.06 | F13: =E13*D13 -> 58622.673 | G13: 56759.55 | H13: =G13/D13 -> 450.27964 | I13: =F13-G13 -> 1863.1232 | J13: =E13-H13 -> 14.780358 | K13: 45327 | L13: =DAYS360(K13,$C$1) -> 11 | M13: =(I13/G13) -> 0.032824842 | N13: 9 | O13: 94 | P13: 83 | Q13: 442.84 | R13: =Q13*0.93 -> 411.8412 | S13: 400.52 | T13: =Q13*1.25 -> 553.55 | U13: =Q13*1.5 -> 664.26 | V13: =Q13*2 -> 885.68 | W13: =H13-(H13*0.07) -> 418.76007 | X13: 445 | Y13: =(X13-H13)/H13 -> -0.011725252 | Z13: =F13/F$19 -> 0.11364768 | AB13: 45358 | AC13: 99 | AD13: Bought day 1 of b/o.
A14: IOT | B14: Long | C14: Samsara | D14: =846.327+640.0668 -> 1486.3938 | E14: 34.44 | F14: =E14*D14 -> 51191.402 | G14: =30020.93+21858.29 -> 51879.22 | H14: =G14/D14 -> 34.902742 | I14: =F14-G14 -> -687.81753 | J14: =E14-H14 -> -0.46274246 | K14: 45331 | L14: =DAYS360(K14,$C$1) -> 7 | M14: =(I14/G14) -> -0.013258055 | N14: 16 | O14: 95 | P14: 81 | Q14: 32.41 | R14: =Q14*0.93 -> 30.1413 | S14: 29.8 | T14: =Q14*1.25 -> 40.5125 | U14: =Q14*1.5 -> 48.615 | V14: =Q14*2 -> 64.82 | W14: =H14-(H14*0.07) -> 32.45955 | X14: 32.75 | Y14: =(X14-H14)/H14 -> -0.061678318 | Z14: =F14/F$19 -> 0.099241194 | AB14: 45358 | AC14: 95 | AD14: Broke out of consolidation above pivot.
F15: =E15*D15 -> 0 | H15: =G15/D15 -> #DIV/0! | I15: =F15-G15 -> 0 | J15: =E15-H15 -> #DIV/0! | L15: =DAYS360(K15,$C$1) -> 44686 | M15: =(I15/G15) -> #DIV/0! | R15: =Q15*0.93 -> 0 | T15: =Q15*1.25 -> 0 | U15: =Q15*1.5 -> 0 | V15: =Q15*2 -> 0 | W15: =H15-(H15*0.07) -> #DIV/0! | Y15: =(X15-H15)/H15 -> #DIV/0! | Z15: =F15/F$19 -> 0
A16: BIL | B16: Long | C16: Tbill ETF | D16: 277.4286 | E16: 91.63 | F16: =E16*D16 -> 25420.783 | G16: 25401.36 | H16: =G16/D16 -> 91.559991 | I16: =F16-G16 -> 19.422618 | J16: =E16-H16 -> 0.070009429 | M16: =(I16/G16) -> 0.00076462906 | R16: =Q16*0.93 -> 0 | T16: =Q16*1.25 -> 0 | U16: =Q16*1.5 -> 0 | V16: =Q16*2 -> 0 | W16: =H16-(H16*0.07) -> 85.150791 | Y16: =(X16-H16)/H16 -> -1 | Z16: =F16/F$19 -> 0.049281494
A17: Sub-Total | F17: =SUM(F6:F16) -> 492925.16 | G17: =SUM(G6:G16) -> 426736.05 | I17: =SUM(I6:I16) -> 66189.111
D18: Cash, other | F18: 22903 | G18: =F18/F19 -> 0.044400445
D19: Total | F19: =SUM(F17:F18) -> 515828.16
H20: Last week's close | I20: ='02-09-24'!F19 -> 508506.21 | K20: 45291 | L20: 476160.6
A21: * | H21: Week's change | I21: =(F19-I20)/I20 -> 0.014398941 | K21: chg % | L21: =(F19-L20)/L20 -> 0.083307106
M23: days
A24: 2024 Closed Trades - Managed Acct | D24: Qty | E24: Cost/sh | F24: $ cost | G24: $Proc | H24: Proc/sh | I24: Profit/loss | J24: % | K24: Date purch | L24: Date sold | M24: held | P24: Comments
A25: YELP | B25: Long | C25: Yelp Inc | D25: 808.573 | E25: =F25/D25 -> 47.428062 | F25: 38349.05 | G25: 35186.18 | H25: =G25/D25 -> 43.516392 | I25: =G25-F25 -> -3162.87 | J25: =I25/F25 -> -0.082475837 | K25: 45286 | L25: 45302 | M25: =DAYS360(K25,L25) -> 15 | O25: Closed below stop for 2 days.
A26: TS | B26: Long | C26: Tenaris | D26: 1166.935 | E26: =F26/D26 -> 35.085005 | F26: 40941.92 | G26: 36634.59 | H26: =G26/D26 -> 31.393857 | I26: =G26-F26 -> -4307.33 | J26: =I26/F26 -> -0.10520586 | K26: 45233 | L26: 45307 | M26: =DAYS360(K26,L26) -> 73
A27: MNSO | B27: Long | C27: Minoso | D27: =1211.7123+804.6763 -> 2016.3886 | E27: =F27/D27 -> 20.49104 | F27: 41317.9 | G27: 42071.53 | H27: =G27/D27 -> 20.864793 | I27: =G27-F27 -> 753.63 | J27: =I27/F27 -> 0.018239794 | K27: 45135 | L27: 45308 | M27: =DAYS360(K27,L27) -> 169 | O27: Totally blew this trade. Had a nearly 50% profit.
A28: ACMR | B28: Long | C28: ACM Research | D28: =1339.9646+918.07 -> 2258.0346 | E28: =F28/D28 -> 21.193736 | F28: =28457.8+19398.39 -> 47856.19 | G28: 39178.27 | H28: =G28/D28 -> 17.350607 | I28: =G28-F28 -> -8677.92 | J28: =I28/F28 -> -0.18133328 | K28: 45302 | L28: 45322 | M28: =DAYS360(K28,L28) -> 20
I32: =SUM(I25:I31) -> -15394.49
I39: =SUM(I26:I38) -> -27626.11 | J39: Avg
H40: # of losses
H41: # of wins

Sheet 02-23-24
C1: 45345
C3: MANAGED ACCT | X3: Current | AC3: IBD
H4: Cost | J4: P/L | N4: Group | P4: EPS | R4: pivot | S4: last | W4: cost | X4: Stop | Y4: Stop | Z4: % | AB4: EPS | AC4: Comp
A5: Symbol | B5: Position | C5: Name | D5: Qty | E5: Current | F5: Value | G5: Cost | H5: per share | I5: P/L $ | J5: per sh | K5: Date purch | L5: days held | M5: % incr | N5: Rank | O5: RS | P5: RS | Q5: pivot | R5: -0.07 | S5: low | T5: 0.25 | U5: 0.5 | V5: 1 | W5: -0.07 | X5: Loss | Y5: Loss% | Z5: of port | AB5: Due | AC5: Rank
A7: AXON | B7: Long | C7: Axon Enterprise | D7: 267.8431 | E7: 270.63 | F7: =E7*D7 -> 72486.378 | G7: 61166.24 | H7: =G7/D7 -> 228.36594 | I7: =F7-G7 -> 11320.138 | J7: =E7-H7 -> 42.264065 | K7: 45238 | L7: =DAYS360(K7,$C$1) -> 105 | M7: =(I7/G7) -> 0.18507167 | N7: 26 | O7: 89 | P7: 99 | Q7: 223.3 | R7: =Q7*0.93 -> 207.669 | S7: 241.72 | T7: =Q7*1.25 -> 279.125 | U7: =Q7*1.5 -> 334.95 | V7: =Q7*2 -> 446.6 | W7: =H7-(H7*0.07) -> 212.38032 | X7: 250 | Y7: =(X7-H7)/H7 -> 0.094734203 | Z7: =F7/F$19 -> 0.14235115 | AB7: 45349 | AC7: 99 | AD7: Bought as it gapped out of base on EPS.
A8: KD | B8: Long | C8: Kyndryl Hldgs | D8: =1160.2602+1046.0778 -> 2206.338 | E8: 21.54 | F8: =E8*D8 -> 47524.521 | G8: =20288.83+19170.47 -> 39459.3 | H8: =G8/D8 -> 17.884522 | I8: =F8-G8 -> 8065.2205 | J8: =E8-H8 -> 3.6554782 | K8: 45243 | L8: =DAYS360(K8,$C$1) -> 100 | M8: =(I8/G8) -> 0.2043934 | N8: 21 | O8: 91 | P8: 22 | Q8: 17.32 | R8: =Q8*0.93 -> 16.1076 | S8: 20.03 | T8: =Q8*1.25 -> 21.65 | U8: =Q8*1.5 -> 25.98 | V8: =Q8*2 -> 34.64 | W8: =H8-(H8*0.07) -> 16.632605 | X8: 19.75 | Y8: =(X8-H8)/H8 -> 0.10430686 | Z8: =F8/F$19 -> 0.093330228 | AB8: 45427 | AC8: 66 | AD8: Bought after 11/08 b/o. Trading tightly here.
A9: DDOG | B9: Long | C9: Datadog | D9: =308.2955+142.5312 -> 450.8267 | E9: 129.51 | F9: =E9*D9 -> 58386.566 | G9: =38082.35+18004.55 -> 56086.9 | H9: =G9/D9 -> 124.409 | I9: =F9-G9 -> 2299.6659 | J9: =E9-H9 -> 5.1009976 | K9: 45286 | L9: =DAYS360(K9,$C$1) -> 57 | M9: =(I9/G9) -> 0.041001837 | N9: 21 | O9: 91 | P9: 99 | Q9: 120.26 | R9: =Q9*0.93 -> 111.8418 | S9: 119.34 | T9: =Q9*1.25 -> 150.325 | U9: =Q9*1.5 -> 180.39 | V9: =Q9*2 -> 240.52 | W9: =H9-(H9*0.07) -> 115.70037 | X9: 122 | Y9: =(X9-H9)/H9 -> -0.01936357 | Z9: =F9/F$19 -> 0.11466147 | AB9: 45414 | AC9: 99 | AD9: Trading tightly since b/o.
A10: VKTX | B10: Long | C10: Viking Therap | D10: =1286.8297+948.5633-808.6324 -> 1426.7606 | E10: 37.42 | F10: =E10*D10 -> 53389.382 | G10: =28174.78+19947.6-17409.86 -> 30712.52 | H10: =G10/D10 -> 21.52605 | I10: =F10-G10 -> 22676.862 | J10: =E10-H10 -> 15.89395 | K10: 45309 | L10: =DAYS360(K10,$C$1) -> 35 | M10: =(I10/G10) -> 0.73835887 | N10: 4 | O10: 99 | P10: 22 | Q10: 20.03 | R10: =Q10*0.93 -> 18.6279 | S10: 22.51 | T10: =Q10*1.25 -> 25.0375 | U10: =Q10*1.5 -> 30.045 | V10: =Q10*2 -> 40.06 | W10: =H10-(H10*0.07) -> 20.019226 | X10: 28 | Y10: =(X10-H10)/H10 -> 0.30074956 | Z10: =F10/F$19 -> 0.10484784 | AB10: 45406 | AC10: 83 | AD10: Bought after pivot test.
A11: AAON | B11: Long | C11: AAON | D11: =532.4164+77.1815 -> 609.5979 | E11: 84.05 | F11: =E11*D11 -> 51236.703 | G11: =38270.34+5640.4 -> 43910.74 | H11: =G11/D11 -> 72.032302 | I11: =F11-G11 -> 7325.9635 | J11: =E11-H11 -> 12.017698 | K11: 45313 | L11: =DAYS360(K11,$C$1) -> 31 | M11: =(I11/G11) -> 0.16683762 | N11: 51 | O11: 92 | P11: 98 | Q11: 71.39 | R11: =Q11*0.93 -> 66.3927 | S11: 68.38 | T11: =Q11*1.25 -> 89.2375 | U11: =Q11*1.5 -> 107.085 | V11: =Q11*2 -> 142.78 | W11: =H11-(H11*0.07) -> 66.990041 | X11: 77 | Y11: =(X11-H11)/H11 -> 0.068964866 | Z11: =F11/F$19 -> 0.10062034 | AB11: 45350 | AC11: 99 | AD11: Bought after pivot test.
A12: BLBD | B12: Long | C12: Bluebird | D12: =952.002+512.6146 -> 1464.6166 | E12: 31.5 | F12: =E12*D12 -> 46135.423 | G12: =28303.96+15646.4 -> 43950.36 | H12: =G12/D12 -> 30.008099 | I12: =F12-G12 -> 2185.0629 | J12: =E12-H12 -> 1.491901 | K12: 45321 | L12: =DAYS360(K12,$C$1) -> 23 | M12: =(I12/G12) -> 0.04971661 | N12: 46 | O12: 95 | P12: 81 | Q12: 28.39 | R12: =Q12*0.93 -> 26.4027 | S12: 24.09 | T12: =Q12*1.25 -> 35.4875 | U12: =Q12*1.5 -> 42.585 | V12: =Q12*2 -> 56.78 | W12: =H12-(H12*0.07) -> 27.907532 | X12: 29 | Y12: =(X12-H12)/H12 -> -0.033594232 | Z12: =F12/F$19 -> 0.090602272 | AB12: 45421 | AC12: 99 | AD12: Bought day 2 after b/o.
A13: IOT | B13: Long | C13: Samsara | D13: =846.327+640.0668 -> 1486.3938 | E13: 33.31 | F13: =E13*D13 -> 49511.777 | G13: =30020.93+21858.29 -> 51879.22 | H13: =G13/D13 -> 34.902742 | I13: =F13-G13 -> -2367.4425 | J13: =E13-H13 -> -1.5927425 | K13: 45331 | L13: =DAYS360(K13,$C$1) -> 14 | M13: =(I13/G13) -> -0.045633734 | N13: 21 | O13: 94 | P13: 81 | Q13: 32.41 | R13: =Q13*0.93 -> 30.1413 | S13: 29.8 | T13: =Q13*1.25 -> 40.5125 | U13: =Q13*1.5 -> 48.615 | V13: =Q13*2 -> 64.82 | W13: =H13-(H13*0.07) -> 32.45955 | X13: 32.75 | Y13: =(X13-H13)/H13 -> -0.061678318 | Z13: =F13/F$19 -> 0.097232869 | AB13: 45358 | AC13: 95 | AD13: Broke out of consolidation above pivot.
A14: BIRK | B14: Long | C14: Birkenstock Hldg | D14: =567.3728+414.8485 -> 982.2213 | E14: 52 | F14: =E14*D14 -> 51075.508 | G14: =30558.32+21471.26 -> 52029.58 | H14: =G14/D14 -> 52.971342 | I14: =F14-G14 -> -954.0724 | J14: =E14-H14 -> -0.97134159 | K14: 45344 | L14: =DAYS360(K14,$C$1) -> 1 | M14: =(I14/G14) -> -0.018337115 | N14: 2 | O14: 87 | P14: 60 | Q14: 51.09 | R14: =Q14*0.93 -> 47.5137 | S14: 48.63 | T14: =Q14*1.25 -> 63.8625 | U14: =Q14*1.5 -> 76.635 | V14: =Q14*2 -> 102.18 | W14: =H14-(H14*0.07) -> 49.263348 | X14: 50.25 | Y14: =(X14-H14)/H14 -> -0.051373847 | Z14: =F14/F$19 -> 0.10030377 | AB14: 45351 | AC14: 94 | AD14: Bought day 2 after b/o.
F15: =E15*D15 -> 0 | H15: =G15/D15 -> #DIV/0! | I15: =F15-G15 -> 0 | J15: =E15-H15 -> #DIV/0! | L15: =DAYS360(K15,$C$1) -> 44693 | M15: =(I15/G15) -> #DIV/0! | R15: =Q15*0.93 -> 0 | T15: =Q15*1.25 -> 0 | U15: =Q15*1.5 -> 0 | V15: =Q15*2 -> 0 | W15: =H15-(H15*0.07) -> #DIV/0! | Y15: =(X15-H15)/H15 -> #DIV/0! | Z15: =F15/F$19 -> 0
A16: BIL | B16: Long | C16: Tbill ETF | D16: 277.4286 | E16: 91.71 | F16: =E16*D16 -> 25442.977 | G16: 25401.36 | H16: =G16/D16 -> 91.559991 | I16: =F16-G16 -> 41.616906 | J16: =E16-H16 -> 0.15000943 | M16: =(I16/G16) -> 0.0016383731 | R16: =Q16*0.93 -> 0 | T16: =Q16*1.25 -> 0 | U16: =Q16*1.5 -> 0 | V16: =Q16*2 -> 0 | W16: =H16-(H16*0.07) -> 85.150791 | Y16: =(X16-H16)/H16 -> -1 | Z16: =F16/F$19 -> 0.049965761
A17: Sub-Total | F17: =SUM(F6:F16) -> 455189.23 | G17: =SUM(G6:G16) -> 404596.22 | I17: =SUM(I6:I16) -> 50593.015
D18: Cash, other | F18: 54019 | G18: =F18/F19 -> 0.1060843
D19: Total | F19: =SUM(F17:F18) -> 509208.23
H20: Last week's close | I20: ='02-16-24'!F19 -> 515828.16 | K20: 45291 | L20: 476160.6
A21: * | H21: Week's change | I21: =(F19-I20)/I20 -> -0.012833589 | K21: chg % | L21: =(F19-L20)/L20 -> 0.069404387
M23: days
A24: 2024 Closed Trades - Managed Acct | D24: Qty | E24: Cost/sh | F24: $ cost | G24: $Proc | H24: Proc/sh | I24: Profit/loss | J24: % | K24: Date purch | L24: Date sold | M24: held | P24: Comments
A25: YELP | B25: Long | C25: Yelp Inc | D25: 808.573 | E25: =F25/D25 -> 47.428062 | F25: 38349.05 | G25: 35186.18 | H25: =G25/D25 -> 43.516392 | I25: =G25-F25 -> -3162.87 | J25: =I25/F25 -> -0.082475837 | K25: 45286 | L25: 45302 | M25: =DAYS360(K25,L25) -> 15 | O25: Closed below stop for 2 days.
A26: TS | B26: Long | C26: Tenaris | D26: 1166.935 | E26: =F26/D26 -> 35.085005 | F26: 40941.92 | G26: 36634.59 | H26: =G26/D26 -> 31.393857 | I26: =G26-F26 -> -4307.33 | J26: =I26/F26 -> -0.10520586 | K26: 45233 | L26: 45307 | M26: =DAYS360(K26,L26) -> 73
A27: MNSO | B27: Long | C27: Minoso | D27: =1211.7123+804.6763 -> 2016.3886 | E27: =F27/D27 -> 20.49104 | F27: 41317.9 | G27: 42071.53 | H27: =G27/D27 -> 20.864793 | I27: =G27-F27 -> 753.63 | J27: =I27/F27 -> 0.018239794 | K27: 45135 | L27: 45308 | M27: =DAYS360(K27,L27) -> 169 | O27: Totally blew this trade. Had a nearly 50% profit.
A28: ACMR | B28: Long | C28: ACM Research | D28: =1339.9646+918.07 -> 2258.0346 | E28: =F28/D28 -> 21.193736 | F28: =28457.8+19398.39 -> 47856.19 | G28: 39178.27 | H28: =G28/D28 -> 17.350607 | I28: =G28-F28 -> -8677.92 | J28: =I28/F28 -> -0.18133328 | K28: 45302 | L28: 45322 | M28: =DAYS360(K28,L28) -> 20
A29: MDB | B29: Long | C29: MongoDB | D29: 126.054 | E29: =F29/D29 -> 450.27964 | F29: 56759.55 | G29: 54939.36 | H29: =G29/D29 -> 435.83988 | I29: =G29-F29 -> -1820.19 | J29: =I29/F29 -> -0.032068436 | K29: 45327 | L29: 45342 | M29: =DAYS360(K29,L29) -> 15 | O29: Stopped out.
A30: VKTX | B30: Long | C30: Viking Therap | D30: 808.6324 | E30: =F30/D30 -> 21.530005 | F30: 17409.86 | G30: 28227.27 | H30: =G30/D30 -> 34.907419 | I30: =G30-F30 -> 10817.41 | J30: =I30/F30 -> 0.62133814 | K30: 45309 | L30: 45343 | M30: =DAYS360(K30,L30) -> 33 | O30: Took partial profit.
I32: =SUM(I25:I31) -> -6397.27
I39: =SUM(I26:I38) -> -9631.67 | J39: Avg
H40: # of losses
H41: # of wins

Sheet 03-01-24
C1: 45352
C3: MANAGED ACCT | X3: Current | AC3: IBD
H4: Cost | J4: P/L | N4: Group | P4: EPS | R4: pivot | S4: last | W4: cost | X4: Stop | Y4: Stop | Z4: % | AB4: EPS | AC4: Comp
A5: Symbol | B5: Position | C5: Name | D5: Qty | E5: Current | F5: Value | G5: Cost | H5: per share | I5: P/L $ | J5: per sh | K5: Date purch | L5: days held | M5: % incr | N5: Rank | O5: RS | P5: RS | Q5: pivot | R5: -0.07 | S5: low | T5: 0.25 | U5: 0.5 | V5: 1 | W5: -0.07 | X5: Loss | Y5: Loss% | Z5: of port | AB5: Due | AC5: Rank
A7: AXON | B7: Long | C7: Axon Enterprise | D7: 267.8431 | E7: 314.25 | F7: =E7*D7 -> 84169.694 | G7: 61166.24 | H7: =G7/D7 -> 228.36594 | I7: =F7-G7 -> 23003.454 | J7: =E7-H7 -> 85.884065 | K7: 45238 | L7: =DAYS360(K7,$C$1) -> 113 | M7: =(I7/G7) -> 0.37608089 | N7: 15 | O7: 93 | P7: 99 | Q7: 223.3 | R7: =Q7*0.93 -> 207.669 | S7: 255.68 | T7: =Q7*1.25 -> 279.125 | U7: =Q7*1.5 -> 334.95 | V7: =Q7*2 -> 446.6 | W7: =H7-(H7*0.07) -> 212.38032 | X7: 275 | Y7: =(X7-H7)/H7 -> 0.20420762 | Z7: =F7/F$19 -> 0.14223363 | AB7: 45421 | AC7: 99 | AD7: Bought as it gapped out of base on EPS.
A8: KD | B8: Long | C8: Kyndryl Hldgs | D8: =1160.2602+1046.0778 -> 2206.338 | E8: 22.24 | F8: =E8*D8 -> 49068.957 | G8: =20288.83+19170.47 -> 39459.3 | H8: =G8/D8 -> 17.884522 | I8: =F8-G8 -> 9609.6571 | J8: =E8-H8 -> 4.3554782 | K8: 45243 | L8: =DAYS360(K8,$C$1) -> 108 | M8: =(I8/G8) -> 0.24353339 | N8: 36 | O8: 91 | P8: 22 | Q8: 17.32 | R8: =Q8*0.93 -> 16.1076 | S8: 20.89 | T8: =Q8*1.25 -> 21.65 | U8: =Q8*1.5 -> 25.98 | V8: =Q8*2 -> 34.64 | W8: =H8-(H8*0.07) -> 16.632605 | X8: 20.5 | Y8: =(X8-H8)/H8 -> 0.14624256 | Z8: =F8/F$19 -> 0.082918869 | AB8: 45427 | AC8: 65 | AD8: Bought after 11/08 b/o. Trading tightly here.
A9: DDOG | B9: Long | C9: Datadog | D9: =308.2955+142.5312 -> 450.8267 | E9: 130.22 | F9: =E9*D9 -> 58706.653 | G9: =38082.35+18004.55 -> 56086.9 | H9: =G9/D9 -> 124.409 | I9: =F9-G9 -> 2619.7529 | J9: =E9-H9 -> 5.8109976 | K9: 45286 | L9: =DAYS360(K9,$C$1) -> 65 | M9: =(I9/G9) -> 0.046708819 | N9: 36 | O9: 91 | P9: 99 | Q9: 120.26 | R9: =Q9*0.93 -> 111.8418 | S9: 119.34 | T9: =Q9*1.25 -> 150.325 | U9: =Q9*1.5 -> 180.39 | V9: =Q9*2 -> 240.52 | W9: =H9-(H9*0.07) -> 115.70037 | X9: 122 | Y9: =(X9-H9)/H9 -> -0.01936357 | Z9: =F9/F$19 -> 0.099205068 | AB9: 45414 | AC9: 99 | AD9: Trading tightly since b/o.
A10: VKTX | B10: Long | C10: Viking Therap | D10: =1286.8297+948.5633-808.6324 -> 1426.7606 | E10: 85.22 | F10: =E10*D10 -> 121588.54 | G10: =28174.78+19947.6-17409.86 -> 30712.52 | H10: =G10/D10 -> 21.52605 | I10: =F10-G10 -> 90876.018 | J10: =E10-H10 -> 63.69395 | K10: 45309 | L10: =DAYS360(K10,$C$1) -> 43 | M10: =(I10/G10) -> 2.9589242 | N10: 5 | O10: 99 | P10: 22 | Q10: 20.03 | R10: =Q10*0.93 -> 18.6279 | S10: 34.04 | T10: =Q10*1.25 -> 25.0375 | U10: =Q10*1.5 -> 30.045 | V10: =Q10*2 -> 40.06 | W10: =H10-(H10*0.07) -> 20.019226 | X10: 55 | Y10: =(X10-H10)/H10 -> 1.5550438 | Z10: =F10/F$19 -> 0.20546563 | AB10: 45406 | AC10: 81 | AD10: Bought after pivot test.
A11: AAON | B11: Long | C11: AAON | D11: =532.4164+77.1815 -> 609.5979 | E11: 83.26 | F11: =E11*D11 -> 50755.121 | G11: =38270.34+5640.4 -> 43910.74 | H11: =G11/D11 -> 72.032302 | I11: =F11-G11 -> 6844.3812 | J11: =E11-H11 -> 11.227698 | K11: 45313 | L11: =DAYS360(K11,$C$1) -> 39 | M11: =(I11/G11) -> 0.15587032 | N11: 27 | O11: 91 | P11: 96 | Q11: 71.39 | R11: =Q11*0.93 -> 66.3927 | S11: 78.07 | T11: =Q11*1.25 -> 89.2375 | U11: =Q11*1.5 -> 107.085 | V11: =Q11*2 -> 142.78 | W11: =H11-(H11*0.07) -> 66.990041 | X11: 77 | Y11: =(X11-H11)/H11 -> 0.068964866 | Z11: =F11/F$19 -> 0.085768222 | AB11: 45414 | AC11: 97 | AD11: Bought after pivot test.
A12: BLBD | B12: Long | C12: Bluebird | D12: =952.002+512.6146 -> 1464.6166 | E12: 34.43 | F12: =E12*D12 -> 50426.75 | G12: =28303.96+15646.4 -> 43950.36 | H12: =G12/D12 -> 30.008099 | I12: =F12-G12 -> 6476.3895 | J12: =E12-H12 -> 4.421901 | K12: 45321 | L12: =DAYS360(K12,$C$1) -> 31 | M12: =(I12/G12) -> 0.14735692 | N12: 39 | O12: 95 | P12: 81 | Q12: 28.39 | R12: =Q12*0.93 -> 26.4027 | S12: 29.78 | T12: =Q12*1.25 -> 35.4875 | U12: =Q12*1.5 -> 42.585 | V12: =Q12*2 -> 56.78 | W12: =H12-(H12*0.07) -> 27.907532 | X12: 30 | Y12: =(X12-H12)/H12 -> -0.0002698954 | Z12: =F12/F$19 -> 0.085213326 | AB12: 45421 | AC12: 99 | AD12: Bought day 2 after b/o.
A13: IOT | B13: Long | C13: Samsara | D13: =846.327+640.0668 -> 1486.3938 | E13: 34.99 | F13: =E13*D13 -> 52008.919 | G13: =30020.93+21858.29 -> 51879.22 | H13: =G13/D13 -> 34.902742 | I13: =F13-G13 -> 129.69906 | J13: =E13-H13 -> 0.087257537 | K13: 45331 | L13: =DAYS360(K13,$C$1) -> 22 | M13: =(I13/G13) -> 0.0025000195 | N13: 36 | O13: 94 | P13: 81 | Q13: 32.41 | R13: =Q13*0.93 -> 30.1413 | S13: 30.71 | T13: =Q13*1.25 -> 40.5125 | U13: =Q13*1.5 -> 48.615 | V13: =Q13*2 -> 64.82 | W13: =H13-(H13*0.07) -> 32.45955 | X13: 32.75 | Y13: =(X13-H13)/H13 -> -0.061678318 | Z13: =F13/F$19 -> 0.087886945 | AB13: 45358 | AC13: 93 | AD13: Broke out of consolidation above pivot.
A14: BPMC | B14: Long | C14: Blueprint Med | D14: =464.2554+269.0604 -> 733.3158 | E14: 95.12 | F14: =E14*D14 -> 69752.999 | G14: =45518.9+25760.58 -> 71279.48 | H14: =G14/D14 -> 97.201615 | I14: =F14-G14 -> -1526.4811 | J14: =E14-H14 -> -2.0816149 | K14: 45349 | L14: =DAYS360(K14,$C$1) -> 4 | M14: =(I14/G14) -> -0.021415435 | N14: 5 | O14: 96 | P14: 34 | Q14: 94.47 | R14: =Q14*0.93 -> 87.8571 | S14: 80.42 | T14: =Q14*1.25 -> 118.0875 | U14: =Q14*1.5 -> 141.705 | V14: =Q14*2 -> 188.94 | W14: =H14-(H14*0.07) -> 90.397502 | X14: 90 | Y14: =(X14-H14)/H14 -> -0.074089457 | Z14: =F14/F$19 -> 0.11787167 | AB14: 45413 | AC14: 82 | AD14: Bought the b/o day.
F15: =E15*D15 -> 0 | H15: =G15/D15 -> #DIV/0! | I15: =F15-G15 -> 0 | J15: =E15-H15 -> #DIV/0! | L15: =DAYS360(K15,$C$1) -> 44701 | M15: =(I15/G15) -> #DIV/0! | R15: =Q15*0.93 -> 0 | T15: =Q15*1.25 -> 0 | U15: =Q15*1.5 -> 0 | V15: =Q15*2 -> 0 | W15: =H15-(H15*0.07) -> #DIV/0! | Y15: =(X15-H15)/H15 -> #DIV/0! | Z15: =F15/F$19 -> 0
A16: BIL | B16: Long | C16: Tbill ETF | D16: 277.4286 | E16: 91.44 | F16: =E16*D16 -> 25368.071 | G16: 25401.36 | H16: =G16/D16 -> 91.559991 | I16: =F16-G16 -> -33.288816 | J16: =E16-H16 -> -0.11999057 | M16: =(I16/G16) -> -0.0013105131 | R16: =Q16*0.93 -> 0 | T16: =Q16*1.25 -> 0 | U16: =Q16*1.5 -> 0 | V16: =Q16*2 -> 0 | W16: =H16-(H16*0.07) -> 85.150791 | Y16: =(X16-H16)/H16 -> -1 | Z16: =F16/F$19 -> 0.042868076
A17: Sub-Total | F17: =SUM(F6:F16) -> 561845.7 | G17: =SUM(G6:G16) -> 423846.12 | I17: =SUM(I6:I16) -> 137999.58
D18: Cash, other | F18: 29925 | G18: =F18/F19 -> 0.050568573
D19: Total | F19: =SUM(F17:F18) -> 591770.7
H20: Last week's close | I20: ='02-23-24'!F19 -> 509208.23 | K20: 45291 | L20: 476160.6
A21: * | H21: Week's change | I21: =(F19-I20)/I20 -> 0.16213891 | K21: chg % | L21: =(F19-L20)/L20 -> 0.24279645
M23: days
A24: 2024 Closed Trades - Managed Acct | D24: Qty | E24: Cost/sh | F24: $ cost | G24: $Proc | H24: Proc/sh | I24: Profit/loss | J24: % | K24: Date purch | L24: Date sold | M24: held | P24: Comments
A25: YELP | B25: Long | C25: Yelp Inc | D25: 808.573 | E25: =F25/D25 -> 47.428062 | F25: 38349.05 | G25: 35186.18 | H25: =G25/D25 -> 43.516392 | I25: =G25-F25 -> -3162.87 | J25: =I25/F25 -> -0.082475837 | K25: 45286 | L25: 45302 | M25: =DAYS360(K25,L25) -> 15 | O25: Closed below stop for 2 days.
A26: TS | B26: Long | C26: Tenaris | D26: 1166.935 | E26: =F26/D26 -> 35.085005 | F26: 40941.92 | G26: 36634.59 | H26: =G26/D26 -> 31.393857 | I26: =G26-F26 -> -4307.33 | J26: =I26/F26 -> -0.10520586 | K26: 45233 | L26: 45307 | M26: =DAYS360(K26,L26) -> 73
A27: MNSO | B27: Long | C27: Minoso | D27: =1211.7123+804.6763 -> 2016.3886 | E27: =F27/D27 -> 20.49104 | F27: 41317.9 | G27: 42071.53 | H27: =G27/D27 -> 20.864793 | I27: =G27-F27 -> 753.63 | J27: =I27/F27 -> 0.018239794 | K27: 45135 | L27: 45308 | M27: =DAYS360(K27,L27) -> 169 | O27: Totally blew this trade. Had a nearly 50% profit.
A28: ACMR | B28: Long | C28: ACM Research | D28: =1339.9646+918.07 -> 2258.0346 | E28: =F28/D28 -> 21.193736 | F28: =28457.8+19398.39 -> 47856.19 | G28: 39178.27 | H28: =G28/D28 -> 17.350607 | I28: =G28-F28 -> -8677.92 | J28: =I28/F28 -> -0.18133328 | K28: 45302 | L28: 45322 | M28: =DAYS360(K28,L28) -> 20
A29: MDB | B29: Long | C29: MongoDB | D29: 126.054 | E29: =F29/D29 -> 450.27964 | F29: 56759.55 | G29: 54939.36 | H29: =G29/D29 -> 435.83988 | I29: =G29-F29 -> -1820.19 | J29: =I29/F29 -> -0.032068436 | K29: 45327 | L29: 45342 | M29: =DAYS360(K29,L29) -> 15 | O29: Stopped out.
A30: VKTX | B30: Long | C30: Viking Therap | D30: 808.6324 | E30: =F30/D30 -> 21.530005 | F30: 17409.86 | G30: 28227.27 | H30: =G30/D30 -> 34.907419 | I30: =G30-F30 -> 10817.41 | J30: =I30/F30 -> 0.62133814 | K30: 45309 | L30: 45343 | M30: =DAYS360(K30,L30) -> 33 | O30: Took partial profit.
A31: BIRK | B31: Long | C31: Birkenstock Hldg | D31: =567.3728+414.8485 -> 982.2213 | E31: =F31/D31 -> 52.971342 | F31: 52029.58 | G31: 47202.25 | H31: =G31/D31 -> 48.056634 | I31: =G31-F31 -> -4827.33 | J31: =I31/F31 -> -0.092780491 | K31: 45344 | L31: 45351 | M31: =DAYS360(K31,L31) -> 7 | O31: Stopped out after earnings.
I32: =SUM(I25:I31) -> -11224.6
I39: =SUM(I26:I38) -> -19286.33 | J39: Avg
H40: # of losses
H41: # of wins

Sheet 03-08-24
C1: 45359
C3: MANAGED ACCT | X3: Current | AC3: IBD
H4: Cost | J4: P/L | N4: Group | P4: EPS | R4: pivot | S4: last | W4: cost | X4: Stop | Y4: Stop | Z4: % | AB4: EPS | AC4: Comp
A5: Symbol | B5: Position | C5: Name | D5: Qty | E5: Current | F5: Value | G5: Cost | H5: per share | I5: P/L $ | J5: per sh | K5: Date purch | L5: days held | M5: % incr | N5: Rank | O5: RS | P5: RS | Q5: pivot | R5: -0.07 | S5: low | T5: 0.25 | U5: 0.5 | V5: 1 | W5: -0.07 | X5: Loss | Y5: Loss% | Z5: of port | AB5: Due | AC5: Rank
A7: AXON | B7: Long | C7: Axon Enterprise | D7: 267.8431 | E7: 312.79 | F7: =E7*D7 -> 83778.643 | G7: 61166.24 | H7: =G7/D7 -> 228.36594 | I7: =F7-G7 -> 22612.403 | J7: =E7-H7 -> 84.424065 | K7: 45238 | L7: =DAYS360(K7,$C$1) -> 120 | M7: =(I7/G7) -> 0.36968765 | N7: 14 | O7: 93 | P7: 99 | Q7: 223.3 | R7: =Q7*0.93 -> 207.669 | S7: 255.68 | T7: =Q7*1.25 -> 279.125 | U7: =Q7*1.5 -> 334.95 | V7: =Q7*2 -> 446.6 | W7: =H7-(H7*0.07) -> 212.38032 | X7: 275 | Y7: =(X7-H7)/H7 -> 0.20420762 | Z7: =F7/F$19 -> 0.14732538 | AB7: 45421 | AC7: 99 | AD7: Bought as it gapped out of base on EPS.
A8: KD | B8: Long | C8: Kyndryl Hldgs | D8: =1160.2602+1046.0778 -> 2206.338 | E8: 21.62 | F8: =E8*D8 -> 47701.028 | G8: =20288.83+19170.47 -> 39459.3 | H8: =G8/D8 -> 17.884522 | I8: =F8-G8 -> 8241.7276 | J8: =E8-H8 -> 3.7354782 | K8: 45243 | L8: =DAYS360(K8,$C$1) -> 115 | M8: =(I8/G8) -> 0.20886654 | N8: 46 | O8: 91 | P8: 22 | Q8: 17.32 | R8: =Q8*0.93 -> 16.1076 | S8: 20.89 | T8: =Q8*1.25 -> 21.65 | U8: =Q8*1.5 -> 25.98 | V8: =Q8*2 -> 34.64 | W8: =H8-(H8*0.07) -> 16.632605 | X8: 20.5 | Y8: =(X8-H8)/H8 -> 0.14624256 | Z8: =F8/F$19 -> 0.083882619 | AB8: 45427 | AC8: 61 | AD8: Bought after 11/08 b/o. Trading tightly here.
F9: =E9*D9 -> 0 | H9: =G9/D9 -> #DIV/0! | I9: =F9-G9 -> 0 | J9: =E9-H9 -> #DIV/0! | L9: =DAYS360(K9,$C$1) -> 44708 | M9: =(I9/G9) -> #DIV/0! | R9: =Q9*0.93 -> 0 | T9: =Q9*1.25 -> 0 | U9: =Q9*1.5 -> 0 | V9: =Q9*2 -> 0 | W9: =H9-(H9*0.07) -> #DIV/0! | Y9: =(X9-H9)/H9 -> #DIV/0! | Z9: =F9/F$19 -> 0
A10: VKTX | B10: Long | C10: Viking Therap | D10: =1286.8297+948.5633-808.6324 -> 1426.7606 | E10: 71.78 | F10: =E10*D10 -> 102412.88 | G10: =28174.78+19947.6-17409.86 -> 30712.52 | H10: =G10/D10 -> 21.52605 | I10: =F10-G10 -> 71700.356 | J10: =E10-H10 -> 50.25395 | K10: 45309 | L10: =DAYS360(K10,$C$1) -> 50 | M10: =(I10/G10) -> 2.3345644 | N10: 6 | O10: 99 | P10: 22 | Q10: 20.03 | R10: =Q10*0.93 -> 18.6279 | S10: 34.04 | T10: =Q10*1.25 -> 25.0375 | U10: =Q10*1.5 -> 30.045 | V10: =Q10*2 -> 40.06 | W10: =H10-(H10*0.07) -> 20.019226 | X10: 55 | Y10: =(X10-H10)/H10 -> 1.5550438 | Z10: =F10/F$19 -> 0.18009382 | AB10: 45406 | AC10: 81 | AD10: Bought after pivot test.
A11: AAON | B11: Long | C11: AAON | D11: =532.4164+77.1815 -> 609.5979 | E11: 81.75 | F11: =E11*D11 -> 49834.628 | G11: =38270.34+5640.4 -> 43910.74 | H11: =G11/D11 -> 72.032302 | I11: =F11-G11 -> 5923.8883 | J11: =E11-H11 -> 9.7176981 | K11: 45313 | L11: =DAYS360(K11,$C$1) -> 46 | M11: =(I11/G11) -> 0.1349075 | N11: 33 | O11: 86 | P11: 96 | Q11: 71.39 | R11: =Q11*0.93 -> 66.3927 | S11: 78.07 | T11: =Q11*1.25 -> 89.2375 | U11: =Q11*1.5 -> 107.085 | V11: =Q11*2 -> 142.78 | W11: =H11-(H11*0.07) -> 66.990041 | X11: 77 | Y11: =(X11-H11)/H11 -> 0.068964866 | Z11: =F11/F$19 -> 0.087634572 | AB11: 45414 | AC11: 96 | AD11: Bought after pivot test.
A12: BLBD | B12: Long | C12: Bluebird | D12: =952.002+512.6146 -> 1464.6166 | E12: 32.4 | F12: =E12*D12 -> 47453.578 | G12: =28303.96+15646.4 -> 43950.36 | H12: =G12/D12 -> 30.008099 | I12: =F12-G12 -> 3503.2178 | J12: =E12-H12 -> 2.391901 | K12: 45321 | L12: =DAYS360(K12,$C$1) -> 38 | M12: =(I12/G12) -> 0.079708513 | N12: 28 | O12: 94 | P12: 81 | Q12: 28.39 | R12: =Q12*0.93 -> 26.4027 | S12: 29.78 | T12: =Q12*1.25 -> 35.4875 | U12: =Q12*1.5 -> 42.585 | V12: =Q12*2 -> 56.78 | W12: =H12-(H12*0.07) -> 27.907532 | X12: 30 | Y12: =(X12-H12)/H12 -> -0.0002698954 | Z12: =F12/F$19 -> 0.083447477 | AB12: 45421 | AC12: 99 | AD12: Bought day 2 after b/o.
A13: IOT | B13: Long | C13: Samsara | D13: =846.327+640.0668 -> 1486.3938 | E13: 39.16 | F13: =E13*D13 -> 58207.181 | G13: =30020.93+21858.29 -> 51879.22 | H13: =G13/D13 -> 34.902742 | I13: =F13-G13 -> 6327.9612 | J13: =E13-H13 -> 4.2572575 | K13: 45331 | L13: =DAYS360(K13,$C$1) -> 29 | M13: =(I13/G13) -> 0.12197487 | N13: 46 | O13: 83 | P13: 81 | Q13: 32.41 | R13: =Q13*0.93 -> 30.1413 | S13: 30.71 | T13: =Q13*1.25 -> 40.5125 | U13: =Q13*1.5 -> 48.615 | V13: =Q13*2 -> 64.82 | W13: =H13-(H13*0.07) -> 32.45955 | X13: 32.75 | Y13: =(X13-H13)/H13 -> -0.061678318 | Z13: =F13/F$19 -> 0.10235777 | AB13: 45443 | AC13: 87 | AD13: Broke out of consolidation above pivot.
A14: BPMC | B14: Long | C14: Blueprint Med | D14: =464.2554+269.0604 -> 733.3158 | E14: 92.3 | F14: =E14*D14 -> 67685.048 | G14: =45518.9+25760.58 -> 71279.48 | H14: =G14/D14 -> 97.201615 | I14: =F14-G14 -> -3594.4317 | J14: =E14-H14 -> -4.9016149 | K14: 45349 | L14: =DAYS360(K14,$C$1) -> 11 | M14: =(I14/G14) -> -0.050427299 | N14: 6 | O14: 95 | P14: 34 | Q14: 94.47 | R14: =Q14*0.93 -> 87.8571 | S14: 80.42 | T14: =Q14*1.25 -> 118.0875 | U14: =Q14*1.5 -> 141.705 | V14: =Q14*2 -> 188.94 | W14: =H14-(H14*0.07) -> 90.397502 | X14: 90 | Y14: =(X14-H14)/H14 -> -0.074089457 | Z14: =F14/F$19 -> 0.11902467 | AB14: 45413 | AC14: 82 | AD14: Bought the b/o day.
F15: =E15*D15 -> 0 | H15: =G15/D15 -> #DIV/0! | I15: =F15-G15 -> 0 | J15: =E15-H15 -> #DIV/0! | L15: =DAYS360(K15,$C$1) -> 44708 | M15: =(I15/G15) -> #DIV/0! | R15: =Q15*0.93 -> 0 | T15: =Q15*1.25 -> 0 | U15: =Q15*1.5 -> 0 | V15: =Q15*2 -> 0 | W15: =H15-(H15*0.07) -> #DIV/0! | Y15: =(X15-H15)/H15 -> #DIV/0! | Z15: =F15/F$19 -> 0
A16: BIL | B16: Long | C16: Tbill ETF | D16: 277.4286 | E16: 91.53 | F16: =E16*D16 -> 25393.04 | G16: 25401.36 | H16: =G16/D16 -> 91.559991 | I16: =F16-G16 -> -8.320242 | J16: =E16-H16 -> -0.029990571 | M16: =(I16/G16) -> -0.00032755104 | R16: =Q16*0.93 -> 0 | T16: =Q16*1.25 -> 0 | U16: =Q16*1.5 -> 0 | V16: =Q16*2 -> 0 | W16: =H16-(H16*0.07) -> 85.150791 | Y16: =(X16-H16)/H16 -> -1 | Z16: =F16/F$19 -> 0.044653853
A17: Sub-Total | F17: =SUM(F6:F16) -> 482466.02 | G17: =SUM(G6:G16) -> 367759.22 | I17: =SUM(I6:I16) -> 114706.8
D18: Cash, other | F18: 86198 | G18: =F18/F19 -> 0.15157984
D19: Total | F19: =SUM(F17:F18) -> 568664.02
H20: Last week's close | I20: ='03-01-24'!F19 -> 591770.7 | K20: 45291 | L20: 476160.6
A21: * | H21: Week's change | I21: =(F19-I20)/I20 -> -0.039046678 | K21: chg % | L21: =(F19-L20)/L20 -> 0.19426937
M23: days
A24: 2024 Closed Trades - Managed Acct | D24: Qty | E24: Cost/sh | F24: $ cost | G24: $Proc | H24: Proc/sh | I24: Profit/loss | J24: % | K24: Date purch | L24: Date sold | M24: held | P24: Comments
A25: YELP | B25: Long | C25: Yelp Inc | D25: 808.573 | E25: =F25/D25 -> 47.428062 | F25: 38349.05 | G25: 35186.18 | H25: =G25/D25 -> 43.516392 | I25: =G25-F25 -> -3162.87 | J25: =I25/F25 -> -0.082475837 | K25: 45286 | L25: 45302 | M25: =DAYS360(K25,L25) -> 15 | O25: Closed below stop for 2 days.
A26: TS | B26: Long | C26: Tenaris | D26: 1166.935 | E26: =F26/D26 -> 35.085005 | F26: 40941.92 | G26: 36634.59 | H26: =G26/D26 -> 31.393857 | I26: =G26-F26 -> -4307.33 | J26: =I26/F26 -> -0.10520586 | K26: 45233 | L26: 45307 | M26: =DAYS360(K26,L26) -> 73
A27: MNSO | B27: Long | C27: Minoso | D27: =1211.7123+804.6763 -> 2016.3886 | E27: =F27/D27 -> 20.49104 | F27: 41317.9 | G27: 42071.53 | H27: =G27/D27 -> 20.864793 | I27: =G27-F27 -> 753.63 | J27: =I27/F27 -> 0.018239794 | K27: 45135 | L27: 45308 | M27: =DAYS360(K27,L27) -> 169 | O27: Totally blew this trade. Had a nearly 50% profit.
A28: ACMR | B28: Long | C28: ACM Research | D28: =1339.9646+918.07 -> 2258.0346 | E28: =F28/D28 -> 21.193736 | F28: =28457.8+19398.39 -> 47856.19 | G28: 39178.27 | H28: =G28/D28 -> 17.350607 | I28: =G28-F28 -> -8677.92 | J28: =I28/F28 -> -0.18133328 | K28: 45302 | L28: 45322 | M28: =DAYS360(K28,L28) -> 20
A29: MDB | B29: Long | C29: MongoDB | D29: 126.054 | E29: =F29/D29 -> 450.27964 | F29: 56759.55 | G29: 54939.36 | H29: =G29/D29 -> 435.83988 | I29: =G29-F29 -> -1820.19 | J29: =I29/F29 -> -0.032068436 | K29: 45327 | L29: 45342 | M29: =DAYS360(K29,L29) -> 15 | O29: Stopped out.
A30: VKTX | B30: Long | C30: Viking Therap | D30: 808.6324 | E30: =F30/D30 -> 21.530005 | F30: 17409.86 | G30: 28227.27 | H30: =G30/D30 -> 34.907419 | I30: =G30-F30 -> 10817.41 | J30: =I30/F30 -> 0.62133814 | K30: 45309 | L30: 45343 | M30: =DAYS360(K30,L30) -> 33 | O30: Took partial profit.
A31: BIRK | B31: Long | C31: Birkenstock Hldg | D31: =567.3728+414.8485 -> 982.2213 | E31: =F31/D31 -> 52.971342 | F31: 52029.58 | G31: 47202.25 | H31: =G31/D31 -> 48.056634 | I31: =G31-F31 -> -4827.33 | J31: =I31/F31 -> -0.092780491 | K31: 45344 | L31: 45351 | M31: =DAYS360(K31,L31) -> 7 | O31: Stopped out after earnings.
A32: DDOG | B32: Long | C32: Datadog | D32: =308.2955+142.5312 -> 450.8267 | E32: =F32/D32 -> 130.66999 | F32: 58909.52 | G32: 55702.82 | H32: =G32/D32 -> 123.55706 | I32: =G32-F32 -> -3206.7 | J32: =I32/F32 -> -0.054434326 | K32: 45286 | L32: 45356 | M32: =DAYS360(K32,L32) -> 69 | O32: Broke 50dma
I37: =SUM(I25:I31) -> -11224.6
J39: Avg
H40: # of losses | I40: 5 | J40: -0.0914
H41: # of wins | I41: 2 | J41: 0.3198

Sheet 03-15-24
C1: 45366
C3: MANAGED ACCT | X3: Current | AC3: IBD
H4: Cost | J4: P/L | N4: Group | P4: EPS | R4: pivot | S4: last | W4: cost | X4: Stop | Y4: Stop | Z4: % | AB4: EPS | AC4: Comp
A5: Symbol | B5: Position | C5: Name | D5: Qty | E5: Current | F5: Value | G5: Cost | H5: per share | I5: P/L $ | J5: per sh | K5: Date purch | L5: days held | M5: % incr | N5: Rank | O5: RS | P5: RS | Q5: pivot | R5: -0.07 | S5: low | T5: 0.25 | U5: 0.5 | V5: 1 | W5: -0.07 | X5: Loss | Y5: Loss% | Z5: of port | AB5: Due | AC5: Rank
A7: AXON | B7: Long | C7: Axon Enterprise | D7: 267.8431 | E7: 307.65 | F7: =E7*D7 -> 82401.93 | G7: 61166.24 | H7: =G7/D7 -> 228.36594 | I7: =F7-G7 -> 21235.69 | J7: =E7-H7 -> 79.284065 | K7: 45238 | L7: =DAYS360(K7,$C$1) -> 127 | M7: =(I7/G7) -> 0.34717991 | N7: 12 | O7: 91 | P7: 99 | Q7: 223.3 | R7: =Q7*0.93 -> 207.669 | S7: 255.68 | T7: =Q7*1.25 -> 279.125 | U7: =Q7*1.5 -> 334.95 | V7: =Q7*2 -> 446.6 | W7: =H7-(H7*0.07) -> 212.38032 | X7: 275 | Y7: =(X7-H7)/H7 -> 0.20420762 | Z7: =F7/F$19 -> 0.15101652 | AB7: 45421 | AC7: 99 | AD7: Bought as it gapped out of base on EPS.
A8: KD | B8: Long | C8: Kyndryl Hldgs | D8: =1160.2602+1046.0778 -> 2206.338 | E8: 21.63 | F8: =E8*D8 -> 47723.091 | G8: =20288.83+19170.47 -> 39459.3 | H8: =G8/D8 -> 17.884522 | I8: =F8-G8 -> 8263.7909 | J8: =E8-H8 -> 3.7454782 | K8: 45243 | L8: =DAYS360(K8,$C$1) -> 122 | M8: =(I8/G8) -> 0.20942569 | N8: 44 | O8: 92 | P8: 22 | Q8: 17.32 | R8: =Q8*0.93 -> 16.1076 | S8: 20.89 | T8: =Q8*1.25 -> 21.65 | U8: =Q8*1.5 -> 25.98 | V8: =Q8*2 -> 34.64 | W8: =H8-(H8*0.07) -> 16.632605 | X8: 20.5 | Y8: =(X8-H8)/H8 -> 0.14624256 | Z8: =F8/F$19 -> 0.08746124 | AB8: 45427 | AC8: 59 | AD8: Bought after 11/08 b/o. Trading tightly here.
A9: VKTX | B9: Long | C9: Viking Therap | D9: =1286.8297+948.5633-808.6324 -> 1426.7606 | E9: 62.56 | F9: =E9*D9 -> 89258.143 | G9: =28174.78+19947.6-17409.86 -> 30712.52 | H9: =G9/D9 -> 21.52605 | I9: =F9-G9 -> 58545.623 | J9: =E9-H9 -> 41.03395 | K9: 45309 | L9: =DAYS360(K9,$C$1) -> 57 | M9: =(I9/G9) -> 1.9062462 | N9: 9 | O9: 99 | P9: 22 | Q9: 20.03 | R9: =Q9*0.93 -> 18.6279 | S9: 34.04 | T9: =Q9*1.25 -> 25.0375 | U9: =Q9*1.5 -> 30.045 | V9: =Q9*2 -> 40.06 | W9: =H9-(H9*0.07) -> 20.019226 | X9: 55 | Y9: =(X9-H9)/H9 -> 1.5550438 | Z9: =F9/F$19 -> 0.16358177 | AB9: 45406 | AC9: 67 | AD9: Bought after pivot test.
A10: AAON | B10: Long | C10: AAON | D10: =532.4164+77.1815 -> 609.5979 | E10: 81.75 | F10: =E10*D10 -> 49834.628 | G10: =38270.34+5640.4 -> 43910.74 | H10: =G10/D10 -> 72.032302 | I10: =F10-G10 -> 5923.8883 | J10: =E10-H10 -> 9.7176981 | K10: 45313 | L10: =DAYS360(K10,$C$1) -> 53 | M10: =(I10/G10) -> 0.1349075 | N10: 33 | O10: 86 | P10: 96 | Q10: 71.39 | R10: =Q10*0.93 -> 66.3927 | S10: 78.07 | T10: =Q10*1.25 -> 89.2375 | U10: =Q10*1.5 -> 107.085 | V10: =Q10*2 -> 142.78 | W10: =H10-(H10*0.07) -> 66.990041 | X10: 77 | Y10: =(X10-H10)/H10 -> 0.068964866 | Z10: =F10/F$19 -> 0.091331016 | AB10: 45414 | AC10: 96 | AD10: Bought after pivot test.
A11: BLBD | B11: Long | C11: Bluebird | D11: =952.002+512.6146 -> 1464.6166 | E11: 31.8 | F11: =E11*D11 -> 46574.808 | G11: =28303.96+15646.4 -> 43950.36 | H11: =G11/D11 -> 30.008099 | I11: =F11-G11 -> 2624.4479 | J11: =E11-H11 -> 1.791901 | K11: 45321 | L11: =DAYS360(K11,$C$1) -> 45 | M11: =(I11/G11) -> 0.059713911 | N11: 30 | O11: 93 | P11: 81 | Q11: 28.39 | R11: =Q11*0.93 -> 26.4027 | S11: 29.78 | T11: =Q11*1.25 -> 35.4875 | U11: =Q11*1.5 -> 42.585 | V11: =Q11*2 -> 56.78 | W11: =H11-(H11*0.07) -> 27.907532 | X11: 30 | Y11: =(X11-H11)/H11 -> -0.0002698954 | Z11: =F11/F$19 -> 0.085356802 | AB11: 45421 | AC11: 99 | AD11: Bought day 2 after b/o.
A12: BPMC | B12: Long | C12: Blueprint Med | D12: =464.2554+269.0604 -> 733.3158 | E12: 90.5 | F12: =E12*D12 -> 66365.08 | G12: =45518.9+25760.58 -> 71279.48 | H12: =G12/D12 -> 97.201615 | I12: =F12-G12 -> -4914.4001 | J12: =E12-H12 -> -6.7016149 | K12: 45349 | L12: =DAYS360(K12,$C$1) -> 18 | M12: =(I12/G12) -> -0.06894551 | N12: 9 | O12: 94 | P12: 34 | Q12: 94.47 | R12: =Q12*0.93 -> 87.8571 | S12: 80.42 | T12: =Q12*1.25 -> 118.0875 | U12: =Q12*1.5 -> 141.705 | V12: =Q12*2 -> 188.94 | W12: =H12-(H12*0.07) -> 90.397502 | X12: 90 | Y12: =(X12-H12)/H12 -> -0.074089457 | Z12: =F12/F$19 -> 0.12162607 | AB12: 45413 | AC12: 84 | AD12: Bought the b/o day.
F13: =E13*D13 -> 0 | H13: =G13/D13 -> #DIV/0! | I13: =F13-G13 -> 0 | J13: =E13-H13 -> #DIV/0! | L13: =DAYS360(K13,$C$1) -> 44715 | M13: =(I13/G13) -> #DIV/0! | R13: =Q13*0.93 -> 0 | T13: =Q13*1.25 -> 0 | U13: =Q13*1.5 -> 0 | V13: =Q13*2 -> 0 | W13: =H13-(H13*0.07) -> #DIV/0! | Y13: =(X13-H13)/H13 -> #DIV/0! | Z13: =F13/F$19 -> 0
F14: =E14*D14 -> 0 | H14: =G14/D14 -> #DIV/0! | I14: =F14-G14 -> 0 | J14: =E14-H14 -> #DIV/0! | L14: =DAYS360(K14,$C$1) -> 44715 | M14: =(I14/G14) -> #DIV/0! | R14: =Q14*0.93 -> 0 | T14: =Q14*1.25 -> 0 | U14: =Q14*1.5 -> 0 | V14: =Q14*2 -> 0 | W14: =H14-(H14*0.07) -> #DIV/0! | Y14: =(X14-H14)/H14 -> #DIV/0! | Z14: =F14/F$19 -> 0
F15: =E15*D15 -> 0 | H15: =G15/D15 -> #DIV/0! | I15: =F15-G15 -> 0 | J15: =E15-H15 -> #DIV/0! | L15: =DAYS360(K15,$C$1) -> 44715 | M15: =(I15/G15) -> #DIV/0! | R15: =Q15*0.93 -> 0 | T15: =Q15*1.25 -> 0 | U15: =Q15*1.5 -> 0 | V15: =Q15*2 -> 0 | W15: =H15-(H15*0.07) -> #DIV/0! | Y15: =(X15-H15)/H15 -> #DIV/0! | Z15: =F15/F$19 -> 0
A16: BIL | B16: Long | C16: Tbill ETF | D16: 277.4286 | E16: 91.63 | F16: =E16*D16 -> 25420.783 | G16: 25401.36 | H16: =G16/D16 -> 91.559991 | I16: =F16-G16 -> 19.422618 | J16: =E16-H16 -> 0.070009429 | M16: =(I16/G16) -> 0.00076462906 | R16: =Q16*0.93 -> 0 | T16: =Q16*1.25 -> 0 | U16: =Q16*1.5 -> 0 | V16: =Q16*2 -> 0 | W16: =H16-(H16*0.07) -> 85.150791 | Y16: =(X16-H16)/H16 -> -1 | Z16: =F16/F$19 -> 0.046588205
A17: Sub-Total | F17: =SUM(F6:F16) -> 407578.46 | G17: =SUM(G6:G16) -> 315880 | I17: =SUM(I6:I16) -> 91698.463
D18: Cash, other | F18: 138070 | G18: =F18/F19 -> 0.25303837
D19: Total | F19: =SUM(F17:F18) -> 545648.46
H20: Last week's close | I20: ='03-08-24'!F19 -> 568664.02 | K20: 45291 | L20: 476160.6
A21: * | H21: Week's change | I21: =(F19-I20)/I20 -> -0.040473036 | K21: chg % | L21: =(F19-L20)/L20 -> 0.14593367
M23: days
A24: 2024 Closed Trades - Managed Acct | D24: Qty | E24: Cost/sh | F24: $ cost | G24: $Proc | H24: Proc/sh | I24: Profit/loss | J24: % | K24: Date purch | L24: Date sold | M24: held | P24: Comments
A25: YELP | B25: Long | C25: Yelp Inc | D25: 808.573 | E25: =F25/D25 -> 47.428062 | F25: 38349.05 | G25: 35186.18 | H25: =G25/D25 -> 43.516392 | I25: =G25-F25 -> -3162.87 | J25: =I25/F25 -> -0.082475837 | K25: 45286 | L25: 45302 | M25: =DAYS360(K25,L25) -> 15 | O25: Closed below stop for 2 days.
A26: TS | B26: Long | C26: Tenaris | D26: 1166.935 | E26: =F26/D26 -> 35.085005 | F26: 40941.92 | G26: 36634.59 | H26: =G26/D26 -> 31.393857 | I26: =G26-F26 -> -4307.33 | J26: =I26/F26 -> -0.10520586 | K26: 45233 | L26: 45307 | M26: =DAYS360(K26,L26) -> 73
A27: MNSO | B27: Long | C27: Minoso | D27: =1211.7123+804.6763 -> 2016.3886 | E27: =F27/D27 -> 20.49104 | F27: 41317.9 | G27: 42071.53 | H27: =G27/D27 -> 20.864793 | I27: =G27-F27 -> 753.63 | J27: =I27/F27 -> 0.018239794 | K27: 45135 | L27: 45308 | M27: =DAYS360(K27,L27) -> 169 | O27: Totally blew this trade. Had a nearly 50% profit.
A28: ACMR | B28: Long | C28: ACM Research | D28: =1339.9646+918.07 -> 2258.0346 | E28: =F28/D28 -> 21.193736 | F28: =28457.8+19398.39 -> 47856.19 | G28: 39178.27 | H28: =G28/D28 -> 17.350607 | I28: =G28-F28 -> -8677.92 | J28: =I28/F28 -> -0.18133328 | K28: 45302 | L28: 45322 | M28: =DAYS360(K28,L28) -> 20
A29: MDB | B29: Long | C29: MongoDB | D29: 126.054 | E29: =F29/D29 -> 450.27964 | F29: 56759.55 | G29: 54939.36 | H29: =G29/D29 -> 435.83988 | I29: =G29-F29 -> -1820.19 | J29: =I29/F29 -> -0.032068436 | K29: 45327 | L29: 45342 | M29: =DAYS360(K29,L29) -> 15 | O29: Stopped out.
A30: VKTX | B30: Long | C30: Viking Therap | D30: 808.6324 | E30: =F30/D30 -> 21.530005 | F30: 17409.86 | G30: 28227.27 | H30: =G30/D30 -> 34.907419 | I30: =G30-F30 -> 10817.41 | J30: =I30/F30 -> 0.62133814 | K30: 45309 | L30: 45343 | M30: =DAYS360(K30,L30) -> 33 | O30: Took partial profit.
A31: BIRK | B31: Long | C31: Birkenstock Hldg | D31: =567.3728+414.8485 -> 982.2213 | E31: =F31/D31 -> 52.971342 | F31: 52029.58 | G31: 47202.25 | H31: =G31/D31 -> 48.056634 | I31: =G31-F31 -> -4827.33 | J31: =I31/F31 -> -0.092780491 | K31: 45344 | L31: 45351 | M31: =DAYS360(K31,L31) -> 7 | O31: Stopped out after earnings.
A32: DDOG | B32: Long | C32: Datadog | D32: =308.2955+142.5312 -> 450.8267 | E32: =F32/D32 -> 130.66999 | F32: 58909.52 | G32: 55702.82 | H32: =G32/D32 -> 123.55706 | I32: =G32-F32 -> -3206.7 | J32: =I32/F32 -> -0.054434326 | K32: 45286 | L32: 45356 | M32: =DAYS360(K32,L32) -> 69 | O32: Broke 50dma
A33: IOT | B33: Long | C33: Samsara | D33: =846.327+640.0668 -> 1486.3938 | E33: =F33/D33 -> 34.902742 | F33: =30020.93+21858.29 -> 51879.22 | G33: 51882.03 | H33: =G33/D33 -> 34.904633 | I33: =G33-F33 -> 2.81 | J33: =I33/F33 -> 5.4164268e-05 | K33: 45331 | L33: 45366 | M33: =DAYS360(K33,L33) -> 36 | O33: B/o did not follow through. Sold at my cost.
I37: =SUM(I25:I31) -> -11224.6
J39: Avg
H40: # of losses | I40: 5 | J40: -0.0914
H41: # of wins | I41: 2 | J41: 0.3198

Sheet 03-22-24
C1: 45373
C3: MANAGED ACCT | X3: Current | AC3: IBD
H4: Cost | J4: P/L | N4: Group | P4: EPS | R4: pivot | S4: last | W4: cost | X4: Stop | Y4: Stop | Z4: % | AB4: EPS | AC4: Comp
A5: Symbol | B5: Position | C5: Name | D5: Qty | E5: Current | F5: Value | G5: Cost | H5: per share | I5: P/L $ | J5: per sh | K5: Date purch | L5: days held | M5: % incr | N5: Rank | O5: RS | P5: RS | Q5: pivot | R5: -0.07 | S5: low | T5: 0.25 | U5: 0.5 | V5: 1 | W5: -0.07 | X5: Loss | Y5: Loss% | Z5: of port | AB5: Due | AC5: Rank
A7: AXON | B7: Long | C7: Axon Enterprise | D7: 267.8431 | E7: 316.32 | F7: =E7*D7 -> 84724.129 | G7: 61166.24 | H7: =G7/D7 -> 228.36594 | I7: =F7-G7 -> 23557.889 | J7: =E7-H7 -> 87.954065 | K7: 45238 | L7: =DAYS360(K7,$C$1) -> 134 | M7: =(I7/G7) -> 0.38514529 | N7: 14 | O7: 92 | P7: 99 | Q7: 223.3 | R7: =Q7*0.93 -> 207.669 | S7: 255.68 | T7: =Q7*1.25 -> 279.125 | U7: =Q7*1.5 -> 334.95 | V7: =Q7*2 -> 446.6 | W7: =H7-(H7*0.07) -> 212.38032 | X7: 290 | Y7: =(X7-H7)/H7 -> 0.26989168 | Z7: =F7/F$19 -> 0.14703455 | AB7: 45421 | AC7: 99 | AD7: Bought as it gapped out of base on EPS.
A8: VKTX | B8: Long | C8: Viking Therap | D8: =1286.8297+948.5633-808.6324 -> 1426.7606 | E8: 69.55 | F8: =E8*D8 -> 99231.2 | G8: =28174.78+19947.6-17409.86 -> 30712.52 | H8: =G8/D8 -> 21.52605 | I8: =F8-G8 -> 68518.68 | J8: =E8-H8 -> 48.02395 | K8: 45309 | L8: =DAYS360(K8,$C$1) -> 64 | M8: =(I8/G8) -> 2.230969 | N8: 10 | O8: 99 | P8: 22 | Q8: 20.03 | R8: =Q8*0.93 -> 18.6279 | S8: 34.04 | T8: =Q8*1.25 -> 25.0375 | U8: =Q8*1.5 -> 30.045 | V8: =Q8*2 -> 40.06 | W8: =H8-(H8*0.07) -> 20.019226 | X8: 55 | Y8: =(X8-H8)/H8 -> 1.5550438 | Z8: =F8/F$19 -> 0.17221085 | AB8: 45406 | AC8: 67 | AD8: Bought after pivot test.
A9: AAON | B9: Long | C9: AAON | D9: =532.4164+77.1815 -> 609.5979 | E9: 86.45 | F9: =E9*D9 -> 52699.738 | G9: =38270.34+5640.4 -> 43910.74 | H9: =G9/D9 -> 72.032302 | I9: =F9-G9 -> 8788.9985 | J9: =E9-H9 -> 14.417698 | K9: 45313 | L9: =DAYS360(K9,$C$1) -> 60 | M9: =(I9/G9) -> 0.20015601 | N9: 31 | O9: 89 | P9: 96 | Q9: 71.39 | R9: =Q9*0.93 -> 66.3927 | S9: 78.71 | T9: =Q9*1.25 -> 89.2375 | U9: =Q9*1.5 -> 107.085 | V9: =Q9*2 -> 142.78 | W9: =H9-(H9*0.07) -> 66.990041 | X9: 77 | Y9: =(X9-H9)/H9 -> 0.068964866 | Z9: =F9/F$19 -> 0.091457796 | AB9: 45414 | AC9: 98 | AD9: Bought after pivot test.
A10: BLBD | B10: Long | C10: Bluebird | D10: =952.002+512.6146 -> 1464.6166 | E10: 36.33 | F10: =E10*D10 -> 53209.521 | G10: =28303.96+15646.4 -> 43950.36 | H10: =G10/D10 -> 30.008099 | I10: =F10-G10 -> 9259.1611 | J10: =E10-H10 -> 6.321901 | K10: 45321 | L10: =DAYS360(K10,$C$1) -> 52 | M10: =(I10/G10) -> 0.21067316 | N10: 29 | O10: 95 | P10: 81 | Q10: 28.39 | R10: =Q10*0.93 -> 26.4027 | S10: 31.42 | T10: =Q10*1.25 -> 35.4875 | U10: =Q10*1.5 -> 42.585 | V10: =Q10*2 -> 56.78 | W10: =H10-(H10*0.07) -> 27.907532 | X10: 32 | Y10: =(X10-H10)/H10 -> 0.066378778 | Z10: =F10/F$19 -> 0.092342498 | AB10: 45421 | AC10: 99 | AD10: Bought day 2 after b/o.
A11: BPMC | B11: Long | C11: Blueprint Med | D11: =464.2554+269.0604 -> 733.3158 | E11: 87.04 | F11: =E11*D11 -> 63827.807 | G11: =45518.9+25760.58 -> 71279.48 | H11: =G11/D11 -> 97.201615 | I11: =F11-G11 -> -7451.6728 | J11: =E11-H11 -> -10.161615 | K11: 45349 | L11: =DAYS360(K11,$C$1) -> 25 | M11: =(I11/G11) -> -0.10454163 | N11: 10 | O11: 92 | P11: 33 | Q11: 94.47 | R11: =Q11*0.93 -> 87.8571 | S11: 80.42 | T11: =Q11*1.25 -> 118.0875 | U11: =Q11*1.5 -> 141.705 | V11: =Q11*2 -> 188.94 | W11: =H11-(H11*0.07) -> 90.397502 | X11: 90 | Y11: =(X11-H11)/H11 -> -0.074089457 | Z11: =F11/F$19 -> 0.11077001 | AB11: 45413 | AC11: 79 | AD11: Bought the b/o day.
A12: UFPT | B12: Long | C12: UFP Technologies | D12: 268.5725 | E12: 244.6 | F12: =E12*D12 -> 65692.833 | G12: 54466.53 | H12: =G12/D12 -> 202.8001 | I12: =F12-G12 -> 11226.303 | J12: =E12-H12 -> 41.799899 | K12: 45370 | L12: =DAYS360(K12,$C$1) -> 3 | M12: =(I12/G12) -> 0.2061138 | N12: 63 | O12: 94 | P12: 94 | Q12: 200 | R12: =Q12*0.93 -> 186 | S12: 188.5 | T12: =Q12*1.25 -> 250 | U12: =Q12*1.5 -> 300 | V12: =Q12*2 -> 400 | W12: =H12-(H12*0.07) -> 188.60409 | X12: 202 | Y12: =(X12-H12)/H12 -> -0.0039452669 | Z12: =F12/F$19 -> 0.11400667 | AB12: 45412 | AC12: 95 | AD12: Bought the test of the 10wma. First pullback.
F13: =E13*D13 -> 0 | H13: =G13/D13 -> #DIV/0! | I13: =F13-G13 -> 0 | J13: =E13-H13 -> #DIV/0! | L13: =DAYS360(K13,$C$1) -> 44722 | M13: =(I13/G13) -> #DIV/0! | R13: =Q13*0.93 -> 0 | T13: =Q13*1.25 -> 0 | U13: =Q13*1.5 -> 0 | V13: =Q13*2 -> 0 | W13: =H13-(H13*0.07) -> #DIV/0! | Y13: =(X13-H13)/H13 -> #DIV/0! | Z13: =F13/F$19 -> 0
F14: =E14*D14 -> 0 | H14: =G14/D14 -> #DIV/0! | I14: =F14-G14 -> 0 | J14: =E14-H14 -> #DIV/0! | L14: =DAYS360(K14,$C$1) -> 44722 | M14: =(I14/G14) -> #DIV/0! | R14: =Q14*0.93 -> 0 | T14: =Q14*1.25 -> 0 | U14: =Q14*1.5 -> 0 | V14: =Q14*2 -> 0 | W14: =H14-(H14*0.07) -> #DIV/0! | Y14: =(X14-H14)/H14 -> #DIV/0! | Z14: =F14/F$19 -> 0
F15: =E15*D15 -> 0 | H15: =G15/D15 -> #DIV/0! | I15: =F15-G15 -> 0 | J15: =E15-H15 -> #DIV/0! | L15: =DAYS360(K15,$C$1) -> 44722 | M15: =(I15/G15) -> #DIV/0! | R15: =Q15*0.93 -> 0 | T15: =Q15*1.25 -> 0 | U15: =Q15*1.5 -> 0 | V15: =Q15*2 -> 0 | W15: =H15-(H15*0.07) -> #DIV/0! | Y15: =(X15-H15)/H15 -> #DIV/0! | Z15: =F15/F$19 -> 0
A16: BIL | B16: Long | C16: Tbill ETF | D16: 277.4286 | E16: 91.71 | F16: =E16*D16 -> 25442.977 | G16: 25401.36 | H16: =G16/D16 -> 91.559991 | I16: =F16-G16 -> 41.616906 | J16: =E16-H16 -> 0.15000943 | M16: =(I16/G16) -> 0.0016383731 | R16: =Q16*0.93 -> 0 | T16: =Q16*1.25 -> 0 | U16: =Q16*1.5 -> 0 | V16: =Q16*2 -> 0 | W16: =H16-(H16*0.07) -> 85.150791 | Y16: =(X16-H16)/H16 -> -1 | Z16: =F16/F$19 -> 0.044155031
A17: Sub-Total | F17: =SUM(F6:F16) -> 444828.21 | G17: =SUM(G6:G16) -> 330887.23 | I17: =SUM(I6:I16) -> 113940.98
D18: Cash, other | F18: 131391 | G18: =F18/F19 -> 0.2280226
D19: Total | F19: =SUM(F17:F18) -> 576219.21
H20: Last week's close | I20: ='03-15-24'!F19 -> 545648.46 | K20: 45291 | L20: 476160.6
A21: * | H21: Week's change | I21: =(F19-I20)/I20 -> 0.056026445 | K21: chg % | L21: =(F19-L20)/L20 -> 0.21013626
M23: days
A24: 2024 Closed Trades - Managed Acct | D24: Qty | E24: Cost/sh | F24: $ cost | G24: $Proc | H24: Proc/sh | I24: Profit/loss | J24: % | K24: Date purch | L24: Date sold | M24: held | P24: Comments
A25: YELP | B25: Long | C25: Yelp Inc | D25: 808.573 | E25: =F25/D25 -> 47.428062 | F25: 38349.05 | G25: 35186.18 | H25: =G25/D25 -> 43.516392 | I25: =G25-F25 -> -3162.87 | J25: =I25/F25 -> -0.082475837 | K25: 45286 | L25: 45302 | M25: =DAYS360(K25,L25) -> 15 | O25: Closed below stop for 2 days.
A26: TS | B26: Long | C26: Tenaris | D26: 1166.935 | E26: =F26/D26 -> 35.085005 | F26: 40941.92 | G26: 36634.59 | H26: =G26/D26 -> 31.393857 | I26: =G26-F26 -> -4307.33 | J26: =I26/F26 -> -0.10520586 | K26: 45233 | L26: 45307 | M26: =DAYS360(K26,L26) -> 73
A27: MNSO | B27: Long | C27: Minoso | D27: =1211.7123+804.6763 -> 2016.3886 | E27: =F27/D27 -> 20.49104 | F27: 41317.9 | G27: 42071.53 | H27: =G27/D27 -> 20.864793 | I27: =G27-F27 -> 753.63 | J27: =I27/F27 -> 0.018239794 | K27: 45135 | L27: 45308 | M27: =DAYS360(K27,L27) -> 169 | O27: Totally blew this trade. Had a nearly 50% profit.
A28: ACMR | B28: Long | C28: ACM Research | D28: =1339.9646+918.07 -> 2258.0346 | E28: =F28/D28 -> 21.193736 | F28: =28457.8+19398.39 -> 47856.19 | G28: 39178.27 | H28: =G28/D28 -> 17.350607 | I28: =G28-F28 -> -8677.92 | J28: =I28/F28 -> -0.18133328 | K28: 45302 | L28: 45322 | M28: =DAYS360(K28,L28) -> 20
A29: MDB | B29: Long | C29: MongoDB | D29: 126.054 | E29: =F29/D29 -> 450.27964 | F29: 56759.55 | G29: 54939.36 | H29: =G29/D29 -> 435.83988 | I29: =G29-F29 -> -1820.19 | J29: =I29/F29 -> -0.032068436 | K29: 45327 | L29: 45342 | M29: =DAYS360(K29,L29) -> 15 | O29: Stopped out.
A30: VKTX | B30: Long | C30: Viking Therap | D30: 808.6324 | E30: =F30/D30 -> 21.530005 | F30: 17409.86 | G30: 28227.27 | H30: =G30/D30 -> 34.907419 | I30: =G30-F30 -> 10817.41 | J30: =I30/F30 -> 0.62133814 | K30: 45309 | L30: 45343 | M30: =DAYS360(K30,L30) -> 33 | O30: Took partial profit.
A31: BIRK | B31: Long | C31: Birkenstock Hldg | D31: =567.3728+414.8485 -> 982.2213 | E31: =F31/D31 -> 52.971342 | F31: 52029.58 | G31: 47202.25 | H31: =G31/D31 -> 48.056634 | I31: =G31-F31 -> -4827.33 | J31: =I31/F31 -> -0.092780491 | K31: 45344 | L31: 45351 | M31: =DAYS360(K31,L31) -> 7 | O31: Stopped out after earnings.
A32: DDOG | B32: Long | C32: Datadog | D32: =308.2955+142.5312 -> 450.8267 | E32: =F32/D32 -> 130.66999 | F32: 58909.52 | G32: 55702.82 | H32: =G32/D32 -> 123.55706 | I32: =G32-F32 -> -3206.7 | J32: =I32/F32 -> -0.054434326 | K32: 45286 | L32: 45356 | M32: =DAYS360(K32,L32) -> 69 | O32: Broke 50dma
A33: IOT | B33: Long | C33: Samsara | D33: =846.327+640.0668 -> 1486.3938 | E33: =F33/D33 -> 34.902742 | F33: =30020.93+21858.29 -> 51879.22 | G33: 51882.03 | H33: =G33/D33 -> 34.904633 | I33: =G33-F33 -> 2.81 | J33: =I33/F33 -> 5.4164268e-05 | K33: 45331 | L33: 45366 | M33: =DAYS360(K33,L33) -> 36 | O33: B/o did not follow through. Sold at my cost.
A34: KD | B34: Long | C34: Kyndryl Hldgs | D34: =1160.2602+1046.0778 -> 2206.338 | E34: =F34/D34 -> 17.884522 | F34: =20288.83+19170.47 -> 39459.3 | G34: 47805.42 | H34: =G34/D34 -> 21.667315 | I34: =G34-F34 -> 8346.12 | J34: =I34/F34 -> 0.21151212 | K34: 45243 | L34: 45373 | M34: =DAYS360(K34,L34) -> 129 | O34: Took profit.
I37: =SUM(I25:I36) -> -6082.37
J39: Avg
H40: # of losses | I40: 6 | J40: -0.0914
H41: # of wins | I41: 4 | J41: 0.2128

Sheet 03-29-24
C1: 45380
C3: MANAGED ACCT | X3: Current | AC3: IBD
H4: Cost | J4: P/L | N4: Group | P4: EPS | R4: pivot | S4: last | W4: cost | X4: Stop | Y4: Stop | Z4: % | AB4: EPS | AC4: Comp
A5: Symbol | B5: Position | C5: Name | D5: Qty | E5: Current | F5: Value | G5: Cost | H5: per share | I5: P/L $ | J5: per sh | K5: Date purch | L5: days held | M5: % incr | N5: Rank | O5: RS | P5: RS | Q5: pivot | R5: -0.07 | S5: low | T5: 0.25 | U5: 0.5 | V5: 1 | W5: -0.07 | X5: Loss | Y5: Loss% | Z5: of port | AB5: Due | AC5: Rank
A7: AXON | B7: Long | C7: Axon Enterprise | D7: 267.8431 | E7: 312.88 | F7: =E7*D7 -> 83802.749 | G7: 61166.24 | H7: =G7/D7 -> 228.36594 | I7: =F7-G7 -> 22636.509 | J7: =E7-H7 -> 84.514065 | K7: 45238 | L7: =DAYS360(K7,$C$1) -> 141 | M7: =(I7/G7) -> 0.37008175 | N7: 14 | O7: 92 | P7: 99 | Q7: 223.3 | R7: =Q7*0.93 -> 207.669 | S7: 255.68 | T7: =Q7*1.25 -> 279.125 | U7: =Q7*1.5 -> 334.95 | V7: =Q7*2 -> 446.6 | W7: =H7-(H7*0.07) -> 212.38032 | X7: 290 | Y7: =(X7-H7)/H7 -> 0.26989168 | Z7: =F7/F$19 -> 0.13804431 | AB7: 45421 | AC7: 99 | AD7: Bought as it gapped out of base on EPS.
A8: VKTX | B8: Long | C8: Viking Therap | D8: =1286.8297+948.5633-808.6324 -> 1426.7606 | E8: 82 | F8: =E8*D8 -> 116994.37 | G8: =28174.78+19947.6-17409.86 -> 30712.52 | H8: =G8/D8 -> 21.52605 | I8: =F8-G8 -> 86281.849 | J8: =E8-H8 -> 60.47395 | K8: 45309 | L8: =DAYS360(K8,$C$1) -> 71 | M8: =(I8/G8) -> 2.809338 | N8: 11 | O8: 99 | P8: 22 | Q8: 20.03 | R8: =Q8*0.93 -> 18.6279 | S8: 34.04 | T8: =Q8*1.25 -> 25.0375 | U8: =Q8*1.5 -> 30.045 | V8: =Q8*2 -> 40.06 | W8: =H8-(H8*0.07) -> 20.019226 | X8: 55 | Y8: =(X8-H8)/H8 -> 1.5550438 | Z8: =F8/F$19 -> 0.1927193 | AB8: 45406 | AC8: 75 | AD8: Bought after pivot test.
A9: AAON | B9: Long | C9: AAON | D9: =532.4164+77.1815 -> 609.5979 | E9: 88.1 | F9: =E9*D9 -> 53705.575 | G9: =38270.34+5640.4 -> 43910.74 | H9: =G9/D9 -> 72.032302 | I9: =F9-G9 -> 9794.835 | J9: =E9-H9 -> 16.067698 | K9: 45313 | L9: =DAYS360(K9,$C$1) -> 67 | M9: =(I9/G9) -> 0.2230624 | N9: 39 | O9: 89 | P9: 96 | Q9: 71.39 | R9: =Q9*0.93 -> 66.3927 | S9: 78.71 | T9: =Q9*1.25 -> 89.2375 | U9: =Q9*1.5 -> 107.085 | V9: =Q9*2 -> 142.78 | W9: =H9-(H9*0.07) -> 66.990041 | X9: 77 | Y9: =(X9-H9)/H9 -> 0.068964866 | Z9: =F9/F$19 -> 0.088466658 | AB9: 45414 | AC9: 98 | AD9: Bought after pivot test.
A10: BLBD | B10: Long | C10: Bluebird | D10: =952.002+512.6146 -> 1464.6166 | E10: 38.34 | F10: =E10*D10 -> 56153.4 | G10: =28303.96+15646.4 -> 43950.36 | H10: =G10/D10 -> 30.008099 | I10: =F10-G10 -> 12203.04 | J10: =E10-H10 -> 8.331901 | K10: 45321 | L10: =DAYS360(K10,$C$1) -> 59 | M10: =(I10/G10) -> 0.27765507 | N10: 28 | O10: 95 | P10: 81 | Q10: 28.39 | R10: =Q10*0.93 -> 26.4027 | S10: 31.42 | T10: =Q10*1.25 -> 35.4875 | U10: =Q10*1.5 -> 42.585 | V10: =Q10*2 -> 56.78 | W10: =H10-(H10*0.07) -> 27.907532 | X10: 32 | Y10: =(X10-H10)/H10 -> 0.066378778 | Z10: =F10/F$19 -> 0.092498845 | AB10: 45421 | AC10: 99 | AD10: Bought day 2 after b/o.
A11: BPMC | B11: Long | C11: Blueprint Med | D11: =464.2554+269.0604 -> 733.3158 | E11: 94.86 | F11: =E11*D11 -> 69562.337 | G11: =45518.9+25760.58 -> 71279.48 | H11: =G11/D11 -> 97.201615 | I11: =F11-G11 -> -1717.1432 | J11: =E11-H11 -> -2.3416149 | K11: 45349 | L11: =DAYS360(K11,$C$1) -> 32 | M11: =(I11/G11) -> -0.024090288 | N11: 11 | O11: 94 | P11: 33 | Q11: 94.47 | R11: =Q11*0.93 -> 87.8571 | S11: 80.42 | T11: =Q11*1.25 -> 118.0875 | U11: =Q11*1.5 -> 141.705 | V11: =Q11*2 -> 188.94 | W11: =H11-(H11*0.07) -> 90.397502 | X11: 90 | Y11: =(X11-H11)/H11 -> -0.074089457 | Z11: =F11/F$19 -> 0.11458675 | AB11: 45413 | AC11: 82 | AD11: Bought the b/o day.
A12: UFPT | B12: Long | C12: UFP Technologies | D12: 268.5725 | E12: 252.2 | F12: =E12*D12 -> 67733.984 | G12: 54466.53 | H12: =G12/D12 -> 202.8001 | I12: =F12-G12 -> 13267.454 | J12: =E12-H12 -> 49.399899 | K12: 45370 | L12: =DAYS360(K12,$C$1) -> 10 | M12: =(I12/G12) -> 0.24358913 | N12: 68 | O12: 94 | P12: 94 | Q12: 200 | R12: =Q12*0.93 -> 186 | S12: 188.5 | T12: =Q12*1.25 -> 250 | U12: =Q12*1.5 -> 300 | V12: =Q12*2 -> 400 | W12: =H12-(H12*0.07) -> 188.60409 | X12: 202 | Y12: =(X12-H12)/H12 -> -0.0039452669 | Z12: =F12/F$19 -> 0.11157499 | AB12: 45412 | AC12: 94 | AD12: Bought the test of the 10wma. First pullback.
A13: HMY | B13: Long | C13: Harmony Gold | D13: 2972.4372 | E13: 8.17 | F13: =E13*D13 -> 24284.812 | G13: 23794.37 | H13: =G13/D13 -> 8.0050034 | I13: =F13-G13 -> 490.44192 | J13: =E13-H13 -> 0.16499656 | K13: 45378 | L13: =DAYS360(K13,$C$1) -> 2 | M13: =(I13/G13) -> 0.020611679 | N13: 64 | O13: 96 | P13: 99 | Q13: 6.76 | R13: =Q13*0.93 -> 6.2868 | S13: 7.21 | T13: =Q13*1.25 -> 8.45 | U13: =Q13*1.5 -> 10.14 | V13: =Q13*2 -> 13.52 | W13: =H13-(H13*0.07) -> 7.4446532 | X13: 7.35 | Y13: =(X13-H13)/H13 -> -0.081824254 | Z13: =F13/F$19 -> 0.040003224 | AB13: 45401 | AC13: 99
A14: AEM | B14: Long | C14: Agnico-Eagle Mines | D14: 828.4023 | E14: 59.65 | F14: =E14*D14 -> 49414.197 | G14: 47623.59 | H14: =G14/D14 -> 57.488481 | I14: =F14-G14 -> 1790.6072 | J14: =E14-H14 -> 2.1615189 | K14: 45378 | L14: =DAYS360(K14,$C$1) -> 2 | M14: =(I14/G14) -> 0.037599165 | N14: 64 | O14: 69 | P14: 93 | Q14: 57.16 | R14: =Q14*0.93 -> 53.1588 | S14: 54.02 | T14: =Q14*1.25 -> 71.45 | U14: =Q14*1.5 -> 85.74 | V14: =Q14*2 -> 114.32 | W14: =H14-(H14*0.07) -> 53.464287 | X14: 54.75 | Y14: =(X14-H14)/H14 -> -0.047635302 | Z14: =F14/F$19 -> 0.081397674 | AB14: 45407 | AC14: 95 | AD14: Bought the b/o. Vol not impressive, yet. Watch.
F15: =E15*D15 -> 0 | H15: =G15/D15 -> #DIV/0! | I15: =F15-G15 -> 0 | J15: =E15-H15 -> #DIV/0! | L15: =DAYS360(K15,$C$1) -> 44729 | M15: =(I15/G15) -> #DIV/0! | R15: =Q15*0.93 -> 0 | T15: =Q15*1.25 -> 0 | U15: =Q15*1.5 -> 0 | V15: =Q15*2 -> 0 | W15: =H15-(H15*0.07) -> #DIV/0! | Y15: =(X15-H15)/H15 -> #DIV/0! | Z15: =F15/F$19 -> 0
A16: BIL | B16: Long | C16: Tbill ETF | D16: 277.4286 | E16: 91.8 | F16: =E16*D16 -> 25467.945 | G16: 25401.36 | H16: =G16/D16 -> 91.559991 | I16: =F16-G16 -> 66.58548 | J16: =E16-H16 -> 0.24000943 | M16: =(I16/G16) -> 0.0026213352 | R16: =Q16*0.93 -> 0 | T16: =Q16*1.25 -> 0 | U16: =Q16*1.5 -> 0 | V16: =Q16*2 -> 0 | W16: =H16-(H16*0.07) -> 85.150791 | Y16: =(X16-H16)/H16 -> -1 | Z16: =F16/F$19 -> 0.041952144
A17: Sub-Total | F17: =SUM(F6:F16) -> 547119.37 | G17: =SUM(G6:G16) -> 402305.19 | I17: =SUM(I6:I16) -> 144814.18
D18: Cash, other | F18: 59952 | G18: =F18/F19 -> 0.098756099
D19: Total | F19: =SUM(F17:F18) -> 607071.37
H20: Last week's close | I20: ='03-22-24'!F19 -> 576219.21 | K20: 45291 | L20: 476160.6
A21: * | H21: Week's change | I21: =(F19-I20)/I20 -> 0.053542407 | K21: chg % | L21: =(F19-L20)/L20 -> 0.27492987
M23: days
A24: 2024 Closed Trades - Managed Acct | D24: Qty | E24: Cost/sh | F24: $ cost | G24: $Proc | H24: Proc/sh | I24: Profit/loss | J24: % | K24: Date purch | L24: Date sold | M24: held | P24: Comments
A25: YELP | B25: Long | C25: Yelp Inc | D25: 808.573 | E25: =F25/D25 -> 47.428062 | F25: 38349.05 | G25: 35186.18 | H25: =G25/D25 -> 43.516392 | I25: =G25-F25 -> -3162.87 | J25: =I25/F25 -> -0.082475837 | K25: 45286 | L25: 45302 | M25: =DAYS360(K25,L25) -> 15 | O25: Closed below stop for 2 days.
A26: TS | B26: Long | C26: Tenaris | D26: 1166.935 | E26: =F26/D26 -> 35.085005 | F26: 40941.92 | G26: 36634.59 | H26: =G26/D26 -> 31.393857 | I26: =G26-F26 -> -4307.33 | J26: =I26/F26 -> -0.10520586 | K26: 45233 | L26: 45307 | M26: =DAYS360(K26,L26) -> 73
A27: MNSO | B27: Long | C27: Minoso | D27: =1211.7123+804.6763 -> 2016.3886 | E27: =F27/D27 -> 20.49104 | F27: 41317.9 | G27: 42071.53 | H27: =G27/D27 -> 20.864793 | I27: =G27-F27 -> 753.63 | J27: =I27/F27 -> 0.018239794 | K27: 45135 | L27: 45308 | M27: =DAYS360(K27,L27) -> 169 | O27: Totally blew this trade. Had a nearly 50% profit.
A28: ACMR | B28: Long | C28: ACM Research | D28: =1339.9646+918.07 -> 2258.0346 | E28: =F28/D28 -> 21.193736 | F28: =28457.8+19398.39 -> 47856.19 | G28: 39178.27 | H28: =G28/D28 -> 17.350607 | I28: =G28-F28 -> -8677.92 | J28: =I28/F28 -> -0.18133328 | K28: 45302 | L28: 45322 | M28: =DAYS360(K28,L28) -> 20
A29: MDB | B29: Long | C29: MongoDB | D29: 126.054 | E29: =F29/D29 -> 450.27964 | F29: 56759.55 | G29: 54939.36 | H29: =G29/D29 -> 435.83988 | I29: =G29-F29 -> -1820.19 | J29: =I29/F29 -> -0.032068436 | K29: 45327 | L29: 45342 | M29: =DAYS360(K29,L29) -> 15 | O29: Stopped out.
A30: VKTX | B30: Long | C30: Viking Therap | D30: 808.6324 | E30: =F30/D30 -> 21.530005 | F30: 17409.86 | G30: 28227.27 | H30: =G30/D30 -> 34.907419 | I30: =G30-F30 -> 10817.41 | J30: =I30/F30 -> 0.62133814 | K30: 45309 | L30: 45343 | M30: =DAYS360(K30,L30) -> 33 | O30: Took partial profit.
A31: BIRK | B31: Long | C31: Birkenstock Hldg | D31: =567.3728+414.8485 -> 982.2213 | E31: =F31/D31 -> 52.971342 | F31: 52029.58 | G31: 47202.25 | H31: =G31/D31 -> 48.056634 | I31: =G31-F31 -> -4827.33 | J31: =I31/F31 -> -0.092780491 | K31: 45344 | L31: 45351 | M31: =DAYS360(K31,L31) -> 7 | O31: Stopped out after earnings.
A32: DDOG | B32: Long | C32: Datadog | D32: =308.2955+142.5312 -> 450.8267 | E32: =F32/D32 -> 130.66999 | F32: 58909.52 | G32: 55702.82 | H32: =G32/D32 -> 123.55706 | I32: =G32-F32 -> -3206.7 | J32: =I32/F32 -> -0.054434326 | K32: 45286 | L32: 45356 | M32: =DAYS360(K32,L32) -> 69 | O32: Broke 50dma
A33: IOT | B33: Long | C33: Samsara | D33: =846.327+640.0668 -> 1486.3938 | E33: =F33/D33 -> 34.902742 | F33: =30020.93+21858.29 -> 51879.22 | G33: 51882.03 | H33: =G33/D33 -> 34.904633 | I33: =G33-F33 -> 2.81 | J33: =I33/F33 -> 5.4164268e-05 | K33: 45331 | L33: 45366 | M33: =DAYS360(K33,L33) -> 36 | O33: B/o did not follow through. Sold at my cost.
A34: KD | B34: Long | C34: Kyndryl Hldgs | D34: =1160.2602+1046.0778 -> 2206.338 | E34: =F34/D34 -> 17.884522 | F34: =20288.83+19170.47 -> 39459.3 | G34: 47805.42 | H34: =G34/D34 -> 21.667315 | I34: =G34-F34 -> 8346.12 | J34: =I34/F34 -> 0.21151212 | K34: 45243 | L34: 45373 | M34: =DAYS360(K34,L34) -> 129 | O34: Took profit.
I37: =SUM(I25:I36) -> -6082.37
J39: Avg
H40: # of losses | I40: 6 | J40: -0.0914
H41: # of wins | I41: 4 | J41: 0.2128

Sheet 04-05-24
C1: 45387
C3: MANAGED ACCT | X3: Current | AC3: IBD
H4: Cost | J4: P/L | N4: Group | P4: EPS | R4: pivot | S4: last | W4: cost | X4: Stop | Y4: Stop | Z4: % | AB4: EPS | AC4: Comp
A5: Symbol | B5: Position | C5: Name | D5: Qty | E5: Current | F5: Value | G5: Cost | H5: per share | I5: P/L $ | J5: per sh | K5: Date purch | L5: days held | M5: % incr | N5: Rank | O5: RS | P5: RS | Q5: pivot | R5: -0.07 | S5: low | T5: 0.25 | U5: 0.5 | V5: 1 | W5: -0.07 | X5: Loss | Y5: Loss% | Z5: of port | AB5: Due | AC5: Rank
A7: AXON | B7: Long | C7: Axon Enterprise | D7: 267.8431 | E7: 309.9 | F7: =E7*D7 -> 83004.577 | G7: 61166.24 | H7: =G7/D7 -> 228.36594 | I7: =F7-G7 -> 21838.337 | J7: =E7-H7 -> 81.534065 | K7: 45238 | L7: =DAYS360(K7,$C$1) -> 147 | M7: =(I7/G7) -> 0.35703252 | N7: 15 | O7: 92 | P7: 99 | Q7: 223.3 | R7: =Q7*0.93 -> 207.669 | S7: 255.68 | T7: =Q7*1.25 -> 279.125 | U7: =Q7*1.5 -> 334.95 | V7: =Q7*2 -> 446.6 | W7: =H7-(H7*0.07) -> 212.38032 | X7: 290 | Y7: =(X7-H7)/H7 -> 0.26989168 | Z7: =F7/F$19 -> 0.13844109 | AB7: 45421 | AC7: 99 | AD7: Bought as it gapped out of base on EPS.
A8: VKTX | B8: Long | C8: Viking Therap | D8: =1286.8297+948.5633-808.6324 -> 1426.7606 | E8: 76.45 | F8: =E8*D8 -> 109075.85 | G8: =28174.78+19947.6-17409.86 -> 30712.52 | H8: =G8/D8 -> 21.52605 | I8: =F8-G8 -> 78363.328 | J8: =E8-H8 -> 54.92395 | K8: 45309 | L8: =DAYS360(K8,$C$1) -> 77 | M8: =(I8/G8) -> 2.5515108 | N8: 13 | O8: 99 | P8: 22 | Q8: 20.03 | R8: =Q8*0.93 -> 18.6279 | S8: 34.04 | T8: =Q8*1.25 -> 25.0375 | U8: =Q8*1.5 -> 30.045 | V8: =Q8*2 -> 40.06 | W8: =H8-(H8*0.07) -> 20.019226 | X8: 55 | Y8: =(X8-H8)/H8 -> 1.5550438 | Z8: =F8/F$19 -> 0.18192466 | AB8: 45406 | AC8: 74 | AD8: Bought after pivot test.
A9: AAON | B9: Long | C9: AAON | D9: =532.4164+77.1815 -> 609.5979 | E9: 89.92 | F9: =E9*D9 -> 54815.043 | G9: =38270.34+5640.4 -> 43910.74 | H9: =G9/D9 -> 72.032302 | I9: =F9-G9 -> 10904.303 | J9: =E9-H9 -> 17.887698 | K9: 45313 | L9: =DAYS360(K9,$C$1) -> 73 | M9: =(I9/G9) -> 0.24832884 | N9: 22 | O9: 90 | P9: 96 | Q9: 71.39 | R9: =Q9*0.93 -> 66.3927 | S9: 78.71 | T9: =Q9*1.25 -> 89.2375 | U9: =Q9*1.5 -> 107.085 | V9: =Q9*2 -> 142.78 | W9: =H9-(H9*0.07) -> 66.990041 | X9: 77 | Y9: =(X9-H9)/H9 -> 0.068964866 | Z9: =F9/F$19 -> 0.091424528 | AB9: 45414 | AC9: 98 | AD9: Bought after pivot test.
A10: BLBD | B10: Long | C10: Bluebird | D10: =952.002+512.6146 -> 1464.6166 | E10: 37.43 | F10: =E10*D10 -> 54820.599 | G10: =28303.96+15646.4 -> 43950.36 | H10: =G10/D10 -> 30.008099 | I10: =F10-G10 -> 10870.239 | J10: =E10-H10 -> 7.421901 | K10: 45321 | L10: =DAYS360(K10,$C$1) -> 65 | M10: =(I10/G10) -> 0.24732993 | N10: 18 | O10: 96 | P10: 81 | Q10: 28.39 | R10: =Q10*0.93 -> 26.4027 | S10: 31.42 | T10: =Q10*1.25 -> 35.4875 | U10: =Q10*1.5 -> 42.585 | V10: =Q10*2 -> 56.78 | W10: =H10-(H10*0.07) -> 27.907532 | X10: 32 | Y10: =(X10-H10)/H10 -> 0.066378778 | Z10: =F10/F$19 -> 0.091433795 | AB10: 45421 | AC10: 99 | AD10: Bought day 2 after b/o.
A11: BPMC | B11: Long | C11: Blueprint Med | D11: =464.2554+269.0604 -> 733.3158 | E11: 91.65 | F11: =E11*D11 -> 67208.393 | G11: =45518.9+25760.58 -> 71279.48 | H11: =G11/D11 -> 97.201615 | I11: =F11-G11 -> -4071.0869 | J11: =E11-H11 -> -5.5516149 | K11: 45349 | L11: =DAYS360(K11,$C$1) -> 38 | M11: =(I11/G11) -> -0.057114431 | N11: 13 | O11: 94 | P11: 33 | Q11: 94.47 | R11: =Q11*0.93 -> 87.8571 | S11: 80.42 | T11: =Q11*1.25 -> 118.0875 | U11: =Q11*1.5 -> 141.705 | V11: =Q11*2 -> 188.94 | W11: =H11-(H11*0.07) -> 90.397502 | X11: 90 | Y11: =(X11-H11)/H11 -> -0.074089457 | Z11: =F11/F$19 -> 0.11209506 | AB11: 45413 | AC11: 81 | AD11: Bought the b/o day.
A12: UFPT | B12: Long | C12: UFP Technologies | D12: 268.5725 | E12: 250.59 | F12: =E12*D12 -> 67301.583 | G12: 54466.53 | H12: =G12/D12 -> 202.8001 | I12: =F12-G12 -> 12835.053 | J12: =E12-H12 -> 47.789899 | K12: 45370 | L12: =DAYS360(K12,$C$1) -> 16 | M12: =(I12/G12) -> 0.23565028 | N12: 68 | O12: 94 | P12: 94 | Q12: 200 | R12: =Q12*0.93 -> 186 | S12: 188.5 | T12: =Q12*1.25 -> 250 | U12: =Q12*1.5 -> 300 | V12: =Q12*2 -> 400 | W12: =H12-(H12*0.07) -> 188.60409 | X12: 202 | Y12: =(X12-H12)/H12 -> -0.0039452669 | Z12: =F12/F$19 -> 0.11225049 | AB12: 45412 | AC12: 94 | AD12: Bought the test of the 10wma. First pullback.
A13: HMY | B13: Long | C13: Harmony Gold | D13: 2972.4372 | E13: 8.84 | F13: =E13*D13 -> 26276.345 | G13: 23794.37 | H13: =G13/D13 -> 8.0050034 | I13: =F13-G13 -> 2481.9748 | J13: =E13-H13 -> 0.83499656 | K13: 45378 | L13: =DAYS360(K13,$C$1) -> 8 | M13: =(I13/G13) -> 0.10430933 | N13: 37 | O13: 97 | P13: 99 | Q13: 6.76 | R13: =Q13*0.93 -> 6.2868 | S13: 7.21 | T13: =Q13*1.25 -> 8.45 | U13: =Q13*1.5 -> 10.14 | V13: =Q13*2 -> 13.52 | W13: =H13-(H13*0.07) -> 7.4446532 | X13: 7.75 | Y13: =(X13-H13)/H13 -> -0.031855506 | Z13: =F13/F$19 -> 0.043825605 | AB13: 45401 | AC13: 99
A14: AEM | B14: Long | C14: Agnico-Eagle Mines | D14: 828.4023 | E14: 62 | F14: =E14*D14 -> 51360.943 | G14: 47623.59 | H14: =G14/D14 -> 57.488481 | I14: =F14-G14 -> 3737.3526 | J14: =E14-H14 -> 4.5115189 | K14: 45378 | L14: =DAYS360(K14,$C$1) -> 8 | M14: =(I14/G14) -> 0.078476919 | N14: 37 | O14: 82 | P14: 92 | Q14: 57.16 | R14: =Q14*0.93 -> 53.1588 | S14: 54.02 | T14: =Q14*1.25 -> 71.45 | U14: =Q14*1.5 -> 85.74 | V14: =Q14*2 -> 114.32 | W14: =H14-(H14*0.07) -> 53.464287 | X14: 57 | Y14: =(X14-H14)/H14 -> -0.0084970264 | Z14: =F14/F$19 -> 0.085663528 | AB14: 45407 | AC14: 97 | AD14: Bought the b/o. Vol not impressive, yet. Watch.
F15: =E15*D15 -> 0 | H15: =G15/D15 -> #DIV/0! | I15: =F15-G15 -> 0 | J15: =E15-H15 -> #DIV/0! | L15: =DAYS360(K15,$C$1) -> 44735 | M15: =(I15/G15) -> #DIV/0! | R15: =Q15*0.93 -> 0 | T15: =Q15*1.25 -> 0 | U15: =Q15*1.5 -> 0 | V15: =Q15*2 -> 0 | W15: =H15-(H15*0.07) -> #DIV/0! | Y15: =(X15-H15)/H15 -> #DIV/0! | Z15: =F15/F$19 -> 0
A16: BIL | B16: Long | C16: Tbill ETF | D16: 277.4286 | E16: 91.5 | F16: =E16*D16 -> 25384.717 | G16: 25401.36 | H16: =G16/D16 -> 91.559991 | I16: =F16-G16 -> -16.6431 | J16: =E16-H16 -> -0.059990571 | M16: =(I16/G16) -> -0.00065520508 | R16: =Q16*0.93 -> 0 | T16: =Q16*1.25 -> 0 | U16: =Q16*1.5 -> 0 | V16: =Q16*2 -> 0 | W16: =H16-(H16*0.07) -> 85.150791 | Y16: =(X16-H16)/H16 -> -1 | Z16: =F16/F$19 -> 0.042338483
A17: Sub-Total | F17: =SUM(F6:F16) -> 539248.05 | G17: =SUM(G6:G16) -> 402305.19 | I17: =SUM(I6:I16) -> 136942.86
D18: Cash, other | F18: 60318 | G18: =F18/F19 -> 0.10060276
D19: Total | F19: =SUM(F17:F18) -> 599566.05
H20: Last week's close | I20: ='03-29-24'!F19 -> 607071.37 | K20: 45291 | L20: 476160.6
A21: * | H21: Week's change | I21: =(F19-I20)/I20 -> -0.012363163 | K21: chg % | L21: =(F19-L20)/L20 -> 0.2591677
M23: days
A24: 2024 Closed Trades - Managed Acct | D24: Qty | E24: Cost/sh | F24: $ cost | G24: $Proc | H24: Proc/sh | I24: Profit/loss | J24: % | K24: Date purch | L24: Date sold | M24: held | P24: Comments
A25: YELP | B25: Long | C25: Yelp Inc | D25: 808.573 | E25: =F25/D25 -> 47.428062 | F25: 38349.05 | G25: 35186.18 | H25: =G25/D25 -> 43.516392 | I25: =G25-F25 -> -3162.87 | J25: =I25/F25 -> -0.082475837 | K25: 45286 | L25: 45302 | M25: =DAYS360(K25,L25) -> 15 | O25: Closed below stop for 2 days.
A26: TS | B26: Long | C26: Tenaris | D26: 1166.935 | E26: =F26/D26 -> 35.085005 | F26: 40941.92 | G26: 36634.59 | H26: =G26/D26 -> 31.393857 | I26: =G26-F26 -> -4307.33 | J26: =I26/F26 -> -0.10520586 | K26: 45233 | L26: 45307 | M26: =DAYS360(K26,L26) -> 73
A27: MNSO | B27: Long | C27: Minoso | D27: =1211.7123+804.6763 -> 2016.3886 | E27: =F27/D27 -> 20.49104 | F27: 41317.9 | G27: 42071.53 | H27: =G27/D27 -> 20.864793 | I27: =G27-F27 -> 753.63 | J27: =I27/F27 -> 0.018239794 | K27: 45135 | L27: 45308 | M27: =DAYS360(K27,L27) -> 169 | O27: Totally blew this trade. Had a nearly 50% profit.
A28: ACMR | B28: Long | C28: ACM Research | D28: =1339.9646+918.07 -> 2258.0346 | E28: =F28/D28 -> 21.193736 | F28: =28457.8+19398.39 -> 47856.19 | G28: 39178.27 | H28: =G28/D28 -> 17.350607 | I28: =G28-F28 -> -8677.92 | J28: =I28/F28 -> -0.18133328 | K28: 45302 | L28: 45322 | M28: =DAYS360(K28,L28) -> 20
A29: MDB | B29: Long | C29: MongoDB | D29: 126.054 | E29: =F29/D29 -> 450.27964 | F29: 56759.55 | G29: 54939.36 | H29: =G29/D29 -> 435.83988 | I29: =G29-F29 -> -1820.19 | J29: =I29/F29 -> -0.032068436 | K29: 45327 | L29: 45342 | M29: =DAYS360(K29,L29) -> 15 | O29: Stopped out.
A30: VKTX | B30: Long | C30: Viking Therap | D30: 808.6324 | E30: =F30/D30 -> 21.530005 | F30: 17409.86 | G30: 28227.27 | H30: =G30/D30 -> 34.907419 | I30: =G30-F30 -> 10817.41 | J30: =I30/F30 -> 0.62133814 | K30: 45309 | L30: 45343 | M30: =DAYS360(K30,L30) -> 33 | O30: Took partial profit.
A31: BIRK | B31: Long | C31: Birkenstock Hldg | D31: =567.3728+414.8485 -> 982.2213 | E31: =F31/D31 -> 52.971342 | F31: 52029.58 | G31: 47202.25 | H31: =G31/D31 -> 48.056634 | I31: =G31-F31 -> -4827.33 | J31: =I31/F31 -> -0.092780491 | K31: 45344 | L31: 45351 | M31: =DAYS360(K31,L31) -> 7 | O31: Stopped out after earnings.
A32: DDOG | B32: Long | C32: Datadog | D32: =308.2955+142.5312 -> 450.8267 | E32: =F32/D32 -> 130.66999 | F32: 58909.52 | G32: 55702.82 | H32: =G32/D32 -> 123.55706 | I32: =G32-F32 -> -3206.7 | J32: =I32/F32 -> -0.054434326 | K32: 45286 | L32: 45356 | M32: =DAYS360(K32,L32) -> 69 | O32: Broke 50dma
A33: IOT | B33: Long | C33: Samsara | D33: =846.327+640.0668 -> 1486.3938 | E33: =F33/D33 -> 34.902742 | F33: =30020.93+21858.29 -> 51879.22 | G33: 51882.03 | H33: =G33/D33 -> 34.904633 | I33: =G33-F33 -> 2.81 | J33: =I33/F33 -> 5.4164268e-05 | K33: 45331 | L33: 45366 | M33: =DAYS360(K33,L33) -> 36 | O33: B/o did not follow through. Sold at my cost.
A34: KD | B34: Long | C34: Kyndryl Hldgs | D34: =1160.2602+1046.0778 -> 2206.338 | E34: =F34/D34 -> 17.884522 | F34: =20288.83+19170.47 -> 39459.3 | G34: 47805.42 | H34: =G34/D34 -> 21.667315 | I34: =G34-F34 -> 8346.12 | J34: =I34/F34 -> 0.21151212 | K34: 45243 | L34: 45373 | M34: =DAYS360(K34,L34) -> 129 | O34: Took profit.
I37: =SUM(I25:I36) -> -6082.37
J39: Avg
H40: # of losses | I40: 6 | J40: -0.0914
H41: # of wins | I41: 4 | J41: 0.2128

Sheet 04-12-24
C1: 45394
C3: MANAGED ACCT | X3: Current | AC3: IBD
H4: Cost | J4: P/L | N4: Group | P4: EPS | R4: pivot | S4: last | W4: cost | X4: Stop | Y4: Stop | Z4: % | AB4: EPS | AC4: Comp
A5: Symbol | B5: Position | C5: Name | D5: Qty | E5: Current | F5: Value | G5: Cost | H5: per share | I5: P/L $ | J5: per sh | K5: Date purch | L5: days held | M5: % incr | N5: Rank | O5: RS | P5: RS | Q5: pivot | R5: -0.07 | S5: low | T5: 0.25 | U5: 0.5 | V5: 1 | W5: -0.07 | X5: Loss | Y5: Loss% | Z5: of port | AB5: Due | AC5: Rank
A7: AXON | B7: Long | C7: Axon Enterprise | D7: 267.8431 | E7: 310.81 | F7: =E7*D7 -> 83248.314 | G7: 61166.24 | H7: =G7/D7 -> 228.36594 | I7: =F7-G7 -> 22082.074 | J7: =E7-H7 -> 82.444065 | K7: 45238 | L7: =DAYS360(K7,$C$1) -> 154 | M7: =(I7/G7) -> 0.36101735 | N7: 13 | O7: 93 | P7: 99 | Q7: 223.3 | R7: =Q7*0.93 -> 207.669 | S7: 255.68 | T7: =Q7*1.25 -> 279.125 | U7: =Q7*1.5 -> 334.95 | V7: =Q7*2 -> 446.6 | W7: =H7-(H7*0.07) -> 212.38032 | X7: 300 | Y7: =(X7-H7)/H7 -> 0.31368104 | Z7: =F7/F$19 -> 0.14447472 | AB7: 45421 | AC7: 99 | AD7: Bought as it gapped out of base on EPS.
A8: VKTX | B8: Long | C8: Viking Therap | D8: =1286.8297+948.5633-808.6324 -> 1426.7606 | E8: 68.62 | F8: =E8*D8 -> 97904.312 | G8: =28174.78+19947.6-17409.86 -> 30712.52 | H8: =G8/D8 -> 21.52605 | I8: =F8-G8 -> 67191.792 | J8: =E8-H8 -> 47.09395 | K8: 45309 | L8: =DAYS360(K8,$C$1) -> 84 | M8: =(I8/G8) -> 2.1877655 | N8: 17 | O8: 99 | P8: 22 | Q8: 20.03 | R8: =Q8*0.93 -> 18.6279 | S8: 34.04 | T8: =Q8*1.25 -> 25.0375 | U8: =Q8*1.5 -> 30.045 | V8: =Q8*2 -> 40.06 | W8: =H8-(H8*0.07) -> 20.019226 | X8: 55 | Y8: =(X8-H8)/H8 -> 1.5550438 | Z8: =F8/F$19 -> 0.16990973 | AB8: 45406 | AC8: 73 | AD8: Bought after pivot test.
A9: AAON | B9: Long | C9: AAON | D9: =532.4164+77.1815 -> 609.5979 | E9: 88.01 | F9: =E9*D9 -> 53650.711 | G9: =38270.34+5640.4 -> 43910.74 | H9: =G9/D9 -> 72.032302 | I9: =F9-G9 -> 9739.9712 | J9: =E9-H9 -> 15.977698 | K9: 45313 | L9: =DAYS360(K9,$C$1) -> 80 | M9: =(I9/G9) -> 0.22181296 | N9: 21 | O9: 90 | P9: 96 | Q9: 71.39 | R9: =Q9*0.93 -> 66.3927 | S9: 78.71 | T9: =Q9*1.25 -> 89.2375 | U9: =Q9*1.5 -> 107.085 | V9: =Q9*2 -> 142.78 | W9: =H9-(H9*0.07) -> 66.990041 | X9: 82 | Y9: =(X9-H9)/H9 -> 0.13837817 | Z9: =F9/F$19 -> 0.093109054 | AB9: 45414 | AC9: 97 | AD9: Bought after pivot test.
A10: BLBD | B10: Long | C10: Bluebird | D10: =952.002+512.6146 -> 1464.6166 | E10: 36.03 | F10: =E10*D10 -> 52770.136 | G10: =28303.96+15646.4 -> 43950.36 | H10: =G10/D10 -> 30.008099 | I10: =F10-G10 -> 8819.7761 | J10: =E10-H10 -> 6.021901 | K10: 45321 | L10: =DAYS360(K10,$C$1) -> 72 | M10: =(I10/G10) -> 0.20067586 | N10: 15 | O10: 96 | P10: 81 | Q10: 28.39 | R10: =Q10*0.93 -> 26.4027 | S10: 31.42 | T10: =Q10*1.25 -> 35.4875 | U10: =Q10*1.5 -> 42.585 | V10: =Q10*2 -> 56.78 | W10: =H10-(H10*0.07) -> 27.907532 | X10: 32 | Y10: =(X10-H10)/H10 -> 0.066378778 | Z10: =F10/F$19 -> 0.091580844 | AB10: 45421 | AC10: 99 | AD10: Bought day 2 after b/o.
A11: UFPT | B11: Long | C11: UFP Technologies | D11: 268.5725 | E11: 228.99 | F11: =E11*D11 -> 61500.417 | G11: 54466.53 | H11: =G11/D11 -> 202.8001 | I11: =F11-G11 -> 7033.8868 | J11: =E11-H11 -> 26.189899 | K11: 45370 | L11: =DAYS360(K11,$C$1) -> 23 | M11: =(I11/G11) -> 0.12914145 | N11: 66 | O11: 92 | P11: 94 | Q11: 200 | R11: =Q11*0.93 -> 186 | S11: 188.5 | T11: =Q11*1.25 -> 250 | U11: =Q11*1.5 -> 300 | V11: =Q11*2 -> 400 | W11: =H11-(H11*0.07) -> 188.60409 | X11: 215 | Y11: =(X11-H11)/H11 -> 0.060157265 | Z11: =F11/F$19 -> 0.10673196 | AB11: 45412 | AC11: 95 | AD11: Bought the test of the 10wma. First pullback.
A12: HMY | B12: Long | C12: Harmony Gold | D12: 2972.4372 | E12: 9.11 | F12: =E12*D12 -> 27078.903 | G12: 23794.37 | H12: =G12/D12 -> 8.0050034 | I12: =F12-G12 -> 3284.5329 | J12: =E12-H12 -> 1.1049966 | K12: 45378 | L12: =DAYS360(K12,$C$1) -> 15 | M12: =(I12/G12) -> 0.13803824 | N12: 27 | O12: 97 | P12: 99 | Q12: 6.76 | R12: =Q12*0.93 -> 6.2868 | S12: 7.21 | T12: =Q12*1.25 -> 8.45 | U12: =Q12*1.5 -> 10.14 | V12: =Q12*2 -> 13.52 | W12: =H12-(H12*0.07) -> 7.4446532 | X12: 7.75 | Y12: =(X12-H12)/H12 -> -0.031855506 | Z12: =F12/F$19 -> 0.04699455 | AB12: 45401 | AC12: 99
A13: AEM | B13: Long | C13: Agnico-Eagle Mines | D13: 828.4023 | E13: 61.45 | F13: =E13*D13 -> 50905.321 | G13: 47623.59 | H13: =G13/D13 -> 57.488481 | I13: =F13-G13 -> 3281.7313 | J13: =E13-H13 -> 3.9615189 | K13: 45378 | L13: =DAYS360(K13,$C$1) -> 15 | M13: =(I13/G13) -> 0.068909785 | N13: 27 | O13: 80 | P13: 92 | Q13: 57.16 | R13: =Q13*0.93 -> 53.1588 | S13: 54.02 | T13: =Q13*1.25 -> 71.45 | U13: =Q13*1.5 -> 85.74 | V13: =Q13*2 -> 114.32 | W13: =H13-(H13*0.07) -> 53.464287 | X13: 57 | Y13: =(X13-H13)/H13 -> -0.0084970264 | Z13: =F13/F$19 -> 0.088344519 | AB13: 45407 | AC13: 98 | AD13: Bought the b/o. Vol not impressive, yet. Watch.
A14: ARM | B14: Long | C14: Arm Holdings | D14: 224.4175 | E14: 126.33 | F14: =E14*D14 -> 28350.663 | G14: 29415.63 | H14: =G14/D14 -> 131.07547 | I14: =F14-G14 -> -1064.9672 | J14: =E14-H14 -> -4.7454732 | K14: 45393 | L14: =DAYS360(K14,$C$1) -> 1 | M14: =(I14/G14) -> -0.036204128 | N14: 50 | O14: 98 | P14: 99 | Q14: 149.92 | R14: =Q14*0.93 -> 139.4256 | S14: 120.02 | T14: =Q14*1.25 -> 187.4 | U14: =Q14*1.5 -> 224.88 | V14: =Q14*2 -> 299.84 | W14: =H14-(H14*0.07) -> 121.90019 | X14: 122 | Y14: =(X14-H14)/H14 -> -0.069238531 | Z14: =F14/F$19 -> 0.049201647 | AB14: 45420 | AC14: 99 | AD14: Bought as it bounced off the 50dma.
F15: =E15*D15 -> 0 | H15: =G15/D15 -> #DIV/0! | I15: =F15-G15 -> 0 | J15: =E15-H15 -> #DIV/0! | L15: =DAYS360(K15,$C$1) -> 44742 | M15: =(I15/G15) -> #DIV/0! | R15: =Q15*0.93 -> 0 | T15: =Q15*1.25 -> 0 | U15: =Q15*1.5 -> 0 | V15: =Q15*2 -> 0 | W15: =H15-(H15*0.07) -> #DIV/0! | Y15: =(X15-H15)/H15 -> #DIV/0! | Z15: =F15/F$19 -> 0
A16: BIL | B16: Long | C16: Tbill ETF | D16: 277.4286 | E16: 91.58 | F16: =E16*D16 -> 25406.911 | G16: 25401.36 | H16: =G16/D16 -> 91.559991 | I16: =F16-G16 -> 5.551188 | J16: =E16-H16 -> 0.020009429 | M16: =(I16/G16) -> 0.00021853901 | R16: =Q16*0.93 -> 0 | T16: =Q16*1.25 -> 0 | U16: =Q16*1.5 -> 0 | V16: =Q16*2 -> 0 | W16: =H16-(H16*0.07) -> 85.150791 | Y16: =(X16-H16)/H16 -> -1 | Z16: =F16/F$19 -> 0.044092863
A17: Sub-Total | F17: =SUM(F6:F16) -> 480815.69 | G17: =SUM(G6:G16) -> 360441.34 | I17: =SUM(I6:I16) -> 120374.35
D18: Cash, other | F18: 95398 | G18: =F18/F19 -> 0.16556011
D19: Total | F19: =SUM(F17:F18) -> 576213.69
H20: Last week's close | I20: ='04-05-24'!F19 -> 599566.05 | K20: 45291 | L20: 476160.6
A21: * | H21: Week's change | I21: =(F19-I20)/I20 -> -0.038948768 | K21: chg % | L21: =(F19-L20)/L20 -> 0.21012467
M23: days
A24: 2024 Closed Trades - Managed Acct | D24: Qty | E24: Cost/sh | F24: $ cost | G24: $Proc | H24: Proc/sh | I24: Profit/loss | J24: % | K24: Date purch | L24: Date sold | M24: held | P24: Comments
A25: YELP | B25: Long | C25: Yelp Inc | D25: 808.573 | E25: =F25/D25 -> 47.428062 | F25: 38349.05 | G25: 35186.18 | H25: =G25/D25 -> 43.516392 | I25: =G25-F25 -> -3162.87 | J25: =I25/F25 -> -0.082475837 | K25: 45286 | L25: 45302 | M25: =DAYS360(K25,L25) -> 15 | O25: Closed below stop for 2 days.
A26: TS | B26: Long | C26: Tenaris | D26: 1166.935 | E26: =F26/D26 -> 35.085005 | F26: 40941.92 | G26: 36634.59 | H26: =G26/D26 -> 31.393857 | I26: =G26-F26 -> -4307.33 | J26: =I26/F26 -> -0.10520586 | K26: 45233 | L26: 45307 | M26: =DAYS360(K26,L26) -> 73
A27: MNSO | B27: Long | C27: Minoso | D27: =1211.7123+804.6763 -> 2016.3886 | E27: =F27/D27 -> 20.49104 | F27: 41317.9 | G27: 42071.53 | H27: =G27/D27 -> 20.864793 | I27: =G27-F27 -> 753.63 | J27: =I27/F27 -> 0.018239794 | K27: 45135 | L27: 45308 | M27: =DAYS360(K27,L27) -> 169 | O27: Totally blew this trade. Had a nearly 50% profit.
A28: ACMR | B28: Long | C28: ACM Research | D28: =1339.9646+918.07 -> 2258.0346 | E28: =F28/D28 -> 21.193736 | F28: =28457.8+19398.39 -> 47856.19 | G28: 39178.27 | H28: =G28/D28 -> 17.350607 | I28: =G28-F28 -> -8677.92 | J28: =I28/F28 -> -0.18133328 | K28: 45302 | L28: 45322 | M28: =DAYS360(K28,L28) -> 20
A29: MDB | B29: Long | C29: MongoDB | D29: 126.054 | E29: =F29/D29 -> 450.27964 | F29: 56759.55 | G29: 54939.36 | H29: =G29/D29 -> 435.83988 | I29: =G29-F29 -> -1820.19 | J29: =I29/F29 -> -0.032068436 | K29: 45327 | L29: 45342 | M29: =DAYS360(K29,L29) -> 15 | O29: Stopped out.
A30: VKTX | B30: Long | C30: Viking Therap | D30: 808.6324 | E30: =F30/D30 -> 21.530005 | F30: 17409.86 | G30: 28227.27 | H30: =G30/D30 -> 34.907419 | I30: =G30-F30 -> 10817.41 | J30: =I30/F30 -> 0.62133814 | K30: 45309 | L30: 45343 | M30: =DAYS360(K30,L30) -> 33 | O30: Took partial profit.
A31: BIRK | B31: Long | C31: Birkenstock Hldg | D31: =567.3728+414.8485 -> 982.2213 | E31: =F31/D31 -> 52.971342 | F31: 52029.58 | G31: 47202.25 | H31: =G31/D31 -> 48.056634 | I31: =G31-F31 -> -4827.33 | J31: =I31/F31 -> -0.092780491 | K31: 45344 | L31: 45351 | M31: =DAYS360(K31,L31) -> 7 | O31: Stopped out after earnings.
A32: DDOG | B32: Long | C32: Datadog | D32: =308.2955+142.5312 -> 450.8267 | E32: =F32/D32 -> 130.66999 | F32: 58909.52 | G32: 55702.82 | H32: =G32/D32 -> 123.55706 | I32: =G32-F32 -> -3206.7 | J32: =I32/F32 -> -0.054434326 | K32: 45286 | L32: 45356 | M32: =DAYS360(K32,L32) -> 69 | O32: Broke 50dma
A33: IOT | B33: Long | C33: Samsara | D33: =846.327+640.0668 -> 1486.3938 | E33: =F33/D33 -> 34.902742 | F33: =30020.93+21858.29 -> 51879.22 | G33: 51882.03 | H33: =G33/D33 -> 34.904633 | I33: =G33-F33 -> 2.81 | J33: =I33/F33 -> 5.4164268e-05 | K33: 45331 | L33: 45366 | M33: =DAYS360(K33,L33) -> 36 | O33: B/o did not follow through. Sold at my cost.
A34: KD | B34: Long | C34: Kyndryl Hldgs | D34: =1160.2602+1046.0778 -> 2206.338 | E34: =F34/D34 -> 17.884522 | F34: =20288.83+19170.47 -> 39459.3 | G34: 47805.42 | H34: =G34/D34 -> 21.667315 | I34: =G34-F34 -> 8346.12 | J34: =I34/F34 -> 0.21151212 | K34: 45243 | L34: 45373 | M34: =DAYS360(K34,L34) -> 129 | O34: Took profit.
A35: BPMC | B35: Long | C35: Blueprint Med | D35: =464.2554+269.0604 -> 733.3158 | E35: =F35/D35 -> 97.201615 | F35: 71279.48 | G35: 66395.73 | H35: =G35/D35 -> 90.541797 | I35: =G35-F35 -> -4883.75 | J35: =I35/F35 -> -0.068515511 | K35: 45349 | L35: 45394 | M35: =DAYS360(K35,L35) -> 45 | O35: Bad market day. Took the loss above my stop.
A36: CCJ | B36: Long | C36: Cameco | D36: 901.358 | E36: =F36/D36 -> 51.760011 | F36: 46654.3 | G36: 44379.95 | H36: =G36/D36 -> 49.236763 | I36: =G36-F36 -> -2274.35 | J36: =I36/F36 -> -0.04874899 | K36: 45394 | L36: 45394 | M36: =DAYS360(K36,L36) -> 0 | O36: Breakout rejected same day as I bought.
J39: Avg
H40: # of losses | I40: 6 | J40: -0.0914
H41: # of wins | I41: 4 | J41: 0.2128

Sheet 04-19-24
C1: 45401
C3: MANAGED ACCT | X3: Current | AC3: IBD
H4: Cost | J4: P/L | N4: Group | P4: EPS | R4: pivot | S4: last | W4: cost | X4: Stop | Y4: Stop | Z4: % | AB4: EPS | AC4: Comp
A5: Symbol | B5: Position | C5: Name | D5: Qty | E5: Current | F5: Value | G5: Cost | H5: per share | I5: P/L $ | J5: per sh | K5: Date purch | L5: days held | M5: % incr | N5: Rank | O5: RS | P5: RS | Q5: pivot | R5: -0.07 | S5: low | T5: 0.25 | U5: 0.5 | V5: 1 | W5: -0.07 | X5: Loss | Y5: Loss% | Z5: of port | AB5: Due | AC5: Rank
A7: VKTX | B7: Long | C7: Viking Therap | D7: =1286.8297+948.5633-808.6324 -> 1426.7606 | E7: 63.48 | F7: =E7*D7 -> 90570.763 | G7: =28174.78+19947.6-17409.86 -> 30712.52 | H7: =G7/D7 -> 21.52605 | I7: =F7-G7 -> 59858.243 | J7: =E7-H7 -> 41.95395 | K7: 45309 | L7: =DAYS360(K7,$C$1) -> 91 | M7: =(I7/G7) -> 1.9489851 | N7: 19 | O7: 99 | P7: 22 | Q7: 20.03 | R7: =Q7*0.93 -> 18.6279 | S7: 34.04 | T7: =Q7*1.25 -> 25.0375 | U7: =Q7*1.5 -> 30.045 | V7: =Q7*2 -> 40.06 | W7: =H7-(H7*0.07) -> 20.019226 | X7: 55 | Y7: =(X7-H7)/H7 -> 1.5550438 | Z7: =F7/F$19 -> 0.16202303 | AB7: 45406 | AC7: 72
A8: AAON | B8: Long | C8: AAON | D8: =532.4164+77.1815 -> 609.5979 | E8: 85.41 | F8: =E8*D8 -> 52065.757 | G8: =38270.34+5640.4 -> 43910.74 | H8: =G8/D8 -> 72.032302 | I8: =F8-G8 -> 8155.0166 | J8: =E8-H8 -> 13.377698 | K8: 45313 | L8: =DAYS360(K8,$C$1) -> 87 | M8: =(I8/G8) -> 0.18571804 | N8: 25 | O8: 92 | P8: 96 | Q8: 71.39 | R8: =Q8*0.93 -> 66.3927 | S8: 78.71 | T8: =Q8*1.25 -> 89.2375 | U8: =Q8*1.5 -> 107.085 | V8: =Q8*2 -> 142.78 | W8: =H8-(H8*0.07) -> 66.990041 | X8: 82 | Y8: =(X8-H8)/H8 -> 0.13837817 | Z8: =F8/F$19 -> 0.093141002 | AB8: 45414 | AC8: 98 | AD8: Bought the b/o. Vol not impressive, yet. Watch.
A9: HMY | B9: Long | C9: Harmony Gold | D9: 2972.4372 | E9: 9.29 | F9: =E9*D9 -> 27613.942 | G9: 23794.37 | H9: =G9/D9 -> 8.0050034 | I9: =F9-G9 -> 3819.5716 | J9: =E9-H9 -> 1.2849966 | K9: 45378 | L9: =DAYS360(K9,$C$1) -> 22 | M9: =(I9/G9) -> 0.16052417 | N9: 21 | O9: 98 | P9: 99 | Q9: 6.76 | R9: =Q9*0.93 -> 6.2868 | S9: 7.21 | T9: =Q9*1.25 -> 8.45 | U9: =Q9*1.5 -> 10.14 | V9: =Q9*2 -> 13.52 | W9: =H9-(H9*0.07) -> 7.4446532 | X9: 7.75 | Y9: =(X9-H9)/H9 -> -0.031855506 | Z9: =F9/F$19 -> 0.049398882 | AB9: 45401 | AC9: 99
A10: AEM | B10: Long | C10: Agnico-Eagle Mines | D10: 828.4023 | E10: 63.84 | F10: =E10*D10 -> 52885.203 | G10: 47623.59 | H10: =G10/D10 -> 57.488481 | I10: =F10-G10 -> 5261.6128 | J10: =E10-H10 -> 6.3515189 | K10: 45378 | L10: =DAYS360(K10,$C$1) -> 22 | M10: =(I10/G10) -> 0.11048333 | N10: 21 | O10: 89 | P10: 93 | Q10: 57.16 | R10: =Q10*0.93 -> 53.1588 | S10: 54.02 | T10: =Q10*1.25 -> 71.45 | U10: =Q10*1.5 -> 85.74 | V10: =Q10*2 -> 114.32 | W10: =H10-(H10*0.07) -> 53.464287 | X10: 57 | Y10: =(X10-H10)/H10 -> -0.0084970264 | Z10: =F10/F$19 -> 0.094606918 | AB10: 45407 | AC10: 99
F11: =E11*D11 -> 0 | H11: =G11/D11 -> #DIV/0! | I11: =F11-G11 -> 0 | J11: =E11-H11 -> #DIV/0! | L11: =DAYS360(K11,$C$1) -> 44749 | M11: =(I11/G11) -> #DIV/0! | R11: =Q11*0.93 -> 0 | T11: =Q11*1.25 -> 0 | U11: =Q11*1.5 -> 0 | V11: =Q11*2 -> 0 | W11: =H11-(H11*0.07) -> #DIV/0! | Y11: =(X11-H11)/H11 -> #DIV/0! | Z11: =F11/F$19 -> 0
F12: =E12*D12 -> 0 | H12: =G12/D12 -> #DIV/0! | I12: =F12-G12 -> 0 | J12: =E12-H12 -> #DIV/0! | L12: =DAYS360(K12,$C$1) -> 44749 | M12: =(I12/G12) -> #DIV/0! | R12: =Q12*0.93 -> 0 | T12: =Q12*1.25 -> 0 | U12: =Q12*1.5 -> 0 | V12: =Q12*2 -> 0 | W12: =H12-(H12*0.07) -> #DIV/0! | Y12: =(X12-H12)/H12 -> #DIV/0! | Z12: =F12/F$19 -> 0 | AD12: Bought after pivot test.
F13: =E13*D13 -> 0 | H13: =G13/D13 -> #DIV/0! | I13: =F13-G13 -> 0 | J13: =E13-H13 -> #DIV/0! | L13: =DAYS360(K13,$C$1) -> 44749 | M13: =(I13/G13) -> #DIV/0! | R13: =Q13*0.93 -> 0 | T13: =Q13*1.25 -> 0 | U13: =Q13*1.5 -> 0 | V13: =Q13*2 -> 0 | W13: =H13-(H13*0.07) -> #DIV/0! | Y13: =(X13-H13)/H13 -> #DIV/0! | Z13: =F13/F$19 -> 0 | AD13: Bought after pivot test.
F14: =E14*D14 -> 0 | H14: =G14/D14 -> #DIV/0! | I14: =F14-G14 -> 0 | J14: =E14-H14 -> #DIV/0! | L14: =DAYS360(K14,$C$1) -> 44749 | M14: =(I14/G14) -> #DIV/0! | R14: =Q14*0.93 -> 0 | T14: =Q14*1.25 -> 0 | U14: =Q14*1.5 -> 0 | V14: =Q14*2 -> 0 | W14: =H14-(H14*0.07) -> #DIV/0! | Y14: =(X14-H14)/H14 -> #DIV/0! | Z14: =F14/F$19 -> 0
F15: =E15*D15 -> 0 | H15: =G15/D15 -> #DIV/0! | I15: =F15-G15 -> 0 | J15: =E15-H15 -> #DIV/0! | L15: =DAYS360(K15,$C$1) -> 44749 | M15: =(I15/G15) -> #DIV/0! | R15: =Q15*0.93 -> 0 | T15: =Q15*1.25 -> 0 | U15: =Q15*1.5 -> 0 | V15: =Q15*2 -> 0 | W15: =H15-(H15*0.07) -> #DIV/0! | Y15: =(X15-H15)/H15 -> #DIV/0! | Z15: =F15/F$19 -> 0
A16: BIL | B16: Long | C16: Tbill ETF | D16: 277.4286 | E16: 91.68 | F16: =E16*D16 -> 25434.654 | G16: 25401.36 | H16: =G16/D16 -> 91.559991 | I16: =F16-G16 -> 33.294048 | J16: =E16-H16 -> 0.12000943 | M16: =(I16/G16) -> 0.0013107191 | R16: =Q16*0.93 -> 0 | T16: =Q16*1.25 -> 0 | U16: =Q16*1.5 -> 0 | V16: =Q16*2 -> 0 | W16: =H16-(H16*0.07) -> 85.150791 | Y16: =(X16-H16)/H16 -> -1 | Z16: =F16/F$19 -> 0.045500331
A17: Sub-Total | F17: =SUM(F6:F16) -> 248570.32 | G17: =SUM(G6:G16) -> 171442.58 | I17: =SUM(I6:I16) -> 77127.738
D18: Cash, other | F18: 310429 | G18: =F18/F19 -> 0.55532984
D19: Total | F19: =SUM(F17:F18) -> 558999.32
H20: Last week's close | I20: ='04-12-24'!F19 -> 576213.69 | K20: 45291 | L20: 476160.6
A21: * | H21: Week's change | I21: =(F19-I20)/I20 -> -0.029874977 | K21: chg % | L21: =(F19-L20)/L20 -> 0.17397222
M23: days
A24: 2024 Closed Trades - Managed Acct | D24: Qty | E24: Cost/sh | F24: $ cost | G24: $Proc | H24: Proc/sh | I24: Profit/loss | J24: % | K24: Date purch | L24: Date sold | M24: held | P24: Comments
A25: YELP | B25: Long | C25: Yelp Inc | D25: 808.573 | E25: =F25/D25 -> 47.428062 | F25: 38349.05 | G25: 35186.18 | H25: =G25/D25 -> 43.516392 | I25: =G25-F25 -> -3162.87 | J25: =I25/F25 -> -0.082475837 | K25: 45286 | L25: 45302 | M25: =DAYS360(K25,L25) -> 15 | O25: Closed below stop for 2 days.
A26: TS | B26: Long | C26: Tenaris | D26: 1166.935 | E26: =F26/D26 -> 35.085005 | F26: 40941.92 | G26: 36634.59 | H26: =G26/D26 -> 31.393857 | I26: =G26-F26 -> -4307.33 | J26: =I26/F26 -> -0.10520586 | K26: 45233 | L26: 45307 | M26: =DAYS360(K26,L26) -> 73
A27: MNSO | B27: Long | C27: Minoso | D27: =1211.7123+804.6763 -> 2016.3886 | E27: =F27/D27 -> 20.49104 | F27: 41317.9 | G27: 42071.53 | H27: =G27/D27 -> 20.864793 | I27: =G27-F27 -> 753.63 | J27: =I27/F27 -> 0.018239794 | K27: 45135 | L27: 45308 | M27: =DAYS360(K27,L27) -> 169 | O27: Totally blew this trade. Had a nearly 50% profit.
A28: ACMR | B28: Long | C28: ACM Research | D28: =1339.9646+918.07 -> 2258.0346 | E28: =F28/D28 -> 21.193736 | F28: =28457.8+19398.39 -> 47856.19 | G28: 39178.27 | H28: =G28/D28 -> 17.350607 | I28: =G28-F28 -> -8677.92 | J28: =I28/F28 -> -0.18133328 | K28: 45302 | L28: 45322 | M28: =DAYS360(K28,L28) -> 20
A29: MDB | B29: Long | C29: MongoDB | D29: 126.054 | E29: =F29/D29 -> 450.27964 | F29: 56759.55 | G29: 54939.36 | H29: =G29/D29 -> 435.83988 | I29: =G29-F29 -> -1820.19 | J29: =I29/F29 -> -0.032068436 | K29: 45327 | L29: 45342 | M29: =DAYS360(K29,L29) -> 15 | O29: Stopped out.
A30: VKTX | B30: Long | C30: Viking Therap | D30: 808.6324 | E30: =F30/D30 -> 21.530005 | F30: 17409.86 | G30: 28227.27 | H30: =G30/D30 -> 34.907419 | I30: =G30-F30 -> 10817.41 | J30: =I30/F30 -> 0.62133814 | K30: 45309 | L30: 45343 | M30: =DAYS360(K30,L30) -> 33 | O30: Took partial profit.
A31: BIRK | B31: Long | C31: Birkenstock Hldg | D31: =567.3728+414.8485 -> 982.2213 | E31: =F31/D31 -> 52.971342 | F31: 52029.58 | G31: 47202.25 | H31: =G31/D31 -> 48.056634 | I31: =G31-F31 -> -4827.33 | J31: =I31/F31 -> -0.092780491 | K31: 45344 | L31: 45351 | M31: =DAYS360(K31,L31) -> 7 | O31: Stopped out after earnings.
A32: DDOG | B32: Long | C32: Datadog | D32: =308.2955+142.5312 -> 450.8267 | E32: =F32/D32 -> 130.66999 | F32: 58909.52 | G32: 55702.82 | H32: =G32/D32 -> 123.55706 | I32: =G32-F32 -> -3206.7 | J32: =I32/F32 -> -0.054434326 | K32: 45286 | L32: 45356 | M32: =DAYS360(K32,L32) -> 69 | O32: Broke 50dma
A33: IOT | B33: Long | C33: Samsara | D33: =846.327+640.0668 -> 1486.3938 | E33: =F33/D33 -> 34.902742 | F33: =30020.93+21858.29 -> 51879.22 | G33: 51882.03 | H33: =G33/D33 -> 34.904633 | I33: =G33-F33 -> 2.81 | J33: =I33/F33 -> 5.4164268e-05 | K33: 45331 | L33: 45366 | M33: =DAYS360(K33,L33) -> 36 | O33: B/o did not follow through. Sold at my cost.
A34: KD | B34: Long | C34: Kyndryl Hldgs | D34: =1160.2602+1046.0778 -> 2206.338 | E34: =F34/D34 -> 17.884522 | F34: =20288.83+19170.47 -> 39459.3 | G34: 47805.42 | H34: =G34/D34 -> 21.667315 | I34: =G34-F34 -> 8346.12 | J34: =I34/F34 -> 0.21151212 | K34: 45243 | L34: 45373 | M34: =DAYS360(K34,L34) -> 129 | O34: Took profit.
A35: BPMC | B35: Long | C35: Blueprint Med | D35: =464.2554+269.0604 -> 733.3158 | E35: =F35/D35 -> 97.201615 | F35: 71279.48 | G35: 66395.73 | H35: =G35/D35 -> 90.541797 | I35: =G35-F35 -> -4883.75 | J35: =I35/F35 -> -0.068515511 | K35: 45349 | L35: 45394 | M35: =DAYS360(K35,L35) -> 45 | O35: Bad market day. Took the loss above my stop.
A36: CCJ | B36: Long | C36: Cameco | D36: 901.358 | E36: =F36/D36 -> 51.760011 | F36: 46654.3 | G36: 44379.95 | H36: =G36/D36 -> 49.236763 | I36: =G36-F36 -> -2274.35 | J36: =I36/F36 -> -0.04874899 | K36: 45394 | L36: 45394 | M36: =DAYS360(K36,L36) -> 0 | O36: Breakout rejected same day as I bought.
A37: AXON | B37: Long | C37: Axon Enterprise | D37: 267.8431 | E37: =F37/D37 -> 228.36594 | F37: 61166.24 | G37: 81558.94 | H37: =G37/D37 -> 304.50267 | I37: =G37-F37 -> 20392.7 | J37: =I37/F37 -> 0.33339797 | K37: 45238 | L37: 45397 | M37: =DAYS360(K37,L37) -> 157 | O37: Taking profits. Broke 21dema and consolidation.
A38: ARM | B38: Long | C38: Arm Holdings | D38: 224.4175 | E38: =F38/D38 -> 131.07547 | F38: 29415.63 | G38: 27481.43 | H38: =G38/D38 -> 122.45672 | I38: =G38-F38 -> -1934.2 | J38: =I38/F38 -> -0.065754159 | K38: 45393 | L38: 45397 | M38: =DAYS360(K38,L38) -> 4 | O38: Broke 50dma. Near stop loss.
A39: BLBD | B39: Long | C39: Bluebird | D39: =952.002+512.6146 -> 1464.6166 | E39: =F39/D39 -> 30.008099 | F39: 43950.36 | G39: 49174.83 | H39: =G39/D39 -> 33.575224 | I39: =G39-F39 -> 5224.47 | J39: =I39/F39 -> 0.11887206 | K39: 45321 | L39: 45400 | M39: =DAYS360(K39,L39) -> 78 | O39: Broke 50dma. Near stop loss.
A40: UFPT | B40: Long | C40: UFP Technologies | D40: 268.5725 | E40: =F40/D40 -> 202.8001 | F40: 54466.53 | G40: 57142.12 | H40: =G40/D40 -> 212.76236 | I40: =G40-F40 -> 2675.59 | J40: =I40/F40 -> 0.049123563 | K40: 45370 | L40: 45401 | M40: =DAYS360(K40,L40) -> 30 | O40: Stopped out.
J42: Avg
H43: # of losses | I43: 9 | J43: -0.0813
H44: # of wins | I44: 7 | J44: 0.1933

Sheet 05-03-24
C1: 45415
C3: MANAGED ACCT | X3: Current | AC3: IBD
H4: Cost | J4: P/L | N4: Group | P4: EPS | R4: pivot | S4: last | W4: cost | X4: Stop | Y4: Stop | Z4: % | AB4: EPS | AC4: Comp
A5: Symbol | B5: Position | C5: Name | D5: Qty | E5: Current | F5: Value | G5: Cost | H5: per share | I5: P/L $ | J5: per sh | K5: Date purch | L5: days held | M5: % incr | N5: Rank | O5: RS | P5: RS | Q5: pivot | R5: -0.07 | S5: low | T5: 0.25 | U5: 0.5 | V5: 1 | W5: -0.07 | X5: Loss | Y5: Loss% | Z5: of port | AB5: Due | AC5: Rank
A7: VKTX | B7: Long | C7: Viking Therap | D7: =1286.8297+948.5633-808.6324 -> 1426.7606 | E7: 76.97 | F7: =E7*D7 -> 109817.76 | G7: =28174.78+19947.6-17409.86 -> 30712.52 | H7: =G7/D7 -> 21.52605 | I7: =F7-G7 -> 79105.243 | J7: =E7-H7 -> 55.44395 | K7: 45309 | L7: =DAYS360(K7,$C$1) -> 105 | M7: =(I7/G7) -> 2.5756676 | N7: 26 | O7: 99 | P7: 22 | Q7: 20.03 | R7: =Q7*0.93 -> 18.6279 | S7: 60.3 | T7: =Q7*1.25 -> 25.0375 | U7: =Q7*1.5 -> 30.045 | V7: =Q7*2 -> 40.06 | W7: =H7-(H7*0.07) -> 20.019226 | X7: 55 | Y7: =(X7-H7)/H7 -> 1.5550438 | Z7: =F7/F$19 -> 0.19166893 | AB7: 45497 | AC7: 72
A8: AAON | B8: Long | C8: AAON | D8: =532.4164+77.1815 -> 609.5979 | E8: 78.4 | F8: =E8*D8 -> 47792.475 | G8: =38270.34+5640.4 -> 43910.74 | H8: =G8/D8 -> 72.032302 | I8: =F8-G8 -> 3881.7354 | J8: =E8-H8 -> 6.3676981 | K8: 45313 | L8: =DAYS360(K8,$C$1) -> 101 | M8: =(I8/G8) -> 0.088400591 | N8: 25 | O8: 92 | P8: 96 | Q8: 71.39 | R8: =Q8*0.93 -> 66.3927 | S8: 84.27 | T8: =Q8*1.25 -> 89.2375 | U8: =Q8*1.5 -> 107.085 | V8: =Q8*2 -> 142.78 | W8: =H8-(H8*0.07) -> 66.990041 | X8: 82 | Y8: =(X8-H8)/H8 -> 0.13837817 | Z8: =F8/F$19 -> 0.083413942 | AB8: 45505 | AC8: 98 | AD8: Bought the b/o. Vol not impressive, yet. Watch.
A9: HMY | B9: Long | C9: Harmony Gold | D9: 2972.4372 | E9: 8.57 | F9: =E9*D9 -> 25473.787 | G9: 23794.37 | H9: =G9/D9 -> 8.0050034 | I9: =F9-G9 -> 1679.4168 | J9: =E9-H9 -> 0.56499656 | K9: 45378 | L9: =DAYS360(K9,$C$1) -> 36 | M9: =(I9/G9) -> 0.070580427 | N9: 20 | O9: 96 | P9: 98 | Q9: 6.76 | R9: =Q9*0.93 -> 6.2868 | S9: 7.21 | T9: =Q9*1.25 -> 8.45 | U9: =Q9*1.5 -> 10.14 | V9: =Q9*2 -> 13.52 | W9: =H9-(H9*0.07) -> 7.4446532 | X9: 7.75 | Y9: =(X9-H9)/H9 -> -0.031855506 | Z9: =F9/F$19 -> 0.044460325 | AB9: 45531 | AC9: 99
A10: AEM | B10: Long | C10: Agnico-Eagle Mines | D10: 828.4023 | E10: 65.04 | F10: =E10*D10 -> 53879.286 | G10: 47623.59 | H10: =G10/D10 -> 57.488481 | I10: =F10-G10 -> 6255.6956 | J10: =E10-H10 -> 7.5515189 | K10: 45378 | L10: =DAYS360(K10,$C$1) -> 36 | M10: =(I10/G10) -> 0.13135708 | N10: 20 | O10: 89 | P10: 97 | Q10: 57.16 | R10: =Q10*0.93 -> 53.1588 | S10: 60.15 | T10: =Q10*1.25 -> 71.45 | U10: =Q10*1.5 -> 85.74 | V10: =Q10*2 -> 114.32 | W10: =H10-(H10*0.07) -> 53.464287 | X10: 59 | Y10: =(X10-H10)/H10 -> 0.026292552 | Z10: =F10/F$19 -> 0.094037473 | AB10: 45504 | AC10: 99
F11: =E11*D11 -> 0 | H11: =G11/D11 -> #DIV/0! | I11: =F11-G11 -> 0 | J11: =E11-H11 -> #DIV/0! | L11: =DAYS360(K11,$C$1) -> 44763 | M11: =(I11/G11) -> #DIV/0! | R11: =Q11*0.93 -> 0 | T11: =Q11*1.25 -> 0 | U11: =Q11*1.5 -> 0 | V11: =Q11*2 -> 0 | W11: =H11-(H11*0.07) -> #DIV/0! | Y11: =(X11-H11)/H11 -> #DIV/0! | Z11: =F11/F$19 -> 0
F12: =E12*D12 -> 0 | H12: =G12/D12 -> #DIV/0! | I12: =F12-G12 -> 0 | J12: =E12-H12 -> #DIV/0! | L12: =DAYS360(K12,$C$1) -> 44763 | M12: =(I12/G12) -> #DIV/0! | R12: =Q12*0.93 -> 0 | T12: =Q12*1.25 -> 0 | U12: =Q12*1.5 -> 0 | V12: =Q12*2 -> 0 | W12: =H12-(H12*0.07) -> #DIV/0! | Y12: =(X12-H12)/H12 -> #DIV/0! | Z12: =F12/F$19 -> 0 | AD12: Bought after pivot test.
F13: =E13*D13 -> 0 | H13: =G13/D13 -> #DIV/0! | I13: =F13-G13 -> 0 | J13: =E13-H13 -> #DIV/0! | L13: =DAYS360(K13,$C$1) -> 44763 | M13: =(I13/G13) -> #DIV/0! | R13: =Q13*0.93 -> 0 | T13: =Q13*1.25 -> 0 | U13: =Q13*1.5 -> 0 | V13: =Q13*2 -> 0 | W13: =H13-(H13*0.07) -> #DIV/0! | Y13: =(X13-H13)/H13 -> #DIV/0! | Z13: =F13/F$19 -> 0 | AD13: Bought after pivot test.
F14: =E14*D14 -> 0 | H14: =G14/D14 -> #DIV/0! | I14: =F14-G14 -> 0 | J14: =E14-H14 -> #DIV/0! | L14: =DAYS360(K14,$C$1) -> 44763 | M14: =(I14/G14) -> #DIV/0! | R14: =Q14*0.93 -> 0 | T14: =Q14*1.25 -> 0 | U14: =Q14*1.5 -> 0 | V14: =Q14*2 -> 0 | W14: =H14-(H14*0.07) -> #DIV/0! | Y14: =(X14-H14)/H14 -> #DIV/0! | Z14: =F14/F$19 -> 0
F15: =E15*D15 -> 0 | H15: =G15/D15 -> #DIV/0! | I15: =F15-G15 -> 0 | J15: =E15-H15 -> #DIV/0! | L15: =DAYS360(K15,$C$1) -> 44763 | M15: =(I15/G15) -> #DIV/0! | R15: =Q15*0.93 -> 0 | T15: =Q15*1.25 -> 0 | U15: =Q15*1.5 -> 0 | V15: =Q15*2 -> 0 | W15: =H15-(H15*0.07) -> #DIV/0! | Y15: =(X15-H15)/H15 -> #DIV/0! | Z15: =F15/F$19 -> 0
A16: BIL | B16: Long | C16: Tbill ETF | D16: 277.4286 | E16: 91.48 | F16: =E16*D16 -> 25379.168 | G16: 25401.36 | H16: =G16/D16 -> 91.559991 | I16: =F16-G16 -> -22.191672 | J16: =E16-H16 -> -0.079990571 | M16: =(I16/G16) -> -0.0008736411 | R16: =Q16*0.93 -> 0 | T16: =Q16*1.25 -> 0 | U16: =Q16*1.5 -> 0 | V16: =Q16*2 -> 0 | W16: =H16-(H16*0.07) -> 85.150791 | Y16: =(X16-H16)/H16 -> -1 | Z16: =F16/F$19 -> 0.044295184
A17: Sub-Total | F17: =SUM(F6:F16) -> 262342.48 | G17: =SUM(G6:G16) -> 171442.58 | I17: =SUM(I6:I16) -> 90899.899
D18: Cash, other | F18: 310613 | G18: =F18/F19 -> 0.54212415
D19: Total | F19: =SUM(F17:F18) -> 572955.48
H20: 04/12/24 close | I20: ='04-19-24'!F19 -> 558999.32 | K20: 45291 | L20: 476160.6
A21: * | H21: Week's change | I21: =(F19-I20)/I20 -> 0.02496633 | K21: chg % | L21: =(F19-L20)/L20 -> 0.203282
M23: days
A24: 2024 Closed Trades - Managed Acct | D24: Qty | E24: Cost/sh | F24: $ cost | G24: $Proc | H24: Proc/sh | I24: Profit/loss | J24: % | K24: Date purch | L24: Date sold | M24: held | P24: Comments
A25: YELP | B25: Long | C25: Yelp Inc | D25: 808.573 | E25: =F25/D25 -> 47.428062 | F25: 38349.05 | G25: 35186.18 | H25: =G25/D25 -> 43.516392 | I25: =G25-F25 -> -3162.87 | J25: =I25/F25 -> -0.082475837 | K25: 45286 | L25: 45302 | M25: =DAYS360(K25,L25) -> 15 | O25: Closed below stop for 2 days.
A26: TS | B26: Long | C26: Tenaris | D26: 1166.935 | E26: =F26/D26 -> 35.085005 | F26: 40941.92 | G26: 36634.59 | H26: =G26/D26 -> 31.393857 | I26: =G26-F26 -> -4307.33 | J26: =I26/F26 -> -0.10520586 | K26: 45233 | L26: 45307 | M26: =DAYS360(K26,L26) -> 73
A27: MNSO | B27: Long | C27: Minoso | D27: =1211.7123+804.6763 -> 2016.3886 | E27: =F27/D27 -> 20.49104 | F27: 41317.9 | G27: 42071.53 | H27: =G27/D27 -> 20.864793 | I27: =G27-F27 -> 753.63 | J27: =I27/F27 -> 0.018239794 | K27: 45135 | L27: 45308 | M27: =DAYS360(K27,L27) -> 169 | O27: Totally blew this trade. Had a nearly 50% profit.
A28: ACMR | B28: Long | C28: ACM Research | D28: =1339.9646+918.07 -> 2258.0346 | E28: =F28/D28 -> 21.193736 | F28: =28457.8+19398.39 -> 47856.19 | G28: 39178.27 | H28: =G28/D28 -> 17.350607 | I28: =G28-F28 -> -8677.92 | J28: =I28/F28 -> -0.18133328 | K28: 45302 | L28: 45322 | M28: =DAYS360(K28,L28) -> 20
A29: MDB | B29: Long | C29: MongoDB | D29: 126.054 | E29: =F29/D29 -> 450.27964 | F29: 56759.55 | G29: 54939.36 | H29: =G29/D29 -> 435.83988 | I29: =G29-F29 -> -1820.19 | J29: =I29/F29 -> -0.032068436 | K29: 45327 | L29: 45342 | M29: =DAYS360(K29,L29) -> 15 | O29: Stopped out.
A30: VKTX | B30: Long | C30: Viking Therap | D30: 808.6324 | E30: =F30/D30 -> 21.530005 | F30: 17409.86 | G30: 28227.27 | H30: =G30/D30 -> 34.907419 | I30: =G30-F30 -> 10817.41 | J30: =I30/F30 -> 0.62133814 | K30: 45309 | L30: 45343 | M30: =DAYS360(K30,L30) -> 33 | O30: Took partial profit.
A31: BIRK | B31: Long | C31: Birkenstock Hldg | D31: =567.3728+414.8485 -> 982.2213 | E31: =F31/D31 -> 52.971342 | F31: 52029.58 | G31: 47202.25 | H31: =G31/D31 -> 48.056634 | I31: =G31-F31 -> -4827.33 | J31: =I31/F31 -> -0.092780491 | K31: 45344 | L31: 45351 | M31: =DAYS360(K31,L31) -> 7 | O31: Stopped out after earnings.
A32: DDOG | B32: Long | C32: Datadog | D32: =308.2955+142.5312 -> 450.8267 | E32: =F32/D32 -> 130.66999 | F32: 58909.52 | G32: 55702.82 | H32: =G32/D32 -> 123.55706 | I32: =G32-F32 -> -3206.7 | J32: =I32/F32 -> -0.054434326 | K32: 45286 | L32: 45356 | M32: =DAYS360(K32,L32) -> 69 | O32: Broke 50dma
A33: IOT | B33: Long | C33: Samsara | D33: =846.327+640.0668 -> 1486.3938 | E33: =F33/D33 -> 34.902742 | F33: =30020.93+21858.29 -> 51879.22 | G33: 51882.03 | H33: =G33/D33 -> 34.904633 | I33: =G33-F33 -> 2.81 | J33: =I33/F33 -> 5.4164268e-05 | K33: 45331 | L33: 45366 | M33: =DAYS360(K33,L33) -> 36 | O33: B/o did not follow through. Sold at my cost.
A34: KD | B34: Long | C34: Kyndryl Hldgs | D34: =1160.2602+1046.0778 -> 2206.338 | E34: =F34/D34 -> 17.884522 | F34: =20288.83+19170.47 -> 39459.3 | G34: 47805.42 | H34: =G34/D34 -> 21.667315 | I34: =G34-F34 -> 8346.12 | J34: =I34/F34 -> 0.21151212 | K34: 45243 | L34: 45373 | M34: =DAYS360(K34,L34) -> 129 | O34: Took profit.
A35: BPMC | B35: Long | C35: Blueprint Med | D35: =464.2554+269.0604 -> 733.3158 | E35: =F35/D35 -> 97.201615 | F35: 71279.48 | G35: 66395.73 | H35: =G35/D35 -> 90.541797 | I35: =G35-F35 -> -4883.75 | J35: =I35/F35 -> -0.068515511 | K35: 45349 | L35: 45394 | M35: =DAYS360(K35,L35) -> 45 | O35: Bad market day. Took the loss above my stop.
A36: CCJ | B36: Long | C36: Cameco | D36: 901.358 | E36: =F36/D36 -> 51.760011 | F36: 46654.3 | G36: 44379.95 | H36: =G36/D36 -> 49.236763 | I36: =G36-F36 -> -2274.35 | J36: =I36/F36 -> -0.04874899 | K36: 45394 | L36: 45394 | M36: =DAYS360(K36,L36) -> 0 | O36: Breakout rejected same day as I bought.
A37: AXON | B37: Long | C37: Axon Enterprise | D37: 267.8431 | E37: =F37/D37 -> 228.36594 | F37: 61166.24 | G37: 81558.94 | H37: =G37/D37 -> 304.50267 | I37: =G37-F37 -> 20392.7 | J37: =I37/F37 -> 0.33339797 | K37: 45238 | L37: 45397 | M37: =DAYS360(K37,L37) -> 157 | O37: Taking profits. Broke 21dema and consolidation.
A38: ARM | B38: Long | C38: Arm Holdings | D38: 224.4175 | E38: =F38/D38 -> 131.07547 | F38: 29415.63 | G38: 27481.43 | H38: =G38/D38 -> 122.45672 | I38: =G38-F38 -> -1934.2 | J38: =I38/F38 -> -0.065754159 | K38: 45393 | L38: 45397 | M38: =DAYS360(K38,L38) -> 4 | O38: Broke 50dma. Near stop loss.
A39: BLBD | B39: Long | C39: Bluebird | D39: =952.002+512.6146 -> 1464.6166 | E39: =F39/D39 -> 30.008099 | F39: 43950.36 | G39: 49174.83 | H39: =G39/D39 -> 33.575224 | I39: =G39-F39 -> 5224.47 | J39: =I39/F39 -> 0.11887206 | K39: 45321 | L39: 45400 | M39: =DAYS360(K39,L39) -> 78 | O39: Broke 50dma. Near stop loss.
A40: UFPT | B40: Long | C40: UFP Technologies | D40: 268.5725 | E40: =F40/D40 -> 202.8001 | F40: 54466.53 | G40: 57142.12 | H40: =G40/D40 -> 212.76236 | I40: =G40-F40 -> 2675.59 | J40: =I40/F40 -> 0.049123563 | K40: 45370 | L40: 45401 | M40: =DAYS360(K40,L40) -> 30 | O40: Stopped out.
J42: Avg
H43: # of losses | I43: 9 | J43: -0.0813
H44: # of wins | I44: 7 | J44: 0.1933

Sheet 05-10-24
C1: 45422
C3: MANAGED ACCT | X3: Current | AC3: IBD
H4: Cost | J4: P/L | N4: Group | P4: EPS | R4: pivot | S4: last | W4: cost | X4: Stop | Y4: Stop | Z4: % | AB4: EPS | AC4: Comp
A5: Symbol | B5: Position | C5: Name | D5: Qty | E5: Current | F5: Value | G5: Cost | H5: per share | I5: P/L $ | J5: per sh | K5: Date purch | L5: days held | M5: % incr | N5: Rank | O5: RS | P5: RS | Q5: pivot | R5: -0.07 | S5: low | T5: 0.25 | U5: 0.5 | V5: 1 | W5: -0.07 | X5: Loss | Y5: Loss% | Z5: of port | AB5: Due | AC5: Rank
A7: VKTX | B7: Long | C7: Viking Therap | D7: =1286.8297+948.5633-808.6324 -> 1426.7606 | E7: 73.64 | F7: =E7*D7 -> 105066.65 | G7: =28174.78+19947.6-17409.86 -> 30712.52 | H7: =G7/D7 -> 21.52605 | I7: =F7-G7 -> 74354.131 | J7: =E7-H7 -> 52.11395 | K7: 45309 | L7: =DAYS360(K7,$C$1) -> 112 | M7: =(I7/G7) -> 2.4209713 | N7: 26 | O7: 99 | P7: 21 | Q7: 20.03 | R7: =Q7*0.93 -> 18.6279 | S7: 60.3 | T7: =Q7*1.25 -> 25.0375 | U7: =Q7*1.5 -> 30.045 | V7: =Q7*2 -> 40.06 | W7: =H7-(H7*0.07) -> 20.019226 | X7: 55 | Y7: =(X7-H7)/H7 -> 1.5550438 | Z7: =F7/F$19 -> 0.14385801 | AB7: 45497 | AC7: 74
A8: HMY | B8: Long | C8: Harmony Gold | D8: =2972.4372+3509.2812 -> 6481.7184 | E8: 9.21 | F8: =E8*D8 -> 59696.626 | G8: =23794.37+31996.67 -> 55791.04 | H8: =G8/D8 -> 8.6074458 | I8: =F8-G8 -> 3905.5865 | J8: =E8-H8 -> 0.60255417 | K8: 45378 | L8: =DAYS360(K8,$C$1) -> 43 | M8: =(I8/G8) -> 0.07000383 | N8: 6 | O8: 97 | P8: 99 | Q8: 6.76 | R8: =Q8*0.93 -> 6.2868 | S8: 7.21 | T8: =Q8*1.25 -> 8.45 | U8: =Q8*1.5 -> 10.14 | V8: =Q8*2 -> 13.52 | W8: =H8-(H8*0.07) -> 8.0049246 | X8: 8.25 | Y8: =(X8-H8)/H8 -> -0.041527514 | Z8: =F8/F$19 -> 0.08173705 | AB8: 45531 | AC8: 99
A9: AEM | B9: Long | C9: Agnico-Eagle Mines | D9: 828.4023 | E9: 68.4 | F9: =E9*D9 -> 56662.717 | G9: 47623.59 | H9: =G9/D9 -> 57.488481 | I9: =F9-G9 -> 9039.1273 | J9: =E9-H9 -> 10.911519 | K9: 45378 | L9: =DAYS360(K9,$C$1) -> 43 | M9: =(I9/G9) -> 0.18980357 | N9: 6 | O9: 92 | P9: 97 | Q9: 57.16 | R9: =Q9*0.93 -> 53.1588 | S9: 60.15 | T9: =Q9*1.25 -> 71.45 | U9: =Q9*1.5 -> 85.74 | V9: =Q9*2 -> 114.32 | W9: =H9-(H9*0.07) -> 53.464287 | X9: 62 | Y9: =(X9-H9)/H9 -> 0.078476919 | Z9: =F9/F$19 -> 0.077582999 | AB9: 45504 | AC9: 99
A10: TOST | B10: Long | C10: Toast | D10: 1366.874 | E10: 26.83 | F10: =E10*D10 -> 36673.229 | G10: 36957.24 | H10: =G10/D10 -> 27.037781 | I10: =F10-G10 -> -284.01058 | J10: =E10-H10 -> -0.2077811 | K10: 45421 | L10: =DAYS360(K10,$C$1) -> 1 | M10: =(I10/G10) -> -0.0076848428 | N10: 50 | O10: 93 | P10: 35 | Q10: 25.63 | R10: =Q10*0.93 -> 23.8359 | S10: 21.53 | T10: =Q10*1.25 -> 32.0375 | U10: =Q10*1.5 -> 38.445 | V10: =Q10*2 -> 51.26 | W10: =H10-(H10*0.07) -> 25.145136 | X10: 24.75 | Y10: =(X10-H10)/H10 -> -0.084614233 | Z10: =F10/F$19 -> 0.050213249 | AB10: 45511 | AC10: 83
A11: SCCO | B11: Long | C11: Southern Copper | D11: 494.9036 | E11: 118.75 | F11: =E11*D11 -> 58769.802 | G11: 59378.55 | H11: =G11/D11 -> 119.98003 | I11: =F11-G11 -> -608.7475 | J11: =E11-H11 -> -1.2300325 | K11: 45422 | L11: =DAYS360(K11,$C$1) -> 0 | M11: =(I11/G11) -> -0.010251977 | N11: 14 | O11: 95 | P11: 60 | Q11: 121 | R11: =Q11*0.93 -> 112.53 | S11: 110.91 | T11: =Q11*1.25 -> 151.25 | U11: =Q11*1.5 -> 181.5 | V11: =Q11*2 -> 242 | W11: =H11-(H11*0.07) -> 111.58143 | X11: 112 | Y11: =(X11-H11)/H11 -> -0.066511338 | Z11: =F11/F$19 -> 0.080468035 | AB11: 45496 | AC11: 89
F12: =E12*D12 -> 0 | H12: =G12/D12 -> #DIV/0! | I12: =F12-G12 -> 0 | J12: =E12-H12 -> #DIV/0! | L12: =DAYS360(K12,$C$1) -> 44770 | M12: =(I12/G12) -> #DIV/0! | R12: =Q12*0.93 -> 0 | T12: =Q12*1.25 -> 0 | U12: =Q12*1.5 -> 0 | V12: =Q12*2 -> 0 | W12: =H12-(H12*0.07) -> #DIV/0! | Y12: =(X12-H12)/H12 -> #DIV/0! | Z12: =F12/F$19 -> 0
F13: =E13*D13 -> 0 | H13: =G13/D13 -> #DIV/0! | I13: =F13-G13 -> 0 | J13: =E13-H13 -> #DIV/0! | L13: =DAYS360(K13,$C$1) -> 44770 | M13: =(I13/G13) -> #DIV/0! | R13: =Q13*0.93 -> 0 | T13: =Q13*1.25 -> 0 | U13: =Q13*1.5 -> 0 | V13: =Q13*2 -> 0 | W13: =H13-(H13*0.07) -> #DIV/0! | Y13: =(X13-H13)/H13 -> #DIV/0! | Z13: =F13/F$19 -> 0
F14: =E14*D14 -> 0 | H14: =G14/D14 -> #DIV/0! | I14: =F14-G14 -> 0 | J14: =E14-H14 -> #DIV/0! | L14: =DAYS360(K14,$C$1) -> 44770 | M14: =(I14/G14) -> #DIV/0! | R14: =Q14*0.93 -> 0 | T14: =Q14*1.25 -> 0 | U14: =Q14*1.5 -> 0 | V14: =Q14*2 -> 0 | W14: =H14-(H14*0.07) -> #DIV/0! | Y14: =(X14-H14)/H14 -> #DIV/0! | Z14: =F14/F$19 -> 0
F15: =E15*D15 -> 0 | H15: =G15/D15 -> #DIV/0! | I15: =F15-G15 -> 0 | J15: =E15-H15 -> #DIV/0! | L15: =DAYS360(K15,$C$1) -> 44770 | M15: =(I15/G15) -> #DIV/0! | R15: =Q15*0.93 -> 0 | T15: =Q15*1.25 -> 0 | U15: =Q15*1.5 -> 0 | V15: =Q15*2 -> 0 | W15: =H15-(H15*0.07) -> #DIV/0! | Y15: =(X15-H15)/H15 -> #DIV/0! | Z15: =F15/F$19 -> 0
A16: BIL | B16: Long | C16: Tbill ETF | D16: 363.7138 | E16: 91.56 | F16: =E16*D16 -> 33301.636 | G16: 25401.36 | H16: =G16/D16 -> 69.838868 | I16: =F16-G16 -> 7900.2755 | J16: =E16-H16 -> 21.721132 | M16: =(I16/G16) -> 0.31101782 | R16: =Q16*0.93 -> 0 | T16: =Q16*1.25 -> 0 | U16: =Q16*1.5 -> 0 | V16: =Q16*2 -> 0 | W16: =H16-(H16*0.07) -> 64.950147 | Y16: =(X16-H16)/H16 -> -1 | Z16: =F16/F$19 -> 0.045596838
A17: Sub-Total | F17: =SUM(F6:F16) -> 350170.66 | G17: =SUM(G6:G16) -> 255864.3 | I17: =SUM(I6:I16) -> 94306.362
D18: Cash, other | F18: 380179 | G18: =F18/F19 -> 0.52054382
D19: Total | F19: =SUM(F17:F18) -> 730349.66 | K19: Control acct (Doug's IRA) | M19: Today
H20: 04/12/24 close | I20: ='04-19-24'!F19 -> 558999.32 | K20: 45291 | L20: 139707.06 | M20: 167180
A21: * | H21: Week's change | I21: =(F19-I20)/I20 -> 0.30653051 | K21: chg % | L21: =(M20-L20)/L20 -> 0.19664676
H22: Added Dale this week.
M23: days
A24: 2024 Closed Trades - Managed Acct | D24: Qty | E24: Cost/sh | F24: $ cost | G24: $Proc | H24: Proc/sh | I24: Profit/loss | J24: % | K24: Date purch | L24: Date sold | M24: held | P24: Comments
A25: YELP | B25: Long | C25: Yelp Inc | D25: 808.573 | E25: =F25/D25 -> 47.428062 | F25: 38349.05 | G25: 35186.18 | H25: =G25/D25 -> 43.516392 | I25: =G25-F25 -> -3162.87 | J25: =I25/F25 -> -0.082475837 | K25: 45286 | L25: 45302 | M25: =DAYS360(K25,L25) -> 15 | O25: Closed below stop for 2 days.
A26: TS | B26: Long | C26: Tenaris | D26: 1166.935 | E26: =F26/D26 -> 35.085005 | F26: 40941.92 | G26: 36634.59 | H26: =G26/D26 -> 31.393857 | I26: =G26-F26 -> -4307.33 | J26: =I26/F26 -> -0.10520586 | K26: 45233 | L26: 45307 | M26: =DAYS360(K26,L26) -> 73
A27: MNSO | B27: Long | C27: Minoso | D27: =1211.7123+804.6763 -> 2016.3886 | E27: =F27/D27 -> 20.49104 | F27: 41317.9 | G27: 42071.53 | H27: =G27/D27 -> 20.864793 | I27: =G27-F27 -> 753.63 | J27: =I27/F27 -> 0.018239794 | K27: 45135 | L27: 45308 | M27: =DAYS360(K27,L27) -> 169 | O27: Totally blew this trade. Had a nearly 50% profit.
A28: ACMR | B28: Long | C28: ACM Research | D28: =1339.9646+918.07 -> 2258.0346 | E28: =F28/D28 -> 21.193736 | F28: =28457.8+19398.39 -> 47856.19 | G28: 39178.27 | H28: =G28/D28 -> 17.350607 | I28: =G28-F28 -> -8677.92 | J28: =I28/F28 -> -0.18133328 | K28: 45302 | L28: 45322 | M28: =DAYS360(K28,L28) -> 20
A29: MDB | B29: Long | C29: MongoDB | D29: 126.054 | E29: =F29/D29 -> 450.27964 | F29: 56759.55 | G29: 54939.36 | H29: =G29/D29 -> 435.83988 | I29: =G29-F29 -> -1820.19 | J29: =I29/F29 -> -0.032068436 | K29: 45327 | L29: 45342 | M29: =DAYS360(K29,L29) -> 15 | O29: Stopped out.
A30: VKTX | B30: Long | C30: Viking Therap | D30: 808.6324 | E30: =F30/D30 -> 21.530005 | F30: 17409.86 | G30: 28227.27 | H30: =G30/D30 -> 34.907419 | I30: =G30-F30 -> 10817.41 | J30: =I30/F30 -> 0.62133814 | K30: 45309 | L30: 45343 | M30: =DAYS360(K30,L30) -> 33 | O30: Took partial profit.
A31: BIRK | B31: Long | C31: Birkenstock Hldg | D31: =567.3728+414.8485 -> 982.2213 | E31: =F31/D31 -> 52.971342 | F31: 52029.58 | G31: 47202.25 | H31: =G31/D31 -> 48.056634 | I31: =G31-F31 -> -4827.33 | J31: =I31/F31 -> -0.092780491 | K31: 45344 | L31: 45351 | M31: =DAYS360(K31,L31) -> 7 | O31: Stopped out after earnings.
A32: DDOG | B32: Long | C32: Datadog | D32: =308.2955+142.5312 -> 450.8267 | E32: =F32/D32 -> 130.66999 | F32: 58909.52 | G32: 55702.82 | H32: =G32/D32 -> 123.55706 | I32: =G32-F32 -> -3206.7 | J32: =I32/F32 -> -0.054434326 | K32: 45286 | L32: 45356 | M32: =DAYS360(K32,L32) -> 69 | O32: Broke 50dma
A33: IOT | B33: Long | C33: Samsara | D33: =846.327+640.0668 -> 1486.3938 | E33: =F33/D33 -> 34.902742 | F33: =30020.93+21858.29 -> 51879.22 | G33: 51882.03 | H33: =G33/D33 -> 34.904633 | I33: =G33-F33 -> 2.81 | J33: =I33/F33 -> 5.4164268e-05 | K33: 45331 | L33: 45366 | M33: =DAYS360(K33,L33) -> 36 | O33: B/o did not follow through. Sold at my cost.
A34: KD | B34: Long | C34: Kyndryl Hldgs | D34: =1160.2602+1046.0778 -> 2206.338 | E34: =F34/D34 -> 17.884522 | F34: =20288.83+19170.47 -> 39459.3 | G34: 47805.42 | H34: =G34/D34 -> 21.667315 | I34: =G34-F34 -> 8346.12 | J34: =I34/F34 -> 0.21151212 | K34: 45243 | L34: 45373 | M34: =DAYS360(K34,L34) -> 129 | O34: Took profit.
A35: BPMC | B35: Long | C35: Blueprint Med | D35: =464.2554+269.0604 -> 733.3158 | E35: =F35/D35 -> 97.201615 | F35: 71279.48 | G35: 66395.73 | H35: =G35/D35 -> 90.541797 | I35: =G35-F35 -> -4883.75 | J35: =I35/F35 -> -0.068515511 | K35: 45349 | L35: 45394 | M35: =DAYS360(K35,L35) -> 45 | O35: Bad market day. Took the loss above my stop.
A36: CCJ | B36: Long | C36: Cameco | D36: 901.358 | E36: =F36/D36 -> 51.760011 | F36: 46654.3 | G36: 44379.95 | H36: =G36/D36 -> 49.236763 | I36: =G36-F36 -> -2274.35 | J36: =I36/F36 -> -0.04874899 | K36: 45394 | L36: 45394 | M36: =DAYS360(K36,L36) -> 0 | O36: Breakout rejected same day as I bought.
A37: AXON | B37: Long | C37: Axon Enterprise | D37: 267.8431 | E37: =F37/D37 -> 228.36594 | F37: 61166.24 | G37: 81558.94 | H37: =G37/D37 -> 304.50267 | I37: =G37-F37 -> 20392.7 | J37: =I37/F37 -> 0.33339797 | K37: 45238 | L37: 45397 | M37: =DAYS360(K37,L37) -> 157 | O37: Taking profits. Broke 21dema and consolidation.
A38: ARM | B38: Long | C38: Arm Holdings | D38: 224.4175 | E38: =F38/D38 -> 131.07547 | F38: 29415.63 | G38: 27481.43 | H38: =G38/D38 -> 122.45672 | I38: =G38-F38 -> -1934.2 | J38: =I38/F38 -> -0.065754159 | K38: 45393 | L38: 45397 | M38: =DAYS360(K38,L38) -> 4 | O38: Broke 50dma. Near stop loss.
A39: BLBD | B39: Long | C39: Bluebird | D39: =952.002+512.6146 -> 1464.6166 | E39: =F39/D39 -> 30.008099 | F39: 43950.36 | G39: 49174.83 | H39: =G39/D39 -> 33.575224 | I39: =G39-F39 -> 5224.47 | J39: =I39/F39 -> 0.11887206 | K39: 45321 | L39: 45400 | M39: =DAYS360(K39,L39) -> 78 | O39: Broke 50dma. Near stop loss.
A40: UFPT | B40: Long | C40: UFP Technologies | D40: 268.5725 | E40: =F40/D40 -> 202.8001 | F40: 54466.53 | G40: 57142.12 | H40: =G40/D40 -> 212.76236 | I40: =G40-F40 -> 2675.59 | J40: =I40/F40 -> 0.049123563 | K40: 45370 | L40: 45401 | M40: =DAYS360(K40,L40) -> 30 | O40: Stopped out.
A41: AAON | B41: Long | C41: AAON | D41: =532.4164+77.1815 -> 609.5979 | E41: =F41/D41 -> 72.032302 | F41: =38270.34+5640.4 -> 43910.74 | G41: 46906.35 | H41: =G41/D41 -> 76.946377 | I41: =G41-F41 -> 2995.61 | J41: =I41/F41 -> 0.06822044 | K41: 45313 | L41: 45420 | M41: =DAYS360(K41,L41) -> 106 | O41: Bad reaction to earnings.
J45: Avg
H46: # of losses | I46: 9 | J46: -0.0813
H47: # of wins | I47: 8 | J47: 0.1776

Sheet 05-17-24
C1: 45429
C3: MANAGED ACCT | X3: Current | AC3: IBD
H4: Cost | J4: P/L | N4: Group | P4: EPS | R4: pivot | S4: last | W4: cost | X4: Stop | Y4: Stop | Z4: % | AB4: EPS | AC4: Comp
A5: Symbol | B5: Position | C5: Name | D5: Qty | E5: Current | F5: Value | G5: Cost | H5: per share | I5: P/L $ | J5: per sh | K5: Date purch | L5: days held | M5: % incr | N5: Rank | O5: RS | P5: RS | Q5: pivot | R5: -0.07 | S5: low | T5: 0.25 | U5: 0.5 | V5: 1 | W5: -0.07 | X5: Loss | Y5: Loss% | Z5: of port | AB5: Due | AC5: Rank
A7: VKTX | B7: Long | C7: Viking Therap | D7: =1286.8297+948.5633-808.6324 -> 1426.7606 | E7: 67 | F7: =E7*D7 -> 95592.96 | G7: =28174.78+19947.6-17409.86 -> 30712.52 | H7: =G7/D7 -> 21.52605 | I7: =F7-G7 -> 64880.44 | J7: =E7-H7 -> 45.47395 | K7: 45309 | L7: =DAYS360(K7,$C$1) -> 119 | M7: =(I7/G7) -> 2.1125079 | N7: 26 | O7: 99 | P7: 21 | Q7: 20.03 | R7: =Q7*0.93 -> 18.6279 | S7: 60.3 | T7: =Q7*1.25 -> 25.0375 | U7: =Q7*1.5 -> 30.045 | V7: =Q7*2 -> 40.06 | W7: =H7-(H7*0.07) -> 20.019226 | X7: 55 | Y7: =(X7-H7)/H7 -> 1.5550438 | Z7: =F7/F$19 -> 0.13060657 | AB7: 45497 | AC7: 64
A8: HMY | B8: Long | C8: Harmony Gold | D8: =2972.4372+3509.2812 -> 6481.7184 | E8: 9.76 | F8: =E8*D8 -> 63261.572 | G8: =23794.37+31996.67 -> 55791.04 | H8: =G8/D8 -> 8.6074458 | I8: =F8-G8 -> 7470.5316 | J8: =E8-H8 -> 1.1525542 | K8: 45378 | L8: =DAYS360(K8,$C$1) -> 50 | M8: =(I8/G8) -> 0.133902 | N8: 8 | O8: 98 | P8: 98 | Q8: 6.76 | R8: =Q8*0.93 -> 6.2868 | S8: 7.21 | T8: =Q8*1.25 -> 8.45 | U8: =Q8*1.5 -> 10.14 | V8: =Q8*2 -> 13.52 | W8: =H8-(H8*0.07) -> 8.0049246 | X8: 8.25 | Y8: =(X8-H8)/H8 -> -0.041527514 | Z8: =F8/F$19 -> 0.086432899 | AB8: 45531 | AC8: 99
A9: AEM | B9: Long | C9: Agnico-Eagle Mines | D9: 828.4023 | E9: 70.11 | F9: =E9*D9 -> 58079.285 | G9: 47623.59 | H9: =G9/D9 -> 57.488481 | I9: =F9-G9 -> 10455.695 | J9: =E9-H9 -> 12.621519 | K9: 45378 | L9: =DAYS360(K9,$C$1) -> 50 | M9: =(I9/G9) -> 0.21954866 | N9: 8 | O9: 93 | P9: 97 | Q9: 57.16 | R9: =Q9*0.93 -> 53.1588 | S9: 60.15 | T9: =Q9*1.25 -> 71.45 | U9: =Q9*1.5 -> 85.74 | V9: =Q9*2 -> 114.32 | W9: =H9-(H9*0.07) -> 53.464287 | X9: 65 | Y9: =(X9-H9)/H9 -> 0.13066129 | Z9: =F9/F$19 -> 0.079352455 | AB9: 45504 | AC9: 99
A10: TOST | B10: Long | C10: Toast | D10: 1366.874 | E10: 26.99 | F10: =E10*D10 -> 36891.929 | G10: 36957.24 | H10: =G10/D10 -> 27.037781 | I10: =F10-G10 -> -65.31074 | J10: =E10-H10 -> -0.047781098 | K10: 45421 | L10: =DAYS360(K10,$C$1) -> 8 | M10: =(I10/G10) -> -0.0017671974 | N10: 49 | O10: 94 | P10: 35 | Q10: 25.63 | R10: =Q10*0.93 -> 23.8359 | S10: 21.53 | T10: =Q10*1.25 -> 32.0375 | U10: =Q10*1.5 -> 38.445 | V10: =Q10*2 -> 51.26 | W10: =H10-(H10*0.07) -> 25.145136 | X10: 24.75 | Y10: =(X10-H10)/H10 -> -0.084614233 | Z10: =F10/F$19 -> 0.050404634 | AB10: 45511 | AC10: 81
A11: SCCO | B11: Long | C11: Southern Copper | D11: 494.9036 | E11: 125.39 | F11: =E11*D11 -> 62055.962 | G11: 59378.55 | H11: =G11/D11 -> 119.98003 | I11: =F11-G11 -> 2677.4124 | J11: =E11-H11 -> 5.4099675 | K11: 45422 | L11: =DAYS360(K11,$C$1) -> 7 | M11: =(I11/G11) -> 0.045090566 | N11: 12 | O11: 95 | P11: 59 | Q11: 121 | R11: =Q11*0.93 -> 112.53 | S11: 110.91 | T11: =Q11*1.25 -> 151.25 | U11: =Q11*1.5 -> 181.5 | V11: =Q11*2 -> 242 | W11: =H11-(H11*0.07) -> 111.58143 | X11: 115 | Y11: =(X11-H11)/H11 -> -0.041507177 | Z11: =F11/F$19 -> 0.084785701 | AB11: 45496 | AC11: 90
A12: TSM | B12: Long | C12: Taiwan Semi | D12: 390.4513 | E12: 151.68 | F12: =E12*D12 -> 59223.653 | G12: 58706.59 | H12: =G12/D12 -> 150.35573 | I12: =F12-G12 -> 517.06318 | J12: =E12-H12 -> 1.3242706 | K12: 45426 | L12: =DAYS360(K12,$C$1) -> 3 | M12: =(I12/G12) -> 0.0088075833 | N12: 100 | O12: 93 | P12: 81 | Q12: 148.43 | R12: =Q12*0.93 -> 138.0399 | S12: 125.78 | T12: =Q12*1.25 -> 185.5375 | U12: =Q12*1.5 -> 222.645 | V12: =Q12*2 -> 296.86 | W12: =H12-(H12*0.07) -> 139.83083 | X12: 139 | Y12: =(X12-H12)/H12 -> -0.075525751 | Z12: =F12/F$19 -> 0.080915979 | AB12: 45491 | AC12: 93
A13: ERJ | B13: Long | C13: Embraer ADR | D13: 1542.0192 | E13: 30.93 | F13: =E13*D13 -> 47694.654 | G13: 44039.07 | H13: =G13/D13 -> 28.559353 | I13: =F13-G13 -> 3655.5839 | J13: =E13-H13 -> 2.3706474 | K13: 45426 | L13: =DAYS360(K13,$C$1) -> 3 | M13: =(I13/G13) -> 0.083007744 | N13: 39 | O13: 97 | P13: 72 | Q13: 27.47 | R13: =Q13*0.93 -> 25.5471 | S13: 25.73 | T13: =Q13*1.25 -> 34.3375 | U13: =Q13*1.5 -> 41.205 | V13: =Q13*2 -> 54.94 | W13: =H13-(H13*0.07) -> 26.560198 | X13: 27 | Y13: =(X13-H13)/H13 -> -0.054600417 | Z13: =F13/F$19 -> 0.06516416 | AB13: 45513 | AC13: 99
A14: NVDA | B14: Long | C14: Nvidia | D14: 94.0668 | E14: 924.79 | F14: =E14*D14 -> 86992.036 | G14: 88627.87 | H14: =G14/D14 -> 942.18013 | I14: =F14-G14 -> -1635.834 | J14: =E14-H14 -> -17.390132 | K14: 45427 | L14: =DAYS360(K14,$C$1) -> 2 | M14: =(I14/G14) -> -0.018457332 | N14: 15 | O14: 98 | P14: 99 | Q14: 922.2 | R14: =Q14*0.93 -> 857.646 | S14: 812.55 | T14: =Q14*1.25 -> 1152.75 | U14: =Q14*1.5 -> 1383.3 | V14: =Q14*2 -> 1844.4 | W14: =H14-(H14*0.07) -> 876.22752 | X14: 880 | Y14: =(X14-H14)/H14 -> -0.065996012 | Z14: =F14/F$19 -> 0.11885531 | AB14: 45434 | AC14: 99
F15: =E15*D15 -> 0 | H15: =G15/D15 -> #DIV/0! | I15: =F15-G15 -> 0 | J15: =E15-H15 -> #DIV/0! | L15: =DAYS360(K15,$C$1) -> 44777 | M15: =(I15/G15) -> #DIV/0! | R15: =Q15*0.93 -> 0 | T15: =Q15*1.25 -> 0 | U15: =Q15*1.5 -> 0 | V15: =Q15*2 -> 0 | W15: =H15-(H15*0.07) -> #DIV/0! | Y15: =(X15-H15)/H15 -> #DIV/0! | Z15: =F15/F$19 -> 0
A16: BIL | B16: Long | C16: Tbill ETF | D16: 363.7138 | E16: 91.65 | F16: =E16*D16 -> 33334.37 | G16: 25401.36 | H16: =G16/D16 -> 69.838868 | I16: =F16-G16 -> 7933.0098 | J16: =E16-H16 -> 21.811132 | M16: =(I16/G16) -> 0.3123065 | R16: =Q16*0.93 -> 0 | T16: =Q16*1.25 -> 0 | U16: =Q16*1.5 -> 0 | V16: =Q16*2 -> 0 | W16: =H16-(H16*0.07) -> 64.950147 | Y16: =(X16-H16)/H16 -> -1 | Z16: =F16/F$19 -> 0.045544019
A17: Sub-Total | F17: =SUM(F6:F16) -> 543126.42 | G17: =SUM(G6:G16) -> 447237.83 | I17: =SUM(I6:I16) -> 95888.591
D18: Cash, other | F18: 188789 | G18: =F18/F19 -> 0.25793827
D19: Total | F19: =SUM(F17:F18) -> 731915.42 | K19: Control acct (Doug's IRA) | M19: Today
H20: Last week's close | I20: ='05-10-24'!F19 -> 730349.66 | K20: 45291 | L20: 139707.06 | M20: 167049
A21: * | H21: Week's change | I21: =(F19-I20)/I20 -> 0.0021438494 | K21: chg % | L21: =(M20-L20)/L20 -> 0.19570908
M23: days
A24: 2024 Closed Trades - Managed Acct | D24: Qty | E24: Cost/sh | F24: $ cost | G24: $Proc | H24: Proc/sh | I24: Profit/loss | J24: % | K24: Date purch | L24: Date sold | M24: held | P24: Comments
A25: YELP | B25: Long | C25: Yelp Inc | D25: 808.573 | E25: =F25/D25 -> 47.428062 | F25: 38349.05 | G25: 35186.18 | H25: =G25/D25 -> 43.516392 | I25: =G25-F25 -> -3162.87 | J25: =I25/F25 -> -0.082475837 | K25: 45286 | L25: 45302 | M25: =DAYS360(K25,L25) -> 15 | O25: Closed below stop for 2 days.
A26: TS | B26: Long | C26: Tenaris | D26: 1166.935 | E26: =F26/D26 -> 35.085005 | F26: 40941.92 | G26: 36634.59 | H26: =G26/D26 -> 31.393857 | I26: =G26-F26 -> -4307.33 | J26: =I26/F26 -> -0.10520586 | K26: 45233 | L26: 45307 | M26: =DAYS360(K26,L26) -> 73
A27: MNSO | B27: Long | C27: Minoso | D27: =1211.7123+804.6763 -> 2016.3886 | E27: =F27/D27 -> 20.49104 | F27: 41317.9 | G27: 42071.53 | H27: =G27/D27 -> 20.864793 | I27: =G27-F27 -> 753.63 | J27: =I27/F27 -> 0.018239794 | K27: 45135 | L27: 45308 | M27: =DAYS360(K27,L27) -> 169 | O27: Totally blew this trade. Had a nearly 50% profit.
A28: ACMR | B28: Long | C28: ACM Research | D28: =1339.9646+918.07 -> 2258.0346 | E28: =F28/D28 -> 21.193736 | F28: =28457.8+19398.39 -> 47856.19 | G28: 39178.27 | H28: =G28/D28 -> 17.350607 | I28: =G28-F28 -> -8677.92 | J28: =I28/F28 -> -0.18133328 | K28: 45302 | L28: 45322 | M28: =DAYS360(K28,L28) -> 20
A29: MDB | B29: Long | C29: MongoDB | D29: 126.054 | E29: =F29/D29 -> 450.27964 | F29: 56759.55 | G29: 54939.36 | H29: =G29/D29 -> 435.83988 | I29: =G29-F29 -> -1820.19 | J29: =I29/F29 -> -0.032068436 | K29: 45327 | L29: 45342 | M29: =DAYS360(K29,L29) -> 15 | O29: Stopped out.
A30: VKTX | B30: Long | C30: Viking Therap | D30: 808.6324 | E30: =F30/D30 -> 21.530005 | F30: 17409.86 | G30: 28227.27 | H30: =G30/D30 -> 34.907419 | I30: =G30-F30 -> 10817.41 | J30: =I30/F30 -> 0.62133814 | K30: 45309 | L30: 45343 | M30: =DAYS360(K30,L30) -> 33 | O30: Took partial profit.
A31: BIRK | B31: Long | C31: Birkenstock Hldg | D31: =567.3728+414.8485 -> 982.2213 | E31: =F31/D31 -> 52.971342 | F31: 52029.58 | G31: 47202.25 | H31: =G31/D31 -> 48.056634 | I31: =G31-F31 -> -4827.33 | J31: =I31/F31 -> -0.092780491 | K31: 45344 | L31: 45351 | M31: =DAYS360(K31,L31) -> 7 | O31: Stopped out after earnings.
A32: DDOG | B32: Long | C32: Datadog | D32: =308.2955+142.5312 -> 450.8267 | E32: =F32/D32 -> 130.66999 | F32: 58909.52 | G32: 55702.82 | H32: =G32/D32 -> 123.55706 | I32: =G32-F32 -> -3206.7 | J32: =I32/F32 -> -0.054434326 | K32: 45286 | L32: 45356 | M32: =DAYS360(K32,L32) -> 69 | O32: Broke 50dma
A33: IOT | B33: Long | C33: Samsara | D33: =846.327+640.0668 -> 1486.3938 | E33: =F33/D33 -> 34.902742 | F33: =30020.93+21858.29 -> 51879.22 | G33: 51882.03 | H33: =G33/D33 -> 34.904633 | I33: =G33-F33 -> 2.81 | J33: =I33/F33 -> 5.4164268e-05 | K33: 45331 | L33: 45366 | M33: =DAYS360(K33,L33) -> 36 | O33: B/o did not follow through. Sold at my cost.
A34: KD | B34: Long | C34: Kyndryl Hldgs | D34: =1160.2602+1046.0778 -> 2206.338 | E34: =F34/D34 -> 17.884522 | F34: =20288.83+19170.47 -> 39459.3 | G34: 47805.42 | H34: =G34/D34 -> 21.667315 | I34: =G34-F34 -> 8346.12 | J34: =I34/F34 -> 0.21151212 | K34: 45243 | L34: 45373 | M34: =DAYS360(K34,L34) -> 129 | O34: Took profit.
A35: BPMC | B35: Long | C35: Blueprint Med | D35: =464.2554+269.0604 -> 733.3158 | E35: =F35/D35 -> 97.201615 | F35: 71279.48 | G35: 66395.73 | H35: =G35/D35 -> 90.541797 | I35: =G35-F35 -> -4883.75 | J35: =I35/F35 -> -0.068515511 | K35: 45349 | L35: 45394 | M35: =DAYS360(K35,L35) -> 45 | O35: Bad market day. Took the loss above my stop.
A36: CCJ | B36: Long | C36: Cameco | D36: 901.358 | E36: =F36/D36 -> 51.760011 | F36: 46654.3 | G36: 44379.95 | H36: =G36/D36 -> 49.236763 | I36: =G36-F36 -> -2274.35 | J36: =I36/F36 -> -0.04874899 | K36: 45394 | L36: 45394 | M36: =DAYS360(K36,L36) -> 0 | O36: Breakout rejected same day as I bought.
A37: AXON | B37: Long | C37: Axon Enterprise | D37: 267.8431 | E37: =F37/D37 -> 228.36594 | F37: 61166.24 | G37: 81558.94 | H37: =G37/D37 -> 304.50267 | I37: =G37-F37 -> 20392.7 | J37: =I37/F37 -> 0.33339797 | K37: 45238 | L37: 45397 | M37: =DAYS360(K37,L37) -> 157 | O37: Taking profits. Broke 21dema and consolidation.
A38: ARM | B38: Long | C38: Arm Holdings | D38: 224.4175 | E38: =F38/D38 -> 131.07547 | F38: 29415.63 | G38: 27481.43 | H38: =G38/D38 -> 122.45672 | I38: =G38-F38 -> -1934.2 | J38: =I38/F38 -> -0.065754159 | K38: 45393 | L38: 45397 | M38: =DAYS360(K38,L38) -> 4 | O38: Broke 50dma. Near stop loss.
A39: BLBD | B39: Long | C39: Bluebird | D39: =952.002+512.6146 -> 1464.6166 | E39: =F39/D39 -> 30.008099 | F39: 43950.36 | G39: 49174.83 | H39: =G39/D39 -> 33.575224 | I39: =G39-F39 -> 5224.47 | J39: =I39/F39 -> 0.11887206 | K39: 45321 | L39: 45400 | M39: =DAYS360(K39,L39) -> 78 | O39: Broke 50dma. Near stop loss.
A40: UFPT | B40: Long | C40: UFP Technologies | D40: 268.5725 | E40: =F40/D40 -> 202.8001 | F40: 54466.53 | G40: 57142.12 | H40: =G40/D40 -> 212.76236 | I40: =G40-F40 -> 2675.59 | J40: =I40/F40 -> 0.049123563 | K40: 45370 | L40: 45401 | M40: =DAYS360(K40,L40) -> 30 | O40: Stopped out.
A41: AAON | B41: Long | C41: AAON | D41: =532.4164+77.1815 -> 609.5979 | E41: =F41/D41 -> 72.032302 | F41: =38270.34+5640.4 -> 43910.74 | G41: 46906.35 | H41: =G41/D41 -> 76.946377 | I41: =G41-F41 -> 2995.61 | J41: =I41/F41 -> 0.06822044 | K41: 45313 | L41: 45420 | M41: =DAYS360(K41,L41) -> 106 | O41: Bad reaction to earnings.
J45: Avg
H46: # of losses | I46: 9 | J46: -0.0813
H47: # of wins | I47: 8 | J47: 0.1776

Sheet 05-24-24
C1: 45436
C3: MANAGED ACCT | X3: Current | AC3: IBD
H4: Cost | J4: P/L | N4: Group | P4: EPS | R4: pivot | S4: last | W4: cost | X4: Stop | Y4: Stop | Z4: % | AB4: EPS | AC4: Comp
A5: Symbol | B5: Position | C5: Name | D5: Qty | E5: Current | F5: Value | G5: Cost | H5: per share | I5: P/L $ | J5: per sh | K5: Date purch | L5: days held | M5: % incr | N5: Rank | O5: RS | P5: RS | Q5: pivot | R5: -0.07 | S5: low | T5: 0.25 | U5: 0.5 | V5: 1 | W5: -0.07 | X5: Loss | Y5: Loss% | Z5: of port | AB5: Due | AC5: Rank
A7: VKTX | B7: Long | C7: Viking Therap | D7: =1286.8297+948.5633-808.6324 -> 1426.7606 | E7: 62.75 | F7: =E7*D7 -> 89529.228 | G7: =28174.78+19947.6-17409.86 -> 30712.52 | H7: =G7/D7 -> 21.52605 | I7: =F7-G7 -> 58816.708 | J7: =E7-H7 -> 41.22395 | K7: 45309 | L7: =DAYS360(K7,$C$1) -> 126 | M7: =(I7/G7) -> 1.9150727 | N7: 35 | O7: 99 | P7: 21 | Q7: 20.03 | R7: =Q7*0.93 -> 18.6279 | S7: 60.3 | T7: =Q7*1.25 -> 25.0375 | U7: =Q7*1.5 -> 30.045 | V7: =Q7*2 -> 40.06 | W7: =H7-(H7*0.07) -> 20.019226 | X7: 58 | Y7: =(X7-H7)/H7 -> 1.6944098 | Z7: =F7/F$19 -> 0.12320788 | AB7: 45497 | AC7: 60
A8: HMY | B8: Long | C8: Harmony Gold | D8: =2972.4372+3509.2812 -> 6481.7184 | E8: 9.25 | F8: =E8*D8 -> 59955.895 | G8: =23794.37+31996.67 -> 55791.04 | H8: =G8/D8 -> 8.6074458 | I8: =F8-G8 -> 4164.8552 | J8: =E8-H8 -> 0.64255417 | K8: 45378 | L8: =DAYS360(K8,$C$1) -> 57 | M8: =(I8/G8) -> 0.074650969 | N8: 7 | O8: 97 | P8: 99 | Q8: 6.76 | R8: =Q8*0.93 -> 6.2868 | S8: 7.21 | T8: =Q8*1.25 -> 8.45 | U8: =Q8*1.5 -> 10.14 | V8: =Q8*2 -> 13.52 | W8: =H8-(H8*0.07) -> 8.0049246 | X8: 8.75 | Y8: =(X8-H8)/H8 -> 0.016561727 | Z8: =F8/F$19 -> 0.082509798 | AB8: 45531 | AC8: 99
A9: AEM | B9: Long | C9: Agnico-Eagle Mines | D9: 828.4023 | E9: 67.71 | F9: =E9*D9 -> 56091.12 | G9: 47623.59 | H9: =G9/D9 -> 57.488481 | I9: =F9-G9 -> 8467.5297 | J9: =E9-H9 -> 10.221519 | K9: 45378 | L9: =DAYS360(K9,$C$1) -> 57 | M9: =(I9/G9) -> 0.17780116 | N9: 7 | O9: 92 | P9: 97 | Q9: 57.16 | R9: =Q9*0.93 -> 53.1588 | S9: 60.15 | T9: =Q9*1.25 -> 71.45 | U9: =Q9*1.5 -> 85.74 | V9: =Q9*2 -> 114.32 | W9: =H9-(H9*0.07) -> 53.464287 | X9: 65 | Y9: =(X9-H9)/H9 -> 0.13066129 | Z9: =F9/F$19 -> 0.077191191 | AB9: 45504 | AC9: 99
A10: TOST | B10: Long | C10: Toast | D10: =1366.874+867.842 -> 2234.716 | E10: 25.46 | F10: =E10*D10 -> 56895.869 | G10: =36957.24+22924.55 -> 59881.79 | H10: =G10/D10 -> 26.796152 | I10: =F10-G10 -> -2985.9206 | J10: =E10-H10 -> -1.3361522 | K10: 45421 | L10: =DAYS360(K10,$C$1) -> 15 | M10: =(I10/G10) -> -0.049863584 | N10: 85 | O10: 90 | P10: 35 | Q10: 25.63 | R10: =Q10*0.93 -> 23.8359 | S10: 21.53 | T10: =Q10*1.25 -> 32.0375 | U10: =Q10*1.5 -> 38.445 | V10: =Q10*2 -> 51.26 | W10: =H10-(H10*0.07) -> 24.920422 | X10: 24.75 | Y10: =(X10-H10)/H10 -> -0.076359925 | Z10: =F10/F$19 -> 0.078298667 | AB10: 45511 | AC10: 75
A11: SCCO | B11: Long | C11: Southern Copper | D11: 494.9036 | E11: 117.51 | F11: =E11*D11 -> 58156.122 | G11: 59378.55 | H11: =G11/D11 -> 119.98003 | I11: =F11-G11 -> -1222.428 | J11: =E11-H11 -> -2.4700325 | K11: 45422 | L11: =DAYS360(K11,$C$1) -> 14 | M11: =(I11/G11) -> -0.02058703 | N11: 15 | O11: 95 | P11: 59 | Q11: 121 | R11: =Q11*0.93 -> 112.53 | S11: 110.91 | T11: =Q11*1.25 -> 151.25 | U11: =Q11*1.5 -> 181.5 | V11: =Q11*2 -> 242 | W11: =H11-(H11*0.07) -> 111.58143 | X11: 115 | Y11: =(X11-H11)/H11 -> -0.041507177 | Z11: =F11/F$19 -> 0.080032995 | AB11: 45496 | AC11: 90
A12: TSM | B12: Long | C12: Taiwan Semi | D12: 390.4513 | E12: 160 | F12: =E12*D12 -> 62472.208 | G12: 58706.59 | H12: =G12/D12 -> 150.35573 | I12: =F12-G12 -> 3765.618 | J12: =E12-H12 -> 9.6442706 | K12: 45426 | L12: =DAYS360(K12,$C$1) -> 10 | M12: =(I12/G12) -> 0.06414302 | N12: 79 | O12: 94 | P12: 81 | Q12: 148.43 | R12: =Q12*0.93 -> 138.0399 | S12: 125.78 | T12: =Q12*1.25 -> 185.5375 | U12: =Q12*1.5 -> 222.645 | V12: =Q12*2 -> 296.86 | W12: =H12-(H12*0.07) -> 139.83083 | X12: 139 | Y12: =(X12-H12)/H12 -> -0.075525751 | Z12: =F12/F$19 -> 0.085972685 | AB12: 45491 | AC12: 95
A13: ERJ | B13: Long | C13: Embraer ADR | D13: =1542.0192+932.4994 -> 2474.5186 | E13: 29.12 | F13: =E13*D13 -> 72057.982 | G13: =44039.07+27471.43 -> 71510.5 | H13: =G13/D13 -> 28.898752 | I13: =F13-G13 -> 547.48163 | J13: =E13-H13 -> 0.22124773 | K13: 45426 | L13: =DAYS360(K13,$C$1) -> 10 | M13: =(I13/G13) -> 0.0076559615 | N13: 29 | O13: 97 | P13: 72 | Q13: 27.47 | R13: =Q13*0.93 -> 25.5471 | S13: 25.73 | T13: =Q13*1.25 -> 34.3375 | U13: =Q13*1.5 -> 41.205 | V13: =Q13*2 -> 54.94 | W13: =H13-(H13*0.07) -> 26.87584 | X13: 27 | Y13: =(X13-H13)/H13 -> -0.065703607 | Z13: =F13/F$19 -> 0.099164386 | AB13: 45513 | AC13: 99
A14: NVDA | B14: Long | C14: Nvidia | D14: 94.0668 | E14: 1060.24 | F14: =E14*D14 -> 99733.384 | G14: 88627.87 | H14: =G14/D14 -> 942.18013 | I14: =F14-G14 -> 11105.514 | J14: =E14-H14 -> 118.05987 | K14: 45427 | L14: =DAYS360(K14,$C$1) -> 9 | M14: =(I14/G14) -> 0.12530499 | N14: 8 | O14: 98 | P14: 99 | Q14: 922.2 | R14: =Q14*0.93 -> 857.646 | S14: 812.55 | T14: =Q14*1.25 -> 1152.75 | U14: =Q14*1.5 -> 1383.3 | V14: =Q14*2 -> 1844.4 | W14: =H14-(H14*0.07) -> 876.22752 | X14: 920 | Y14: =(X14-H14)/H14 -> -0.023541286 | Z14: =F14/F$19 -> 0.13725058 | AB14: 45519 | AC14: 99
F15: =E15*D15 -> 0 | H15: =G15/D15 -> #DIV/0! | I15: =F15-G15 -> 0 | J15: =E15-H15 -> #DIV/0! | L15: =DAYS360(K15,$C$1) -> 44784 | M15: =(I15/G15) -> #DIV/0! | R15: =Q15*0.93 -> 0 | T15: =Q15*1.25 -> 0 | U15: =Q15*1.5 -> 0 | V15: =Q15*2 -> 0 | W15: =H15-(H15*0.07) -> #DIV/0! | Y15: =(X15-H15)/H15 -> #DIV/0! | Z15: =F15/F$19 -> 0
A16: BIL | B16: Long | C16: Tbill ETF | D16: 363.7138 | E16: 91.77 | F16: =E16*D16 -> 33378.015 | G16: 25401.36 | H16: =G16/D16 -> 69.838868 | I16: =F16-G16 -> 7976.6554 | J16: =E16-H16 -> 21.931132 | M16: =(I16/G16) -> 0.31402474 | R16: =Q16*0.93 -> 0 | T16: =Q16*1.25 -> 0 | U16: =Q16*1.5 -> 0 | V16: =Q16*2 -> 0 | W16: =H16-(H16*0.07) -> 64.950147 | Y16: =(X16-H16)/H16 -> -1 | Z16: =F16/F$19 -> 0.045933987
A17: Sub-Total | F17: =SUM(F6:F16) -> 588269.82 | G17: =SUM(G6:G16) -> 497633.81 | I17: =SUM(I6:I16) -> 90636.013
D18: Cash, other | F18: 138382 | G18: =F18/F19 -> 0.19043784
D19: Total | F19: =SUM(F17:F18) -> 726651.82 | K19: Control acct (Doug's IRA) | M19: Today
H20: Last week's close | I20: ='05-17-24'!F19 -> 731915.42 | K20: 45291 | L20: 139707.06 | M20: 165625
A21: * | H21: Week's change | I21: =(F19-I20)/I20 -> -0.0071915392 | K21: chg % | L21: =(M20-L20)/L20 -> 0.18551632
M23: days
A24: 2024 Closed Trades - Managed Acct | D24: Qty | E24: Cost/sh | F24: $ cost | G24: $Proc | H24: Proc/sh | I24: Profit/loss | J24: % | K24: Date purch | L24: Date sold | M24: held | P24: Comments
A25: YELP | B25: Long | C25: Yelp Inc | D25: 808.573 | E25: =F25/D25 -> 47.428062 | F25: 38349.05 | G25: 35186.18 | H25: =G25/D25 -> 43.516392 | I25: =G25-F25 -> -3162.87 | J25: =I25/F25 -> -0.082475837 | K25: 45286 | L25: 45302 | M25: =DAYS360(K25,L25) -> 15 | O25: Closed below stop for 2 days.
A26: TS | B26: Long | C26: Tenaris | D26: 1166.935 | E26: =F26/D26 -> 35.085005 | F26: 40941.92 | G26: 36634.59 | H26: =G26/D26 -> 31.393857 | I26: =G26-F26 -> -4307.33 | J26: =I26/F26 -> -0.10520586 | K26: 45233 | L26: 45307 | M26: =DAYS360(K26,L26) -> 73
A27: MNSO | B27: Long | C27: Minoso | D27: =1211.7123+804.6763 -> 2016.3886 | E27: =F27/D27 -> 20.49104 | F27: 41317.9 | G27: 42071.53 | H27: =G27/D27 -> 20.864793 | I27: =G27-F27 -> 753.63 | J27: =I27/F27 -> 0.018239794 | K27: 45135 | L27: 45308 | M27: =DAYS360(K27,L27) -> 169 | O27: Totally blew this trade. Had a nearly 50% profit.
A28: ACMR | B28: Long | C28: ACM Research | D28: =1339.9646+918.07 -> 2258.0346 | E28: =F28/D28 -> 21.193736 | F28: =28457.8+19398.39 -> 47856.19 | G28: 39178.27 | H28: =G28/D28 -> 17.350607 | I28: =G28-F28 -> -8677.92 | J28: =I28/F28 -> -0.18133328 | K28: 45302 | L28: 45322 | M28: =DAYS360(K28,L28) -> 20
A29: MDB | B29: Long | C29: MongoDB | D29: 126.054 | E29: =F29/D29 -> 450.27964 | F29: 56759.55 | G29: 54939.36 | H29: =G29/D29 -> 435.83988 | I29: =G29-F29 -> -1820.19 | J29: =I29/F29 -> -0.032068436 | K29: 45327 | L29: 45342 | M29: =DAYS360(K29,L29) -> 15 | O29: Stopped out.
A30: VKTX | B30: Long | C30: Viking Therap | D30: 808.6324 | E30: =F30/D30 -> 21.530005 | F30: 17409.86 | G30: 28227.27 | H30: =G30/D30 -> 34.907419 | I30: =G30-F30 -> 10817.41 | J30: =I30/F30 -> 0.62133814 | K30: 45309 | L30: 45343 | M30: =DAYS360(K30,L30) -> 33 | O30: Took partial profit.
A31: BIRK | B31: Long | C31: Birkenstock Hldg | D31: =567.3728+414.8485 -> 982.2213 | E31: =F31/D31 -> 52.971342 | F31: 52029.58 | G31: 47202.25 | H31: =G31/D31 -> 48.056634 | I31: =G31-F31 -> -4827.33 | J31: =I31/F31 -> -0.092780491 | K31: 45344 | L31: 45351 | M31: =DAYS360(K31,L31) -> 7 | O31: Stopped out after earnings.
A32: DDOG | B32: Long | C32: Datadog | D32: =308.2955+142.5312 -> 450.8267 | E32: =F32/D32 -> 130.66999 | F32: 58909.52 | G32: 55702.82 | H32: =G32/D32 -> 123.55706 | I32: =G32-F32 -> -3206.7 | J32: =I32/F32 -> -0.054434326 | K32: 45286 | L32: 45356 | M32: =DAYS360(K32,L32) -> 69 | O32: Broke 50dma
A33: IOT | B33: Long | C33: Samsara | D33: =846.327+640.0668 -> 1486.3938 | E33: =F33/D33 -> 34.902742 | F33: =30020.93+21858.29 -> 51879.22 | G33: 51882.03 | H33: =G33/D33 -> 34.904633 | I33: =G33-F33 -> 2.81 | J33: =I33/F33 -> 5.4164268e-05 | K33: 45331 | L33: 45366 | M33: =DAYS360(K33,L33) -> 36 | O33: B/o did not follow through. Sold at my cost.
A34: KD | B34: Long | C34: Kyndryl Hldgs | D34: =1160.2602+1046.0778 -> 2206.338 | E34: =F34/D34 -> 17.884522 | F34: =20288.83+19170.47 -> 39459.3 | G34: 47805.42 | H34: =G34/D34 -> 21.667315 | I34: =G34-F34 -> 8346.12 | J34: =I34/F34 -> 0.21151212 | K34: 45243 | L34: 45373 | M34: =DAYS360(K34,L34) -> 129 | O34: Took profit.
A35: BPMC | B35: Long | C35: Blueprint Med | D35: =464.2554+269.0604 -> 733.3158 | E35: =F35/D35 -> 97.201615 | F35: 71279.48 | G35: 66395.73 | H35: =G35/D35 -> 90.541797 | I35: =G35-F35 -> -4883.75 | J35: =I35/F35 -> -0.068515511 | K35: 45349 | L35: 45394 | M35: =DAYS360(K35,L35) -> 45 | O35: Bad market day. Took the loss above my stop.
A36: CCJ | B36: Long | C36: Cameco | D36: 901.358 | E36: =F36/D36 -> 51.760011 | F36: 46654.3 | G36: 44379.95 | H36: =G36/D36 -> 49.236763 | I36: =G36-F36 -> -2274.35 | J36: =I36/F36 -> -0.04874899 | K36: 45394 | L36: 45394 | M36: =DAYS360(K36,L36) -> 0 | O36: Breakout rejected same day as I bought.
A37: AXON | B37: Long | C37: Axon Enterprise | D37: 267.8431 | E37: =F37/D37 -> 228.36594 | F37: 61166.24 | G37: 81558.94 | H37: =G37/D37 -> 304.50267 | I37: =G37-F37 -> 20392.7 | J37: =I37/F37 -> 0.33339797 | K37: 45238 | L37: 45397 | M37: =DAYS360(K37,L37) -> 157 | O37: Taking profits. Broke 21dema and consolidation.
A38: ARM | B38: Long | C38: Arm Holdings | D38: 224.4175 | E38: =F38/D38 -> 131.07547 | F38: 29415.63 | G38: 27481.43 | H38: =G38/D38 -> 122.45672 | I38: =G38-F38 -> -1934.2 | J38: =I38/F38 -> -0.065754159 | K38: 45393 | L38: 45397 | M38: =DAYS360(K38,L38) -> 4 | O38: Broke 50dma. Near stop loss.
A39: BLBD | B39: Long | C39: Bluebird | D39: =952.002+512.6146 -> 1464.6166 | E39: =F39/D39 -> 30.008099 | F39: 43950.36 | G39: 49174.83 | H39: =G39/D39 -> 33.575224 | I39: =G39-F39 -> 5224.47 | J39: =I39/F39 -> 0.11887206 | K39: 45321 | L39: 45400 | M39: =DAYS360(K39,L39) -> 78 | O39: Broke 50dma. Near stop loss.
A40: UFPT | B40: Long | C40: UFP Technologies | D40: 268.5725 | E40: =F40/D40 -> 202.8001 | F40: 54466.53 | G40: 57142.12 | H40: =G40/D40 -> 212.76236 | I40: =G40-F40 -> 2675.59 | J40: =I40/F40 -> 0.049123563 | K40: 45370 | L40: 45401 | M40: =DAYS360(K40,L40) -> 30 | O40: Stopped out.
A41: AAON | B41: Long | C41: AAON | D41: =532.4164+77.1815 -> 609.5979 | E41: =F41/D41 -> 72.032302 | F41: =38270.34+5640.4 -> 43910.74 | G41: 46906.35 | H41: =G41/D41 -> 76.946377 | I41: =G41-F41 -> 2995.61 | J41: =I41/F41 -> 0.06822044 | K41: 45313 | L41: 45420 | M41: =DAYS360(K41,L41) -> 106 | O41: Bad reaction to earnings.
J45: Avg
H46: # of losses | I46: 9 | J46: -0.0813
H47: # of wins | I47: 8 | J47: 0.1776

Sheet 05-31-24
C1: 45443
C3: MANAGED ACCT | X3: Current | AC3: IBD
H4: Cost | J4: P/L | N4: Group | P4: EPS | R4: pivot | S4: last | W4: cost | X4: Stop | Y4: Stop | Z4: % | AB4: EPS | AC4: Comp
A5: Symbol | B5: Position | C5: Name | D5: Qty | E5: Current | F5: Value | G5: Cost | H5: per share | I5: P/L $ | J5: per sh | K5: Date purch | L5: days held | M5: % incr | N5: Rank | O5: RS | P5: RS | Q5: pivot | R5: -0.07 | S5: low | T5: 0.25 | U5: 0.5 | V5: 1 | W5: -0.07 | X5: Loss | Y5: Loss% | Z5: of port | AB5: Due | AC5: Rank
A7: VKTX | B7: Long | C7: Viking Therap | D7: =1286.8297+948.5633-808.6324 -> 1426.7606 | E7: 62.26 | F7: =E7*D7 -> 88830.115 | G7: =28174.78+19947.6-17409.86 -> 30712.52 | H7: =G7/D7 -> 21.52605 | I7: =F7-G7 -> 58117.595 | J7: =E7-H7 -> 40.73395 | K7: 45309 | L7: =DAYS360(K7,$C$1) -> 133 | M7: =(I7/G7) -> 1.8923096 | N7: 36 | O7: 99 | P7: 21 | Q7: 20.03 | R7: =Q7*0.93 -> 18.6279 | S7: 60.3 | T7: =Q7*1.25 -> 25.0375 | U7: =Q7*1.5 -> 30.045 | V7: =Q7*2 -> 40.06 | W7: =H7-(H7*0.07) -> 20.019226 | X7: 58 | Y7: =(X7-H7)/H7 -> 1.6944098 | Z7: =F7/F$19 -> 0.12333782 | AB7: 45497 | AC7: 59
A8: HMY | B8: Long | C8: Harmony Gold | D8: =2972.4372+3509.2812 -> 6481.7184 | E8: 9.1 | F8: =E8*D8 -> 58983.637 | G8: =23794.37+31996.67 -> 55791.04 | H8: =G8/D8 -> 8.6074458 | I8: =F8-G8 -> 3192.5974 | J8: =E8-H8 -> 0.49255417 | K8: 45378 | L8: =DAYS360(K8,$C$1) -> 64 | M8: =(I8/G8) -> 0.057224197 | N8: 17 | O8: 97 | P8: 99 | Q8: 6.76 | R8: =Q8*0.93 -> 6.2868 | S8: 7.21 | T8: =Q8*1.25 -> 8.45 | U8: =Q8*1.5 -> 10.14 | V8: =Q8*2 -> 13.52 | W8: =H8-(H8*0.07) -> 8.0049246 | X8: 8.75 | Y8: =(X8-H8)/H8 -> 0.016561727 | Z8: =F8/F$19 -> 0.081896928 | AB8: 45531 | AC8: 99
A9: AEM | B9: Long | C9: Agnico-Eagle Mines | D9: 828.4023 | E9: 68.21 | F9: =E9*D9 -> 56505.321 | G9: 47623.59 | H9: =G9/D9 -> 57.488481 | I9: =F9-G9 -> 8881.7309 | J9: =E9-H9 -> 10.721519 | K9: 45378 | L9: =DAYS360(K9,$C$1) -> 64 | M9: =(I9/G9) -> 0.18649856 | N9: 17 | O9: 92 | P9: 97 | Q9: 57.16 | R9: =Q9*0.93 -> 53.1588 | S9: 60.15 | T9: =Q9*1.25 -> 71.45 | U9: =Q9*1.5 -> 85.74 | V9: =Q9*2 -> 114.32 | W9: =H9-(H9*0.07) -> 53.464287 | X9: 65 | Y9: =(X9-H9)/H9 -> 0.13066129 | Z9: =F9/F$19 -> 0.078455863 | AB9: 45504 | AC9: 99
A10: SCCO | B10: Long | C10: Southern Copper | D10: 494.9036 | E10: 118.63 | F10: =E10*D10 -> 58710.414 | G10: 59378.55 | H10: =G10/D10 -> 119.98003 | I10: =F10-G10 -> -668.13593 | J10: =E10-H10 -> -1.3500325 | K10: 45422 | L10: =DAYS360(K10,$C$1) -> 21 | M10: =(I10/G10) -> -0.011252143 | N10: 14 | O10: 96 | P10: 59 | Q10: 121 | R10: =Q10*0.93 -> 112.53 | S10: 110.91 | T10: =Q10*1.25 -> 151.25 | U10: =Q10*1.5 -> 181.5 | V10: =Q10*2 -> 242 | W10: =H10-(H10*0.07) -> 111.58143 | X10: 115 | Y10: =(X10-H10)/H10 -> -0.041507177 | Z10: =F10/F$19 -> 0.081517566 | AB10: 45496 | AC10: 91
A11: TSM | B11: Long | C11: Taiwan Semi | D11: 390.4513 | E11: 151.04 | F11: =E11*D11 -> 58973.764 | G11: 58706.59 | H11: =G11/D11 -> 150.35573 | I11: =F11-G11 -> 267.17435 | J11: =E11-H11 -> 0.68427062 | K11: 45426 | L11: =DAYS360(K11,$C$1) -> 17 | M11: =(I11/G11) -> 0.0045510113 | N11: 65 | O11: 93 | P11: 81 | Q11: 148.43 | R11: =Q11*0.93 -> 138.0399 | S11: 125.78 | T11: =Q11*1.25 -> 185.5375 | U11: =Q11*1.5 -> 222.645 | V11: =Q11*2 -> 296.86 | W11: =H11-(H11*0.07) -> 139.83083 | X11: 142 | Y11: =(X11-H11)/H11 -> -0.055573069 | Z11: =F11/F$19 -> 0.081883219 | AB11: 45491 | AC11: 94
A12: ERJ | B12: Long | C12: Embraer ADR | D12: =1542.0192+932.4994 -> 2474.5186 | E12: 27.79 | F12: =E12*D12 -> 68766.872 | G12: =44039.07+27471.43 -> 71510.5 | H12: =G12/D12 -> 28.898752 | I12: =F12-G12 -> -2743.6281 | J12: =E12-H12 -> -1.1087523 | K12: 45426 | L12: =DAYS360(K12,$C$1) -> 17 | M12: =(I12/G12) -> -0.038366787 | N12: 34 | O12: 96 | P12: 72 | Q12: 27.47 | R12: =Q12*0.93 -> 25.5471 | S12: 25.73 | T12: =Q12*1.25 -> 34.3375 | U12: =Q12*1.5 -> 41.205 | V12: =Q12*2 -> 54.94 | W12: =H12-(H12*0.07) -> 26.87584 | X12: 27 | Y12: =(X12-H12)/H12 -> -0.065703607 | Z12: =F12/F$19 -> 0.095480641 | AB12: 45513 | AC12: 99
A13: NVDA | B13: Long | C13: Nvidia | D13: 94.0668 | E13: 1095.95 | F13: =E13*D13 -> 103092.51 | G13: 88627.87 | H13: =G13/D13 -> 942.18013 | I13: =F13-G13 -> 14464.639 | J13: =E13-H13 -> 153.76987 | K13: 45427 | L13: =DAYS360(K13,$C$1) -> 16 | M13: =(I13/G13) -> 0.16320644 | N13: 4 | O13: 98 | P13: 99 | Q13: 922.2 | R13: =Q13*0.93 -> 857.646 | S13: 812.55 | T13: =Q13*1.25 -> 1152.75 | U13: =Q13*1.5 -> 1383.3 | V13: =Q13*2 -> 1844.4 | W13: =H13-(H13*0.07) -> 876.22752 | X13: 945 | Y13: =(X13-H13)/H13 -> 0.0029929186 | Z13: =F13/F$19 -> 0.14314071 | AB13: 45519 | AC13: 99
A14: CROX | B14: Long | C14: Crocs | D14: 389.7843 | E14: 155.64 | F14: =E14*D14 -> 60666.028 | G14: 59201.71 | H14: =G14/D14 -> 151.88326 | I14: =F14-G14 -> 1464.3185 | J14: =E14-H14 -> 3.7567405 | K14: 45440 | L14: =DAYS360(K14,$C$1) -> 3 | M14: =(I14/G14) -> 0.024734395 | N14: 13 | O14: 93 | P14: 92 | Q14: 148.16 | R14: =Q14*0.93 -> 137.7888 | S14: 139.01 | T14: =Q14*1.25 -> 185.2 | U14: =Q14*1.5 -> 222.24 | V14: =Q14*2 -> 296.32 | W14: =H14-(H14*0.07) -> 141.25143 | X14: 142 | Y14: =(X14-H14)/H14 -> -0.065071421 | Z14: =F14/F$19 -> 0.084232875 | AB14: 45491 | AC14: 97
F15: =E15*D15 -> 0 | H15: =G15/D15 -> #DIV/0! | I15: =F15-G15 -> 0 | J15: =E15-H15 -> #DIV/0! | L15: =DAYS360(K15,$C$1) -> 44791 | M15: =(I15/G15) -> #DIV/0! | R15: =Q15*0.93 -> 0 | T15: =Q15*1.25 -> 0 | U15: =Q15*1.5 -> 0 | V15: =Q15*2 -> 0 | W15: =H15-(H15*0.07) -> #DIV/0! | Y15: =(X15-H15)/H15 -> #DIV/0! | Z15: =F15/F$19 -> 0
A16: BIL | B16: Long | C16: Tbill ETF | D16: 363.7138 | E16: 91.79 | F16: =E16*D16 -> 33385.29 | G16: 25401.36 | H16: =G16/D16 -> 69.838868 | I16: =F16-G16 -> 7983.9297 | J16: =E16-H16 -> 21.951132 | M16: =(I16/G16) -> 0.31431111 | R16: =Q16*0.93 -> 0 | T16: =Q16*1.25 -> 0 | U16: =Q16*1.5 -> 0 | V16: =Q16*2 -> 0 | W16: =H16-(H16*0.07) -> 64.950147 | Y16: =(X16-H16)/H16 -> -1 | Z16: =F16/F$19 -> 0.046354426
A17: Sub-Total | F17: =SUM(F6:F16) -> 587913.95 | G17: =SUM(G6:G16) -> 496953.73 | I17: =SUM(I6:I16) -> 90960.221
D18: Cash, other | F18: 132304 | G18: =F18/F19 -> 0.18369995
D19: Total | F19: =SUM(F17:F18) -> 720217.95 | K19: Control acct (Doug's IRA) | M19: Today
H20: Last week's close | I20: ='05-24-24'!F19 -> 726651.82 | K20: 45291 | L20: 139707.06 | M20: 163925
A21: * | H21: Week's change | I21: =(F19-I20)/I20 -> -0.008854133 | K21: chg % | L21: =(M20-L20)/L20 -> 0.173348
M23: days
A24: 2024 Closed Trades - Managed Acct | D24: Qty | E24: Cost/sh | F24: $ cost | G24: $Proc | H24: Proc/sh | I24: Profit/loss | J24: % | K24: Date purch | L24: Date sold | M24: held | P24: Comments
A25: YELP | B25: Long | C25: Yelp Inc | D25: 808.573 | E25: =F25/D25 -> 47.428062 | F25: 38349.05 | G25: 35186.18 | H25: =G25/D25 -> 43.516392 | I25: =G25-F25 -> -3162.87 | J25: =I25/F25 -> -0.082475837 | K25: 45286 | L25: 45302 | M25: =DAYS360(K25,L25) -> 15 | O25: Closed below stop for 2 days.
A26: TS | B26: Long | C26: Tenaris | D26: 1166.935 | E26: =F26/D26 -> 35.085005 | F26: 40941.92 | G26: 36634.59 | H26: =G26/D26 -> 31.393857 | I26: =G26-F26 -> -4307.33 | J26: =I26/F26 -> -0.10520586 | K26: 45233 | L26: 45307 | M26: =DAYS360(K26,L26) -> 73
A27: MNSO | B27: Long | C27: Minoso | D27: =1211.7123+804.6763 -> 2016.3886 | E27: =F27/D27 -> 20.49104 | F27: 41317.9 | G27: 42071.53 | H27: =G27/D27 -> 20.864793 | I27: =G27-F27 -> 753.63 | J27: =I27/F27 -> 0.018239794 | K27: 45135 | L27: 45308 | M27: =DAYS360(K27,L27) -> 169 | O27: Totally blew this trade. Had a nearly 50% profit.
A28: ACMR | B28: Long | C28: ACM Research | D28: =1339.9646+918.07 -> 2258.0346 | E28: =F28/D28 -> 21.193736 | F28: =28457.8+19398.39 -> 47856.19 | G28: 39178.27 | H28: =G28/D28 -> 17.350607 | I28: =G28-F28 -> -8677.92 | J28: =I28/F28 -> -0.18133328 | K28: 45302 | L28: 45322 | M28: =DAYS360(K28,L28) -> 20
A29: MDB | B29: Long | C29: MongoDB | D29: 126.054 | E29: =F29/D29 -> 450.27964 | F29: 56759.55 | G29: 54939.36 | H29: =G29/D29 -> 435.83988 | I29: =G29-F29 -> -1820.19 | J29: =I29/F29 -> -0.032068436 | K29: 45327 | L29: 45342 | M29: =DAYS360(K29,L29) -> 15 | O29: Stopped out.
A30: VKTX | B30: Long | C30: Viking Therap | D30: 808.6324 | E30: =F30/D30 -> 21.530005 | F30: 17409.86 | G30: 28227.27 | H30: =G30/D30 -> 34.907419 | I30: =G30-F30 -> 10817.41 | J30: =I30/F30 -> 0.62133814 | K30: 45309 | L30: 45343 | M30: =DAYS360(K30,L30) -> 33 | O30: Took partial profit.
A31: BIRK | B31: Long | C31: Birkenstock Hldg | D31: =567.3728+414.8485 -> 982.2213 | E31: =F31/D31 -> 52.971342 | F31: 52029.58 | G31: 47202.25 | H31: =G31/D31 -> 48.056634 | I31: =G31-F31 -> -4827.33 | J31: =I31/F31 -> -0.092780491 | K31: 45344 | L31: 45351 | M31: =DAYS360(K31,L31) -> 7 | O31: Stopped out after earnings.
A32: DDOG | B32: Long | C32: Datadog | D32: =308.2955+142.5312 -> 450.8267 | E32: =F32/D32 -> 130.66999 | F32: 58909.52 | G32: 55702.82 | H32: =G32/D32 -> 123.55706 | I32: =G32-F32 -> -3206.7 | J32: =I32/F32 -> -0.054434326 | K32: 45286 | L32: 45356 | M32: =DAYS360(K32,L32) -> 69 | O32: Broke 50dma
A33: IOT | B33: Long | C33: Samsara | D33: =846.327+640.0668 -> 1486.3938 | E33: =F33/D33 -> 34.902742 | F33: =30020.93+21858.29 -> 51879.22 | G33: 51882.03 | H33: =G33/D33 -> 34.904633 | I33: =G33-F33 -> 2.81 | J33: =I33/F33 -> 5.4164268e-05 | K33: 45331 | L33: 45366 | M33: =DAYS360(K33,L33) -> 36 | O33: B/o did not follow through. Sold at my cost.
A34: KD | B34: Long | C34: Kyndryl Hldgs | D34: =1160.2602+1046.0778 -> 2206.338 | E34: =F34/D34 -> 17.884522 | F34: =20288.83+19170.47 -> 39459.3 | G34: 47805.42 | H34: =G34/D34 -> 21.667315 | I34: =G34-F34 -> 8346.12 | J34: =I34/F34 -> 0.21151212 | K34: 45243 | L34: 45373 | M34: =DAYS360(K34,L34) -> 129 | O34: Took profit.
A35: BPMC | B35: Long | C35: Blueprint Med | D35: =464.2554+269.0604 -> 733.3158 | E35: =F35/D35 -> 97.201615 | F35: 71279.48 | G35: 66395.73 | H35: =G35/D35 -> 90.541797 | I35: =G35-F35 -> -4883.75 | J35: =I35/F35 -> -0.068515511 | K35: 45349 | L35: 45394 | M35: =DAYS360(K35,L35) -> 45 | O35: Bad market day. Took the loss above my stop.
A36: CCJ | B36: Long | C36: Cameco | D36: 901.358 | E36: =F36/D36 -> 51.760011 | F36: 46654.3 | G36: 44379.95 | H36: =G36/D36 -> 49.236763 | I36: =G36-F36 -> -2274.35 | J36: =I36/F36 -> -0.04874899 | K36: 45394 | L36: 45394 | M36: =DAYS360(K36,L36) -> 0 | O36: Breakout rejected same day as I bought.
A37: AXON | B37: Long | C37: Axon Enterprise | D37: 267.8431 | E37: =F37/D37 -> 228.36594 | F37: 61166.24 | G37: 81558.94 | H37: =G37/D37 -> 304.50267 | I37: =G37-F37 -> 20392.7 | J37: =I37/F37 -> 0.33339797 | K37: 45238 | L37: 45397 | M37: =DAYS360(K37,L37) -> 157 | O37: Taking profits. Broke 21dema and consolidation.
A38: ARM | B38: Long | C38: Arm Holdings | D38: 224.4175 | E38: =F38/D38 -> 131.07547 | F38: 29415.63 | G38: 27481.43 | H38: =G38/D38 -> 122.45672 | I38: =G38-F38 -> -1934.2 | J38: =I38/F38 -> -0.065754159 | K38: 45393 | L38: 45397 | M38: =DAYS360(K38,L38) -> 4 | O38: Broke 50dma. Near stop loss.
A39: BLBD | B39: Long | C39: Bluebird | D39: =952.002+512.6146 -> 1464.6166 | E39: =F39/D39 -> 30.008099 | F39: 43950.36 | G39: 49174.83 | H39: =G39/D39 -> 33.575224 | I39: =G39-F39 -> 5224.47 | J39: =I39/F39 -> 0.11887206 | K39: 45321 | L39: 45400 | M39: =DAYS360(K39,L39) -> 78 | O39: Broke 50dma. Near stop loss.
A40: UFPT | B40: Long | C40: UFP Technologies | D40: 268.5725 | E40: =F40/D40 -> 202.8001 | F40: 54466.53 | G40: 57142.12 | H40: =G40/D40 -> 212.76236 | I40: =G40-F40 -> 2675.59 | J40: =I40/F40 -> 0.049123563 | K40: 45370 | L40: 45401 | M40: =DAYS360(K40,L40) -> 30 | O40: Stopped out.
A41: AAON | B41: Long | C41: AAON | D41: =532.4164+77.1815 -> 609.5979 | E41: =F41/D41 -> 72.032302 | F41: =38270.34+5640.4 -> 43910.74 | G41: 46906.35 | H41: =G41/D41 -> 76.946377 | I41: =G41-F41 -> 2995.61 | J41: =I41/F41 -> 0.06822044 | K41: 45313 | L41: 45420 | M41: =DAYS360(K41,L41) -> 106 | O41: Bad reaction to earnings.
A42: TOST | B42: Long | C42: Toast | D42: =1366.874+867.842 -> 2234.716 | E42: =F42/D42 -> 26.796152 | F42: =36957.24+22924.55 -> 59881.79 | G42: 53143.62 | H42: =G42/D42 -> 23.780928 | I42: =G42-F42 -> -6738.17 | J42: =I42/F42 -> -0.11252453 | K42: 45421 | L42: 45441 | M42: =DAYS360(K42,L42) -> 20 | O42: Broke 50dma and stop loss.
I45: =SUM(I25:I44) -> 9375.53 | J45: Avg
H46: # of losses | I46: 10 | J46: -0.0844
H47: # of wins | I47: 8 | J47: 0.1776

Sheet 06-07-24
C1: 45450
C3: MANAGED ACCT | X3: Current | AC3: IBD
H4: Cost | J4: P/L | N4: Group | P4: EPS | R4: pivot | S4: last | W4: cost | X4: Stop | Y4: Stop | Z4: % | AB4: EPS | AC4: Comp
A5: Symbol | B5: Position | C5: Name | D5: Qty | E5: Current | F5: Value | G5: Cost | H5: per share | I5: P/L $ | J5: per sh | K5: Date purch | L5: days held | M5: % incr | N5: Rank | O5: RS | P5: RS | Q5: pivot | R5: -0.07 | S5: low | T5: 0.25 | U5: 0.5 | V5: 1 | W5: -0.07 | X5: Loss | Y5: Loss% | Z5: of port | AB5: Due | AC5: Rank
A7: HMY | B7: Long | C7: Harmony Gold | D7: =2972.4372+3509.2812 -> 6481.7184 | E7: 8.24 | F7: =E7*D7 -> 53409.36 | G7: =23794.37+31996.67 -> 55791.04 | H7: =G7/D7 -> 8.6074458 | I7: =F7-G7 -> -2381.6804 | J7: =E7-H7 -> -0.36744583 | K7: 45378 | L7: =DAYS360(K7,$C$1) -> 70 | M7: =(I7/G7) -> -0.042689299 | N7: 19 | O7: 96 | P7: 99 | Q7: 6.76 | R7: =Q7*0.93 -> 6.2868 | S7: 7.21 | T7: =Q7*1.25 -> 8.45 | U7: =Q7*1.5 -> 10.14 | V7: =Q7*2 -> 13.52 | W7: =H7-(H7*0.07) -> 8.0049246 | X7: 8.75 | Y7: =(X7-H7)/H7 -> 0.016561727 | Z7: =F7/F$19 -> 0.075085427 | AB7: 45531 | AC7: 99
A8: AEM | B8: Long | C8: Agnico-Eagle Mines | D8: 828.4023 | E8: 63.8 | F8: =E8*D8 -> 52852.067 | G8: 47623.59 | H8: =G8/D8 -> 57.488481 | I8: =F8-G8 -> 5228.4767 | J8: =E8-H8 -> 6.3115189 | K8: 45378 | L8: =DAYS360(K8,$C$1) -> 70 | M8: =(I8/G8) -> 0.10978754 | N8: 19 | O8: 89 | P8: 97 | Q8: 57.16 | R8: =Q8*0.93 -> 53.1588 | S8: 60.15 | T8: =Q8*1.25 -> 71.45 | U8: =Q8*1.5 -> 85.74 | V8: =Q8*2 -> 114.32 | W8: =H8-(H8*0.07) -> 53.464287 | X8: 65 | Y8: =(X8-H8)/H8 -> 0.13066129 | Z8: =F8/F$19 -> 0.074301958 | AB8: 45504 | AC8: 98
A9: SCCO | B9: Long | C9: Southern Copper | D9: 494.9036 | E9: 108.9 | F9: =E9*D9 -> 53895.002 | G9: 59378.55 | H9: =G9/D9 -> 119.98003 | I9: =F9-G9 -> -5483.548 | J9: =E9-H9 -> -11.080032 | K9: 45422 | L9: =DAYS360(K9,$C$1) -> 27 | M9: =(I9/G9) -> -0.09234897 | N9: 18 | O9: 96 | P9: 59 | Q9: 121 | R9: =Q9*0.93 -> 112.53 | S9: 110.91 | T9: =Q9*1.25 -> 151.25 | U9: =Q9*1.5 -> 181.5 | V9: =Q9*2 -> 242 | W9: =H9-(H9*0.07) -> 111.58143 | X9: 115 | Y9: =(X9-H9)/H9 -> -0.041507177 | Z9: =F9/F$19 -> 0.075768166 | AB9: 45496 | AC9: 84
A10: TSM | B10: Long | C10: Taiwan Semi | D10: 390.4513 | E10: 164.39 | F10: =E10*D10 -> 64186.289 | G10: 58706.59 | H10: =G10/D10 -> 150.35573 | I10: =F10-G10 -> 5479.6992 | J10: =E10-H10 -> 14.034271 | K10: 45426 | L10: =DAYS360(K10,$C$1) -> 23 | M10: =(I10/G10) -> 0.093340445 | N10: 52 | O10: 95 | P10: 81 | Q10: 148.43 | R10: =Q10*0.93 -> 138.0399 | S10: 125.78 | T10: =Q10*1.25 -> 185.5375 | U10: =Q10*1.5 -> 222.645 | V10: =Q10*2 -> 296.86 | W10: =H10-(H10*0.07) -> 139.83083 | X10: 142 | Y10: =(X10-H10)/H10 -> -0.055573069 | Z10: =F10/F$19 -> 0.090236149 | AB10: 45491 | AC10: 96
